Workbook

Sheet Distribucion Contrato
A1: DISTRIBUCIÓN DEL SALDO CONTRACTUAL CERTIFICABLE – AGUA Y CLOACA
A3: Criterio: mantener la misma proporción económica de la oferta aceptada ($400 M Agua / $680 M Cloaca) para distribuir el saldo contractual de $374,4 M IVA incluido.
A5: Concepto | B5: Oferta original s/IVA | C5: Participación | D5: Saldo certificable s/IVA | E5: IVA | F5: Saldo certificable c/IVA
A6: Red de Agua | B6: =Configuracion!B10 -> 400000000 | C6: =Configuracion!B13 -> 0.37037037 | D6: =Configuracion!B18 -> 1.1460055e+08 | E6: =D6*Configuracion!B16 -> 24066116 | F6: =Configuracion!B19 -> 1.3866667e+08
A7: Red Cloacal | B7: =Configuracion!B11 -> 680000000 | C7: =Configuracion!B14 -> 0.62962963 | D7: =Configuracion!B20 -> 1.9482094e+08 | E7: =D7*Configuracion!B16 -> 40912397 | F7: =Configuracion!B21 -> 2.3573333e+08
A8: TOTAL | B8: =SUM(B6:B7) -> 1080000000 | C8: =SUM(C6:C7) -> 1 | D8: =SUM(D6:D7) -> 3.0942149e+08 | E8: =SUM(E6:E7) -> 64978512 | F8: =SUM(F6:F7) -> 3.744e+08
A10: Referencia contractual
A11: Cláusula c) | B11: $374.400.000 IVA incluido mediante certificaciones mensuales según avance de obra.
A12: Actualización | B12: Índice UOCRA – mes base JULIO 2026.
A13: Aclaración | B13: La distribución Agua/Cloaca es un criterio interno basado en la proporción de la oferta aceptada.

Sheet Resumen
A1: ECAR – CONTROL ECONÓMICO Y CERTIFICACIÓN | RED DE AGUA – LOTEO ROQUE
A3: Panel ejecutivo vinculado al Presupuesto Base, Medición y Certificado.
A5: INDICADOR | B5: VALOR | D5: CONTROL | E5: ESTADO
A6: Valor original Red de Agua s/IVA | B6: =Configuracion!B10 -> 400000000 | D6: Distribución contrato Agua | E6: =IF(ABS('Distribucion Contrato'!F8-Configuracion!B15)<0.01,"OK","REVISAR") -> OK
A7: Saldo certificable Agua s/IVA | B7: =Configuracion!B18 -> 1.1460055e+08 | D7: Incidencias = 100% | E7: =IF(ABS('Presupuesto Base'!G25-1)<0.000001,"OK","REVISAR") -> OK
A8: Saldo certificable Agua c/IVA | B8: =Configuracion!B19 -> 1.3866667e+08 | D8: Excesos en certificado | E8: =IF(Certificado!M28<=Configuracion!B18+0.01,"OK","REVISAR") -> OK
A9: Certificado seleccionado N° | B9: =Certificado!B4 -> 1 | D9: Mes base UOCRA | E9: =Configuracion!B22 -> Julio 2026
A10: Último certificado con movimiento | B10: =MAX(Medicion!$A$6:$A$511) -> 1
A11: Certificados cerrados | B11: =COUNTIF('Historial Certificados'!$E$6:$E$29,"CERRADO") -> 0
A12: Certificación presente seleccionado s/IVA | B12: =IFERROR(VLOOKUP(Certificado!B4,'Historial Certificados'!$A$6:$O$29,8,FALSE),0) -> 14722545
A13: Acumulado certificado seleccionado | B13: =IFERROR(VLOOKUP(Certificado!B4,'Historial Certificados'!$A$6:$O$29,9,FALSE),0) -> 14722545
A14: Saldo luego del certificado | B14: =IFERROR(VLOOKUP(Certificado!B4,'Historial Certificados'!$A$6:$O$29,10,FALSE),Configuracion!B18) -> 99878006
A15: Avance económico acumulado | B15: =IFERROR(VLOOKUP(Certificado!B4,'Historial Certificados'!$A$6:$O$29,11,FALSE),0) -> 0.12846836
A16: Composición saldo certificable Agua | B16: Monto s/IVA
A17: Obra civil lineal | B17: =Configuracion!B18*0.5625 -> 64462810
A18: Cañerías | B18: =Configuracion!B18*0.27 -> 30942149
A19: Conexiones | B19: =Configuracion!B18*0.1 -> 11460055
A20: Válvulas e hidrantes | B20: =Configuracion!B18*0.035 -> 4011019.3
A21: Pruebas / terminaciones / documentación | B21: =Configuracion!B18*0.0325 -> 3724517.9
A22: Conexiones terminadas | B22: =COUNTIF(Conexiones!$J$6:$J$232,"Terminada") -> 0
A23: Conexiones totales | B23: =Configuracion!B30 -> 227
A24: Flujo recomendado: 1) completar período y estado en Historial Certificados; 2) cargar avances en Medicion; 3) seleccionar el Certificado N° en Certificado; 4) revisar ANTERIOR / PRESENTE / ACUMULADO; 5) verificar controles; 6) una vez emitido definitivamente, cambiar Estado a CERRADO y no modificar esas mediciones.

Sheet Configuracion
A1: CONFIGURACIÓN GENERAL – CERTIFICACIÓN RED DE AGUA
A4: Dato | B4: Valor | D4: Código de color | E4: Uso | F4: Descripción
A5: Obra | B5: Red Distribuidora de Agua Potable – Loteo Roque | D5: AMARILLO | E5: Carga manual | F5: Celdas que el usuario puede completar o modificar.
A6: Ubicación | B6: Santa Lucía, San Juan | D6: CELESTE | E6: Cálculo | F6: Celdas con fórmulas o datos vinculados.
A7: Comitente | B7: VALDIVIESO GROUP S.R.L. | D7: VERDE | E7: OK | F7: Control correcto / dentro de límites.
A8: Contratista | B8: ECAR SAS | D8: ROJO | E8: Alerta | F8: Dato excedido, incompleto o inconsistente.
A9: Ente de inspección | B9: O.S.S.E.
A10: Monto original oferta Agua s/IVA | B10: 400000000
A11: Monto original oferta Cloaca s/IVA | B11: 680000000
A12: Monto original oferta Total s/IVA | B12: =B10+B11 -> 1080000000
A13: Participación Agua | B13: =B10/B12 -> 0.37037037
A14: Participación Cloaca | B14: =B11/B12 -> 0.62962963
A15: Saldo contractual certificable TOTAL c/IVA | B15: 374400000
A16: IVA | B16: 0.21
A17: Saldo contractual certificable TOTAL s/IVA | B17: =B15/(1+B16) -> 3.0942149e+08
A18: Saldo certificable Agua s/IVA | B18: =B17*B13 -> 1.1460055e+08
A19: Saldo certificable Agua c/IVA | B19: =B18*(1+B16) -> 1.3866667e+08
A20: Saldo certificable Cloaca s/IVA | B20: =B17*B14 -> 1.9482094e+08
A21: Saldo certificable Cloaca c/IVA | B21: =B20*(1+B16) -> 2.3573333e+08
A22: Mes base actualización | B22: Julio 2026
A23: Índice actualización | B23: UOCRA
A24: NOTA DE USO | D24: NOTA CONTRACTUAL
A25: Longitud PEAD Ø75 mm (ml) | B25: 3170 | D25: El contrato establece un saldo de $374.400.000 IVA incluido a abonar mediante certificaciones mensuales según avance de obra, actualizable por índice UOCRA con mes base JULIO 2026. Para separar Agua y Cloaca se mantiene la proporción económica de la oferta aceptada: Agua $400.000.000 s/IVA y Cloaca $680.000.000 s/IVA. Esta distribución es un criterio interno de certificación y no modifica el valor original de cada red.
A26: Longitud PEAD Ø110 mm (ml) | B26: 1030
A27: Longitud total red (ml) | B27: 4200
A28: Conexiones sobre Ø75 (un) | B28: 165
A29: Conexiones sobre Ø110 (un) | B29: 62
A30: Total conexiones (un) | B30: 227 | D30: FUENTES DE REFERENCIA
A31: Válvulas Ø75 (un) | B31: 2 | D31: Documento | E31: Cotización ECAR SAS Loteo Roque.pdf
A32: Válvulas Ø100 (un) | B32: 4 | D32: Contrato | E32: Cláusula c) – saldo $374.400.000 IVA incluido / certificaciones mensuales
A33: Hidrantes (un) | B33: 15 | D33: Criterio ECAR | E33: Distribución proporcional Agua 37,037% / Cloaca 62,963%

Sheet Sectores
D3: Código | H3: Longitudes
B4: Pasaje 3 | C4: MzaA | D4: 1 | E4: N25 | F4: N30 | G4: =+CONCATENATE(E4,"-",F4) -> N25-N30 | H4: 76
B5: Pasaje 8 | C5: MzaA | D5: =+D4+1 -> 2 | E5: N30 | F5: N29 | G5: =+CONCATENATE(E5,"-",F5) -> N30-N29 | H5: 106
B6: Pasaje 4 | D6: =+D5+1 -> 3 | E6: N29 | F6: N22 | G6: =+CONCATENATE(E6,"-",F6) -> N29-N22 | H6: 92
B7: Pasaje 2 | C7: MzaA | D7: =+D6+1 -> 4 | E7: N22 | F7: N24 | G7: =+CONCATENATE(E7,"-",F7) -> N22-N24 | H7: 96
B8: Pasaje 2 | C8: MzaA | D8: =+D7+1 -> 5 | E8: N24 | F8: N25 | G8: =+CONCATENATE(E8,"-",F8) -> N24-N25 | H8: 15
B10: Pasaje 8 | C10: MzaB | D10: =+D8+1 -> 6 | E10: N29 | F10: N28 | G10: =+CONCATENATE(E10,"-",F10) -> N29-N28 | H10: 100
B11: Pasaje 5 | D11: =+D10+1 -> 7 | E11: N28 | F11: N21 | G11: =+CONCATENATE(E11,"-",F11) -> N28-N21 | H11: 102
B12: Pasaje 2 | C12: MzaB | D12: =+D11+1 -> 8 | E12: N20 | F12: N21 | G12: =+CONCATENATE(E12,"-",F12) -> N20-N21 | H12: 97
B13: Pasaje 2 | D13: =+D12+1 -> 9 | E13: N21 | F13: N22 | G13: =+CONCATENATE(E13,"-",F13) -> N21-N22 | H13: 2
B15: Pasaje 8 | C15: MzaC | D15: =+D13+1 -> 10 | E15: N28 | F15: N27 | G15: =+CONCATENATE(E15,"-",F15) -> N28-N27 | H15: 82
B16: Pasaje 6 | D16: =+D15+1 -> 11 | E16: N27 | F16: N19 | G16: =+CONCATENATE(E16,"-",F16) -> N27-N19 | H16: 117
B17: Pasaje 2 | C17: MzaC | D17: =+D16+1 -> 12 | E17: N19 | F17: N20 | G17: =+CONCATENATE(E17,"-",F17) -> N19-N20 | H17: 77
B19: Pasaje 8 | C19: MzaD | D19: 13 | E19: N27 | F19: N26 | G19: =+CONCATENATE(E19,"-",F19) -> N27-N26 | H19: 81
B20: Pasaje 7 | C20: MzaD | D20: 14 | E20: N26 | F20: N18 | G20: =+CONCATENATE(E20,"-",F20) -> N26-N18 | H20: 113
B21: Pasaje 2 | C21: MzaD | D21: 15 | E21: N18 | F21: N19 | G21: =+CONCATENATE(E21,"-",F21) -> N18-N19 | H21: 88
B23: Pasaje 3 | C23: Mza E | D23: 16 | E23: N13 | F23: N23 | G23: =+CONCATENATE(E23,"-",F23) -> N13-N23 | H23: 78
B24: Pasaje 3 | C24: Mza E | D24: 17 | E24: N23 | F24: N24 | G24: =+CONCATENATE(E24,"-",F24) -> N23-N24 | H24: 8
B25: Pasaje 5 | C25: Mza E | D25: 18 | E25: N20 | F25: N12 | G25: =+CONCATENATE(E25,"-",F25) -> N20-N12 | H25: 98
B26: Pasaje 9 | C26: Mza E | D26: 19 | E26: N12 | F26: N13 | G26: =+CONCATENATE(E26,"-",F26) -> N12-N13 | H26: 200
B28: Pasaje 14 | C28: F | D28: =+D26+1 -> 20 | E28: N18 | F28: N17 | G28: =+CONCATENATE(E28,"-",F28) -> N18-N17 | H28: 24
B29: Pasaje 9 | C29: F | D29: =+D28+1 -> 21 | E29: N17 | F29: N11 | G29: =+CONCATENATE(E29,"-",F29) -> N17-N11 | H29: 92
B30: Pasaje 9 | C30: F | D30: =+D29+1 -> 22 | E30: N11 | F30: N12 | G30: =+CONCATENATE(E30,"-",F30) -> N11-N12 | H30: 182
B32: Pasaje 2 | C32: G | D32: =+D30+1 -> 23 | E32: N17 | F32: N15 | G32: =+CONCATENATE(E32,"-",F32) -> N17-N15 | H32: 245
B33: Pasaje 2 | C33: G | D33: =+D32+1 -> 24 | E33: N16 | F33: N15 | G33: =+CONCATENATE(E33,"-",F33) -> N16-N15 | H33: 7
B34: Pasaje 2 | C34: G | D34: =+D33+1 -> 25 | E34: N15 | F34: N10 | G34: =+CONCATENATE(E34,"-",F34) -> N15-N10 | H34: 81
B35: Pasaje 2 | C35: G | D35: =+D34+1 -> 26 | E35: N10 | F35: N9 | G35: =+CONCATENATE(E35,"-",F35) -> N10-N9 | H35: 10
B36: Pasaje 2 | C36: G | D36: =+D35+1 -> 27 | E36: N9 | F36: N11 | G36: =+CONCATENATE(E36,"-",F36) -> N9-N11 | H36: 210
C38: H | D38: 27 | E38: N16 | F38: N14 | G38: =+CONCATENATE(E38,"-",F38) -> N16-N14 | H38: 136
C39: H | D39: =+D38+1 -> 28 | E39: N14 | F39: N8 | G39: =+CONCATENATE(E39,"-",F39) -> N14-N8 | H39: 110
C40: H | D40: =+D39+1 -> 29 | E40: N8 | F40: N10 | G40: =+CONCATENATE(E40,"-",F40) -> N8-N10 | H40: 140
C42: I | D42: =+D40+1 -> 30 | E42: N7 | F42: N11 | G42: =+CONCATENATE(E42,"-",F42) -> N7-N11 | H42: 80
C43: I | D43: =+D42+1 -> 31 | E43: N9 | F43: N6 | G43: =+CONCATENATE(E43,"-",F43) -> N9-N6 | H43: 91
C44: I | D44: =+D43+1 -> 32 | E44: N6 | F44: N5 | G44: =+CONCATENATE(E44,"-",F44) -> N6-N5 | H44: 10
C45: I | D45: =+D44+1 -> 33 | E45: N5 | F45: N7 | G45: =+CONCATENATE(E45,"-",F45) -> N5-N7 | H45: 188
C47: J | D47: =+D45+1 -> 34 | E47: N8 | F47: N4 | G47: =+CONCATENATE(E47,"-",F47) -> N8-N4 | H47: 118
C48: J | D48: =+D47+1 -> 35 | E48: N4 | F48: N6 | G48: =+CONCATENATE(E48,"-",F48) -> N4-N6 | H48: 167
C50: K | D50: =+D48+1 -> 36 | E50: N3 | F50: N7 | G50: =+CONCATENATE(E50,"-",F50) -> N3-N7 | H50: 64
C51: K | D51: =+D50+1 -> 37 | E51: N5 | F51: N2 | G51: =+CONCATENATE(E51,"-",F51) -> N5-N2 | H51: 55
C52: K | D52: =+D51+1 -> 38 | E52: N2 | F52: N3 | G52: =+CONCATENATE(E52,"-",F52) -> N2-N3 | H52: 190
C54: L | D54: =+D52+1 -> 39 | E54: N4 | F54: N1 | G54: =+CONCATENATE(E54,"-",F54) -> N4-N1 | H54: 82
C55: L | D55: =+D54+1 -> 40 | E55: N1 | F55: N2 | G55: =+CONCATENATE(E55,"-",F55) -> N1-N2 | H55: 165
C57: Garita SL | D57: =+D55+1 -> 41 | E57: N2 | F57: N32 | G57: =+CONCATENATE(E57,"-",F57) -> N2-N32 | H57: 40
C59: Garita Interna | D59: =+D57+1 -> 42 | E59: N23 | F59: N31 | G59: =+CONCATENATE(E59,"-",F59) -> N23-N31 | H59: 84
H61: =SUM(H4:H60) -> 4199

Sheet Presupuesto Base
A1: PRESUPUESTO BASE DE CERTIFICACIÓN – RED DE AGUA – VERSIÓN 2 AJUSTADA A CONTRATO
A4: Apertura interna del SALDO CERTIFICABLE de la Red de Agua. Las incidencias de la Versión 2 se mantienen y los P.U. se recalculan sobre el saldo de Agua asignado proporcionalmente al contrato.
A6: Ítem | B6: Descripción | C6: Unidad | D6: Cantidad contractual | E6: P.U. interno s/IVA | F6: Importe asignado s/IVA | G6: Incidencia
A7: 1 | B7: Replanteo y marcación de traza | C7: ml | D7: 4200 | E7: =IFERROR(F7/D7,0) -> 204.64384 | F7: =Configuracion!$B$18*G7 -> 859504.13 | G7: 0.0075
A8: 2 | B8: Excavación de zanja | C8: ml | D8: 4200 | E8: =IFERROR(F8/D8,0) -> 3683.5891 | F8: =Configuracion!$B$18*G8 -> 15471074 | G8: 0.135
A9: 3 | B9: Nivelación y conformación del fondo de zanja | C9: ml | D9: 4200 | E9: =IFERROR(F9/D9,0) -> 477.5023 | F9: =Configuracion!$B$18*G9 -> 2005509.6 | G9: 0.0175
A10: 4 | B10: Cama de asiento compactada | C10: ml | D10: 4200 | E10: =IFERROR(F10/D10,0) -> 1705.3653 | F10: =Configuracion!$B$18*G10 -> 7162534.4 | G10: 0.0625
A11: 5.1 | B11: PEAD PN10 Ø75 – provisión e instalación | C11: ml | D11: 3170 | E11: =IFERROR(F11/D11,0) -> 5784.2549 | F11: =Configuracion!$B$18*G11 -> 18336088 | G11: 0.16
A12: 5.2 | B12: PEAD PN10 Ø110 – provisión e instalación | C12: ml | D12: 1030 | E12: =IFERROR(F12/D12,0) -> 12238.894 | F12: =Configuracion!$B$18*G12 -> 12606061 | G12: 0.11
A13: 6 | B13: Ejecución de paquete estructural de 30 cm | C13: ml | D13: 4200 | E13: =IFERROR(F13/D13,0) -> 3274.3015 | F13: =Configuracion!$B$18*G13 -> 13752066 | G13: 0.12
A14: 7 | B14: Compactación del paquete estructural de 30 cm | C14: ml | D14: 4200 | E14: =IFERROR(F14/D14,0) -> 1227.863 | F14: =Configuracion!$B$18*G14 -> 5157024.8 | G14: 0.045
A15: 8 | B15: Ejecución y compactación de capa cota -0,60 | C15: ml | D15: 4200 | E15: =IFERROR(F15/D15,0) -> 2592.1553 | F15: =Configuracion!$B$18*G15 -> 10887052 | G15: 0.095
A16: 9 | B16: Ejecución y compactación de capa cota -0,30 | C16: ml | D16: 4200 | E16: =IFERROR(F16/D16,0) -> 2182.8676 | F16: =Configuracion!$B$18*G16 -> 9168044.1 | G16: 0.08
A17: 10.1 | B17: Conexión domiciliaria sobre red Ø75 | C17: un | D17: 165 | E17: =IFERROR(F17/D17,0) -> 48618.416 | F17: =Configuracion!$B$18*G17 -> 8022038.6 | G17: 0.07
A18: 10.2 | B18: Conexión domiciliaria sobre red Ø110 | C18: un | D18: 62 | E18: =IFERROR(F18/D18,0) -> 55451.879 | F18: =Configuracion!$B$18*G18 -> 3438016.5 | G18: 0.03
... A24: 13.3 | B24: Documentación conforme a obra y cierre | C24: gl | D24: 1 | E24: =IFERROR(F24/D24,0) -> 859504.13 | F24: =Configuracion!$B$18*G24 -> 859504.13 | G24: 0.0075
B25: TOTAL RED DE AGUA | F25: =SUM(F7:F24) -> 1.1460055e+08 | G25: =SUM(G7:G24) -> 1
A27: Control | B27: Resultado | C27: Estado
A28: Saldo certificable Agua s/IVA | B28: =Configuracion!B18 -> 1.1460055e+08 | C28: =IF(ABS(F25-B28)<1,"OK","REVISAR") -> OK
A29: Suma incidencias | B29: =SUM(G7:G24) -> 1 | C29: =IF(ABS(B29-1)<0.000001,"OK","REVISAR") -> OK

Sheet Medicion
A1: MEDICIÓN DE AVANCE – CARGA POR TRAMO Y ACTIVIDAD
A3: Cargar una fila por actividad medida. En la columna Ítem seleccionar el código del desplegable (por ejemplo 2, 5.1 o 10.2). La DESCRIPCIÓN, UNIDAD y P.U. se completan automáticamente. Para ítems globales 13.1 a 13.3 cargar una fracción entre 0 y 1.
A5: Cert. N° | B5: Fecha | C5: Código tramo | D5: Nodo inicial | E5: Nodo final | F5: Calle / sector | G5: Ítem | H5: Descripción | I5: Unidad | J5: Diámetro / tipo | K5: Cantidad medida | L5: P.U. s/IVA | M5: Importe s/IVA | N5: Estado OSSE | O5: Acta / inspección | P5: Observaciones | Q5: Estado Cert. | R5: Control histórico
A6: 1 | B6: 46262 | C6: =+CONCATENATE(D6,"-",E6) -> N30-N29 | D6: N30 | E6: N29 | F6: Pasaje 8 | G6: 1 | H6: =IF(G6="","",IFERROR(VLOOKUP(G6&"",'Presupuesto Base'!$A$7:$G$24,2,FALSE),"Ítem no encontrado")) -> Replanteo y marcación de traza | I6: =IF(G6="","",IFERROR(VLOOKUP(G6&"",'Presupuesto Base'!$A$7:$G$24,3,FALSE),"")) -> ml | K6: 106 | L6: =IF(G6="",0,IFERROR(VLOOKUP(G6&"",'Presupuesto Base'!$A$7:$G$24,5,FALSE),0)) -> 204.64384 | M6: =IFERROR(K6*L6,0) -> 21692.247 | Q6: =IFERROR(VLOOKUP(A6,'Historial Certificados'!$A$6:$E$29,5,FALSE),"") -> 0 | R6: =IF(A6="","",IF(Q6="CERRADO","CERTIFICADO CERRADO - NO MODIFICAR","ABIERTO")) -> ABIERTO
A7: 1 | B7: 46262 | C7: =+CONCATENATE(D7,"-",E7) -> N30-N25 | D7: N30 | E7: N25 | F7: Pasaje 3 | G7: 1 | H7: =IF(G7="","",IFERROR(VLOOKUP(G7&"",'Presupuesto Base'!$A$7:$G$24,2,FALSE),"Ítem no encontrado")) -> Replanteo y marcación de traza | I7: =IF(G7="","",IFERROR(VLOOKUP(G7&"",'Presupuesto Base'!$A$7:$G$24,3,FALSE),"")) -> ml | K7: 76 | L7: =IF(G7="",0,IFERROR(VLOOKUP(G7&"",'Presupuesto Base'!$A$7:$G$24,5,FALSE),0)) -> 204.64384 | M7: =IFERROR(K7*L7,0) -> 15552.932 | Q7: =IFERROR(VLOOKUP(A7,'Historial Certificados'!$A$6:$E$29,5,FALSE),"") -> 0 | R7: =IF(A7="","",IF(Q7="CERRADO","CERTIFICADO CERRADO - NO MODIFICAR","ABIERTO")) -> ABIERTO
A8: 1 | B8: 46262 | C8: =+CONCATENATE(D8,"-",E8) -> N25-N24 | D8: N25 | E8: N24 | F8: Pasaje 2 | G8: 1 | H8: =IF(G8="","",IFERROR(VLOOKUP(G8&"",'Presupuesto Base'!$A$7:$G$24,2,FALSE),"Ítem no encontrado")) -> Replanteo y marcación de traza | I8: =IF(G8="","",IFERROR(VLOOKUP(G8&"",'Presupuesto Base'!$A$7:$G$24,3,FALSE),"")) -> ml | K8: 15 | L8: =IF(G8="",0,IFERROR(VLOOKUP(G8&"",'Presupuesto Base'!$A$7:$G$24,5,FALSE),0)) -> 204.64384 | M8: =IFERROR(K8*L8,0) -> 3069.6576 | Q8: =IFERROR(VLOOKUP(A8,'Historial Certificados'!$A$6:$E$29,5,FALSE),"") -> 0 | R8: =IF(A8="","",IF(Q8="CERRADO","CERTIFICADO CERRADO - NO MODIFICAR","ABIERTO")) -> ABIERTO
A9: 1 | B9: 46262 | C9: =+CONCATENATE(D9,"-",E9) -> N24-N22 | D9: N24 | E9: N22 | F9: Pasaje 2 | G9: 1 | H9: =IF(G9="","",IFERROR(VLOOKUP(G9&"",'Presupuesto Base'!$A$7:$G$24,2,FALSE),"Ítem no encontrado")) -> Replanteo y marcación de traza | I9: =IF(G9="","",IFERROR(VLOOKUP(G9&"",'Presupuesto Base'!$A$7:$G$24,3,FALSE),"")) -> ml | K9: 96 | L9: =IF(G9="",0,IFERROR(VLOOKUP(G9&"",'Presupuesto Base'!$A$7:$G$24,5,FALSE),0)) -> 204.64384 | M9: =IFERROR(K9*L9,0) -> 19645.809 | Q9: =IFERROR(VLOOKUP(A9,'Historial Certificados'!$A$6:$E$29,5,FALSE),"") -> 0 | R9: =IF(A9="","",IF(Q9="CERRADO","CERTIFICADO CERRADO - NO MODIFICAR","ABIERTO")) -> ABIERTO
A10: 1 | B10: 46262 | C10: =+CONCATENATE(D10,"-",E10) -> N22-N29 | D10: N22 | E10: N29 | F10: Pasaje 4 | G10: 1 | H10: =IF(G10="","",IFERROR(VLOOKUP(G10&"",'Presupuesto Base'!$A$7:$G$24,2,FALSE),"Ítem no encontrado")) -> Replanteo y marcación de traza | I10: =IF(G10="","",IFERROR(VLOOKUP(G10&"",'Presupuesto Base'!$A$7:$G$24,3,FALSE),"")) -> ml | K10: 92 | L10: =IF(G10="",0,IFERROR(VLOOKUP(G10&"",'Presupuesto Base'!$A$7:$G$24,5,FALSE),0)) -> 204.64384 | M10: =IFERROR(K10*L10,0) -> 18827.233 | Q10: =IFERROR(VLOOKUP(A10,'Historial Certificados'!$A$6:$E$29,5,FALSE),"") -> 0 | R10: =IF(A10="","",IF(Q10="CERRADO","CERTIFICADO CERRADO - NO MODIFICAR","ABIERTO")) -> ABIERTO
A11: 1 | B11: 46262 | C11: =+CONCATENATE(D11,"-",E11) -> N22-N21 | D11: N22 | E11: N21 | F11: Pasaje 2 | G11: 1 | H11: =IF(G11="","",IFERROR(VLOOKUP(G11&"",'Presupuesto Base'!$A$7:$G$24,2,FALSE),"Ítem no encontrado")) -> Replanteo y marcación de traza | I11: =IF(G11="","",IFERROR(VLOOKUP(G11&"",'Presupuesto Base'!$A$7:$G$24,3,FALSE),"")) -> ml | K11: 97 | L11: =IF(G11="",0,IFERROR(VLOOKUP(G11&"",'Presupuesto Base'!$A$7:$G$24,5,FALSE),0)) -> 204.64384 | M11: =IFERROR(K11*L11,0) -> 19850.453 | Q11: =IFERROR(VLOOKUP(A11,'Historial Certificados'!$A$6:$E$29,5,FALSE),"") -> 0 | R11: =IF(A11="","",IF(Q11="CERRADO","CERTIFICADO CERRADO - NO MODIFICAR","ABIERTO")) -> ABIERTO
A12: 1 | B12: 46262 | C12: =+CONCATENATE(D12,"-",E12) -> N21-N20 | D12: N21 | E12: N20 | F12: Pasaje 2 | G12: 1 | H12: =IF(G12="","",IFERROR(VLOOKUP(G12&"",'Presupuesto Base'!$A$7:$G$24,2,FALSE),"Ítem no encontrado")) -> Replanteo y marcación de traza | I12: =IF(G12="","",IFERROR(VLOOKUP(G12&"",'Presupuesto Base'!$A$7:$G$24,3,FALSE),"")) -> ml | K12: 2 | L12: =IF(G12="",0,IFERROR(VLOOKUP(G12&"",'Presupuesto Base'!$A$7:$G$24,5,FALSE),0)) -> 204.64384 | M12: =IFERROR(K12*L12,0) -> 409.28768 | Q12: =IFERROR(VLOOKUP(A12,'Historial Certificados'!$A$6:$E$29,5,FALSE),"") -> 0 | R12: =IF(A12="","",IF(Q12="CERRADO","CERTIFICADO CERRADO - NO MODIFICAR","ABIERTO")) -> ABIERTO
A13: 1 | B13: 46262 | C13: =+CONCATENATE(D13,"-",E13) -> N20-N19 | D13: N20 | E13: N19 | F13: Pasaje 2 | G13: 1 | H13: =IF(G13="","",IFERROR(VLOOKUP(G13&"",'Presupuesto Base'!$A$7:$G$24,2,FALSE),"Ítem no encontrado")) -> Replanteo y marcación de traza | I13: =IF(G13="","",IFERROR(VLOOKUP(G13&"",'Presupuesto Base'!$A$7:$G$24,3,FALSE),"")) -> ml | K13: 77 | L13: =IF(G13="",0,IFERROR(VLOOKUP(G13&"",'Presupuesto Base'!$A$7:$G$24,5,FALSE),0)) -> 204.64384 | M13: =IFERROR(K13*L13,0) -> 15757.576 | Q13: =IFERROR(VLOOKUP(A13,'Historial Certificados'!$A$6:$E$29,5,FALSE),"") -> 0 | R13: =IF(A13="","",IF(Q13="CERRADO","CERTIFICADO CERRADO - NO MODIFICAR","ABIERTO")) -> ABIERTO
A14: 1 | B14: 46262 | C14: =+CONCATENATE(D14,"-",E14) -> N21-N28 | D14: N21 | E14: N28 | F14: Pasaje 5 | G14: 1 | H14: =IF(G14="","",IFERROR(VLOOKUP(G14&"",'Presupuesto Base'!$A$7:$G$24,2,FALSE),"Ítem no encontrado")) -> Replanteo y marcación de traza | I14: =IF(G14="","",IFERROR(VLOOKUP(G14&"",'Presupuesto Base'!$A$7:$G$24,3,FALSE),"")) -> ml | K14: 102 | L14: =IF(G14="",0,IFERROR(VLOOKUP(G14&"",'Presupuesto Base'!$A$7:$G$24,5,FALSE),0)) -> 204.64384 | M14: =IFERROR(K14*L14,0) -> 20873.672 | Q14: =IFERROR(VLOOKUP(A14,'Historial Certificados'!$A$6:$E$29,5,FALSE),"") -> 0 | R14: =IF(A14="","",IF(Q14="CERRADO","CERTIFICADO CERRADO - NO MODIFICAR","ABIERTO")) -> ABIERTO
A15: 1 | B15: 46262 | C15: =+CONCATENATE(D15,"-",E15) -> N29-N28 | D15: N29 | E15: N28 | F15: Pasaje 8 | G15: 1 | H15: =IF(G15="","",IFERROR(VLOOKUP(G15&"",'Presupuesto Base'!$A$7:$G$24,2,FALSE),"Ítem no encontrado")) -> Replanteo y marcación de traza | I15: =IF(G15="","",IFERROR(VLOOKUP(G15&"",'Presupuesto Base'!$A$7:$G$24,3,FALSE),"")) -> ml | K15: 100 | L15: =IF(G15="",0,IFERROR(VLOOKUP(G15&"",'Presupuesto Base'!$A$7:$G$24,5,FALSE),0)) -> 204.64384 | M15: =IFERROR(K15*L15,0) -> 20464.384
A16: 1 | B16: 46262 | C16: =+CONCATENATE(D16,"-",E16) -> N28-N27 | D16: N28 | E16: N27 | F16: Pasaje 8 | G16: 1 | H16: =IF(G16="","",IFERROR(VLOOKUP(G16&"",'Presupuesto Base'!$A$7:$G$24,2,FALSE),"Ítem no encontrado")) -> Replanteo y marcación de traza | I16: =IF(G16="","",IFERROR(VLOOKUP(G16&"",'Presupuesto Base'!$A$7:$G$24,3,FALSE),"")) -> ml | K16: 82 | L16: =IF(G16="",0,IFERROR(VLOOKUP(G16&"",'Presupuesto Base'!$A$7:$G$24,5,FALSE),0)) -> 204.64384 | M16: =IFERROR(K16*L16,0) -> 16780.795 | Q16: =IFERROR(VLOOKUP(A16,'Historial Certificados'!$A$6:$E$29,5,FALSE),"") -> 0 | R16: =IF(A16="","",IF(Q16="CERRADO","CERTIFICADO CERRADO - NO MODIFICAR","ABIERTO")) -> ABIERTO
A17: 1 | B17: 46262 | C17: =+CONCATENATE(D17,"-",E17) -> N30-N29 | D17: N30 | E17: N29 | F17: Pasaje 8 | G17: 2 | H17: =IF(G17="","",IFERROR(VLOOKUP(G17&"",'Presupuesto Base'!$A$7:$G$24,2,FALSE),"Ítem no encontrado")) -> Excavación de zanja | I17: =IF(G17="","",IFERROR(VLOOKUP(G17&"",'Presupuesto Base'!$A$7:$G$24,3,FALSE),"")) -> ml | K17: 106 | L17: =IF(G17="",0,IFERROR(VLOOKUP(G17&"",'Presupuesto Base'!$A$7:$G$24,5,FALSE),0)) -> 3683.5891 | M17: =IFERROR(K17*L17,0) -> 390460.45 | Q17: =IFERROR(VLOOKUP(A17,'Historial Certificados'!$A$6:$E$29,5,FALSE),"") -> 0 | R17: =IF(A17="","",IF(Q17="CERRADO","CERTIFICADO CERRADO - NO MODIFICAR","ABIERTO")) -> ABIERTO
A18: 1 | B18: 46262 | C18: =+CONCATENATE(D18,"-",E18) -> N30-N25 | D18: N30 | E18: N25 | F18: Pasaje 3 | G18: 2 | H18: =IF(G18="","",IFERROR(VLOOKUP(G18&"",'Presupuesto Base'!$A$7:$G$24,2,FALSE),"Ítem no encontrado")) -> Excavación de zanja | I18: =IF(G18="","",IFERROR(VLOOKUP(G18&"",'Presupuesto Base'!$A$7:$G$24,3,FALSE),"")) -> ml | K18: 76 | L18: =IF(G18="",0,IFERROR(VLOOKUP(G18&"",'Presupuesto Base'!$A$7:$G$24,5,FALSE),0)) -> 3683.5891 | M18: =IFERROR(K18*L18,0) -> 279952.77 | Q18: =IFERROR(VLOOKUP(A18,'Historial Certificados'!$A$6:$E$29,5,FALSE),"") -> 0 | R18: =IF(A18="","",IF(Q18="CERRADO","CERTIFICADO CERRADO - NO MODIFICAR","ABIERTO")) -> ABIERTO
A19: 1 | B19: 46262 | C19: =+CONCATENATE(D19,"-",E19) -> N25-N24 | D19: N25 | E19: N24 | F19: Pasaje 2 | G19: 2 | H19: =IF(G19="","",IFERROR(VLOOKUP(G19&"",'Presupuesto Base'!$A$7:$G$24,2,FALSE),"Ítem no encontrado")) -> Excavación de zanja | I19: =IF(G19="","",IFERROR(VLOOKUP(G19&"",'Presupuesto Base'!$A$7:$G$24,3,FALSE),"")) -> ml | K19: 15 | L19: =IF(G19="",0,IFERROR(VLOOKUP(G19&"",'Presupuesto Base'!$A$7:$G$24,5,FALSE),0)) -> 3683.5891 | M19: =IFERROR(K19*L19,0) -> 55253.837 | Q19: =IFERROR(VLOOKUP(A19,'Historial Certificados'!$A$6:$E$29,5,FALSE),"") -> 0 | R19: =IF(A19="","",IF(Q19="CERRADO","CERTIFICADO CERRADO - NO MODIFICAR","ABIERTO")) -> ABIERTO
A20: 1 | B20: 46262 | C20: =+CONCATENATE(D20,"-",E20) -> N24-N22 | D20: N24 | E20: N22 | F20: Pasaje 2 | G20: 2 | H20: =IF(G20="","",IFERROR(VLOOKUP(G20&"",'Presupuesto Base'!$A$7:$G$24,2,FALSE),"Ítem no encontrado")) -> Excavación de zanja | I20: =IF(G20="","",IFERROR(VLOOKUP(G20&"",'Presupuesto Base'!$A$7:$G$24,3,FALSE),"")) -> ml | K20: 96 | L20: =IF(G20="",0,IFERROR(VLOOKUP(G20&"",'Presupuesto Base'!$A$7:$G$24,5,FALSE),0)) -> 3683.5891 | M20: =IFERROR(K20*L20,0) -> 353624.56 | Q20: =IFERROR(VLOOKUP(A20,'Historial Certificados'!$A$6:$E$29,5,FALSE),"") -> 0 | R20: =IF(A20="","",IF(Q20="CERRADO","CERTIFICADO CERRADO - NO MODIFICAR","ABIERTO")) -> ABIERTO
A21: 1 | B21: 46262 | C21: =+CONCATENATE(D21,"-",E21) -> N22-N29 | D21: N22 | E21: N29 | F21: Pasaje 4 | G21: 2 | H21: =IF(G21="","",IFERROR(VLOOKUP(G21&"",'Presupuesto Base'!$A$7:$G$24,2,FALSE),"Ítem no encontrado")) -> Excavación de zanja | I21: =IF(G21="","",IFERROR(VLOOKUP(G21&"",'Presupuesto Base'!$A$7:$G$24,3,FALSE),"")) -> ml | K21: 92 | L21: =IF(G21="",0,IFERROR(VLOOKUP(G21&"",'Presupuesto Base'!$A$7:$G$24,5,FALSE),0)) -> 3683.5891 | M21: =IFERROR(K21*L21,0) -> 338890.2 | Q21: =IFERROR(VLOOKUP(A21,'Historial Certificados'!$A$6:$E$29,5,FALSE),"") -> 0 | R21: =IF(A21="","",IF(Q21="CERRADO","CERTIFICADO CERRADO - NO MODIFICAR","ABIERTO")) -> ABIERTO
A22: 1 | B22: 46262 | C22: =+CONCATENATE(D22,"-",E22) -> N22-N21 | D22: N22 | E22: N21 | F22: Pasaje 2 | G22: 2 | H22: =IF(G22="","",IFERROR(VLOOKUP(G22&"",'Presupuesto Base'!$A$7:$G$24,2,FALSE),"Ítem no encontrado")) -> Excavación de zanja | I22: =IF(G22="","",IFERROR(VLOOKUP(G22&"",'Presupuesto Base'!$A$7:$G$24,3,FALSE),"")) -> ml | K22: 97 | L22: =IF(G22="",0,IFERROR(VLOOKUP(G22&"",'Presupuesto Base'!$A$7:$G$24,5,FALSE),0)) -> 3683.5891 | M22: =IFERROR(K22*L22,0) -> 357308.15 | Q22: =IFERROR(VLOOKUP(A22,'Historial Certificados'!$A$6:$E$29,5,FALSE),"") -> 0 | R22: =IF(A22="","",IF(Q22="CERRADO","CERTIFICADO CERRADO - NO MODIFICAR","ABIERTO")) -> ABIERTO
A23: 1 | B23: 46262 | C23: =+CONCATENATE(D23,"-",E23) -> N21-N20 | D23: N21 | E23: N20 | F23: Pasaje 2 | G23: 2 | H23: =IF(G23="","",IFERROR(VLOOKUP(G23&"",'Presupuesto Base'!$A$7:$G$24,2,FALSE),"Ítem no encontrado")) -> Excavación de zanja | I23: =IF(G23="","",IFERROR(VLOOKUP(G23&"",'Presupuesto Base'!$A$7:$G$24,3,FALSE),"")) -> ml | K23: 2 | L23: =IF(G23="",0,IFERROR(VLOOKUP(G23&"",'Presupuesto Base'!$A$7:$G$24,5,FALSE),0)) -> 3683.5891 | M23: =IFERROR(K23*L23,0) -> 7367.1783 | Q23: =IFERROR(VLOOKUP(A23,'Historial Certificados'!$A$6:$E$29,5,FALSE),"") -> 0 | R23: =IF(A23="","",IF(Q23="CERRADO","CERTIFICADO CERRADO - NO MODIFICAR","ABIERTO")) -> ABIERTO
A24: 1 | B24: 46262 | C24: =+CONCATENATE(D24,"-",E24) -> N20-N19 | D24: N20 | E24: N19 | F24: Pasaje 2 | G24: 2 | H24: =IF(G24="","",IFERROR(VLOOKUP(G24&"",'Presupuesto Base'!$A$7:$G$24,2,FALSE),"Ítem no encontrado")) -> Excavación de zanja | I24: =IF(G24="","",IFERROR(VLOOKUP(G24&"",'Presupuesto Base'!$A$7:$G$24,3,FALSE),"")) -> ml | K24: 77 | L24: =IF(G24="",0,IFERROR(VLOOKUP(G24&"",'Presupuesto Base'!$A$7:$G$24,5,FALSE),0)) -> 3683.5891 | M24: =IFERROR(K24*L24,0) -> 283636.36 | Q24: =IFERROR(VLOOKUP(A24,'Historial Certificados'!$A$6:$E$29,5,FALSE),"") -> 0 | R24: =IF(A24="","",IF(Q24="CERRADO","CERTIFICADO CERRADO - NO MODIFICAR","ABIERTO")) -> ABIERTO
A25: 1 | B25: 46262 | C25: =+CONCATENATE(D25,"-",E25) -> N21-N28 | D25: N21 | E25: N28 | F25: Pasaje 5 | G25: 2 | H25: =IF(G25="","",IFERROR(VLOOKUP(G25&"",'Presupuesto Base'!$A$7:$G$24,2,FALSE),"Ítem no encontrado")) -> Excavación de zanja | I25: =IF(G25="","",IFERROR(VLOOKUP(G25&"",'Presupuesto Base'!$A$7:$G$24,3,FALSE),"")) -> ml | K25: 102 | L25: =IF(G25="",0,IFERROR(VLOOKUP(G25&"",'Presupuesto Base'!$A$7:$G$24,5,FALSE),0)) -> 3683.5891 | M25: =IFERROR(K25*L25,0) -> 375726.09 | Q25: =IFERROR(VLOOKUP(A25,'Historial Certificados'!$A$6:$E$29,5,FALSE),"") -> 0 | R25: =IF(A25="","",IF(Q25="CERRADO","CERTIFICADO CERRADO - NO MODIFICAR","ABIERTO")) -> ABIERTO
A26: 1 | B26: 46262 | C26: =+CONCATENATE(D26,"-",E26) -> N29-N28 | D26: N29 | E26: N28 | F26: Pasaje 8 | G26: 2 | H26: =IF(G26="","",IFERROR(VLOOKUP(G26&"",'Presupuesto Base'!$A$7:$G$24,2,FALSE),"Ítem no encontrado")) -> Excavación de zanja | I26: =IF(G26="","",IFERROR(VLOOKUP(G26&"",'Presupuesto Base'!$A$7:$G$24,3,FALSE),"")) -> ml | K26: 100 | L26: =IF(G26="",0,IFERROR(VLOOKUP(G26&"",'Presupuesto Base'!$A$7:$G$24,5,FALSE),0)) -> 3683.5891 | M26: =IFERROR(K26*L26,0) -> 368358.91
A27: 1 | B27: 46262 | C27: =+CONCATENATE(D27,"-",E27) -> N28-N27 | D27: N28 | E27: N27 | F27: Pasaje 8 | G27: 2 | H27: =IF(G27="","",IFERROR(VLOOKUP(G27&"",'Presupuesto Base'!$A$7:$G$24,2,FALSE),"Ítem no encontrado")) -> Excavación de zanja | I27: =IF(G27="","",IFERROR(VLOOKUP(G27&"",'Presupuesto Base'!$A$7:$G$24,3,FALSE),"")) -> ml | K27: 82 | L27: =IF(G27="",0,IFERROR(VLOOKUP(G27&"",'Presupuesto Base'!$A$7:$G$24,5,FALSE),0)) -> 3683.5891 | M27: =IFERROR(K27*L27,0) -> 302054.31 | Q27: =IFERROR(VLOOKUP(A27,'Historial Certificados'!$A$6:$E$29,5,FALSE),"") -> 0 | R27: =IF(A27="","",IF(Q27="CERRADO","CERTIFICADO CERRADO - NO MODIFICAR","ABIERTO")) -> ABIERTO
A28: 1 | B28: 46262 | C28: =+CONCATENATE(D28,"-",E28) -> N30-N29 | D28: N30 | E28: N29 | F28: Pasaje 8 | G28: 3 | H28: =IF(G28="","",IFERROR(VLOOKUP(G28&"",'Presupuesto Base'!$A$7:$G$24,2,FALSE),"Ítem no encontrado")) -> Nivelación y conformación del fondo de zanja | I28: =IF(G28="","",IFERROR(VLOOKUP(G28&"",'Presupuesto Base'!$A$7:$G$24,3,FALSE),"")) -> ml | K28: 106 | L28: =IF(G28="",0,IFERROR(VLOOKUP(G28&"",'Presupuesto Base'!$A$7:$G$24,5,FALSE),0)) -> 477.5023 | M28: =IFERROR(K28*L28,0) -> 50615.243 | Q28: =IFERROR(VLOOKUP(A28,'Historial Certificados'!$A$6:$E$29,5,FALSE),"") -> 0 | R28: =IF(A28="","",IF(Q28="CERRADO","CERTIFICADO CERRADO - NO MODIFICAR","ABIERTO")) -> ABIERTO
A29: 1 | B29: 46262 | C29: =+CONCATENATE(D29,"-",E29) -> N30-N25 | D29: N30 | E29: N25 | F29: Pasaje 3 | G29: 3 | H29: =IF(G29="","",IFERROR(VLOOKUP(G29&"",'Presupuesto Base'!$A$7:$G$24,2,FALSE),"Ítem no encontrado")) -> Nivelación y conformación del fondo de zanja | I29: =IF(G29="","",IFERROR(VLOOKUP(G29&"",'Presupuesto Base'!$A$7:$G$24,3,FALSE),"")) -> ml | K29: 76 | L29: =IF(G29="",0,IFERROR(VLOOKUP(G29&"",'Presupuesto Base'!$A$7:$G$24,5,FALSE),0)) -> 477.5023 | M29: =IFERROR(K29*L29,0) -> 36290.174 | Q29: =IFERROR(VLOOKUP(A29,'Historial Certificados'!$A$6:$E$29,5,FALSE),"") -> 0 | R29: =IF(A29="","",IF(Q29="CERRADO","CERTIFICADO CERRADO - NO MODIFICAR","ABIERTO")) -> ABIERTO
A30: 1 | B30: 46262 | C30: =+CONCATENATE(D30,"-",E30) -> N25-N24 | D30: N25 | E30: N24 | F30: Pasaje 2 | G30: 3 | H30: =IF(G30="","",IFERROR(VLOOKUP(G30&"",'Presupuesto Base'!$A$7:$G$24,2,FALSE),"Ítem no encontrado")) -> Nivelación y conformación del fondo de zanja | I30: =IF(G30="","",IFERROR(VLOOKUP(G30&"",'Presupuesto Base'!$A$7:$G$24,3,FALSE),"")) -> ml | K30: 15 | L30: =IF(G30="",0,IFERROR(VLOOKUP(G30&"",'Presupuesto Base'!$A$7:$G$24,5,FALSE),0)) -> 477.5023 | M30: =IFERROR(K30*L30,0) -> 7162.5344 | Q30: =IFERROR(VLOOKUP(A30,'Historial Certificados'!$A$6:$E$29,5,FALSE),"") -> 0 | R30: =IF(A30="","",IF(Q30="CERRADO","CERTIFICADO CERRADO - NO MODIFICAR","ABIERTO")) -> ABIERTO
A31: 1 | B31: 46262 | C31: =+CONCATENATE(D31,"-",E31) -> N24-N22 | D31: N24 | E31: N22 | F31: Pasaje 2 | G31: 3 | H31: =IF(G31="","",IFERROR(VLOOKUP(G31&"",'Presupuesto Base'!$A$7:$G$24,2,FALSE),"Ítem no encontrado")) -> Nivelación y conformación del fondo de zanja | I31: =IF(G31="","",IFERROR(VLOOKUP(G31&"",'Presupuesto Base'!$A$7:$G$24,3,FALSE),"")) -> ml | K31: 96 | L31: =IF(G31="",0,IFERROR(VLOOKUP(G31&"",'Presupuesto Base'!$A$7:$G$24,5,FALSE),0)) -> 477.5023 | M31: =IFERROR(K31*L31,0) -> 45840.22 | Q31: =IFERROR(VLOOKUP(A31,'Historial Certificados'!$A$6:$E$29,5,FALSE),"") -> 0 | R31: =IF(A31="","",IF(Q31="CERRADO","CERTIFICADO CERRADO - NO MODIFICAR","ABIERTO")) -> ABIERTO
A32: 1 | B32: 46262 | C32: =+CONCATENATE(D32,"-",E32) -> N22-N29 | D32: N22 | E32: N29 | F32: Pasaje 4 | G32: 3 | H32: =IF(G32="","",IFERROR(VLOOKUP(G32&"",'Presupuesto Base'!$A$7:$G$24,2,FALSE),"Ítem no encontrado")) -> Nivelación y conformación del fondo de zanja | I32: =IF(G32="","",IFERROR(VLOOKUP(G32&"",'Presupuesto Base'!$A$7:$G$24,3,FALSE),"")) -> ml | K32: 92 | L32: =IF(G32="",0,IFERROR(VLOOKUP(G32&"",'Presupuesto Base'!$A$7:$G$24,5,FALSE),0)) -> 477.5023 | M32: =IFERROR(K32*L32,0) -> 43930.211 | Q32: =IFERROR(VLOOKUP(A32,'Historial Certificados'!$A$6:$E$29,5,FALSE),"") -> 0 | R32: =IF(A32="","",IF(Q32="CERRADO","CERTIFICADO CERRADO - NO MODIFICAR","ABIERTO")) -> ABIERTO
A33: 1 | B33: 46262 | C33: =+CONCATENATE(D33,"-",E33) -> N22-N21 | D33: N22 | E33: N21 | F33: Pasaje 2 | G33: 3 | H33: =IF(G33="","",IFERROR(VLOOKUP(G33&"",'Presupuesto Base'!$A$7:$G$24,2,FALSE),"Ítem no encontrado")) -> Nivelación y conformación del fondo de zanja | I33: =IF(G33="","",IFERROR(VLOOKUP(G33&"",'Presupuesto Base'!$A$7:$G$24,3,FALSE),"")) -> ml | K33: 97 | L33: =IF(G33="",0,IFERROR(VLOOKUP(G33&"",'Presupuesto Base'!$A$7:$G$24,5,FALSE),0)) -> 477.5023 | M33: =IFERROR(K33*L33,0) -> 46317.723 | Q33: =IFERROR(VLOOKUP(A33,'Historial Certificados'!$A$6:$E$29,5,FALSE),"") -> 0 | R33: =IF(A33="","",IF(Q33="CERRADO","CERTIFICADO CERRADO - NO MODIFICAR","ABIERTO")) -> ABIERTO
A34: 1 | B34: 46262 | C34: =+CONCATENATE(D34,"-",E34) -> N21-N20 | D34: N21 | E34: N20 | F34: Pasaje 2 | G34: 3 | H34: =IF(G34="","",IFERROR(VLOOKUP(G34&"",'Presupuesto Base'!$A$7:$G$24,2,FALSE),"Ítem no encontrado")) -> Nivelación y conformación del fondo de zanja | I34: =IF(G34="","",IFERROR(VLOOKUP(G34&"",'Presupuesto Base'!$A$7:$G$24,3,FALSE),"")) -> ml | K34: 2 | L34: =IF(G34="",0,IFERROR(VLOOKUP(G34&"",'Presupuesto Base'!$A$7:$G$24,5,FALSE),0)) -> 477.5023 | M34: =IFERROR(K34*L34,0) -> 955.00459 | Q34: =IFERROR(VLOOKUP(A34,'Historial Certificados'!$A$6:$E$29,5,FALSE),"") -> 0 | R34: =IF(A34="","",IF(Q34="CERRADO","CERTIFICADO CERRADO - NO MODIFICAR","ABIERTO")) -> ABIERTO
A35: 1 | B35: 46262 | C35: =+CONCATENATE(D35,"-",E35) -> N20-N19 | D35: N20 | E35: N19 | F35: Pasaje 2 | G35: 3 | H35: =IF(G35="","",IFERROR(VLOOKUP(G35&"",'Presupuesto Base'!$A$7:$G$24,2,FALSE),"Ítem no encontrado")) -> Nivelación y conformación del fondo de zanja | I35: =IF(G35="","",IFERROR(VLOOKUP(G35&"",'Presupuesto Base'!$A$7:$G$24,3,FALSE),"")) -> ml | K35: 77 | L35: =IF(G35="",0,IFERROR(VLOOKUP(G35&"",'Presupuesto Base'!$A$7:$G$24,5,FALSE),0)) -> 477.5023 | M35: =IFERROR(K35*L35,0) -> 36767.677 | Q35: =IFERROR(VLOOKUP(A35,'Historial Certificados'!$A$6:$E$29,5,FALSE),"") -> 0 | R35: =IF(A35="","",IF(Q35="CERRADO","CERTIFICADO CERRADO - NO MODIFICAR","ABIERTO")) -> ABIERTO
A36: 1 | B36: 46262 | C36: =+CONCATENATE(D36,"-",E36) -> N21-N28 | D36: N21 | E36: N28 | F36: Pasaje 5 | G36: 3 | H36: =IF(G36="","",IFERROR(VLOOKUP(G36&"",'Presupuesto Base'!$A$7:$G$24,2,FALSE),"Ítem no encontrado")) -> Nivelación y conformación del fondo de zanja | I36: =IF(G36="","",IFERROR(VLOOKUP(G36&"",'Presupuesto Base'!$A$7:$G$24,3,FALSE),"")) -> ml | K36: 102 | L36: =IF(G36="",0,IFERROR(VLOOKUP(G36&"",'Presupuesto Base'!$A$7:$G$24,5,FALSE),0)) -> 477.5023 | M36: =IFERROR(K36*L36,0) -> 48705.234 | Q36: =IFERROR(VLOOKUP(A36,'Historial Certificados'!$A$6:$E$29,5,FALSE),"") -> 0 | R36: =IF(A36="","",IF(Q36="CERRADO","CERTIFICADO CERRADO - NO MODIFICAR","ABIERTO")) -> ABIERTO
A37: 1 | B37: 46262 | C37: =+CONCATENATE(D37,"-",E37) -> N29-N28 | D37: N29 | E37: N28 | F37: Pasaje 8 | G37: 3 | H37: =IF(G37="","",IFERROR(VLOOKUP(G37&"",'Presupuesto Base'!$A$7:$G$24,2,FALSE),"Ítem no encontrado")) -> Nivelación y conformación del fondo de zanja | I37: =IF(G37="","",IFERROR(VLOOKUP(G37&"",'Presupuesto Base'!$A$7:$G$24,3,FALSE),"")) -> ml | K37: 100 | L37: =IF(G37="",0,IFERROR(VLOOKUP(G37&"",'Presupuesto Base'!$A$7:$G$24,5,FALSE),0)) -> 477.5023 | M37: =IFERROR(K37*L37,0) -> 47750.23
A38: 1 | B38: 46262 | C38: =+CONCATENATE(D38,"-",E38) -> N28-N27 | D38: N28 | E38: N27 | F38: Pasaje 8 | G38: 3 | H38: =IF(G38="","",IFERROR(VLOOKUP(G38&"",'Presupuesto Base'!$A$7:$G$24,2,FALSE),"Ítem no encontrado")) -> Nivelación y conformación del fondo de zanja | I38: =IF(G38="","",IFERROR(VLOOKUP(G38&"",'Presupuesto Base'!$A$7:$G$24,3,FALSE),"")) -> ml | K38: 82 | L38: =IF(G38="",0,IFERROR(VLOOKUP(G38&"",'Presupuesto Base'!$A$7:$G$24,5,FALSE),0)) -> 477.5023 | M38: =IFERROR(K38*L38,0) -> 39155.188 | Q38: =IFERROR(VLOOKUP(A38,'Historial Certificados'!$A$6:$E$29,5,FALSE),"") -> 0 | R38: =IF(A38="","",IF(Q38="CERRADO","CERTIFICADO CERRADO - NO MODIFICAR","ABIERTO")) -> ABIERTO
A39: 1 | B39: 46262 | C39: =+CONCATENATE(D39,"-",E39) -> N30-N29 | D39: N30 | E39: N29 | F39: Pasaje 8 | G39: 4 | H39: =IF(G39="","",IFERROR(VLOOKUP(G39&"",'Presupuesto Base'!$A$7:$G$24,2,FALSE),"Ítem no encontrado")) -> Cama de asiento compactada | I39: =IF(G39="","",IFERROR(VLOOKUP(G39&"",'Presupuesto Base'!$A$7:$G$24,3,FALSE),"")) -> ml | K39: 106 | L39: =IF(G39="",0,IFERROR(VLOOKUP(G39&"",'Presupuesto Base'!$A$7:$G$24,5,FALSE),0)) -> 1705.3653 | M39: =IFERROR(K39*L39,0) -> 180768.73 | Q39: =IFERROR(VLOOKUP(A39,'Historial Certificados'!$A$6:$E$29,5,FALSE),"") -> 0 | R39: =IF(A39="","",IF(Q39="CERRADO","CERTIFICADO CERRADO - NO MODIFICAR","ABIERTO")) -> ABIERTO
A40: 1 | B40: 46262 | C40: =+CONCATENATE(D40,"-",E40) -> N30-N25 | D40: N30 | E40: N25 | F40: Pasaje 3 | G40: 4 | H40: =IF(G40="","",IFERROR(VLOOKUP(G40&"",'Presupuesto Base'!$A$7:$G$24,2,FALSE),"Ítem no encontrado")) -> Cama de asiento compactada | I40: =IF(G40="","",IFERROR(VLOOKUP(G40&"",'Presupuesto Base'!$A$7:$G$24,3,FALSE),"")) -> ml | K40: 76 | L40: =IF(G40="",0,IFERROR(VLOOKUP(G40&"",'Presupuesto Base'!$A$7:$G$24,5,FALSE),0)) -> 1705.3653 | M40: =IFERROR(K40*L40,0) -> 129607.77 | Q40: =IFERROR(VLOOKUP(A40,'Historial Certificados'!$A$6:$E$29,5,FALSE),"") -> 0 | R40: =IF(A40="","",IF(Q40="CERRADO","CERTIFICADO CERRADO - NO MODIFICAR","ABIERTO")) -> ABIERTO
A41: 1 | B41: 46262 | C41: =+CONCATENATE(D41,"-",E41) -> N25-N24 | D41: N25 | E41: N24 | F41: Pasaje 2 | G41: 4 | H41: =IF(G41="","",IFERROR(VLOOKUP(G41&"",'Presupuesto Base'!$A$7:$G$24,2,FALSE),"Ítem no encontrado")) -> Cama de asiento compactada | I41: =IF(G41="","",IFERROR(VLOOKUP(G41&"",'Presupuesto Base'!$A$7:$G$24,3,FALSE),"")) -> ml | K41: 15 | L41: =IF(G41="",0,IFERROR(VLOOKUP(G41&"",'Presupuesto Base'!$A$7:$G$24,5,FALSE),0)) -> 1705.3653 | M41: =IFERROR(K41*L41,0) -> 25580.48 | Q41: =IFERROR(VLOOKUP(A41,'Historial Certificados'!$A$6:$E$29,5,FALSE),"") -> 0 | R41: =IF(A41="","",IF(Q41="CERRADO","CERTIFICADO CERRADO - NO MODIFICAR","ABIERTO")) -> ABIERTO
A42: 1 | B42: 46262 | C42: =+CONCATENATE(D42,"-",E42) -> N24-N22 | D42: N24 | E42: N22 | F42: Pasaje 2 | G42: 4 | H42: =IF(G42="","",IFERROR(VLOOKUP(G42&"",'Presupuesto Base'!$A$7:$G$24,2,FALSE),"Ítem no encontrado")) -> Cama de asiento compactada | I42: =IF(G42="","",IFERROR(VLOOKUP(G42&"",'Presupuesto Base'!$A$7:$G$24,3,FALSE),"")) -> ml | K42: 96 | L42: =IF(G42="",0,IFERROR(VLOOKUP(G42&"",'Presupuesto Base'!$A$7:$G$24,5,FALSE),0)) -> 1705.3653 | M42: =IFERROR(K42*L42,0) -> 163715.07 | Q42: =IFERROR(VLOOKUP(A42,'Historial Certificados'!$A$6:$E$29,5,FALSE),"") -> 0 | R42: =IF(A42="","",IF(Q42="CERRADO","CERTIFICADO CERRADO - NO MODIFICAR","ABIERTO")) -> ABIERTO
A43: 1 | B43: 46262 | C43: =+CONCATENATE(D43,"-",E43) -> N22-N29 | D43: N22 | E43: N29 | F43: Pasaje 4 | G43: 4 | H43: =IF(G43="","",IFERROR(VLOOKUP(G43&"",'Presupuesto Base'!$A$7:$G$24,2,FALSE),"Ítem no encontrado")) -> Cama de asiento compactada | I43: =IF(G43="","",IFERROR(VLOOKUP(G43&"",'Presupuesto Base'!$A$7:$G$24,3,FALSE),"")) -> ml | K43: 92 | L43: =IF(G43="",0,IFERROR(VLOOKUP(G43&"",'Presupuesto Base'!$A$7:$G$24,5,FALSE),0)) -> 1705.3653 | M43: =IFERROR(K43*L43,0) -> 156893.61 | Q43: =IFERROR(VLOOKUP(A43,'Historial Certificados'!$A$6:$E$29,5,FALSE),"") -> 0 | R43: =IF(A43="","",IF(Q43="CERRADO","CERTIFICADO CERRADO - NO MODIFICAR","ABIERTO")) -> ABIERTO
A44: 1 | B44: 46262 | C44: =+CONCATENATE(D44,"-",E44) -> N22-N21 | D44: N22 | E44: N21 | F44: Pasaje 2 | G44: 4 | H44: =IF(G44="","",IFERROR(VLOOKUP(G44&"",'Presupuesto Base'!$A$7:$G$24,2,FALSE),"Ítem no encontrado")) -> Cama de asiento compactada | I44: =IF(G44="","",IFERROR(VLOOKUP(G44&"",'Presupuesto Base'!$A$7:$G$24,3,FALSE),"")) -> ml | K44: 97 | L44: =IF(G44="",0,IFERROR(VLOOKUP(G44&"",'Presupuesto Base'!$A$7:$G$24,5,FALSE),0)) -> 1705.3653 | M44: =IFERROR(K44*L44,0) -> 165420.44 | Q44: =IFERROR(VLOOKUP(A44,'Historial Certificados'!$A$6:$E$29,5,FALSE),"") -> 0 | R44: =IF(A44="","",IF(Q44="CERRADO","CERTIFICADO CERRADO - NO MODIFICAR","ABIERTO")) -> ABIERTO
A45: 1 | B45: 46262 | C45: =+CONCATENATE(D45,"-",E45) -> N21-N20 | D45: N21 | E45: N20 | F45: Pasaje 2 | G45: 4 | H45: =IF(G45="","",IFERROR(VLOOKUP(G45&"",'Presupuesto Base'!$A$7:$G$24,2,FALSE),"Ítem no encontrado")) -> Cama de asiento compactada | I45: =IF(G45="","",IFERROR(VLOOKUP(G45&"",'Presupuesto Base'!$A$7:$G$24,3,FALSE),"")) -> ml | K45: 2 | L45: =IF(G45="",0,IFERROR(VLOOKUP(G45&"",'Presupuesto Base'!$A$7:$G$24,5,FALSE),0)) -> 1705.3653 | M45: =IFERROR(K45*L45,0) -> 3410.7307 | Q45: =IFERROR(VLOOKUP(A45,'Historial Certificados'!$A$6:$E$29,5,FALSE),"") -> 0 | R45: =IF(A45="","",IF(Q45="CERRADO","CERTIFICADO CERRADO - NO MODIFICAR","ABIERTO")) -> ABIERTO
A46: 1 | B46: 46262 | C46: =+CONCATENATE(D46,"-",E46) -> N20-N19 | D46: N20 | E46: N19 | F46: Pasaje 2 | G46: 4 | H46: =IF(G46="","",IFERROR(VLOOKUP(G46&"",'Presupuesto Base'!$A$7:$G$24,2,FALSE),"Ítem no encontrado")) -> Cama de asiento compactada | I46: =IF(G46="","",IFERROR(VLOOKUP(G46&"",'Presupuesto Base'!$A$7:$G$24,3,FALSE),"")) -> ml | K46: 77 | L46: =IF(G46="",0,IFERROR(VLOOKUP(G46&"",'Presupuesto Base'!$A$7:$G$24,5,FALSE),0)) -> 1705.3653 | M46: =IFERROR(K46*L46,0) -> 131313.13 | Q46: =IFERROR(VLOOKUP(A46,'Historial Certificados'!$A$6:$E$29,5,FALSE),"") -> 0 | R46: =IF(A46="","",IF(Q46="CERRADO","CERTIFICADO CERRADO - NO MODIFICAR","ABIERTO")) -> ABIERTO
A47: 1 | B47: 46262 | C47: =+CONCATENATE(D47,"-",E47) -> N21-N28 | D47: N21 | E47: N28 | F47: Pasaje 5 | G47: 4 | H47: =IF(G47="","",IFERROR(VLOOKUP(G47&"",'Presupuesto Base'!$A$7:$G$24,2,FALSE),"Ítem no encontrado")) -> Cama de asiento compactada | I47: =IF(G47="","",IFERROR(VLOOKUP(G47&"",'Presupuesto Base'!$A$7:$G$24,3,FALSE),"")) -> ml | K47: 102 | L47: =IF(G47="",0,IFERROR(VLOOKUP(G47&"",'Presupuesto Base'!$A$7:$G$24,5,FALSE),0)) -> 1705.3653 | M47: =IFERROR(K47*L47,0) -> 173947.26 | Q47: =IFERROR(VLOOKUP(A47,'Historial Certificados'!$A$6:$E$29,5,FALSE),"") -> 0 | R47: =IF(A47="","",IF(Q47="CERRADO","CERTIFICADO CERRADO - NO MODIFICAR","ABIERTO")) -> ABIERTO
A48: 1 | B48: 46262 | C48: =+CONCATENATE(D48,"-",E48) -> N29-N28 | D48: N29 | E48: N28 | F48: Pasaje 8 | G48: 4 | H48: =IF(G48="","",IFERROR(VLOOKUP(G48&"",'Presupuesto Base'!$A$7:$G$24,2,FALSE),"Ítem no encontrado")) -> Cama de asiento compactada | I48: =IF(G48="","",IFERROR(VLOOKUP(G48&"",'Presupuesto Base'!$A$7:$G$24,3,FALSE),"")) -> ml | K48: 100 | L48: =IF(G48="",0,IFERROR(VLOOKUP(G48&"",'Presupuesto Base'!$A$7:$G$24,5,FALSE),0)) -> 1705.3653 | M48: =IFERROR(K48*L48,0) -> 170536.53
A49: 1 | B49: 46262 | C49: =+CONCATENATE(D49,"-",E49) -> N28-N27 | D49: N28 | E49: N27 | F49: Pasaje 8 | G49: 4 | H49: =IF(G49="","",IFERROR(VLOOKUP(G49&"",'Presupuesto Base'!$A$7:$G$24,2,FALSE),"Ítem no encontrado")) -> Cama de asiento compactada | I49: =IF(G49="","",IFERROR(VLOOKUP(G49&"",'Presupuesto Base'!$A$7:$G$24,3,FALSE),"")) -> ml | K49: 82 | L49: =IF(G49="",0,IFERROR(VLOOKUP(G49&"",'Presupuesto Base'!$A$7:$G$24,5,FALSE),0)) -> 1705.3653 | M49: =IFERROR(K49*L49,0) -> 139839.96 | Q49: =IFERROR(VLOOKUP(A49,'Historial Certificados'!$A$6:$E$29,5,FALSE),"") -> 0 | R49: =IF(A49="","",IF(Q49="CERRADO","CERTIFICADO CERRADO - NO MODIFICAR","ABIERTO")) -> ABIERTO
A50: 1 | B50: 46262 | C50: =+CONCATENATE(D50,"-",E50) -> N30-N29 | D50: N30 | E50: N29 | F50: Pasaje 8 | G50: 5.1 | H50: =IF(G50="","",IFERROR(VLOOKUP(G50&"",'Presupuesto Base'!$A$7:$G$24,2,FALSE),"Ítem no encontrado")) -> PEAD PN10 Ø75 – provisión e instalación | I50: =IF(G50="","",IFERROR(VLOOKUP(G50&"",'Presupuesto Base'!$A$7:$G$24,3,FALSE),"")) -> ml | K50: 106 | L50: =IF(G50="",0,IFERROR(VLOOKUP(G50&"",'Presupuesto Base'!$A$7:$G$24,5,FALSE),0)) -> 5784.2549 | M50: =IFERROR(K50*L50,0) -> 613131.02 | Q50: =IFERROR(VLOOKUP(A50,'Historial Certificados'!$A$6:$E$29,5,FALSE),"") -> 0 | R50: =IF(A50="","",IF(Q50="CERRADO","CERTIFICADO CERRADO - NO MODIFICAR","ABIERTO")) -> ABIERTO
A51: 1 | B51: 46262 | C51: =+CONCATENATE(D51,"-",E51) -> N30-N25 | D51: N30 | E51: N25 | F51: Pasaje 3 | G51: 5.1 | H51: =IF(G51="","",IFERROR(VLOOKUP(G51&"",'Presupuesto Base'!$A$7:$G$24,2,FALSE),"Ítem no encontrado")) -> PEAD PN10 Ø75 – provisión e instalación | I51: =IF(G51="","",IFERROR(VLOOKUP(G51&"",'Presupuesto Base'!$A$7:$G$24,3,FALSE),"")) -> ml | K51: 76 | L51: =IF(G51="",0,IFERROR(VLOOKUP(G51&"",'Presupuesto Base'!$A$7:$G$24,5,FALSE),0)) -> 5784.2549 | M51: =IFERROR(K51*L51,0) -> 439603.38 | Q51: =IFERROR(VLOOKUP(A51,'Historial Certificados'!$A$6:$E$29,5,FALSE),"") -> 0 | R51: =IF(A51="","",IF(Q51="CERRADO","CERTIFICADO CERRADO - NO MODIFICAR","ABIERTO")) -> ABIERTO
A52: 1 | B52: 46262 | C52: =+CONCATENATE(D52,"-",E52) -> N25-N24 | D52: N25 | E52: N24 | F52: Pasaje 2 | G52: 5.2 | H52: =IF(G52="","",IFERROR(VLOOKUP(G52&"",'Presupuesto Base'!$A$7:$G$24,2,FALSE),"Ítem no encontrado")) -> PEAD PN10 Ø110 – provisión e instalación | I52: =IF(G52="","",IFERROR(VLOOKUP(G52&"",'Presupuesto Base'!$A$7:$G$24,3,FALSE),"")) -> ml | K52: 15 | L52: =IF(G52="",0,IFERROR(VLOOKUP(G52&"",'Presupuesto Base'!$A$7:$G$24,5,FALSE),0)) -> 12238.894 | M52: =IFERROR(K52*L52,0) -> 183583.41 | Q52: =IFERROR(VLOOKUP(A52,'Historial Certificados'!$A$6:$E$29,5,FALSE),"") -> 0 | R52: =IF(A52="","",IF(Q52="CERRADO","CERTIFICADO CERRADO - NO MODIFICAR","ABIERTO")) -> ABIERTO
A53: 1 | B53: 46262 | C53: =+CONCATENATE(D53,"-",E53) -> N24-N22 | D53: N24 | E53: N22 | F53: Pasaje 2 | G53: 5.2 | H53: =IF(G53="","",IFERROR(VLOOKUP(G53&"",'Presupuesto Base'!$A$7:$G$24,2,FALSE),"Ítem no encontrado")) -> PEAD PN10 Ø110 – provisión e instalación | I53: =IF(G53="","",IFERROR(VLOOKUP(G53&"",'Presupuesto Base'!$A$7:$G$24,3,FALSE),"")) -> ml | K53: 96 | L53: =IF(G53="",0,IFERROR(VLOOKUP(G53&"",'Presupuesto Base'!$A$7:$G$24,5,FALSE),0)) -> 12238.894 | M53: =IFERROR(K53*L53,0) -> 1174933.8 | Q53: =IFERROR(VLOOKUP(A53,'Historial Certificados'!$A$6:$E$29,5,FALSE),"") -> 0 | R53: =IF(A53="","",IF(Q53="CERRADO","CERTIFICADO CERRADO - NO MODIFICAR","ABIERTO")) -> ABIERTO
A54: 1 | B54: 46262 | C54: =+CONCATENATE(D54,"-",E54) -> N22-N29 | D54: N22 | E54: N29 | F54: Pasaje 4 | G54: 5.1 | H54: =IF(G54="","",IFERROR(VLOOKUP(G54&"",'Presupuesto Base'!$A$7:$G$24,2,FALSE),"Ítem no encontrado")) -> PEAD PN10 Ø75 – provisión e instalación | I54: =IF(G54="","",IFERROR(VLOOKUP(G54&"",'Presupuesto Base'!$A$7:$G$24,3,FALSE),"")) -> ml | K54: 92 | L54: =IF(G54="",0,IFERROR(VLOOKUP(G54&"",'Presupuesto Base'!$A$7:$G$24,5,FALSE),0)) -> 5784.2549 | M54: =IFERROR(K54*L54,0) -> 532151.45 | Q54: =IFERROR(VLOOKUP(A54,'Historial Certificados'!$A$6:$E$29,5,FALSE),"") -> 0 | R54: =IF(A54="","",IF(Q54="CERRADO","CERTIFICADO CERRADO - NO MODIFICAR","ABIERTO")) -> ABIERTO
A55: 1 | B55: 46262 | C55: =+CONCATENATE(D55,"-",E55) -> N22-N21 | D55: N22 | E55: N21 | F55: Pasaje 2 | G55: 5.2 | H55: =IF(G55="","",IFERROR(VLOOKUP(G55&"",'Presupuesto Base'!$A$7:$G$24,2,FALSE),"Ítem no encontrado")) -> PEAD PN10 Ø110 – provisión e instalación | I55: =IF(G55="","",IFERROR(VLOOKUP(G55&"",'Presupuesto Base'!$A$7:$G$24,3,FALSE),"")) -> ml | K55: 97 | L55: =IF(G55="",0,IFERROR(VLOOKUP(G55&"",'Presupuesto Base'!$A$7:$G$24,5,FALSE),0)) -> 12238.894 | M55: =IFERROR(K55*L55,0) -> 1187172.7 | Q55: =IFERROR(VLOOKUP(A55,'Historial Certificados'!$A$6:$E$29,5,FALSE),"") -> 0 | R55: =IF(A55="","",IF(Q55="CERRADO","CERTIFICADO CERRADO - NO MODIFICAR","ABIERTO")) -> ABIERTO
A56: 1 | B56: 46262 | C56: =+CONCATENATE(D56,"-",E56) -> N21-N20 | D56: N21 | E56: N20 | F56: Pasaje 2 | G56: 5.2 | H56: =IF(G56="","",IFERROR(VLOOKUP(G56&"",'Presupuesto Base'!$A$7:$G$24,2,FALSE),"Ítem no encontrado")) -> PEAD PN10 Ø110 – provisión e instalación | I56: =IF(G56="","",IFERROR(VLOOKUP(G56&"",'Presupuesto Base'!$A$7:$G$24,3,FALSE),"")) -> ml | K56: 2 | L56: =IF(G56="",0,IFERROR(VLOOKUP(G56&"",'Presupuesto Base'!$A$7:$G$24,5,FALSE),0)) -> 12238.894 | M56: =IFERROR(K56*L56,0) -> 24477.788 | Q56: =IFERROR(VLOOKUP(A56,'Historial Certificados'!$A$6:$E$29,5,FALSE),"") -> 0 | R56: =IF(A56="","",IF(Q56="CERRADO","CERTIFICADO CERRADO - NO MODIFICAR","ABIERTO")) -> ABIERTO
A57: 1 | B57: 46262 | C57: =+CONCATENATE(D57,"-",E57) -> N20-N19 | D57: N20 | E57: N19 | F57: Pasaje 2 | G57: 5.2 | H57: =IF(G57="","",IFERROR(VLOOKUP(G57&"",'Presupuesto Base'!$A$7:$G$24,2,FALSE),"Ítem no encontrado")) -> PEAD PN10 Ø110 – provisión e instalación | I57: =IF(G57="","",IFERROR(VLOOKUP(G57&"",'Presupuesto Base'!$A$7:$G$24,3,FALSE),"")) -> ml | K57: 77 | L57: =IF(G57="",0,IFERROR(VLOOKUP(G57&"",'Presupuesto Base'!$A$7:$G$24,5,FALSE),0)) -> 12238.894 | M57: =IFERROR(K57*L57,0) -> 942394.82 | Q57: =IFERROR(VLOOKUP(A57,'Historial Certificados'!$A$6:$E$29,5,FALSE),"") -> 0 | R57: =IF(A57="","",IF(Q57="CERRADO","CERTIFICADO CERRADO - NO MODIFICAR","ABIERTO")) -> ABIERTO
A58: 1 | B58: 46262 | C58: =+CONCATENATE(D58,"-",E58) -> N21-N28 | D58: N21 | E58: N28 | F58: Pasaje 5 | G58: 5.1 | H58: =IF(G58="","",IFERROR(VLOOKUP(G58&"",'Presupuesto Base'!$A$7:$G$24,2,FALSE),"Ítem no encontrado")) -> PEAD PN10 Ø75 – provisión e instalación | I58: =IF(G58="","",IFERROR(VLOOKUP(G58&"",'Presupuesto Base'!$A$7:$G$24,3,FALSE),"")) -> ml | K58: 102 | L58: =IF(G58="",0,IFERROR(VLOOKUP(G58&"",'Presupuesto Base'!$A$7:$G$24,5,FALSE),0)) -> 5784.2549 | M58: =IFERROR(K58*L58,0) -> 589994 | Q58: =IFERROR(VLOOKUP(A58,'Historial Certificados'!$A$6:$E$29,5,FALSE),"") -> 0 | R58: =IF(A58="","",IF(Q58="CERRADO","CERTIFICADO CERRADO - NO MODIFICAR","ABIERTO")) -> ABIERTO
A59: 1 | B59: 46262 | C59: =+CONCATENATE(D59,"-",E59) -> N29-N28 | D59: N29 | E59: N28 | F59: Pasaje 8 | G59: 5.1 | H59: =IF(G59="","",IFERROR(VLOOKUP(G59&"",'Presupuesto Base'!$A$7:$G$24,2,FALSE),"Ítem no encontrado")) -> PEAD PN10 Ø75 – provisión e instalación | I59: =IF(G59="","",IFERROR(VLOOKUP(G59&"",'Presupuesto Base'!$A$7:$G$24,3,FALSE),"")) -> ml | K59: 100 | L59: =IF(G59="",0,IFERROR(VLOOKUP(G59&"",'Presupuesto Base'!$A$7:$G$24,5,FALSE),0)) -> 5784.2549 | M59: =IFERROR(K59*L59,0) -> 578425.49
A60: 1 | B60: 46262 | C60: =+CONCATENATE(D60,"-",E60) -> N28-N27 | D60: N28 | E60: N27 | F60: Pasaje 8 | G60: 5.1 | H60: =IF(G60="","",IFERROR(VLOOKUP(G60&"",'Presupuesto Base'!$A$7:$G$24,2,FALSE),"Ítem no encontrado")) -> PEAD PN10 Ø75 – provisión e instalación | I60: =IF(G60="","",IFERROR(VLOOKUP(G60&"",'Presupuesto Base'!$A$7:$G$24,3,FALSE),"")) -> ml | K60: 82 | L60: =IF(G60="",0,IFERROR(VLOOKUP(G60&"",'Presupuesto Base'!$A$7:$G$24,5,FALSE),0)) -> 5784.2549 | M60: =IFERROR(K60*L60,0) -> 474308.9 | Q60: =IFERROR(VLOOKUP(A60,'Historial Certificados'!$A$6:$E$29,5,FALSE),"") -> 0 | R60: =IF(A60="","",IF(Q60="CERRADO","CERTIFICADO CERRADO - NO MODIFICAR","ABIERTO")) -> ABIERTO
A61: 1 | B61: 46262 | C61: =+CONCATENATE(D61,"-",E61) -> N30-N29 | D61: N30 | E61: N29 | F61: Pasaje 8 | G61: 6 | H61: =IF(G61="","",IFERROR(VLOOKUP(G61&"",'Presupuesto Base'!$A$7:$G$24,2,FALSE),"Ítem no encontrado")) -> Ejecución de paquete estructural de 30 cm | I61: =IF(G61="","",IFERROR(VLOOKUP(G61&"",'Presupuesto Base'!$A$7:$G$24,3,FALSE),"")) -> ml | K61: 106 | L61: =IF(G61="",0,IFERROR(VLOOKUP(G61&"",'Presupuesto Base'!$A$7:$G$24,5,FALSE),0)) -> 3274.3015 | M61: =IFERROR(K61*L61,0) -> 347075.95 | Q61: =IFERROR(VLOOKUP(A61,'Historial Certificados'!$A$6:$E$29,5,FALSE),"") -> 0 | R61: =IF(A61="","",IF(Q61="CERRADO","CERTIFICADO CERRADO - NO MODIFICAR","ABIERTO")) -> ABIERTO
A62: 1 | B62: 46262 | C62: =+CONCATENATE(D62,"-",E62) -> N30-N25 | D62: N30 | E62: N25 | F62: Pasaje 3 | G62: 6 | H62: =IF(G62="","",IFERROR(VLOOKUP(G62&"",'Presupuesto Base'!$A$7:$G$24,2,FALSE),"Ítem no encontrado")) -> Ejecución de paquete estructural de 30 cm | I62: =IF(G62="","",IFERROR(VLOOKUP(G62&"",'Presupuesto Base'!$A$7:$G$24,3,FALSE),"")) -> ml | K62: 76 | L62: =IF(G62="",0,IFERROR(VLOOKUP(G62&"",'Presupuesto Base'!$A$7:$G$24,5,FALSE),0)) -> 3274.3015 | M62: =IFERROR(K62*L62,0) -> 248846.91 | Q62: =IFERROR(VLOOKUP(A62,'Historial Certificados'!$A$6:$E$29,5,FALSE),"") -> 0 | R62: =IF(A62="","",IF(Q62="CERRADO","CERTIFICADO CERRADO - NO MODIFICAR","ABIERTO")) -> ABIERTO
A63: 1 | B63: 46262 | C63: =+CONCATENATE(D63,"-",E63) -> N25-N24 | D63: N25 | E63: N24 | F63: Pasaje 2 | G63: 6 | H63: =IF(G63="","",IFERROR(VLOOKUP(G63&"",'Presupuesto Base'!$A$7:$G$24,2,FALSE),"Ítem no encontrado")) -> Ejecución de paquete estructural de 30 cm | I63: =IF(G63="","",IFERROR(VLOOKUP(G63&"",'Presupuesto Base'!$A$7:$G$24,3,FALSE),"")) -> ml | K63: 15 | L63: =IF(G63="",0,IFERROR(VLOOKUP(G63&"",'Presupuesto Base'!$A$7:$G$24,5,FALSE),0)) -> 3274.3015 | M63: =IFERROR(K63*L63,0) -> 49114.522 | Q63: =IFERROR(VLOOKUP(A63,'Historial Certificados'!$A$6:$E$29,5,FALSE),"") -> 0 | R63: =IF(A63="","",IF(Q63="CERRADO","CERTIFICADO CERRADO - NO MODIFICAR","ABIERTO")) -> ABIERTO
A64: 1 | B64: 46262 | C64: =+CONCATENATE(D64,"-",E64) -> N24-N22 | D64: N24 | E64: N22 | F64: Pasaje 2 | G64: 6 | H64: =IF(G64="","",IFERROR(VLOOKUP(G64&"",'Presupuesto Base'!$A$7:$G$24,2,FALSE),"Ítem no encontrado")) -> Ejecución de paquete estructural de 30 cm | I64: =IF(G64="","",IFERROR(VLOOKUP(G64&"",'Presupuesto Base'!$A$7:$G$24,3,FALSE),"")) -> ml | K64: 96 | L64: =IF(G64="",0,IFERROR(VLOOKUP(G64&"",'Presupuesto Base'!$A$7:$G$24,5,FALSE),0)) -> 3274.3015 | M64: =IFERROR(K64*L64,0) -> 314332.94 | Q64: =IFERROR(VLOOKUP(A64,'Historial Certificados'!$A$6:$E$29,5,FALSE),"") -> 0 | R64: =IF(A64="","",IF(Q64="CERRADO","CERTIFICADO CERRADO - NO MODIFICAR","ABIERTO")) -> ABIERTO
A65: 1 | B65: 46262 | C65: =+CONCATENATE(D65,"-",E65) -> N22-N29 | D65: N22 | E65: N29 | F65: Pasaje 4 | G65: 6 | H65: =IF(G65="","",IFERROR(VLOOKUP(G65&"",'Presupuesto Base'!$A$7:$G$24,2,FALSE),"Ítem no encontrado")) -> Ejecución de paquete estructural de 30 cm | I65: =IF(G65="","",IFERROR(VLOOKUP(G65&"",'Presupuesto Base'!$A$7:$G$24,3,FALSE),"")) -> ml | K65: 92 | L65: =IF(G65="",0,IFERROR(VLOOKUP(G65&"",'Presupuesto Base'!$A$7:$G$24,5,FALSE),0)) -> 3274.3015 | M65: =IFERROR(K65*L65,0) -> 301235.73 | Q65: =IFERROR(VLOOKUP(A65,'Historial Certificados'!$A$6:$E$29,5,FALSE),"") -> 0 | R65: =IF(A65="","",IF(Q65="CERRADO","CERTIFICADO CERRADO - NO MODIFICAR","ABIERTO")) -> ABIERTO
A66: 1 | B66: 46262 | C66: =+CONCATENATE(D66,"-",E66) -> N22-N21 | D66: N22 | E66: N21 | F66: Pasaje 2 | G66: 6 | H66: =IF(G66="","",IFERROR(VLOOKUP(G66&"",'Presupuesto Base'!$A$7:$G$24,2,FALSE),"Ítem no encontrado")) -> Ejecución de paquete estructural de 30 cm | I66: =IF(G66="","",IFERROR(VLOOKUP(G66&"",'Presupuesto Base'!$A$7:$G$24,3,FALSE),"")) -> ml | K66: 97 | L66: =IF(G66="",0,IFERROR(VLOOKUP(G66&"",'Presupuesto Base'!$A$7:$G$24,5,FALSE),0)) -> 3274.3015 | M66: =IFERROR(K66*L66,0) -> 317607.24 | Q66: =IFERROR(VLOOKUP(A66,'Historial Certificados'!$A$6:$E$29,5,FALSE),"") -> 0 | R66: =IF(A66="","",IF(Q66="CERRADO","CERTIFICADO CERRADO - NO MODIFICAR","ABIERTO")) -> ABIERTO
A67: 1 | B67: 46262 | C67: =+CONCATENATE(D67,"-",E67) -> N21-N20 | D67: N21 | E67: N20 | F67: Pasaje 2 | G67: 6 | H67: =IF(G67="","",IFERROR(VLOOKUP(G67&"",'Presupuesto Base'!$A$7:$G$24,2,FALSE),"Ítem no encontrado")) -> Ejecución de paquete estructural de 30 cm | I67: =IF(G67="","",IFERROR(VLOOKUP(G67&"",'Presupuesto Base'!$A$7:$G$24,3,FALSE),"")) -> ml | K67: 2 | L67: =IF(G67="",0,IFERROR(VLOOKUP(G67&"",'Presupuesto Base'!$A$7:$G$24,5,FALSE),0)) -> 3274.3015 | M67: =IFERROR(K67*L67,0) -> 6548.6029 | Q67: =IFERROR(VLOOKUP(A67,'Historial Certificados'!$A$6:$E$29,5,FALSE),"") -> 0 | R67: =IF(A67="","",IF(Q67="CERRADO","CERTIFICADO CERRADO - NO MODIFICAR","ABIERTO")) -> ABIERTO
A68: 1 | B68: 46262 | C68: =+CONCATENATE(D68,"-",E68) -> N20-N19 | D68: N20 | E68: N19 | F68: Pasaje 2 | G68: 6 | H68: =IF(G68="","",IFERROR(VLOOKUP(G68&"",'Presupuesto Base'!$A$7:$G$24,2,FALSE),"Ítem no encontrado")) -> Ejecución de paquete estructural de 30 cm | I68: =IF(G68="","",IFERROR(VLOOKUP(G68&"",'Presupuesto Base'!$A$7:$G$24,3,FALSE),"")) -> ml | K68: 77 | L68: =IF(G68="",0,IFERROR(VLOOKUP(G68&"",'Presupuesto Base'!$A$7:$G$24,5,FALSE),0)) -> 3274.3015 | M68: =IFERROR(K68*L68,0) -> 252121.21 | Q68: =IFERROR(VLOOKUP(A68,'Historial Certificados'!$A$6:$E$29,5,FALSE),"") -> 0 | R68: =IF(A68="","",IF(Q68="CERRADO","CERTIFICADO CERRADO - NO MODIFICAR","ABIERTO")) -> ABIERTO
A69: 1 | B69: 46262 | C69: =+CONCATENATE(D69,"-",E69) -> N29-N28 | D69: N29 | E69: N28 | F69: Pasaje 8 | G69: 6 | H69: =IF(G69="","",IFERROR(VLOOKUP(G69&"",'Presupuesto Base'!$A$7:$G$24,2,FALSE),"Ítem no encontrado")) -> Ejecución de paquete estructural de 30 cm | I69: =IF(G69="","",IFERROR(VLOOKUP(G69&"",'Presupuesto Base'!$A$7:$G$24,3,FALSE),"")) -> ml | K69: 100 | L69: =IF(G69="",0,IFERROR(VLOOKUP(G69&"",'Presupuesto Base'!$A$7:$G$24,5,FALSE),0)) -> 3274.3015 | M69: =IFERROR(K69*L69,0) -> 327430.15
A70: 1 | B70: 46262 | C70: =+CONCATENATE(D70,"-",E70) -> N21-N28 | D70: N21 | E70: N28 | F70: Pasaje 5 | G70: 6 | H70: =IF(G70="","",IFERROR(VLOOKUP(G70&"",'Presupuesto Base'!$A$7:$G$24,2,FALSE),"Ítem no encontrado")) -> Ejecución de paquete estructural de 30 cm | I70: =IF(G70="","",IFERROR(VLOOKUP(G70&"",'Presupuesto Base'!$A$7:$G$24,3,FALSE),"")) -> ml | K70: 102 | L70: =IF(G70="",0,IFERROR(VLOOKUP(G70&"",'Presupuesto Base'!$A$7:$G$24,5,FALSE),0)) -> 3274.3015 | M70: =IFERROR(K70*L70,0) -> 333978.75 | Q70: =IFERROR(VLOOKUP(A70,'Historial Certificados'!$A$6:$E$29,5,FALSE),"") -> 0 | R70: =IF(A70="","",IF(Q70="CERRADO","CERTIFICADO CERRADO - NO MODIFICAR","ABIERTO")) -> ABIERTO
A71: 1 | B71: 46262 | C71: =+CONCATENATE(D71,"-",E71) -> N30-N25 | D71: N30 | E71: N25 | F71: Pasaje 3 | G71: 10.1 | H71: =IF(G71="","",IFERROR(VLOOKUP(G71&"",'Presupuesto Base'!$A$7:$G$24,2,FALSE),"Ítem no encontrado")) -> Conexión domiciliaria sobre red Ø75 | I71: =IF(G71="","",IFERROR(VLOOKUP(G71&"",'Presupuesto Base'!$A$7:$G$24,3,FALSE),"")) -> un | K71: 1 | L71: =IF(G71="",0,IFERROR(VLOOKUP(G71&"",'Presupuesto Base'!$A$7:$G$24,5,FALSE),0)) -> 48618.416 | M71: =IFERROR(K71*L71,0) -> 48618.416 | Q71: =IFERROR(VLOOKUP(A71,'Historial Certificados'!$A$6:$E$29,5,FALSE),"") -> 0 | R71: =IF(A71="","",IF(Q71="CERRADO","CERTIFICADO CERRADO - NO MODIFICAR","ABIERTO")) -> ABIERTO
A72: 1 | B72: 46262 | C72: =+CONCATENATE(D72,"-",E72) -> N30-N29 | D72: N30 | E72: N29 | F72: Pasaje 8 | G72: 10.1 | H72: =IF(G72="","",IFERROR(VLOOKUP(G72&"",'Presupuesto Base'!$A$7:$G$24,2,FALSE),"Ítem no encontrado")) -> Conexión domiciliaria sobre red Ø75 | I72: =IF(G72="","",IFERROR(VLOOKUP(G72&"",'Presupuesto Base'!$A$7:$G$24,3,FALSE),"")) -> un | K72: 1 | L72: =IF(G72="",0,IFERROR(VLOOKUP(G72&"",'Presupuesto Base'!$A$7:$G$24,5,FALSE),0)) -> 48618.416 | M72: =IFERROR(K72*L72,0) -> 48618.416 | Q72: =IFERROR(VLOOKUP(A72,'Historial Certificados'!$A$6:$E$29,5,FALSE),"") -> 0 | R72: =IF(A72="","",IF(Q72="CERRADO","CERTIFICADO CERRADO - NO MODIFICAR","ABIERTO")) -> ABIERTO
A73: 1 | B73: 46262 | C73: =+CONCATENATE(D73,"-",E73) -> N24-N22 | D73: N24 | E73: N22 | F73: Pasaje 2 | G73: 10.2 | H73: =IF(G73="","",IFERROR(VLOOKUP(G73&"",'Presupuesto Base'!$A$7:$G$24,2,FALSE),"Ítem no encontrado")) -> Conexión domiciliaria sobre red Ø110 | I73: =IF(G73="","",IFERROR(VLOOKUP(G73&"",'Presupuesto Base'!$A$7:$G$24,3,FALSE),"")) -> un | K73: 1 | L73: =IF(G73="",0,IFERROR(VLOOKUP(G73&"",'Presupuesto Base'!$A$7:$G$24,5,FALSE),0)) -> 55451.879 | M73: =IFERROR(K73*L73,0) -> 55451.879 | Q73: =IFERROR(VLOOKUP(A73,'Historial Certificados'!$A$6:$E$29,5,FALSE),"") -> 0 | R73: =IF(A73="","",IF(Q73="CERRADO","CERTIFICADO CERRADO - NO MODIFICAR","ABIERTO")) -> ABIERTO
A74: 1 | B74: 46262 | C74: =+CONCATENATE(D74,"-",E74) -> N29-N28 | D74: N29 | E74: N28 | F74: Pasaje 8 | G74: 10.1 | H74: =IF(G74="","",IFERROR(VLOOKUP(G74&"",'Presupuesto Base'!$A$7:$G$24,2,FALSE),"Ítem no encontrado")) -> Conexión domiciliaria sobre red Ø75 | I74: =IF(G74="","",IFERROR(VLOOKUP(G74&"",'Presupuesto Base'!$A$7:$G$24,3,FALSE),"")) -> un | K74: 1 | L74: =IF(G74="",0,IFERROR(VLOOKUP(G74&"",'Presupuesto Base'!$A$7:$G$24,5,FALSE),0)) -> 48618.416 | M74: =IFERROR(K74*L74,0) -> 48618.416 | Q74: =IFERROR(VLOOKUP(A74,'Historial Certificados'!$A$6:$E$29,5,FALSE),"") -> 0 | R74: =IF(A74="","",IF(Q74="CERRADO","CERTIFICADO CERRADO - NO MODIFICAR","ABIERTO")) -> ABIERTO
A75: 1 | B75: 46262 | C75: =+CONCATENATE(D75,"-",E75) -> N22-N29 | D75: N22 | E75: N29 | F75: Pasaje 4 | G75: 10.1 | H75: =IF(G75="","",IFERROR(VLOOKUP(G75&"",'Presupuesto Base'!$A$7:$G$24,2,FALSE),"Ítem no encontrado")) -> Conexión domiciliaria sobre red Ø75 | I75: =IF(G75="","",IFERROR(VLOOKUP(G75&"",'Presupuesto Base'!$A$7:$G$24,3,FALSE),"")) -> un | K75: 1 | L75: =IF(G75="",0,IFERROR(VLOOKUP(G75&"",'Presupuesto Base'!$A$7:$G$24,5,FALSE),0)) -> 48618.416 | M75: =IFERROR(K75*L75,0) -> 48618.416 | Q75: =IFERROR(VLOOKUP(A75,'Historial Certificados'!$A$6:$E$29,5,FALSE),"") -> 0 | R75: =IF(A75="","",IF(Q75="CERRADO","CERTIFICADO CERRADO - NO MODIFICAR","ABIERTO")) -> ABIERTO
A76: 1 | B76: 46262 | C76: =+CONCATENATE(D76,"-",E76) -> N21-N28 | D76: N21 | E76: N28 | F76: Pasaje 5 | G76: 10.1 | H76: =IF(G76="","",IFERROR(VLOOKUP(G76&"",'Presupuesto Base'!$A$7:$G$24,2,FALSE),"Ítem no encontrado")) -> Conexión domiciliaria sobre red Ø75 | I76: =IF(G76="","",IFERROR(VLOOKUP(G76&"",'Presupuesto Base'!$A$7:$G$24,3,FALSE),"")) -> un | K76: 1 | L76: =IF(G76="",0,IFERROR(VLOOKUP(G76&"",'Presupuesto Base'!$A$7:$G$24,5,FALSE),0)) -> 48618.416 | M76: =IFERROR(K76*L76,0) -> 48618.416 | Q76: =IFERROR(VLOOKUP(A76,'Historial Certificados'!$A$6:$E$29,5,FALSE),"") -> 0 | R76: =IF(A76="","",IF(Q76="CERRADO","CERTIFICADO CERRADO - NO MODIFICAR","ABIERTO")) -> ABIERTO
A77: 1 | B77: 46262 | C77: =+CONCATENATE(D77,"-",E77) -> N21-N22 | D77: N21 | E77: N22 | F77: Pasaje 2 | G77: 10.2 | H77: =IF(G77="","",IFERROR(VLOOKUP(G77&"",'Presupuesto Base'!$A$7:$G$24,2,FALSE),"Ítem no encontrado")) -> Conexión domiciliaria sobre red Ø110 | I77: =IF(G77="","",IFERROR(VLOOKUP(G77&"",'Presupuesto Base'!$A$7:$G$24,3,FALSE),"")) -> un | K77: 1 | L77: =IF(G77="",0,IFERROR(VLOOKUP(G77&"",'Presupuesto Base'!$A$7:$G$24,5,FALSE),0)) -> 55451.879 | M77: =IFERROR(K77*L77,0) -> 55451.879 | Q77: =IFERROR(VLOOKUP(A77,'Historial Certificados'!$A$6:$E$29,5,FALSE),"") -> 0 | R77: =IF(A77="","",IF(Q77="CERRADO","CERTIFICADO CERRADO - NO MODIFICAR","ABIERTO")) -> ABIERTO
G78: 7 | H78: =IF(G78="","",IFERROR(VLOOKUP(G78&"",'Presupuesto Base'!$A$7:$G$24,2,FALSE),"Ítem no encontrado")) -> Compactación del paquete estructural de 30 cm | I78: =IF(G78="","",IFERROR(VLOOKUP(G78&"",'Presupuesto Base'!$A$7:$G$24,3,FALSE),"")) -> ml | L78: =IF(G78="",0,IFERROR(VLOOKUP(G78&"",'Presupuesto Base'!$A$7:$G$24,5,FALSE),0)) -> 1227.863 | M78: =IFERROR(K78*L78,0) -> 0 | Q78: =IFERROR(VLOOKUP(A78,'Historial Certificados'!$A$6:$E$29,5,FALSE),"") | R78: =IF(A78="","",IF(Q78="CERRADO","CERTIFICADO CERRADO - NO MODIFICAR","ABIERTO"))
H79: =IF(G79="","",IFERROR(VLOOKUP(G79&"",'Presupuesto Base'!$A$7:$G$24,2,FALSE),"Ítem no encontrado")) | I79: =IF(G79="","",IFERROR(VLOOKUP(G79&"",'Presupuesto Base'!$A$7:$G$24,3,FALSE),"")) | L79: =IF(G79="",0,IFERROR(VLOOKUP(G79&"",'Presupuesto Base'!$A$7:$G$24,5,FALSE),0)) -> 0 | M79: =IFERROR(K79*L79,0) -> 0 | Q79: =IFERROR(VLOOKUP(A79,'Historial Certificados'!$A$6:$E$29,5,FALSE),"") | R79: =IF(A79="","",IF(Q79="CERRADO","CERTIFICADO CERRADO - NO MODIFICAR","ABIERTO"))
H80: =IF(G80="","",IFERROR(VLOOKUP(G80&"",'Presupuesto Base'!$A$7:$G$24,2,FALSE),"Ítem no encontrado")) | I80: =IF(G80="","",IFERROR(VLOOKUP(G80&"",'Presupuesto Base'!$A$7:$G$24,3,FALSE),"")) | L80: =IF(G80="",0,IFERROR(VLOOKUP(G80&"",'Presupuesto Base'!$A$7:$G$24,5,FALSE),0)) -> 0 | M80: =IFERROR(K80*L80,0) -> 0 | Q80: =IFERROR(VLOOKUP(A80,'Historial Certificados'!$A$6:$E$29,5,FALSE),"") | R80: =IF(A80="","",IF(Q80="CERRADO","CERTIFICADO CERRADO - NO MODIFICAR","ABIERTO"))
H81: =IF(G81="","",IFERROR(VLOOKUP(G81&"",'Presupuesto Base'!$A$7:$G$24,2,FALSE),"Ítem no encontrado")) | I81: =IF(G81="","",IFERROR(VLOOKUP(G81&"",'Presupuesto Base'!$A$7:$G$24,3,FALSE),"")) | L81: =IF(G81="",0,IFERROR(VLOOKUP(G81&"",'Presupuesto Base'!$A$7:$G$24,5,FALSE),0)) -> 0 | M81: =IFERROR(K81*L81,0) -> 0 | Q81: =IFERROR(VLOOKUP(A81,'Historial Certificados'!$A$6:$E$29,5,FALSE),"") | R81: =IF(A81="","",IF(Q81="CERRADO","CERTIFICADO CERRADO - NO MODIFICAR","ABIERTO"))
H82: =IF(G82="","",IFERROR(VLOOKUP(G82&"",'Presupuesto Base'!$A$7:$G$24,2,FALSE),"Ítem no encontrado")) | I82: =IF(G82="","",IFERROR(VLOOKUP(G82&"",'Presupuesto Base'!$A$7:$G$24,3,FALSE),"")) | L82: =IF(G82="",0,IFERROR(VLOOKUP(G82&"",'Presupuesto Base'!$A$7:$G$24,5,FALSE),0)) -> 0 | M82: =IFERROR(K82*L82,0) -> 0 | Q82: =IFERROR(VLOOKUP(A82,'Historial Certificados'!$A$6:$E$29,5,FALSE),"") | R82: =IF(A82="","",IF(Q82="CERRADO","CERTIFICADO CERRADO - NO MODIFICAR","ABIERTO"))
H83: =IF(G83="","",IFERROR(VLOOKUP(G83&"",'Presupuesto Base'!$A$7:$G$24,2,FALSE),"Ítem no encontrado")) | I83: =IF(G83="","",IFERROR(VLOOKUP(G83&"",'Presupuesto Base'!$A$7:$G$24,3,FALSE),"")) | L83: =IF(G83="",0,IFERROR(VLOOKUP(G83&"",'Presupuesto Base'!$A$7:$G$24,5,FALSE),0)) -> 0 | M83: =IFERROR(K83*L83,0) -> 0 | Q83: =IFERROR(VLOOKUP(A83,'Historial Certificados'!$A$6:$E$29,5,FALSE),"") | R83: =IF(A83="","",IF(Q83="CERRADO","CERTIFICADO CERRADO - NO MODIFICAR","ABIERTO"))
H84: =IF(G84="","",IFERROR(VLOOKUP(G84&"",'Presupuesto Base'!$A$7:$G$24,2,FALSE),"Ítem no encontrado")) | I84: =IF(G84="","",IFERROR(VLOOKUP(G84&"",'Presupuesto Base'!$A$7:$G$24,3,FALSE),"")) | L84: =IF(G84="",0,IFERROR(VLOOKUP(G84&"",'Presupuesto Base'!$A$7:$G$24,5,FALSE),0)) -> 0 | M84: =IFERROR(K84*L84,0) -> 0 | Q84: =IFERROR(VLOOKUP(A84,'Historial Certificados'!$A$6:$E$29,5,FALSE),"") | R84: =IF(A84="","",IF(Q84="CERRADO","CERTIFICADO CERRADO - NO MODIFICAR","ABIERTO"))
H85: =IF(G85="","",IFERROR(VLOOKUP(G85&"",'Presupuesto Base'!$A$7:$G$24,2,FALSE),"Ítem no encontrado")) | I85: =IF(G85="","",IFERROR(VLOOKUP(G85&"",'Presupuesto Base'!$A$7:$G$24,3,FALSE),"")) | L85: =IF(G85="",0,IFERROR(VLOOKUP(G85&"",'Presupuesto Base'!$A$7:$G$24,5,FALSE),0)) -> 0 | M85: =IFERROR(K85*L85,0) -> 0 | Q85: =IFERROR(VLOOKUP(A85,'Historial Certificados'!$A$6:$E$29,5,FALSE),"") | R85: =IF(A85="","",IF(Q85="CERRADO","CERTIFICADO CERRADO - NO MODIFICAR","ABIERTO"))
H86: =IF(G86="","",IFERROR(VLOOKUP(G86&"",'Presupuesto Base'!$A$7:$G$24,2,FALSE),"Ítem no encontrado")) | I86: =IF(G86="","",IFERROR(VLOOKUP(G86&"",'Presupuesto Base'!$A$7:$G$24,3,FALSE),"")) | L86: =IF(G86="",0,IFERROR(VLOOKUP(G86&"",'Presupuesto Base'!$A$7:$G$24,5,FALSE),0)) -> 0 | M86: =IFERROR(K86*L86,0) -> 0 | Q86: =IFERROR(VLOOKUP(A86,'Historial Certificados'!$A$6:$E$29,5,FALSE),"") | R86: =IF(A86="","",IF(Q86="CERRADO","CERTIFICADO CERRADO - NO MODIFICAR","ABIERTO"))
H87: =IF(G87="","",IFERROR(VLOOKUP(G87&"",'Presupuesto Base'!$A$7:$G$24,2,FALSE),"Ítem no encontrado")) | I87: =IF(G87="","",IFERROR(VLOOKUP(G87&"",'Presupuesto Base'!$A$7:$G$24,3,FALSE),"")) | L87: =IF(G87="",0,IFERROR(VLOOKUP(G87&"",'Presupuesto Base'!$A$7:$G$24,5,FALSE),0)) -> 0 | M87: =IFERROR(K87*L87,0) -> 0 | Q87: =IFERROR(VLOOKUP(A87,'Historial Certificados'!$A$6:$E$29,5,FALSE),"") | R87: =IF(A87="","",IF(Q87="CERRADO","CERTIFICADO CERRADO - NO MODIFICAR","ABIERTO"))
H88: =IF(G88="","",IFERROR(VLOOKUP(G88&"",'Presupuesto Base'!$A$7:$G$24,2,FALSE),"Ítem no encontrado")) | I88: =IF(G88="","",IFERROR(VLOOKUP(G88&"",'Presupuesto Base'!$A$7:$G$24,3,FALSE),"")) | L88: =IF(G88="",0,IFERROR(VLOOKUP(G88&"",'Presupuesto Base'!$A$7:$G$24,5,FALSE),0)) -> 0 | M88: =IFERROR(K88*L88,0) -> 0 | Q88: =IFERROR(VLOOKUP(A88,'Historial Certificados'!$A$6:$E$29,5,FALSE),"") | R88: =IF(A88="","",IF(Q88="CERRADO","CERTIFICADO CERRADO - NO MODIFICAR","ABIERTO"))
H89: =IF(G89="","",IFERROR(VLOOKUP(G89&"",'Presupuesto Base'!$A$7:$G$24,2,FALSE),"Ítem no encontrado")) | I89: =IF(G89="","",IFERROR(VLOOKUP(G89&"",'Presupuesto Base'!$A$7:$G$24,3,FALSE),"")) | L89: =IF(G89="",0,IFERROR(VLOOKUP(G89&"",'Presupuesto Base'!$A$7:$G$24,5,FALSE),0)) -> 0 | M89: =IFERROR(K89*L89,0) -> 0 | Q89: =IFERROR(VLOOKUP(A89,'Historial Certificados'!$A$6:$E$29,5,FALSE),"") | R89: =IF(A89="","",IF(Q89="CERRADO","CERTIFICADO CERRADO - NO MODIFICAR","ABIERTO"))
H90: =IF(G90="","",IFERROR(VLOOKUP(G90&"",'Presupuesto Base'!$A$7:$G$24,2,FALSE),"Ítem no encontrado")) | I90: =IF(G90="","",IFERROR(VLOOKUP(G90&"",'Presupuesto Base'!$A$7:$G$24,3,FALSE),"")) | L90: =IF(G90="",0,IFERROR(VLOOKUP(G90&"",'Presupuesto Base'!$A$7:$G$24,5,FALSE),0)) -> 0 | M90: =IFERROR(K90*L90,0) -> 0 | Q90: =IFERROR(VLOOKUP(A90,'Historial Certificados'!$A$6:$E$29,5,FALSE),"") | R90: =IF(A90="","",IF(Q90="CERRADO","CERTIFICADO CERRADO - NO MODIFICAR","ABIERTO"))
... H511: =IF(G511="","",IFERROR(VLOOKUP(G511&"",'Presupuesto Base'!$A$7:$G$24,2,FALSE),"Ítem no encontrado")) | I511: =IF(G511="","",IFERROR(VLOOKUP(G511&"",'Presupuesto Base'!$A$7:$G$24,3,FALSE),"")) | L511: =IF(G511="",0,IFERROR(VLOOKUP(G511&"",'Presupuesto Base'!$A$7:$G$24,5,FALSE),0)) -> 0 | M511: =IFERROR(K511*L511,0) -> 0 | Q511: =IFERROR(VLOOKUP(A511,'Historial Certificados'!$A$6:$E$29,5,FALSE),"") | R511: =IF(A511="","",IF(Q511="CERRADO","CERTIFICADO CERRADO - NO MODIFICAR","ABIERTO"))

Sheet Certificado
A1: CERTIFICADO DE OBRA – RED DISTRIBUIDORA DE AGUA POTABLE
A4: Certificado N° | B4: 1 | D4: Obra | E4: =Configuracion!B5 -> Red Distribuidora de Agua Potable – Loteo Roque | H4: Estado | I4: =IFERROR(VLOOKUP($B$4,'Historial Certificados'!$A$6:$O$29,5,FALSE),"") -> 0
A5: Período desde | B5: =IFERROR(VLOOKUP($B$4,'Historial Certificados'!$A$6:$O$29,2,FALSE),"") -> 0 | D5: Comitente | E5: =Configuracion!B7 -> VALDIVIESO GROUP S.R.L. | H5: Control | I5: =IFERROR(VLOOKUP($B$4,'Historial Certificados'!$A$6:$O$29,14,FALSE),"") -> OK
A6: Período hasta | B6: =IFERROR(VLOOKUP($B$4,'Historial Certificados'!$A$6:$O$29,3,FALSE),"") -> 0 | D6: Contratista | E6: =Configuracion!B8 -> ECAR SAS | H6: Registros | I6: =IFERROR(VLOOKUP($B$4,'Historial Certificados'!$A$6:$O$29,6,FALSE),0) -> 72
A7: Fecha emisión | B7: =IFERROR(VLOOKUP($B$4,'Historial Certificados'!$A$6:$O$29,4,FALSE),"") -> 0 | D7: Base económica | E7: Saldo certificable Agua s/IVA | F7: =Configuracion!B18 -> 1.1460055e+08
A9: Ítem | B9: Descripción | C9: Un. | D9: Cant. contractual | E9: P.U. s/IVA | F9: Importe contractual | G9: Cant. anterior | H9: Cant. período | I9: Cant. acumulada | J9: % avance acum. | K9: Importe anterior | L9: Importe período | M9: Importe acumulado | N9: Saldo | O9: Control
A10: ='Presupuesto Base'!A7 -> 1 | B10: ='Presupuesto Base'!B7 -> Replanteo y marcación de traza | C10: ='Presupuesto Base'!C7 -> ml | D10: ='Presupuesto Base'!D7 -> 4200 | E10: ='Presupuesto Base'!E7 -> 204.64384 | F10: ='Presupuesto Base'!F7 -> 859504.13 | G10: =SUMIFS(Medicion!$K$6:$K$511,Medicion!$G$6:$G$511,$A10,Medicion!$A$6:$A$511,"<"&$B$4) -> 0 | H10: =SUMIFS(Medicion!$K$6:$K$511,Medicion!$G$6:$G$511,$A10,Medicion!$A$6:$A$511,$B$4) -> 845 | I10: =MIN(D10,G10+H10) -> 845 | J10: =IFERROR(I10/D10,0) -> 0.20119048 | K10: =MIN(F10,G10*E10) -> 0 | L10: =MIN(F10-K10,H10*E10) -> 172924.05 | M10: =K10+L10 -> 172924.05 | N10: =MAX(0,F10-M10) -> 686580.09 | O10: =IF(OR(G10+H10>D10+0.000001,G10<0,H10<0),"REVISAR","OK") -> OK
A11: ='Presupuesto Base'!A8 -> 2 | B11: ='Presupuesto Base'!B8 -> Excavación de zanja | C11: ='Presupuesto Base'!C8 -> ml | D11: ='Presupuesto Base'!D8 -> 4200 | E11: ='Presupuesto Base'!E8 -> 3683.5891 | F11: ='Presupuesto Base'!F8 -> 15471074 | G11: =SUMIFS(Medicion!$K$6:$K$511,Medicion!$G$6:$G$511,$A11,Medicion!$A$6:$A$511,"<"&$B$4) -> 0 | H11: =SUMIFS(Medicion!$K$6:$K$511,Medicion!$G$6:$G$511,$A11,Medicion!$A$6:$A$511,$B$4) -> 845 | I11: =MIN(D11,G11+H11) -> 845 | J11: =IFERROR(I11/D11,0) -> 0.20119048 | K11: =MIN(F11,G11*E11) -> 0 | L11: =MIN(F11-K11,H11*E11) -> 3112632.8 | M11: =K11+L11 -> 3112632.8 | N11: =MAX(0,F11-M11) -> 12358442 | O11: =IF(OR(G11+H11>D11+0.000001,G11<0,H11<0),"REVISAR","OK") -> OK
A12: ='Presupuesto Base'!A9 -> 3 | B12: ='Presupuesto Base'!B9 -> Nivelación y conformación del fondo de zanja | C12: ='Presupuesto Base'!C9 -> ml | D12: ='Presupuesto Base'!D9 -> 4200 | E12: ='Presupuesto Base'!E9 -> 477.5023 | F12: ='Presupuesto Base'!F9 -> 2005509.6 | G12: =SUMIFS(Medicion!$K$6:$K$511,Medicion!$G$6:$G$511,$A12,Medicion!$A$6:$A$511,"<"&$B$4) -> 0 | H12: =SUMIFS(Medicion!$K$6:$K$511,Medicion!$G$6:$G$511,$A12,Medicion!$A$6:$A$511,$B$4) -> 845 | I12: =MIN(D12,G12+H12) -> 845 | J12: =IFERROR(I12/D12,0) -> 0.20119048 | K12: =MIN(F12,G12*E12) -> 0 | L12: =MIN(F12-K12,H12*E12) -> 403489.44 | M12: =K12+L12 -> 403489.44 | N12: =MAX(0,F12-M12) -> 1602020.2 | O12: =IF(OR(G12+H12>D12+0.000001,G12<0,H12<0),"REVISAR","OK") -> OK
A13: ='Presupuesto Base'!A10 -> 4 | B13: ='Presupuesto Base'!B10 -> Cama de asiento compactada | C13: ='Presupuesto Base'!C10 -> ml | D13: ='Presupuesto Base'!D10 -> 4200 | E13: ='Presupuesto Base'!E10 -> 1705.3653 | F13: ='Presupuesto Base'!F10 -> 7162534.4 | G13: =SUMIFS(Medicion!$K$6:$K$511,Medicion!$G$6:$G$511,$A13,Medicion!$A$6:$A$511,"<"&$B$4) -> 0 | H13: =SUMIFS(Medicion!$K$6:$K$511,Medicion!$G$6:$G$511,$A13,Medicion!$A$6:$A$511,$B$4) -> 845 | I13: =MIN(D13,G13+H13) -> 845 | J13: =IFERROR(I13/D13,0) -> 0.20119048 | K13: =MIN(F13,G13*E13) -> 0 | L13: =MIN(F13-K13,H13*E13) -> 1441033.7 | M13: =K13+L13 -> 1441033.7 | N13: =MAX(0,F13-M13) -> 5721500.7 | O13: =IF(OR(G13+H13>D13+0.000001,G13<0,H13<0),"REVISAR","OK") -> OK
A14: ='Presupuesto Base'!A11 -> 5.1 | B14: ='Presupuesto Base'!B11 -> PEAD PN10 Ø75 – provisión e instalación | C14: ='Presupuesto Base'!C11 -> ml | D14: ='Presupuesto Base'!D11 -> 3170 | E14: ='Presupuesto Base'!E11 -> 5784.2549 | F14: ='Presupuesto Base'!F11 -> 18336088 | G14: =SUMIFS(Medicion!$K$6:$K$511,Medicion!$G$6:$G$511,$A14,Medicion!$A$6:$A$511,"<"&$B$4) -> 0 | H14: =SUMIFS(Medicion!$K$6:$K$511,Medicion!$G$6:$G$511,$A14,Medicion!$A$6:$A$511,$B$4) -> 558 | I14: =MIN(D14,G14+H14) -> 558 | J14: =IFERROR(I14/D14,0) -> 0.17602524 | K14: =MIN(F14,G14*E14) -> 0 | L14: =MIN(F14-K14,H14*E14) -> 3227614.3 | M14: =K14+L14 -> 3227614.3 | N14: =MAX(0,F14-M14) -> 15108474 | O14: =IF(OR(G14+H14>D14+0.000001,G14<0,H14<0),"REVISAR","OK") -> OK
A15: ='Presupuesto Base'!A12 -> 5.2 | B15: ='Presupuesto Base'!B12 -> PEAD PN10 Ø110 – provisión e instalación | C15: ='Presupuesto Base'!C12 -> ml | D15: ='Presupuesto Base'!D12 -> 1030 | E15: ='Presupuesto Base'!E12 -> 12238.894 | F15: ='Presupuesto Base'!F12 -> 12606061 | G15: =SUMIFS(Medicion!$K$6:$K$511,Medicion!$G$6:$G$511,$A15,Medicion!$A$6:$A$511,"<"&$B$4) -> 0 | H15: =SUMIFS(Medicion!$K$6:$K$511,Medicion!$G$6:$G$511,$A15,Medicion!$A$6:$A$511,$B$4) -> 287 | I15: =MIN(D15,G15+H15) -> 287 | J15: =IFERROR(I15/D15,0) -> 0.27864078 | K15: =MIN(F15,G15*E15) -> 0 | L15: =MIN(F15-K15,H15*E15) -> 3512562.5 | M15: =K15+L15 -> 3512562.5 | N15: =MAX(0,F15-M15) -> 9093498.1 | O15: =IF(OR(G15+H15>D15+0.000001,G15<0,H15<0),"REVISAR","OK") -> OK
A16: ='Presupuesto Base'!A13 -> 6 | B16: ='Presupuesto Base'!B13 -> Ejecución de paquete estructural de 30 cm | C16: ='Presupuesto Base'!C13 -> ml | D16: ='Presupuesto Base'!D13 -> 4200 | E16: ='Presupuesto Base'!E13 -> 3274.3015 | F16: ='Presupuesto Base'!F13 -> 13752066 | G16: =SUMIFS(Medicion!$K$6:$K$511,Medicion!$G$6:$G$511,$A16,Medicion!$A$6:$A$511,"<"&$B$4) -> 0 | H16: =SUMIFS(Medicion!$K$6:$K$511,Medicion!$G$6:$G$511,$A16,Medicion!$A$6:$A$511,$B$4) -> 763 | I16: =MIN(D16,G16+H16) -> 763 | J16: =IFERROR(I16/D16,0) -> 0.18166667 | K16: =MIN(F16,G16*E16) -> 0 | L16: =MIN(F16-K16,H16*E16) -> 2498292 | M16: =K16+L16 -> 2498292 | N16: =MAX(0,F16-M16) -> 11253774 | O16: =IF(OR(G16+H16>D16+0.000001,G16<0,H16<0),"REVISAR","OK") -> OK
A17: ='Presupuesto Base'!A14 -> 7 | B17: ='Presupuesto Base'!B14 -> Compactación del paquete estructural de 30 cm | C17: ='Presupuesto Base'!C14 -> ml | D17: ='Presupuesto Base'!D14 -> 4200 | E17: ='Presupuesto Base'!E14 -> 1227.863 | F17: ='Presupuesto Base'!F14 -> 5157024.8 | G17: =SUMIFS(Medicion!$K$6:$K$511,Medicion!$G$6:$G$511,$A17,Medicion!$A$6:$A$511,"<"&$B$4) -> 0 | H17: =SUMIFS(Medicion!$K$6:$K$511,Medicion!$G$6:$G$511,$A17,Medicion!$A$6:$A$511,$B$4) -> 0 | I17: =MIN(D17,G17+H17) -> 0 | J17: =IFERROR(I17/D17,0) -> 0 | K17: =MIN(F17,G17*E17) -> 0 | L17: =MIN(F17-K17,H17*E17) -> 0 | M17: =K17+L17 -> 0 | N17: =MAX(0,F17-M17) -> 5157024.8 | O17: =IF(OR(G17+H17>D17+0.000001,G17<0,H17<0),"REVISAR","OK") -> OK
A18: ='Presupuesto Base'!A15 -> 8 | B18: ='Presupuesto Base'!B15 -> Ejecución y compactación de capa cota -0,60 | C18: ='Presupuesto Base'!C15 -> ml | D18: ='Presupuesto Base'!D15 -> 4200 | E18: ='Presupuesto Base'!E15 -> 2592.1553 | F18: ='Presupuesto Base'!F15 -> 10887052 | G18: =SUMIFS(Medicion!$K$6:$K$511,Medicion!$G$6:$G$511,$A18,Medicion!$A$6:$A$511,"<"&$B$4) -> 0 | H18: =SUMIFS(Medicion!$K$6:$K$511,Medicion!$G$6:$G$511,$A18,Medicion!$A$6:$A$511,$B$4) -> 0 | I18: =MIN(D18,G18+H18) -> 0 | J18: =IFERROR(I18/D18,0) -> 0 | K18: =MIN(F18,G18*E18) -> 0 | L18: =MIN(F18-K18,H18*E18) -> 0 | M18: =K18+L18 -> 0 | N18: =MAX(0,F18-M18) -> 10887052 | O18: =IF(OR(G18+H18>D18+0.000001,G18<0,H18<0),"REVISAR","OK") -> OK
A19: ='Presupuesto Base'!A16 -> 9 | B19: ='Presupuesto Base'!B16 -> Ejecución y compactación de capa cota -0,30 | C19: ='Presupuesto Base'!C16 -> ml | D19: ='Presupuesto Base'!D16 -> 4200 | E19: ='Presupuesto Base'!E16 -> 2182.8676 | F19: ='Presupuesto Base'!F16 -> 9168044.1 | G19: =SUMIFS(Medicion!$K$6:$K$511,Medicion!$G$6:$G$511,$A19,Medicion!$A$6:$A$511,"<"&$B$4) -> 0 | H19: =SUMIFS(Medicion!$K$6:$K$511,Medicion!$G$6:$G$511,$A19,Medicion!$A$6:$A$511,$B$4) -> 0 | I19: =MIN(D19,G19+H19) -> 0 | J19: =IFERROR(I19/D19,0) -> 0 | K19: =MIN(F19,G19*E19) -> 0 | L19: =MIN(F19-K19,H19*E19) -> 0 | M19: =K19+L19 -> 0 | N19: =MAX(0,F19-M19) -> 9168044.1 | O19: =IF(OR(G19+H19>D19+0.000001,G19<0,H19<0),"REVISAR","OK") -> OK
A20: ='Presupuesto Base'!A17 -> 10.1 | B20: ='Presupuesto Base'!B17 -> Conexión domiciliaria sobre red Ø75 | C20: ='Presupuesto Base'!C17 -> un | D20: ='Presupuesto Base'!D17 -> 165 | E20: ='Presupuesto Base'!E17 -> 48618.416 | F20: ='Presupuesto Base'!F17 -> 8022038.6 | G20: =SUMIFS(Medicion!$K$6:$K$511,Medicion!$G$6:$G$511,$A20,Medicion!$A$6:$A$511,"<"&$B$4) -> 0 | H20: =SUMIFS(Medicion!$K$6:$K$511,Medicion!$G$6:$G$511,$A20,Medicion!$A$6:$A$511,$B$4) -> 5 | I20: =MIN(D20,G20+H20) -> 5 | J20: =IFERROR(I20/D20,0) -> 0.03030303 | K20: =MIN(F20,G20*E20) -> 0 | L20: =MIN(F20-K20,H20*E20) -> 243092.08 | M20: =K20+L20 -> 243092.08 | N20: =MAX(0,F20-M20) -> 7778946.5 | O20: =IF(OR(G20+H20>D20+0.000001,G20<0,H20<0),"REVISAR","OK") -> OK
A21: ='Presupuesto Base'!A18 -> 10.2 | B21: ='Presupuesto Base'!B18 -> Conexión domiciliaria sobre red Ø110 | C21: ='Presupuesto Base'!C18 -> un | D21: ='Presupuesto Base'!D18 -> 62 | E21: ='Presupuesto Base'!E18 -> 55451.879 | F21: ='Presupuesto Base'!F18 -> 3438016.5 | G21: =SUMIFS(Medicion!$K$6:$K$511,Medicion!$G$6:$G$511,$A21,Medicion!$A$6:$A$511,"<"&$B$4) -> 0 | H21: =SUMIFS(Medicion!$K$6:$K$511,Medicion!$G$6:$G$511,$A21,Medicion!$A$6:$A$511,$B$4) -> 2 | I21: =MIN(D21,G21+H21) -> 2 | J21: =IFERROR(I21/D21,0) -> 0.032258065 | K21: =MIN(F21,G21*E21) -> 0 | L21: =MIN(F21-K21,H21*E21) -> 110903.76 | M21: =K21+L21 -> 110903.76 | N21: =MAX(0,F21-M21) -> 3327112.8 | O21: =IF(OR(G21+H21>D21+0.000001,G21<0,H21<0),"REVISAR","OK") -> OK
... A27: ='Presupuesto Base'!A24 -> 13.3 | B27: ='Presupuesto Base'!B24 -> Documentación conforme a obra y cierre | C27: ='Presupuesto Base'!C24 -> gl | D27: ='Presupuesto Base'!D24 -> 1 | E27: ='Presupuesto Base'!E24 -> 859504.13 | F27: ='Presupuesto Base'!F24 -> 859504.13 | G27: =SUMIFS(Medicion!$K$6:$K$511,Medicion!$G$6:$G$511,$A27,Medicion!$A$6:$A$511,"<"&$B$4) -> 0 | H27: =SUMIFS(Medicion!$K$6:$K$511,Medicion!$G$6:$G$511,$A27,Medicion!$A$6:$A$511,$B$4) -> 0 | I27: =MIN(D27,G27+H27) -> 0 | J27: =IFERROR(I27/D27,0) -> 0 | K27: =MIN(F27,G27*E27) -> 0 | L27: =MIN(F27-K27,H27*E27) -> 0 | M27: =K27+L27 -> 0 | N27: =MAX(0,F27-M27) -> 859504.13 | O27: =IF(OR(G27+H27>D27+0.000001,G27<0,H27<0),"REVISAR","OK") -> OK
B28: TOTAL | K28: =SUM(K10:K27) -> 0 | L28: =SUM(L10:L27) -> 14722545 | M28: =SUM(M10:M27) -> 14722545 | N28: =SUM(N10:N27) -> 99878006
J31: RESUMEN ECONÓMICO
J32: Saldo base certificable s/IVA | N32: =Configuracion!B18 -> 1.1460055e+08
J33: Certificado anteriormente | N33: =K28 -> 0
J34: Certificación del período s/IVA | N34: =L28 -> 14722545
J35: Total acumulado certificado | N35: =M28 -> 14722545
J36: Saldo certificable pendiente | N36: =N28 -> 99878006
J37: IVA del período | N37: =N34*Configuracion!B16 -> 3091734.4
J38: Total período c/IVA | N38: =N34+N37 -> 17814279
J39: Amortización anticipo (manual) | N39: 0
J40: Retención / fondo de reparo (manual) | N40: 0
J41: Otros descuentos / ajustes (manual) | N41: 0
J42: Neto estimado del período | N42: =N38-N39-N40-N41 -> 17814279
J44: Base del certificado: saldo de Red de Agua asignado proporcionalmente sobre $374.400.000 IVA incluido. Mes base contractual: JULIO 2026 – índice UOCRA.
A45: HISTORIAL: seleccionar el N° de certificado en B4 para consultar cualquier emisión. Las columnas ANTERIOR, PRESENTE y ACUMULADO se reconstruyen automáticamente. Una vez CERRADO el certificado, no modificar sus mediciones.

Sheet Conexiones
A1: CONTROL DE CONEXIONES DOMICILIARIAS – 227 UNIDADES
A3: Completar este registro como respaldo del ítem 10.1 / 10.2. Una conexión se considera certificable cuando está completamente ejecutada.
A5: N° | B5: Lote | C5: Manzana | D5: Tramo | E5: Diámetro red | F5: Ítem cert. | G5: Fecha apertura | H5: Fecha ejecución | I5: Fecha tapado | J5: Estado | K5: Inspección OSSE | L5: Observaciones
A6: 1 | F6: =IF(E6="Ø75","10.1",IF(E6="Ø110","10.2",""))
A7: 2 | F7: =IF(E7="Ø75","10.1",IF(E7="Ø110","10.2",""))
A8: 3 | F8: =IF(E8="Ø75","10.1",IF(E8="Ø110","10.2",""))
A9: 4 | F9: =IF(E9="Ø75","10.1",IF(E9="Ø110","10.2",""))
A10: 5 | F10: =IF(E10="Ø75","10.1",IF(E10="Ø110","10.2",""))
A11: 6 | F11: =IF(E11="Ø75","10.1",IF(E11="Ø110","10.2",""))
A12: 7 | F12: =IF(E12="Ø75","10.1",IF(E12="Ø110","10.2",""))
A13: 8 | F13: =IF(E13="Ø75","10.1",IF(E13="Ø110","10.2",""))
A14: 9 | F14: =IF(E14="Ø75","10.1",IF(E14="Ø110","10.2",""))
A15: 10 | F15: =IF(E15="Ø75","10.1",IF(E15="Ø110","10.2",""))
A16: 11 | F16: =IF(E16="Ø75","10.1",IF(E16="Ø110","10.2",""))
A17: 12 | F17: =IF(E17="Ø75","10.1",IF(E17="Ø110","10.2",""))
... A232: 227 | F232: =IF(E232="Ø75","10.1",IF(E232="Ø110","10.2",""))

Sheet Criterios Medicion
A1: CRITERIOS DE MEDICIÓN Y CERTIFICACIÓN POR ÍTEM
A4: Regla general: certificar cantidades físicamente terminadas y comprobables. Evitar porcentajes subjetivos en ítems lineales o unitarios.
A6: Ítem | B6: Actividad | C6: Unidad | D6: Cómo se mide | E6: Condición para certificar | F6: Carga en hoja Medicion | G6: No incluir / observación | H6: Ejemplo
A7: 1 | B7: Replanteo y marcación | C7: ml | D7: Longitud de traza efectivamente replanteada y marcada en terreno. | E7: Eje y límites de zanja identificados conforme al proyecto. | F7: Ingresar metros lineales terminados. | G7: No volver a certificar el mismo tramo. | H7: 120 ml replanteados = 120
A8: 2 | B8: Excavación de zanja | C8: ml | D8: Longitud de zanja excavada hasta profundidad y geometría necesarias para continuar. | E8: Zanja terminada y apta para acondicionar el fondo. | F8: Ingresar metros lineales de zanja terminada. | G8: Reexcavaciones o correcciones no se duplican salvo adicional aprobado. | H8: 80 ml terminados = 80
A9: 3 | B9: Nivelación y conformación de fondo | C9: ml | D9: Longitud con fondo limpiado, perfilado y nivelado. | E9: Fondo listo para recibir cama de asiento. | F9: Ingresar metros lineales terminados. | G9: No medir excavación; sólo acondicionamiento final del fondo. | H9: 80 ml listos = 80
A10: 4 | B10: Cama de asiento compactada | C10: ml | D10: Longitud donde el material de cama fue colocado, nivelado y compactado. | E10: Cama lista para recibir la cañería. | F10: Ingresar metros lineales terminados. | G10: El material y su compactación quedan incluidos en este ítem. | H10: 75 ml = 75
A11: 5.1 | B11: PEAD PN10 Ø75 – provisión e instalación | C11: ml | D11: Longitud de cañería Ø75 colocada dentro de zanja, unida, alineada y centrada. | E11: Cañería instalada en posición definitiva. | F11: Ingresar metros lineales instalados. | G11: Incluye provisión del caño dentro de esta apertura interna. | H11: 60 ml Ø75 = 60
A12: 5.2 | B12: PEAD PN10 Ø110 – provisión e instalación | C12: ml | D12: Longitud de cañería Ø110 colocada dentro de zanja, unida, alineada y centrada. | E12: Cañería instalada en posición definitiva. | F12: Ingresar metros lineales instalados. | G12: Incluye provisión del caño dentro de esta apertura interna. | H12: 40 ml Ø110 = 40
A13: 6 | B13: Paquete estructural 30 cm | C13: ml | D13: Longitud con material base colocado alrededor/sobre la cañería hasta completar el paquete previsto de 30 cm. | E13: Paquete completamente conformado y emparejado. | F13: Ingresar metros lineales terminados. | G13: No certificar parcialmente el espesor; medir longitud terminada. | H13: 50 ml completos = 50
A14: 7 | B14: Compactación paquete estructural 30 cm | C14: ml | D14: Longitud del paquete de 30 cm efectivamente compactado. | E14: Tramo compactado y en condición de solicitar inspección OSSE. | F14: Ingresar metros lineales compactados. | G14: Si requiere corrección, certificar cuando quede conforme. | H14: 50 ml compactados = 50
A15: 8 | B15: Capa cota -0,60 compactada | C15: ml | D15: Longitud con la capa correspondiente a cota -0,60 ejecutada y compactada. | E15: Capa terminada conforme al procedimiento de obra. | F15: Ingresar metros lineales terminados. | G15: Recomendado ejecutar luego de la liberación del tramo correspondiente. | H15: 40 ml = 40
A16: 9 | B16: Capa cota -0,30 compactada | C16: ml | D16: Longitud con la capa correspondiente a cota -0,30 ejecutada y compactada. | E16: Capa terminada conforme al procedimiento de obra. | F16: Ingresar metros lineales terminados. | G16: No confundir con paquete estructural de 30 cm. | H16: 30 ml = 30
A17: 10.1 | B17: Conexión domiciliaria sobre Ø75 | C17: un | D17: Cantidad de conexiones domiciliarias completas ejecutadas sobre red Ø75. | E17: Conexión realizada, tapada y en condición de quedar definitiva. | F17: Ingresar unidades completas. | G17: No certificar fracciones de una conexión. | H17: 4 conexiones = 4
... A24: 13.3 | B24: Documentación conforme a obra y cierre | C24: gl | D24: Avance de la documentación de cierre efectivamente preparada y aprobada. | E24: Entregables definidos y aceptados. | F24: Preferentemente cargar 1,00 al cierre; si se acuerdan hitos, usar fracciones objetivas. | G24: No anticipar porcentaje sin entregable verificable. | H24: Documentación final aprobada = 1,00
A26: NOTA ECONÓMICA: Los criterios de medición no cambian. Los P.U. se recalculan sobre el saldo certificable de la Red de Agua, distribuido proporcionalmente según la oferta original Agua/Cloaca. | B26: Los criterios de medición no cambian. Los P.U. se recalculan sobre el saldo certificable de la Red de Agua, distribuido proporcionalmente según la oferta original Agua/Cloaca.

Sheet Historial Certificados
A1: HISTORIAL DE CERTIFICADOS – RED DE AGUA | LOTEO ROQUE
A3: Cada emisión queda identificada por N° de certificado. Se calculan automáticamente ANTERIOR, PRESENTE y ACUMULADO. Al marcar un certificado como CERRADO, no deben modificarse sus mediciones.
A5: Cert. N° | B5: Período desde | C5: Período hasta | D5: Fecha emisión | E5: Estado | F5: Registros | G5: Anterior s/IVA | H5: Presente s/IVA | I5: Acumulado s/IVA | J5: Saldo s/IVA | K5: Avance acum. | L5: IVA presente | M5: Presente c/IVA | N5: Control | O5: Observaciones
A6: 1 | F6: =COUNTIF(Medicion!$A$6:$A$511,$A6) -> 72 | G6: =SUMIFS('Historial Detalle'!$K$6:$K$437,'Historial Detalle'!$A$6:$A$437,$A6) -> 0 | H6: =SUMIFS('Historial Detalle'!$L$6:$L$437,'Historial Detalle'!$A$6:$A$437,$A6) -> 14722545 | I6: =SUMIFS('Historial Detalle'!$M$6:$M$437,'Historial Detalle'!$A$6:$A$437,$A6) -> 14722545 | J6: =MAX(0,Configuracion!$B$18-I6) -> 99878006 | K6: =IFERROR(I6/Configuracion!$B$18,0) -> 0.12846836 | L6: =H6*Configuracion!$B$16 -> 3091734.4 | M6: =H6+L6 -> 17814279 | N6: =IF(COUNTIFS('Historial Detalle'!$A$6:$A$437,$A6,'Historial Detalle'!$P$6:$P$437,"REVISAR")>0,"REVISAR",IF(F6=0,"SIN MOVIMIENTO","OK")) -> OK
A7: 2 | F7: =COUNTIF(Medicion!$A$6:$A$511,$A7) -> 0 | G7: =SUMIFS('Historial Detalle'!$K$6:$K$437,'Historial Detalle'!$A$6:$A$437,$A7) -> 14722545 | H7: =SUMIFS('Historial Detalle'!$L$6:$L$437,'Historial Detalle'!$A$6:$A$437,$A7) -> 0 | I7: =SUMIFS('Historial Detalle'!$M$6:$M$437,'Historial Detalle'!$A$6:$A$437,$A7) -> 14722545 | J7: =MAX(0,Configuracion!$B$18-I7) -> 99878006 | K7: =IFERROR(I7/Configuracion!$B$18,0) -> 0.12846836 | L7: =H7*Configuracion!$B$16 -> 0 | M7: =H7+L7 -> 0 | N7: =IF(COUNTIFS('Historial Detalle'!$A$6:$A$437,$A7,'Historial Detalle'!$P$6:$P$437,"REVISAR")>0,"REVISAR",IF(F7=0,"SIN MOVIMIENTO","OK")) -> SIN MOVIMIENTO
A8: 3 | F8: =COUNTIF(Medicion!$A$6:$A$511,$A8) -> 0 | G8: =SUMIFS('Historial Detalle'!$K$6:$K$437,'Historial Detalle'!$A$6:$A$437,$A8) -> 14722545 | H8: =SUMIFS('Historial Detalle'!$L$6:$L$437,'Historial Detalle'!$A$6:$A$437,$A8) -> 0 | I8: =SUMIFS('Historial Detalle'!$M$6:$M$437,'Historial Detalle'!$A$6:$A$437,$A8) -> 14722545 | J8: =MAX(0,Configuracion!$B$18-I8) -> 99878006 | K8: =IFERROR(I8/Configuracion!$B$18,0) -> 0.12846836 | L8: =H8*Configuracion!$B$16 -> 0 | M8: =H8+L8 -> 0 | N8: =IF(COUNTIFS('Historial Detalle'!$A$6:$A$437,$A8,'Historial Detalle'!$P$6:$P$437,"REVISAR")>0,"REVISAR",IF(F8=0,"SIN MOVIMIENTO","OK")) -> SIN MOVIMIENTO
A9: 4 | F9: =COUNTIF(Medicion!$A$6:$A$511,$A9) -> 0 | G9: =SUMIFS('Historial Detalle'!$K$6:$K$437,'Historial Detalle'!$A$6:$A$437,$A9) -> 14722545 | H9: =SUMIFS('Historial Detalle'!$L$6:$L$437,'Historial Detalle'!$A$6:$A$437,$A9) -> 0 | I9: =SUMIFS('Historial Detalle'!$M$6:$M$437,'Historial Detalle'!$A$6:$A$437,$A9) -> 14722545 | J9: =MAX(0,Configuracion!$B$18-I9) -> 99878006 | K9: =IFERROR(I9/Configuracion!$B$18,0) -> 0.12846836 | L9: =H9*Configuracion!$B$16 -> 0 | M9: =H9+L9 -> 0 | N9: =IF(COUNTIFS('Historial Detalle'!$A$6:$A$437,$A9,'Historial Detalle'!$P$6:$P$437,"REVISAR")>0,"REVISAR",IF(F9=0,"SIN MOVIMIENTO","OK")) -> SIN MOVIMIENTO
A10: 5 | F10: =COUNTIF(Medicion!$A$6:$A$511,$A10) -> 0 | G10: =SUMIFS('Historial Detalle'!$K$6:$K$437,'Historial Detalle'!$A$6:$A$437,$A10) -> 14722545 | H10: =SUMIFS('Historial Detalle'!$L$6:$L$437,'Historial Detalle'!$A$6:$A$437,$A10) -> 0 | I10: =SUMIFS('Historial Detalle'!$M$6:$M$437,'Historial Detalle'!$A$6:$A$437,$A10) -> 14722545 | J10: =MAX(0,Configuracion!$B$18-I10) -> 99878006 | K10: =IFERROR(I10/Configuracion!$B$18,0) -> 0.12846836 | L10: =H10*Configuracion!$B$16 -> 0 | M10: =H10+L10 -> 0 | N10: =IF(COUNTIFS('Historial Detalle'!$A$6:$A$437,$A10,'Historial Detalle'!$P$6:$P$437,"REVISAR")>0,"REVISAR",IF(F10=0,"SIN MOVIMIENTO","OK")) -> SIN MOVIMIENTO
A11: 6 | F11: =COUNTIF(Medicion!$A$6:$A$511,$A11) -> 0 | G11: =SUMIFS('Historial Detalle'!$K$6:$K$437,'Historial Detalle'!$A$6:$A$437,$A11) -> 14722545 | H11: =SUMIFS('Historial Detalle'!$L$6:$L$437,'Historial Detalle'!$A$6:$A$437,$A11) -> 0 | I11: =SUMIFS('Historial Detalle'!$M$6:$M$437,'Historial Detalle'!$A$6:$A$437,$A11) -> 14722545 | J11: =MAX(0,Configuracion!$B$18-I11) -> 99878006 | K11: =IFERROR(I11/Configuracion!$B$18,0) -> 0.12846836 | L11: =H11*Configuracion!$B$16 -> 0 | M11: =H11+L11 -> 0 | N11: =IF(COUNTIFS('Historial Detalle'!$A$6:$A$437,$A11,'Historial Detalle'!$P$6:$P$437,"REVISAR")>0,"REVISAR",IF(F11=0,"SIN MOVIMIENTO","OK")) -> SIN MOVIMIENTO
A12: 7 | F12: =COUNTIF(Medicion!$A$6:$A$511,$A12) -> 0 | G12: =SUMIFS('Historial Detalle'!$K$6:$K$437,'Historial Detalle'!$A$6:$A$437,$A12) -> 14722545 | H12: =SUMIFS('Historial Detalle'!$L$6:$L$437,'Historial Detalle'!$A$6:$A$437,$A12) -> 0 | I12: =SUMIFS('Historial Detalle'!$M$6:$M$437,'Historial Detalle'!$A$6:$A$437,$A12) -> 14722545 | J12: =MAX(0,Configuracion!$B$18-I12) -> 99878006 | K12: =IFERROR(I12/Configuracion!$B$18,0) -> 0.12846836 | L12: =H12*Configuracion!$B$16 -> 0 | M12: =H12+L12 -> 0 | N12: =IF(COUNTIFS('Historial Detalle'!$A$6:$A$437,$A12,'Historial Detalle'!$P$6:$P$437,"REVISAR")>0,"REVISAR",IF(F12=0,"SIN MOVIMIENTO","OK")) -> SIN MOVIMIENTO
A13: 8 | F13: =COUNTIF(Medicion!$A$6:$A$511,$A13) -> 0 | G13: =SUMIFS('Historial Detalle'!$K$6:$K$437,'Historial Detalle'!$A$6:$A$437,$A13) -> 14722545 | H13: =SUMIFS('Historial Detalle'!$L$6:$L$437,'Historial Detalle'!$A$6:$A$437,$A13) -> 0 | I13: =SUMIFS('Historial Detalle'!$M$6:$M$437,'Historial Detalle'!$A$6:$A$437,$A13) -> 14722545 | J13: =MAX(0,Configuracion!$B$18-I13) -> 99878006 | K13: =IFERROR(I13/Configuracion!$B$18,0) -> 0.12846836 | L13: =H13*Configuracion!$B$16 -> 0 | M13: =H13+L13 -> 0 | N13: =IF(COUNTIFS('Historial Detalle'!$A$6:$A$437,$A13,'Historial Detalle'!$P$6:$P$437,"REVISAR")>0,"REVISAR",IF(F13=0,"SIN MOVIMIENTO","OK")) -> SIN MOVIMIENTO
A14: 9 | F14: =COUNTIF(Medicion!$A$6:$A$511,$A14) -> 0 | G14: =SUMIFS('Historial Detalle'!$K$6:$K$437,'Historial Detalle'!$A$6:$A$437,$A14) -> 14722545 | H14: =SUMIFS('Historial Detalle'!$L$6:$L$437,'Historial Detalle'!$A$6:$A$437,$A14) -> 0 | I14: =SUMIFS('Historial Detalle'!$M$6:$M$437,'Historial Detalle'!$A$6:$A$437,$A14) -> 14722545 | J14: =MAX(0,Configuracion!$B$18-I14) -> 99878006 | K14: =IFERROR(I14/Configuracion!$B$18,0) -> 0.12846836 | L14: =H14*Configuracion!$B$16 -> 0 | M14: =H14+L14 -> 0 | N14: =IF(COUNTIFS('Historial Detalle'!$A$6:$A$437,$A14,'Historial Detalle'!$P$6:$P$437,"REVISAR")>0,"REVISAR",IF(F14=0,"SIN MOVIMIENTO","OK")) -> SIN MOVIMIENTO
A15: 10 | F15: =COUNTIF(Medicion!$A$6:$A$511,$A15) -> 0 | G15: =SUMIFS('Historial Detalle'!$K$6:$K$437,'Historial Detalle'!$A$6:$A$437,$A15) -> 14722545 | H15: =SUMIFS('Historial Detalle'!$L$6:$L$437,'Historial Detalle'!$A$6:$A$437,$A15) -> 0 | I15: =SUMIFS('Historial Detalle'!$M$6:$M$437,'Historial Detalle'!$A$6:$A$437,$A15) -> 14722545 | J15: =MAX(0,Configuracion!$B$18-I15) -> 99878006 | K15: =IFERROR(I15/Configuracion!$B$18,0) -> 0.12846836 | L15: =H15*Configuracion!$B$16 -> 0 | M15: =H15+L15 -> 0 | N15: =IF(COUNTIFS('Historial Detalle'!$A$6:$A$437,$A15,'Historial Detalle'!$P$6:$P$437,"REVISAR")>0,"REVISAR",IF(F15=0,"SIN MOVIMIENTO","OK")) -> SIN MOVIMIENTO
A16: 11 | F16: =COUNTIF(Medicion!$A$6:$A$511,$A16) -> 0 | G16: =SUMIFS('Historial Detalle'!$K$6:$K$437,'Historial Detalle'!$A$6:$A$437,$A16) -> 14722545 | H16: =SUMIFS('Historial Detalle'!$L$6:$L$437,'Historial Detalle'!$A$6:$A$437,$A16) -> 0 | I16: =SUMIFS('Historial Detalle'!$M$6:$M$437,'Historial Detalle'!$A$6:$A$437,$A16) -> 14722545 | J16: =MAX(0,Configuracion!$B$18-I16) -> 99878006 | K16: =IFERROR(I16/Configuracion!$B$18,0) -> 0.12846836 | L16: =H16*Configuracion!$B$16 -> 0 | M16: =H16+L16 -> 0 | N16: =IF(COUNTIFS('Historial Detalle'!$A$6:$A$437,$A16,'Historial Detalle'!$P$6:$P$437,"REVISAR")>0,"REVISAR",IF(F16=0,"SIN MOVIMIENTO","OK")) -> SIN MOVIMIENTO
A17: 12 | F17: =COUNTIF(Medicion!$A$6:$A$511,$A17) -> 0 | G17: =SUMIFS('Historial Detalle'!$K$6:$K$437,'Historial Detalle'!$A$6:$A$437,$A17) -> 14722545 | H17: =SUMIFS('Historial Detalle'!$L$6:$L$437,'Historial Detalle'!$A$6:$A$437,$A17) -> 0 | I17: =SUMIFS('Historial Detalle'!$M$6:$M$437,'Historial Detalle'!$A$6:$A$437,$A17) -> 14722545 | J17: =MAX(0,Configuracion!$B$18-I17) -> 99878006 | K17: =IFERROR(I17/Configuracion!$B$18,0) -> 0.12846836 | L17: =H17*Configuracion!$B$16 -> 0 | M17: =H17+L17 -> 0 | N17: =IF(COUNTIFS('Historial Detalle'!$A$6:$A$437,$A17,'Historial Detalle'!$P$6:$P$437,"REVISAR")>0,"REVISAR",IF(F17=0,"SIN MOVIMIENTO","OK")) -> SIN MOVIMIENTO
... A29: 24 | F29: =COUNTIF(Medicion!$A$6:$A$511,$A29) -> 0 | G29: =SUMIFS('Historial Detalle'!$K$6:$K$437,'Historial Detalle'!$A$6:$A$437,$A29) -> 14722545 | H29: =SUMIFS('Historial Detalle'!$L$6:$L$437,'Historial Detalle'!$A$6:$A$437,$A29) -> 0 | I29: =SUMIFS('Historial Detalle'!$M$6:$M$437,'Historial Detalle'!$A$6:$A$437,$A29) -> 14722545 | J29: =MAX(0,Configuracion!$B$18-I29) -> 99878006 | K29: =IFERROR(I29/Configuracion!$B$18,0) -> 0.12846836 | L29: =H29*Configuracion!$B$16 -> 0 | M29: =H29+L29 -> 0 | N29: =IF(COUNTIFS('Historial Detalle'!$A$6:$A$437,$A29,'Historial Detalle'!$P$6:$P$437,"REVISAR")>0,"REVISAR",IF(F29=0,"SIN MOVIMIENTO","OK")) -> SIN MOVIMIENTO
A31: CONTROL DE HISTORIAL
A32: Último certificado con movimiento | B32: =MAX(Medicion!$A$6:$A$511) -> 1
A33: Certificados cerrados | B33: =COUNTIF($E$6:$E$29,"CERRADO") -> 0
A34: Saldo certificable base s/IVA | B34: =Configuracion!$B$18 -> 1.1460055e+08
A35: Regla de cierre | B35: Una vez CERRADO, no editar sus mediciones.

Sheet Historial Detalle
A1: HISTORIAL DETALLADO POR ÍTEM – ANTERIOR / PRESENTE / ACUMULADO
A3: Trazabilidad automática de cada ítem en cada certificado. Permite consultar cualquier emisión sin perder las anteriores.
A5: Cert. N° | B5: Ítem | C5: Descripción | D5: Un. | E5: Cant. contractual | F5: P.U. s/IVA | G5: Importe contractual | H5: Cant. anterior | I5: Cant. presente | J5: Cant. acumulada | K5: Importe anterior | L5: Importe presente | M5: Importe acumulado | N5: Saldo | O5: % avance acum. | P5: Control
A6: 1 | B6: ='Presupuesto Base'!A7 -> 1 | C6: ='Presupuesto Base'!B7 -> Replanteo y marcación de traza | D6: ='Presupuesto Base'!C7 -> ml | E6: ='Presupuesto Base'!D7 -> 4200 | F6: ='Presupuesto Base'!E7 -> 204.64384 | G6: ='Presupuesto Base'!F7 -> 859504.13 | H6: =SUMIFS(Medicion!$K$6:$K$511,Medicion!$G$6:$G$511,$B6,Medicion!$A$6:$A$511,"<"&$A6) -> 0 | I6: =SUMIFS(Medicion!$K$6:$K$511,Medicion!$G$6:$G$511,$B6,Medicion!$A$6:$A$511,$A6) -> 845 | J6: =MIN(E6,H6+I6) -> 845 | K6: =MIN(G6,H6*F6) -> 0 | L6: =MIN(G6-K6,I6*F6) -> 172924.05 | M6: =K6+L6 -> 172924.05 | N6: =MAX(0,G6-M6) -> 686580.09 | O6: =IFERROR(J6/E6,0) -> 0.20119048 | P6: =IF(OR(H6+I6>E6+0.000001,H6<0,I6<0),"REVISAR","OK") -> OK
A7: 1 | B7: ='Presupuesto Base'!A8 -> 2 | C7: ='Presupuesto Base'!B8 -> Excavación de zanja | D7: ='Presupuesto Base'!C8 -> ml | E7: ='Presupuesto Base'!D8 -> 4200 | F7: ='Presupuesto Base'!E8 -> 3683.5891 | G7: ='Presupuesto Base'!F8 -> 15471074 | H7: =SUMIFS(Medicion!$K$6:$K$511,Medicion!$G$6:$G$511,$B7,Medicion!$A$6:$A$511,"<"&$A7) -> 0 | I7: =SUMIFS(Medicion!$K$6:$K$511,Medicion!$G$6:$G$511,$B7,Medicion!$A$6:$A$511,$A7) -> 845 | J7: =MIN(E7,H7+I7) -> 845 | K7: =MIN(G7,H7*F7) -> 0 | L7: =MIN(G7-K7,I7*F7) -> 3112632.8 | M7: =K7+L7 -> 3112632.8 | N7: =MAX(0,G7-M7) -> 12358442 | O7: =IFERROR(J7/E7,0) -> 0.20119048 | P7: =IF(OR(H7+I7>E7+0.000001,H7<0,I7<0),"REVISAR","OK") -> OK
A8: 1 | B8: ='Presupuesto Base'!A9 -> 3 | C8: ='Presupuesto Base'!B9 -> Nivelación y conformación del fondo de zanja | D8: ='Presupuesto Base'!C9 -> ml | E8: ='Presupuesto Base'!D9 -> 4200 | F8: ='Presupuesto Base'!E9 -> 477.5023 | G8: ='Presupuesto Base'!F9 -> 2005509.6 | H8: =SUMIFS(Medicion!$K$6:$K$511,Medicion!$G$6:$G$511,$B8,Medicion!$A$6:$A$511,"<"&$A8) -> 0 | I8: =SUMIFS(Medicion!$K$6:$K$511,Medicion!$G$6:$G$511,$B8,Medicion!$A$6:$A$511,$A8) -> 845 | J8: =MIN(E8,H8+I8) -> 845 | K8: =MIN(G8,H8*F8) -> 0 | L8: =MIN(G8-K8,I8*F8) -> 403489.44 | M8: =K8+L8 -> 403489.44 | N8: =MAX(0,G8-M8) -> 1602020.2 | O8: =IFERROR(J8/E8,0) -> 0.20119048 | P8: =IF(OR(H8+I8>E8+0.000001,H8<0,I8<0),"REVISAR","OK") -> OK
A9: 1 | B9: ='Presupuesto Base'!A10 -> 4 | C9: ='Presupuesto Base'!B10 -> Cama de asiento compactada | D9: ='Presupuesto Base'!C10 -> ml | E9: ='Presupuesto Base'!D10 -> 4200 | F9: ='Presupuesto Base'!E10 -> 1705.3653 | G9: ='Presupuesto Base'!F10 -> 7162534.4 | H9: =SUMIFS(Medicion!$K$6:$K$511,Medicion!$G$6:$G$511,$B9,Medicion!$A$6:$A$511,"<"&$A9) -> 0 | I9: =SUMIFS(Medicion!$K$6:$K$511,Medicion!$G$6:$G$511,$B9,Medicion!$A$6:$A$511,$A9) -> 845 | J9: =MIN(E9,H9+I9) -> 845 | K9: =MIN(G9,H9*F9) -> 0 | L9: =MIN(G9-K9,I9*F9) -> 1441033.7 | M9: =K9+L9 -> 1441033.7 | N9: =MAX(0,G9-M9) -> 5721500.7 | O9: =IFERROR(J9/E9,0) -> 0.20119048 | P9: =IF(OR(H9+I9>E9+0.000001,H9<0,I9<0),"REVISAR","OK") -> OK
A10: 1 | B10: ='Presupuesto Base'!A11 -> 5.1 | C10: ='Presupuesto Base'!B11 -> PEAD PN10 Ø75 – provisión e instalación | D10: ='Presupuesto Base'!C11 -> ml | E10: ='Presupuesto Base'!D11 -> 3170 | F10: ='Presupuesto Base'!E11 -> 5784.2549 | G10: ='Presupuesto Base'!F11 -> 18336088 | H10: =SUMIFS(Medicion!$K$6:$K$511,Medicion!$G$6:$G$511,$B10,Medicion!$A$6:$A$511,"<"&$A10) -> 0 | I10: =SUMIFS(Medicion!$K$6:$K$511,Medicion!$G$6:$G$511,$B10,Medicion!$A$6:$A$511,$A10) -> 558 | J10: =MIN(E10,H10+I10) -> 558 | K10: =MIN(G10,H10*F10) -> 0 | L10: =MIN(G10-K10,I10*F10) -> 3227614.3 | M10: =K10+L10 -> 3227614.3 | N10: =MAX(0,G10-M10) -> 15108474 | O10: =IFERROR(J10/E10,0) -> 0.17602524 | P10: =IF(OR(H10+I10>E10+0.000001,H10<0,I10<0),"REVISAR","OK") -> OK
A11: 1 | B11: ='Presupuesto Base'!A12 -> 5.2 | C11: ='Presupuesto Base'!B12 -> PEAD PN10 Ø110 – provisión e instalación | D11: ='Presupuesto Base'!C12 -> ml | E11: ='Presupuesto Base'!D12 -> 1030 | F11: ='Presupuesto Base'!E12 -> 12238.894 | G11: ='Presupuesto Base'!F12 -> 12606061 | H11: =SUMIFS(Medicion!$K$6:$K$511,Medicion!$G$6:$G$511,$B11,Medicion!$A$6:$A$511,"<"&$A11) -> 0 | I11: =SUMIFS(Medicion!$K$6:$K$511,Medicion!$G$6:$G$511,$B11,Medicion!$A$6:$A$511,$A11) -> 287 | J11: =MIN(E11,H11+I11) -> 287 | K11: =MIN(G11,H11*F11) -> 0 | L11: =MIN(G11-K11,I11*F11) -> 3512562.5 | M11: =K11+L11 -> 3512562.5 | N11: =MAX(0,G11-M11) -> 9093498.1 | O11: =IFERROR(J11/E11,0) -> 0.27864078 | P11: =IF(OR(H11+I11>E11+0.000001,H11<0,I11<0),"REVISAR","OK") -> OK
A12: 1 | B12: ='Presupuesto Base'!A13 -> 6 | C12: ='Presupuesto Base'!B13 -> Ejecución de paquete estructural de 30 cm | D12: ='Presupuesto Base'!C13 -> ml | E12: ='Presupuesto Base'!D13 -> 4200 | F12: ='Presupuesto Base'!E13 -> 3274.3015 | G12: ='Presupuesto Base'!F13 -> 13752066 | H12: =SUMIFS(Medicion!$K$6:$K$511,Medicion!$G$6:$G$511,$B12,Medicion!$A$6:$A$511,"<"&$A12) -> 0 | I12: =SUMIFS(Medicion!$K$6:$K$511,Medicion!$G$6:$G$511,$B12,Medicion!$A$6:$A$511,$A12) -> 763 | J12: =MIN(E12,H12+I12) -> 763 | K12: =MIN(G12,H12*F12) -> 0 | L12: =MIN(G12-K12,I12*F12) -> 2498292 | M12: =K12+L12 -> 2498292 | N12: =MAX(0,G12-M12) -> 11253774 | O12: =IFERROR(J12/E12,0) -> 0.18166667 | P12: =IF(OR(H12+I12>E12+0.000001,H12<0,I12<0),"REVISAR","OK") -> OK
A13: 1 | B13: ='Presupuesto Base'!A14 -> 7 | C13: ='Presupuesto Base'!B14 -> Compactación del paquete estructural de 30 cm | D13: ='Presupuesto Base'!C14 -> ml | E13: ='Presupuesto Base'!D14 -> 4200 | F13: ='Presupuesto Base'!E14 -> 1227.863 | G13: ='Presupuesto Base'!F14 -> 5157024.8 | H13: =SUMIFS(Medicion!$K$6:$K$511,Medicion!$G$6:$G$511,$B13,Medicion!$A$6:$A$511,"<"&$A13) -> 0 | I13: =SUMIFS(Medicion!$K$6:$K$511,Medicion!$G$6:$G$511,$B13,Medicion!$A$6:$A$511,$A13) -> 0 | J13: =MIN(E13,H13+I13) -> 0 | K13: =MIN(G13,H13*F13) -> 0 | L13: =MIN(G13-K13,I13*F13) -> 0 | M13: =K13+L13 -> 0 | N13: =MAX(0,G13-M13) -> 5157024.8 | O13: =IFERROR(J13/E13,0) -> 0 | P13: =IF(OR(H13+I13>E13+0.000001,H13<0,I13<0),"REVISAR","OK") -> OK
A14: 1 | B14: ='Presupuesto Base'!A15 -> 8 | C14: ='Presupuesto Base'!B15 -> Ejecución y compactación de capa cota -0,60 | D14: ='Presupuesto Base'!C15 -> ml | E14: ='Presupuesto Base'!D15 -> 4200 | F14: ='Presupuesto Base'!E15 -> 2592.1553 | G14: ='Presupuesto Base'!F15 -> 10887052 | H14: =SUMIFS(Medicion!$K$6:$K$511,Medicion!$G$6:$G$511,$B14,Medicion!$A$6:$A$511,"<"&$A14) -> 0 | I14: =SUMIFS(Medicion!$K$6:$K$511,Medicion!$G$6:$G$511,$B14,Medicion!$A$6:$A$511,$A14) -> 0 | J14: =MIN(E14,H14+I14) -> 0 | K14: =MIN(G14,H14*F14) -> 0 | L14: =MIN(G14-K14,I14*F14) -> 0 | M14: =K14+L14 -> 0 | N14: =MAX(0,G14-M14) -> 10887052 | O14: =IFERROR(J14/E14,0) -> 0 | P14: =IF(OR(H14+I14>E14+0.000001,H14<0,I14<0),"REVISAR","OK") -> OK
A15: 1 | B15: ='Presupuesto Base'!A16 -> 9 | C15: ='Presupuesto Base'!B16 -> Ejecución y compactación de capa cota -0,30 | D15: ='Presupuesto Base'!C16 -> ml | E15: ='Presupuesto Base'!D16 -> 4200 | F15: ='Presupuesto Base'!E16 -> 2182.8676 | G15: ='Presupuesto Base'!F16 -> 9168044.1 | H15: =SUMIFS(Medicion!$K$6:$K$511,Medicion!$G$6:$G$511,$B15,Medicion!$A$6:$A$511,"<"&$A15) -> 0 | I15: =SUMIFS(Medicion!$K$6:$K$511,Medicion!$G$6:$G$511,$B15,Medicion!$A$6:$A$511,$A15) -> 0 | J15: =MIN(E15,H15+I15) -> 0 | K15: =MIN(G15,H15*F15) -> 0 | L15: =MIN(G15-K15,I15*F15) -> 0 | M15: =K15+L15 -> 0 | N15: =MAX(0,G15-M15) -> 9168044.1 | O15: =IFERROR(J15/E15,0) -> 0 | P15: =IF(OR(H15+I15>E15+0.000001,H15<0,I15<0),"REVISAR","OK") -> OK
A16: 1 | B16: ='Presupuesto Base'!A17 -> 10.1 | C16: ='Presupuesto Base'!B17 -> Conexión domiciliaria sobre red Ø75 | D16: ='Presupuesto Base'!C17 -> un | E16: ='Presupuesto Base'!D17 -> 165 | F16: ='Presupuesto Base'!E17 -> 48618.416 | G16: ='Presupuesto Base'!F17 -> 8022038.6 | H16: =SUMIFS(Medicion!$K$6:$K$511,Medicion!$G$6:$G$511,$B16,Medicion!$A$6:$A$511,"<"&$A16) -> 0 | I16: =SUMIFS(Medicion!$K$6:$K$511,Medicion!$G$6:$G$511,$B16,Medicion!$A$6:$A$511,$A16) -> 5 | J16: =MIN(E16,H16+I16) -> 5 | K16: =MIN(G16,H16*F16) -> 0 | L16: =MIN(G16-K16,I16*F16) -> 243092.08 | M16: =K16+L16 -> 243092.08 | N16: =MAX(0,G16-M16) -> 7778946.5 | O16: =IFERROR(J16/E16,0) -> 0.03030303 | P16: =IF(OR(H16+I16>E16+0.000001,H16<0,I16<0),"REVISAR","OK") -> OK
A17: 1 | B17: ='Presupuesto Base'!A18 -> 10.2 | C17: ='Presupuesto Base'!B18 -> Conexión domiciliaria sobre red Ø110 | D17: ='Presupuesto Base'!C18 -> un | E17: ='Presupuesto Base'!D18 -> 62 | F17: ='Presupuesto Base'!E18 -> 55451.879 | G17: ='Presupuesto Base'!F18 -> 3438016.5 | H17: =SUMIFS(Medicion!$K$6:$K$511,Medicion!$G$6:$G$511,$B17,Medicion!$A$6:$A$511,"<"&$A17) -> 0 | I17: =SUMIFS(Medicion!$K$6:$K$511,Medicion!$G$6:$G$511,$B17,Medicion!$A$6:$A$511,$A17) -> 2 | J17: =MIN(E17,H17+I17) -> 2 | K17: =MIN(G17,H17*F17) -> 0 | L17: =MIN(G17-K17,I17*F17) -> 110903.76 | M17: =K17+L17 -> 110903.76 | N17: =MAX(0,G17-M17) -> 3327112.8 | O17: =IFERROR(J17/E17,0) -> 0.032258065 | P17: =IF(OR(H17+I17>E17+0.000001,H17<0,I17<0),"REVISAR","OK") -> OK
... A23: 1 | B23: ='Presupuesto Base'!A24 -> 13.3 | C23: ='Presupuesto Base'!B24 -> Documentación conforme a obra y cierre | D23: ='Presupuesto Base'!C24 -> gl | E23: ='Presupuesto Base'!D24 -> 1 | F23: ='Presupuesto Base'!E24 -> 859504.13 | G23: ='Presupuesto Base'!F24 -> 859504.13 | H23: =SUMIFS(Medicion!$K$6:$K$511,Medicion!$G$6:$G$511,$B23,Medicion!$A$6:$A$511,"<"&$A23) -> 0 | I23: =SUMIFS(Medicion!$K$6:$K$511,Medicion!$G$6:$G$511,$B23,Medicion!$A$6:$A$511,$A23) -> 0 | J23: =MIN(E23,H23+I23) -> 0 | K23: =MIN(G23,H23*F23) -> 0 | L23: =MIN(G23-K23,I23*F23) -> 0 | M23: =K23+L23 -> 0 | N23: =MAX(0,G23-M23) -> 859504.13 | O23: =IFERROR(J23/E23,0) -> 0 | P23: =IF(OR(H23+I23>E23+0.000001,H23<0,I23<0),"REVISAR","OK") -> OK
A24: 2 | B24: ='Presupuesto Base'!A7 -> 1 | C24: ='Presupuesto Base'!B7 -> Replanteo y marcación de traza | D24: ='Presupuesto Base'!C7 -> ml | E24: ='Presupuesto Base'!D7 -> 4200 | F24: ='Presupuesto Base'!E7 -> 204.64384 | G24: ='Presupuesto Base'!F7 -> 859504.13 | H24: =SUMIFS(Medicion!$K$6:$K$511,Medicion!$G$6:$G$511,$B24,Medicion!$A$6:$A$511,"<"&$A24) -> 845 | I24: =SUMIFS(Medicion!$K$6:$K$511,Medicion!$G$6:$G$511,$B24,Medicion!$A$6:$A$511,$A24) -> 0 | J24: =MIN(E24,H24+I24) -> 845 | K24: =MIN(G24,H24*F24) -> 172924.05 | L24: =MIN(G24-K24,I24*F24) -> 0 | M24: =K24+L24 -> 172924.05 | N24: =MAX(0,G24-M24) -> 686580.09 | O24: =IFERROR(J24/E24,0) -> 0.20119048 | P24: =IF(OR(H24+I24>E24+0.000001,H24<0,I24<0),"REVISAR","OK") -> OK
A25: 2 | B25: ='Presupuesto Base'!A8 -> 2 | C25: ='Presupuesto Base'!B8 -> Excavación de zanja | D25: ='Presupuesto Base'!C8 -> ml | E25: ='Presupuesto Base'!D8 -> 4200 | F25: ='Presupuesto Base'!E8 -> 3683.5891 | G25: ='Presupuesto Base'!F8 -> 15471074 | H25: =SUMIFS(Medicion!$K$6:$K$511,Medicion!$G$6:$G$511,$B25,Medicion!$A$6:$A$511,"<"&$A25) -> 845 | I25: =SUMIFS(Medicion!$K$6:$K$511,Medicion!$G$6:$G$511,$B25,Medicion!$A$6:$A$511,$A25) -> 0 | J25: =MIN(E25,H25+I25) -> 845 | K25: =MIN(G25,H25*F25) -> 3112632.8 | L25: =MIN(G25-K25,I25*F25) -> 0 | M25: =K25+L25 -> 3112632.8 | N25: =MAX(0,G25-M25) -> 12358442 | O25: =IFERROR(J25/E25,0) -> 0.20119048 | P25: =IF(OR(H25+I25>E25+0.000001,H25<0,I25<0),"REVISAR","OK") -> OK
A26: 2 | B26: ='Presupuesto Base'!A9 -> 3 | C26: ='Presupuesto Base'!B9 -> Nivelación y conformación del fondo de zanja | D26: ='Presupuesto Base'!C9 -> ml | E26: ='Presupuesto Base'!D9 -> 4200 | F26: ='Presupuesto Base'!E9 -> 477.5023 | G26: ='Presupuesto Base'!F9 -> 2005509.6 | H26: =SUMIFS(Medicion!$K$6:$K$511,Medicion!$G$6:$G$511,$B26,Medicion!$A$6:$A$511,"<"&$A26) -> 845 | I26: =SUMIFS(Medicion!$K$6:$K$511,Medicion!$G$6:$G$511,$B26,Medicion!$A$6:$A$511,$A26) -> 0 | J26: =MIN(E26,H26+I26) -> 845 | K26: =MIN(G26,H26*F26) -> 403489.44 | L26: =MIN(G26-K26,I26*F26) -> 0 | M26: =K26+L26 -> 403489.44 | N26: =MAX(0,G26-M26) -> 1602020.2 | O26: =IFERROR(J26/E26,0) -> 0.20119048 | P26: =IF(OR(H26+I26>E26+0.000001,H26<0,I26<0),"REVISAR","OK") -> OK
A27: 2 | B27: ='Presupuesto Base'!A10 -> 4 | C27: ='Presupuesto Base'!B10 -> Cama de asiento compactada | D27: ='Presupuesto Base'!C10 -> ml | E27: ='Presupuesto Base'!D10 -> 4200 | F27: ='Presupuesto Base'!E10 -> 1705.3653 | G27: ='Presupuesto Base'!F10 -> 7162534.4 | H27: =SUMIFS(Medicion!$K$6:$K$511,Medicion!$G$6:$G$511,$B27,Medicion!$A$6:$A$511,"<"&$A27) -> 845 | I27: =SUMIFS(Medicion!$K$6:$K$511,Medicion!$G$6:$G$511,$B27,Medicion!$A$6:$A$511,$A27) -> 0 | J27: =MIN(E27,H27+I27) -> 845 | K27: =MIN(G27,H27*F27) -> 1441033.7 | L27: =MIN(G27-K27,I27*F27) -> 0 | M27: =K27+L27 -> 1441033.7 | N27: =MAX(0,G27-M27) -> 5721500.7 | O27: =IFERROR(J27/E27,0) -> 0.20119048 | P27: =IF(OR(H27+I27>E27+0.000001,H27<0,I27<0),"REVISAR","OK") -> OK
A28: 2 | B28: ='Presupuesto Base'!A11 -> 5.1 | C28: ='Presupuesto Base'!B11 -> PEAD PN10 Ø75 – provisión e instalación | D28: ='Presupuesto Base'!C11 -> ml | E28: ='Presupuesto Base'!D11 -> 3170 | F28: ='Presupuesto Base'!E11 -> 5784.2549 | G28: ='Presupuesto Base'!F11 -> 18336088 | H28: =SUMIFS(Medicion!$K$6:$K$511,Medicion!$G$6:$G$511,$B28,Medicion!$A$6:$A$511,"<"&$A28) -> 558 | I28: =SUMIFS(Medicion!$K$6:$K$511,Medicion!$G$6:$G$511,$B28,Medicion!$A$6:$A$511,$A28) -> 0 | J28: =MIN(E28,H28+I28) -> 558 | K28: =MIN(G28,H28*F28) -> 3227614.3 | L28: =MIN(G28-K28,I28*F28) -> 0 | M28: =K28+L28 -> 3227614.3 | N28: =MAX(0,G28-M28) -> 15108474 | O28: =IFERROR(J28/E28,0) -> 0.17602524 | P28: =IF(OR(H28+I28>E28+0.000001,H28<0,I28<0),"REVISAR","OK") -> OK
A29: 2 | B29: ='Presupuesto Base'!A12 -> 5.2 | C29: ='Presupuesto Base'!B12 -> PEAD PN10 Ø110 – provisión e instalación | D29: ='Presupuesto Base'!C12 -> ml | E29: ='Presupuesto Base'!D12 -> 1030 | F29: ='Presupuesto Base'!E12 -> 12238.894 | G29: ='Presupuesto Base'!F12 -> 12606061 | H29: =SUMIFS(Medicion!$K$6:$K$511,Medicion!$G$6:$G$511,$B29,Medicion!$A$6:$A$511,"<"&$A29) -> 287 | I29: =SUMIFS(Medicion!$K$6:$K$511,Medicion!$G$6:$G$511,$B29,Medicion!$A$6:$A$511,$A29) -> 0 | J29: =MIN(E29,H29+I29) -> 287 | K29: =MIN(G29,H29*F29) -> 3512562.5 | L29: =MIN(G29-K29,I29*F29) -> 0 | M29: =K29+L29 -> 3512562.5 | N29: =MAX(0,G29-M29) -> 9093498.1 | O29: =IFERROR(J29/E29,0) -> 0.27864078 | P29: =IF(OR(H29+I29>E29+0.000001,H29<0,I29<0),"REVISAR","OK") -> OK
A30: 2 | B30: ='Presupuesto Base'!A13 -> 6 | C30: ='Presupuesto Base'!B13 -> Ejecución de paquete estructural de 30 cm | D30: ='Presupuesto Base'!C13 -> ml | E30: ='Presupuesto Base'!D13 -> 4200 | F30: ='Presupuesto Base'!E13 -> 3274.3015 | G30: ='Presupuesto Base'!F13 -> 13752066 | H30: =SUMIFS(Medicion!$K$6:$K$511,Medicion!$G$6:$G$511,$B30,Medicion!$A$6:$A$511,"<"&$A30) -> 763 | I30: =SUMIFS(Medicion!$K$6:$K$511,Medicion!$G$6:$G$511,$B30,Medicion!$A$6:$A$511,$A30) -> 0 | J30: =MIN(E30,H30+I30) -> 763 | K30: =MIN(G30,H30*F30) -> 2498292 | L30: =MIN(G30-K30,I30*F30) -> 0 | M30: =K30+L30 -> 2498292 | N30: =MAX(0,G30-M30) -> 11253774 | O30: =IFERROR(J30/E30,0) -> 0.18166667 | P30: =IF(OR(H30+I30>E30+0.000001,H30<0,I30<0),"REVISAR","OK") -> OK
A31: 2 | B31: ='Presupuesto Base'!A14 -> 7 | C31: ='Presupuesto Base'!B14 -> Compactación del paquete estructural de 30 cm | D31: ='Presupuesto Base'!C14 -> ml | E31: ='Presupuesto Base'!D14 -> 4200 | F31: ='Presupuesto Base'!E14 -> 1227.863 | G31: ='Presupuesto Base'!F14 -> 5157024.8 | H31: =SUMIFS(Medicion!$K$6:$K$511,Medicion!$G$6:$G$511,$B31,Medicion!$A$6:$A$511,"<"&$A31) -> 0 | I31: =SUMIFS(Medicion!$K$6:$K$511,Medicion!$G$6:$G$511,$B31,Medicion!$A$6:$A$511,$A31) -> 0 | J31: =MIN(E31,H31+I31) -> 0 | K31: =MIN(G31,H31*F31) -> 0 | L31: =MIN(G31-K31,I31*F31) -> 0 | M31: =K31+L31 -> 0 | N31: =MAX(0,G31-M31) -> 5157024.8 | O31: =IFERROR(J31/E31,0) -> 0 | P31: =IF(OR(H31+I31>E31+0.000001,H31<0,I31<0),"REVISAR","OK") -> OK
A32: 2 | B32: ='Presupuesto Base'!A15 -> 8 | C32: ='Presupuesto Base'!B15 -> Ejecución y compactación de capa cota -0,60 | D32: ='Presupuesto Base'!C15 -> ml | E32: ='Presupuesto Base'!D15 -> 4200 | F32: ='Presupuesto Base'!E15 -> 2592.1553 | G32: ='Presupuesto Base'!F15 -> 10887052 | H32: =SUMIFS(Medicion!$K$6:$K$511,Medicion!$G$6:$G$511,$B32,Medicion!$A$6:$A$511,"<"&$A32) -> 0 | I32: =SUMIFS(Medicion!$K$6:$K$511,Medicion!$G$6:$G$511,$B32,Medicion!$A$6:$A$511,$A32) -> 0 | J32: =MIN(E32,H32+I32) -> 0 | K32: =MIN(G32,H32*F32) -> 0 | L32: =MIN(G32-K32,I32*F32) -> 0 | M32: =K32+L32 -> 0 | N32: =MAX(0,G32-M32) -> 10887052 | O32: =IFERROR(J32/E32,0) -> 0 | P32: =IF(OR(H32+I32>E32+0.000001,H32<0,I32<0),"REVISAR","OK") -> OK
A33: 2 | B33: ='Presupuesto Base'!A16 -> 9 | C33: ='Presupuesto Base'!B16 -> Ejecución y compactación de capa cota -0,30 | D33: ='Presupuesto Base'!C16 -> ml | E33: ='Presupuesto Base'!D16 -> 4200 | F33: ='Presupuesto Base'!E16 -> 2182.8676 | G33: ='Presupuesto Base'!F16 -> 9168044.1 | H33: =SUMIFS(Medicion!$K$6:$K$511,Medicion!$G$6:$G$511,$B33,Medicion!$A$6:$A$511,"<"&$A33) -> 0 | I33: =SUMIFS(Medicion!$K$6:$K$511,Medicion!$G$6:$G$511,$B33,Medicion!$A$6:$A$511,$A33) -> 0 | J33: =MIN(E33,H33+I33) -> 0 | K33: =MIN(G33,H33*F33) -> 0 | L33: =MIN(G33-K33,I33*F33) -> 0 | M33: =K33+L33 -> 0 | N33: =MAX(0,G33-M33) -> 9168044.1 | O33: =IFERROR(J33/E33,0) -> 0 | P33: =IF(OR(H33+I33>E33+0.000001,H33<0,I33<0),"REVISAR","OK") -> OK
A34: 2 | B34: ='Presupuesto Base'!A17 -> 10.1 | C34: ='Presupuesto Base'!B17 -> Conexión domiciliaria sobre red Ø75 | D34: ='Presupuesto Base'!C17 -> un | E34: ='Presupuesto Base'!D17 -> 165 | F34: ='Presupuesto Base'!E17 -> 48618.416 | G34: ='Presupuesto Base'!F17 -> 8022038.6 | H34: =SUMIFS(Medicion!$K$6:$K$511,Medicion!$G$6:$G$511,$B34,Medicion!$A$6:$A$511,"<"&$A34) -> 5 | I34: =SUMIFS(Medicion!$K$6:$K$511,Medicion!$G$6:$G$511,$B34,Medicion!$A$6:$A$511,$A34) -> 0 | J34: =MIN(E34,H34+I34) -> 5 | K34: =MIN(G34,H34*F34) -> 243092.08 | L34: =MIN(G34-K34,I34*F34) -> 0 | M34: =K34+L34 -> 243092.08 | N34: =MAX(0,G34-M34) -> 7778946.5 | O34: =IFERROR(J34/E34,0) -> 0.03030303 | P34: =IF(OR(H34+I34>E34+0.000001,H34<0,I34<0),"REVISAR","OK") -> OK
A35: 2 | B35: ='Presupuesto Base'!A18 -> 10.2 | C35: ='Presupuesto Base'!B18 -> Conexión domiciliaria sobre red Ø110 | D35: ='Presupuesto Base'!C18 -> un | E35: ='Presupuesto Base'!D18 -> 62 | F35: ='Presupuesto Base'!E18 -> 55451.879 | G35: ='Presupuesto Base'!F18 -> 3438016.5 | H35: =SUMIFS(Medicion!$K$6:$K$511,Medicion!$G$6:$G$511,$B35,Medicion!$A$6:$A$511,"<"&$A35) -> 2 | I35: =SUMIFS(Medicion!$K$6:$K$511,Medicion!$G$6:$G$511,$B35,Medicion!$A$6:$A$511,$A35) -> 0 | J35: =MIN(E35,H35+I35) -> 2 | K35: =MIN(G35,H35*F35) -> 110903.76 | L35: =MIN(G35-K35,I35*F35) -> 0 | M35: =K35+L35 -> 110903.76 | N35: =MAX(0,G35-M35) -> 3327112.8 | O35: =IFERROR(J35/E35,0) -> 0.032258065 | P35: =IF(OR(H35+I35>E35+0.000001,H35<0,I35<0),"REVISAR","OK") -> OK
... A41: 2 | B41: ='Presupuesto Base'!A24 -> 13.3 | C41: ='Presupuesto Base'!B24 -> Documentación conforme a obra y cierre | D41: ='Presupuesto Base'!C24 -> gl | E41: ='Presupuesto Base'!D24 -> 1 | F41: ='Presupuesto Base'!E24 -> 859504.13 | G41: ='Presupuesto Base'!F24 -> 859504.13 | H41: =SUMIFS(Medicion!$K$6:$K$511,Medicion!$G$6:$G$511,$B41,Medicion!$A$6:$A$511,"<"&$A41) -> 0 | I41: =SUMIFS(Medicion!$K$6:$K$511,Medicion!$G$6:$G$511,$B41,Medicion!$A$6:$A$511,$A41) -> 0 | J41: =MIN(E41,H41+I41) -> 0 | K41: =MIN(G41,H41*F41) -> 0 | L41: =MIN(G41-K41,I41*F41) -> 0 | M41: =K41+L41 -> 0 | N41: =MAX(0,G41-M41) -> 859504.13 | O41: =IFERROR(J41/E41,0) -> 0 | P41: =IF(OR(H41+I41>E41+0.000001,H41<0,I41<0),"REVISAR","OK") -> OK
A42: 3 | B42: ='Presupuesto Base'!A7 -> 1 | C42: ='Presupuesto Base'!B7 -> Replanteo y marcación de traza | D42: ='Presupuesto Base'!C7 -> ml | E42: ='Presupuesto Base'!D7 -> 4200 | F42: ='Presupuesto Base'!E7 -> 204.64384 | G42: ='Presupuesto Base'!F7 -> 859504.13 | H42: =SUMIFS(Medicion!$K$6:$K$511,Medicion!$G$6:$G$511,$B42,Medicion!$A$6:$A$511,"<"&$A42) -> 845 | I42: =SUMIFS(Medicion!$K$6:$K$511,Medicion!$G$6:$G$511,$B42,Medicion!$A$6:$A$511,$A42) -> 0 | J42: =MIN(E42,H42+I42) -> 845 | K42: =MIN(G42,H42*F42) -> 172924.05 | L42: =MIN(G42-K42,I42*F42) -> 0 | M42: =K42+L42 -> 172924.05 | N42: =MAX(0,G42-M42) -> 686580.09 | O42: =IFERROR(J42/E42,0) -> 0.20119048 | P42: =IF(OR(H42+I42>E42+0.000001,H42<0,I42<0),"REVISAR","OK") -> OK
A43: 3 | B43: ='Presupuesto Base'!A8 -> 2 | C43: ='Presupuesto Base'!B8 -> Excavación de zanja | D43: ='Presupuesto Base'!C8 -> ml | E43: ='Presupuesto Base'!D8 -> 4200 | F43: ='Presupuesto Base'!E8 -> 3683.5891 | G43: ='Presupuesto Base'!F8 -> 15471074 | H43: =SUMIFS(Medicion!$K$6:$K$511,Medicion!$G$6:$G$511,$B43,Medicion!$A$6:$A$511,"<"&$A43) -> 845 | I43: =SUMIFS(Medicion!$K$6:$K$511,Medicion!$G$6:$G$511,$B43,Medicion!$A$6:$A$511,$A43) -> 0 | J43: =MIN(E43,H43+I43) -> 845 | K43: =MIN(G43,H43*F43) -> 3112632.8 | L43: =MIN(G43-K43,I43*F43) -> 0 | M43: =K43+L43 -> 3112632.8 | N43: =MAX(0,G43-M43) -> 12358442 | O43: =IFERROR(J43/E43,0) -> 0.20119048 | P43: =IF(OR(H43+I43>E43+0.000001,H43<0,I43<0),"REVISAR","OK") -> OK
A44: 3 | B44: ='Presupuesto Base'!A9 -> 3 | C44: ='Presupuesto Base'!B9 -> Nivelación y conformación del fondo de zanja | D44: ='Presupuesto Base'!C9 -> ml | E44: ='Presupuesto Base'!D9 -> 4200 | F44: ='Presupuesto Base'!E9 -> 477.5023 | G44: ='Presupuesto Base'!F9 -> 2005509.6 | H44: =SUMIFS(Medicion!$K$6:$K$511,Medicion!$G$6:$G$511,$B44,Medicion!$A$6:$A$511,"<"&$A44) -> 845 | I44: =SUMIFS(Medicion!$K$6:$K$511,Medicion!$G$6:$G$511,$B44,Medicion!$A$6:$A$511,$A44) -> 0 | J44: =MIN(E44,H44+I44) -> 845 | K44: =MIN(G44,H44*F44) -> 403489.44 | L44: =MIN(G44-K44,I44*F44) -> 0 | M44: =K44+L44 -> 403489.44 | N44: =MAX(0,G44-M44) -> 1602020.2 | O44: =IFERROR(J44/E44,0) -> 0.20119048 | P44: =IF(OR(H44+I44>E44+0.000001,H44<0,I44<0),"REVISAR","OK") -> OK
A45: 3 | B45: ='Presupuesto Base'!A10 -> 4 | C45: ='Presupuesto Base'!B10 -> Cama de asiento compactada | D45: ='Presupuesto Base'!C10 -> ml | E45: ='Presupuesto Base'!D10 -> 4200 | F45: ='Presupuesto Base'!E10 -> 1705.3653 | G45: ='Presupuesto Base'!F10 -> 7162534.4 | H45: =SUMIFS(Medicion!$K$6:$K$511,Medicion!$G$6:$G$511,$B45,Medicion!$A$6:$A$511,"<"&$A45) -> 845 | I45: =SUMIFS(Medicion!$K$6:$K$511,Medicion!$G$6:$G$511,$B45,Medicion!$A$6:$A$511,$A45) -> 0 | J45: =MIN(E45,H45+I45) -> 845 | K45: =MIN(G45,H45*F45) -> 1441033.7 | L45: =MIN(G45-K45,I45*F45) -> 0 | M45: =K45+L45 -> 1441033.7 | N45: =MAX(0,G45-M45) -> 5721500.7 | O45: =IFERROR(J45/E45,0) -> 0.20119048 | P45: =IF(OR(H45+I45>E45+0.000001,H45<0,I45<0),"REVISAR","OK") -> OK
A46: 3 | B46: ='Presupuesto Base'!A11 -> 5.1 | C46: ='Presupuesto Base'!B11 -> PEAD PN10 Ø75 – provisión e instalación | D46: ='Presupuesto Base'!C11 -> ml | E46: ='Presupuesto Base'!D11 -> 3170 | F46: ='Presupuesto Base'!E11 -> 5784.2549 | G46: ='Presupuesto Base'!F11 -> 18336088 | H46: =SUMIFS(Medicion!$K$6:$K$511,Medicion!$G$6:$G$511,$B46,Medicion!$A$6:$A$511,"<"&$A46) -> 558 | I46: =SUMIFS(Medicion!$K$6:$K$511,Medicion!$G$6:$G$511,$B46,Medicion!$A$6:$A$511,$A46) -> 0 | J46: =MIN(E46,H46+I46) -> 558 | K46: =MIN(G46,H46*F46) -> 3227614.3 | L46: =MIN(G46-K46,I46*F46) -> 0 | M46: =K46+L46 -> 3227614.3 | N46: =MAX(0,G46-M46) -> 15108474 | O46: =IFERROR(J46/E46,0) -> 0.17602524 | P46: =IF(OR(H46+I46>E46+0.000001,H46<0,I46<0),"REVISAR","OK") -> OK
A47: 3 | B47: ='Presupuesto Base'!A12 -> 5.2 | C47: ='Presupuesto Base'!B12 -> PEAD PN10 Ø110 – provisión e instalación | D47: ='Presupuesto Base'!C12 -> ml | E47: ='Presupuesto Base'!D12 -> 1030 | F47: ='Presupuesto Base'!E12 -> 12238.894 | G47: ='Presupuesto Base'!F12 -> 12606061 | H47: =SUMIFS(Medicion!$K$6:$K$511,Medicion!$G$6:$G$511,$B47,Medicion!$A$6:$A$511,"<"&$A47) -> 287 | I47: =SUMIFS(Medicion!$K$6:$K$511,Medicion!$G$6:$G$511,$B47,Medicion!$A$6:$A$511,$A47) -> 0 | J47: =MIN(E47,H47+I47) -> 287 | K47: =MIN(G47,H47*F47) -> 3512562.5 | L47: =MIN(G47-K47,I47*F47) -> 0 | M47: =K47+L47 -> 3512562.5 | N47: =MAX(0,G47-M47) -> 9093498.1 | O47: =IFERROR(J47/E47,0) -> 0.27864078 | P47: =IF(OR(H47+I47>E47+0.000001,H47<0,I47<0),"REVISAR","OK") -> OK
A48: 3 | B48: ='Presupuesto Base'!A13 -> 6 | C48: ='Presupuesto Base'!B13 -> Ejecución de paquete estructural de 30 cm | D48: ='Presupuesto Base'!C13 -> ml | E48: ='Presupuesto Base'!D13 -> 4200 | F48: ='Presupuesto Base'!E13 -> 3274.3015 | G48: ='Presupuesto Base'!F13 -> 13752066 | H48: =SUMIFS(Medicion!$K$6:$K$511,Medicion!$G$6:$G$511,$B48,Medicion!$A$6:$A$511,"<"&$A48) -> 763 | I48: =SUMIFS(Medicion!$K$6:$K$511,Medicion!$G$6:$G$511,$B48,Medicion!$A$6:$A$511,$A48) -> 0 | J48: =MIN(E48,H48+I48) -> 763 | K48: =MIN(G48,H48*F48) -> 2498292 | L48: =MIN(G48-K48,I48*F48) -> 0 | M48: =K48+L48 -> 2498292 | N48: =MAX(0,G48-M48) -> 11253774 | O48: =IFERROR(J48/E48,0) -> 0.18166667 | P48: =IF(OR(H48+I48>E48+0.000001,H48<0,I48<0),"REVISAR","OK") -> OK
A49: 3 | B49: ='Presupuesto Base'!A14 -> 7 | C49: ='Presupuesto Base'!B14 -> Compactación del paquete estructural de 30 cm | D49: ='Presupuesto Base'!C14 -> ml | E49: ='Presupuesto Base'!D14 -> 4200 | F49: ='Presupuesto Base'!E14 -> 1227.863 | G49: ='Presupuesto Base'!F14 -> 5157024.8 | H49: =SUMIFS(Medicion!$K$6:$K$511,Medicion!$G$6:$G$511,$B49,Medicion!$A$6:$A$511,"<"&$A49) -> 0 | I49: =SUMIFS(Medicion!$K$6:$K$511,Medicion!$G$6:$G$511,$B49,Medicion!$A$6:$A$511,$A49) -> 0 | J49: =MIN(E49,H49+I49) -> 0 | K49: =MIN(G49,H49*F49) -> 0 | L49: =MIN(G49-K49,I49*F49) -> 0 | M49: =K49+L49 -> 0 | N49: =MAX(0,G49-M49) -> 5157024.8 | O49: =IFERROR(J49/E49,0) -> 0 | P49: =IF(OR(H49+I49>E49+0.000001,H49<0,I49<0),"REVISAR","OK") -> OK
A50: 3 | B50: ='Presupuesto Base'!A15 -> 8 | C50: ='Presupuesto Base'!B15 -> Ejecución y compactación de capa cota -0,60 | D50: ='Presupuesto Base'!C15 -> ml | E50: ='Presupuesto Base'!D15 -> 4200 | F50: ='Presupuesto Base'!E15 -> 2592.1553 | G50: ='Presupuesto Base'!F15 -> 10887052 | H50: =SUMIFS(Medicion!$K$6:$K$511,Medicion!$G$6:$G$511,$B50,Medicion!$A$6:$A$511,"<"&$A50) -> 0 | I50: =SUMIFS(Medicion!$K$6:$K$511,Medicion!$G$6:$G$511,$B50,Medicion!$A$6:$A$511,$A50) -> 0 | J50: =MIN(E50,H50+I50) -> 0 | K50: =MIN(G50,H50*F50) -> 0 | L50: =MIN(G50-K50,I50*F50) -> 0 | M50: =K50+L50 -> 0 | N50: =MAX(0,G50-M50) -> 10887052 | O50: =IFERROR(J50/E50,0) -> 0 | P50: =IF(OR(H50+I50>E50+0.000001,H50<0,I50<0),"REVISAR","OK") -> OK
A51: 3 | B51: ='Presupuesto Base'!A16 -> 9 | C51: ='Presupuesto Base'!B16 -> Ejecución y compactación de capa cota -0,30 | D51: ='Presupuesto Base'!C16 -> ml | E51: ='Presupuesto Base'!D16 -> 4200 | F51: ='Presupuesto Base'!E16 -> 2182.8676 | G51: ='Presupuesto Base'!F16 -> 9168044.1 | H51: =SUMIFS(Medicion!$K$6:$K$511,Medicion!$G$6:$G$511,$B51,Medicion!$A$6:$A$511,"<"&$A51) -> 0 | I51: =SUMIFS(Medicion!$K$6:$K$511,Medicion!$G$6:$G$511,$B51,Medicion!$A$6:$A$511,$A51) -> 0 | J51: =MIN(E51,H51+I51) -> 0 | K51: =MIN(G51,H51*F51) -> 0 | L51: =MIN(G51-K51,I51*F51) -> 0 | M51: =K51+L51 -> 0 | N51: =MAX(0,G51-M51) -> 9168044.1 | O51: =IFERROR(J51/E51,0) -> 0 | P51: =IF(OR(H51+I51>E51+0.000001,H51<0,I51<0),"REVISAR","OK") -> OK
A52: 3 | B52: ='Presupuesto Base'!A17 -> 10.1 | C52: ='Presupuesto Base'!B17 -> Conexión domiciliaria sobre red Ø75 | D52: ='Presupuesto Base'!C17 -> un | E52: ='Presupuesto Base'!D17 -> 165 | F52: ='Presupuesto Base'!E17 -> 48618.416 | G52: ='Presupuesto Base'!F17 -> 8022038.6 | H52: =SUMIFS(Medicion!$K$6:$K$511,Medicion!$G$6:$G$511,$B52,Medicion!$A$6:$A$511,"<"&$A52) -> 5 | I52: =SUMIFS(Medicion!$K$6:$K$511,Medicion!$G$6:$G$511,$B52,Medicion!$A$6:$A$511,$A52) -> 0 | J52: =MIN(E52,H52+I52) -> 5 | K52: =MIN(G52,H52*F52) -> 243092.08 | L52: =MIN(G52-K52,I52*F52) -> 0 | M52: =K52+L52 -> 243092.08 | N52: =MAX(0,G52-M52) -> 7778946.5 | O52: =IFERROR(J52/E52,0) -> 0.03030303 | P52: =IF(OR(H52+I52>E52+0.000001,H52<0,I52<0),"REVISAR","OK") -> OK
A53: 3 | B53: ='Presupuesto Base'!A18 -> 10.2 | C53: ='Presupuesto Base'!B18 -> Conexión domiciliaria sobre red Ø110 | D53: ='Presupuesto Base'!C18 -> un | E53: ='Presupuesto Base'!D18 -> 62 | F53: ='Presupuesto Base'!E18 -> 55451.879 | G53: ='Presupuesto Base'!F18 -> 3438016.5 | H53: =SUMIFS(Medicion!$K$6:$K$511,Medicion!$G$6:$G$511,$B53,Medicion!$A$6:$A$511,"<"&$A53) -> 2 | I53: =SUMIFS(Medicion!$K$6:$K$511,Medicion!$G$6:$G$511,$B53,Medicion!$A$6:$A$511,$A53) -> 0 | J53: =MIN(E53,H53+I53) -> 2 | K53: =MIN(G53,H53*F53) -> 110903.76 | L53: =MIN(G53-K53,I53*F53) -> 0 | M53: =K53+L53 -> 110903.76 | N53: =MAX(0,G53-M53) -> 3327112.8 | O53: =IFERROR(J53/E53,0) -> 0.032258065 | P53: =IF(OR(H53+I53>E53+0.000001,H53<0,I53<0),"REVISAR","OK") -> OK
... A59: 3 | B59: ='Presupuesto Base'!A24 -> 13.3 | C59: ='Presupuesto Base'!B24 -> Documentación conforme a obra y cierre | D59: ='Presupuesto Base'!C24 -> gl | E59: ='Presupuesto Base'!D24 -> 1 | F59: ='Presupuesto Base'!E24 -> 859504.13 | G59: ='Presupuesto Base'!F24 -> 859504.13 | H59: =SUMIFS(Medicion!$K$6:$K$511,Medicion!$G$6:$G$511,$B59,Medicion!$A$6:$A$511,"<"&$A59) -> 0 | I59: =SUMIFS(Medicion!$K$6:$K$511,Medicion!$G$6:$G$511,$B59,Medicion!$A$6:$A$511,$A59) -> 0 | J59: =MIN(E59,H59+I59) -> 0 | K59: =MIN(G59,H59*F59) -> 0 | L59: =MIN(G59-K59,I59*F59) -> 0 | M59: =K59+L59 -> 0 | N59: =MAX(0,G59-M59) -> 859504.13 | O59: =IFERROR(J59/E59,0) -> 0 | P59: =IF(OR(H59+I59>E59+0.000001,H59<0,I59<0),"REVISAR","OK") -> OK
A60: 4 | B60: ='Presupuesto Base'!A7 -> 1 | C60: ='Presupuesto Base'!B7 -> Replanteo y marcación de traza | D60: ='Presupuesto Base'!C7 -> ml | E60: ='Presupuesto Base'!D7 -> 4200 | F60: ='Presupuesto Base'!E7 -> 204.64384 | G60: ='Presupuesto Base'!F7 -> 859504.13 | H60: =SUMIFS(Medicion!$K$6:$K$511,Medicion!$G$6:$G$511,$B60,Medicion!$A$6:$A$511,"<"&$A60) -> 845 | I60: =SUMIFS(Medicion!$K$6:$K$511,Medicion!$G$6:$G$511,$B60,Medicion!$A$6:$A$511,$A60) -> 0 | J60: =MIN(E60,H60+I60) -> 845 | K60: =MIN(G60,H60*F60) -> 172924.05 | L60: =MIN(G60-K60,I60*F60) -> 0 | M60: =K60+L60 -> 172924.05 | N60: =MAX(0,G60-M60) -> 686580.09 | O60: =IFERROR(J60/E60,0) -> 0.20119048 | P60: =IF(OR(H60+I60>E60+0.000001,H60<0,I60<0),"REVISAR","OK") -> OK
A61: 4 | B61: ='Presupuesto Base'!A8 -> 2 | C61: ='Presupuesto Base'!B8 -> Excavación de zanja | D61: ='Presupuesto Base'!C8 -> ml | E61: ='Presupuesto Base'!D8 -> 4200 | F61: ='Presupuesto Base'!E8 -> 3683.5891 | G61: ='Presupuesto Base'!F8 -> 15471074 | H61: =SUMIFS(Medicion!$K$6:$K$511,Medicion!$G$6:$G$511,$B61,Medicion!$A$6:$A$511,"<"&$A61) -> 845 | I61: =SUMIFS(Medicion!$K$6:$K$511,Medicion!$G$6:$G$511,$B61,Medicion!$A$6:$A$511,$A61) -> 0 | J61: =MIN(E61,H61+I61) -> 845 | K61: =MIN(G61,H61*F61) -> 3112632.8 | L61: =MIN(G61-K61,I61*F61) -> 0 | M61: =K61+L61 -> 3112632.8 | N61: =MAX(0,G61-M61) -> 12358442 | O61: =IFERROR(J61/E61,0) -> 0.20119048 | P61: =IF(OR(H61+I61>E61+0.000001,H61<0,I61<0),"REVISAR","OK") -> OK
A62: 4 | B62: ='Presupuesto Base'!A9 -> 3 | C62: ='Presupuesto Base'!B9 -> Nivelación y conformación del fondo de zanja | D62: ='Presupuesto Base'!C9 -> ml | E62: ='Presupuesto Base'!D9 -> 4200 | F62: ='Presupuesto Base'!E9 -> 477.5023 | G62: ='Presupuesto Base'!F9 -> 2005509.6 | H62: =SUMIFS(Medicion!$K$6:$K$511,Medicion!$G$6:$G$511,$B62,Medicion!$A$6:$A$511,"<"&$A62) -> 845 | I62: =SUMIFS(Medicion!$K$6:$K$511,Medicion!$G$6:$G$511,$B62,Medicion!$A$6:$A$511,$A62) -> 0 | J62: =MIN(E62,H62+I62) -> 845 | K62: =MIN(G62,H62*F62) -> 403489.44 | L62: =MIN(G62-K62,I62*F62) -> 0 | M62: =K62+L62 -> 403489.44 | N62: =MAX(0,G62-M62) -> 1602020.2 | O62: =IFERROR(J62/E62,0) -> 0.20119048 | P62: =IF(OR(H62+I62>E62+0.000001,H62<0,I62<0),"REVISAR","OK") -> OK
A63: 4 | B63: ='Presupuesto Base'!A10 -> 4 | C63: ='Presupuesto Base'!B10 -> Cama de asiento compactada | D63: ='Presupuesto Base'!C10 -> ml | E63: ='Presupuesto Base'!D10 -> 4200 | F63: ='Presupuesto Base'!E10 -> 1705.3653 | G63: ='Presupuesto Base'!F10 -> 7162534.4 | H63: =SUMIFS(Medicion!$K$6:$K$511,Medicion!$G$6:$G$511,$B63,Medicion!$A$6:$A$511,"<"&$A63) -> 845 | I63: =SUMIFS(Medicion!$K$6:$K$511,Medicion!$G$6:$G$511,$B63,Medicion!$A$6:$A$511,$A63) -> 0 | J63: =MIN(E63,H63+I63) -> 845 | K63: =MIN(G63,H63*F63) -> 1441033.7 | L63: =MIN(G63-K63,I63*F63) -> 0 | M63: =K63+L63 -> 1441033.7 | N63: =MAX(0,G63-M63) -> 5721500.7 | O63: =IFERROR(J63/E63,0) -> 0.20119048 | P63: =IF(OR(H63+I63>E63+0.000001,H63<0,I63<0),"REVISAR","OK") -> OK
A64: 4 | B64: ='Presupuesto Base'!A11 -> 5.1 | C64: ='Presupuesto Base'!B11 -> PEAD PN10 Ø75 – provisión e instalación | D64: ='Presupuesto Base'!C11 -> ml | E64: ='Presupuesto Base'!D11 -> 3170 | F64: ='Presupuesto Base'!E11 -> 5784.2549 | G64: ='Presupuesto Base'!F11 -> 18336088 | H64: =SUMIFS(Medicion!$K$6:$K$511,Medicion!$G$6:$G$511,$B64,Medicion!$A$6:$A$511,"<"&$A64) -> 558 | I64: =SUMIFS(Medicion!$K$6:$K$511,Medicion!$G$6:$G$511,$B64,Medicion!$A$6:$A$511,$A64) -> 0 | J64: =MIN(E64,H64+I64) -> 558 | K64: =MIN(G64,H64*F64) -> 3227614.3 | L64: =MIN(G64-K64,I64*F64) -> 0 | M64: =K64+L64 -> 3227614.3 | N64: =MAX(0,G64-M64) -> 15108474 | O64: =IFERROR(J64/E64,0) -> 0.17602524 | P64: =IF(OR(H64+I64>E64+0.000001,H64<0,I64<0),"REVISAR","OK") -> OK
A65: 4 | B65: ='Presupuesto Base'!A12 -> 5.2 | C65: ='Presupuesto Base'!B12 -> PEAD PN10 Ø110 – provisión e instalación | D65: ='Presupuesto Base'!C12 -> ml | E65: ='Presupuesto Base'!D12 -> 1030 | F65: ='Presupuesto Base'!E12 -> 12238.894 | G65: ='Presupuesto Base'!F12 -> 12606061 | H65: =SUMIFS(Medicion!$K$6:$K$511,Medicion!$G$6:$G$511,$B65,Medicion!$A$6:$A$511,"<"&$A65) -> 287 | I65: =SUMIFS(Medicion!$K$6:$K$511,Medicion!$G$6:$G$511,$B65,Medicion!$A$6:$A$511,$A65) -> 0 | J65: =MIN(E65,H65+I65) -> 287 | K65: =MIN(G65,H65*F65) -> 3512562.5 | L65: =MIN(G65-K65,I65*F65) -> 0 | M65: =K65+L65 -> 3512562.5 | N65: =MAX(0,G65-M65) -> 9093498.1 | O65: =IFERROR(J65/E65,0) -> 0.27864078 | P65: =IF(OR(H65+I65>E65+0.000001,H65<0,I65<0),"REVISAR","OK") -> OK
A66: 4 | B66: ='Presupuesto Base'!A13 -> 6 | C66: ='Presupuesto Base'!B13 -> Ejecución de paquete estructural de 30 cm | D66: ='Presupuesto Base'!C13 -> ml | E66: ='Presupuesto Base'!D13 -> 4200 | F66: ='Presupuesto Base'!E13 -> 3274.3015 | G66: ='Presupuesto Base'!F13 -> 13752066 | H66: =SUMIFS(Medicion!$K$6:$K$511,Medicion!$G$6:$G$511,$B66,Medicion!$A$6:$A$511,"<"&$A66) -> 763 | I66: =SUMIFS(Medicion!$K$6:$K$511,Medicion!$G$6:$G$511,$B66,Medicion!$A$6:$A$511,$A66) -> 0 | J66: =MIN(E66,H66+I66) -> 763 | K66: =MIN(G66,H66*F66) -> 2498292 | L66: =MIN(G66-K66,I66*F66) -> 0 | M66: =K66+L66 -> 2498292 | N66: =MAX(0,G66-M66) -> 11253774 | O66: =IFERROR(J66/E66,0) -> 0.18166667 | P66: =IF(OR(H66+I66>E66+0.000001,H66<0,I66<0),"REVISAR","OK") -> OK
A67: 4 | B67: ='Presupuesto Base'!A14 -> 7 | C67: ='Presupuesto Base'!B14 -> Compactación del paquete estructural de 30 cm | D67: ='Presupuesto Base'!C14 -> ml | E67: ='Presupuesto Base'!D14 -> 4200 | F67: ='Presupuesto Base'!E14 -> 1227.863 | G67: ='Presupuesto Base'!F14 -> 5157024.8 | H67: =SUMIFS(Medicion!$K$6:$K$511,Medicion!$G$6:$G$511,$B67,Medicion!$A$6:$A$511,"<"&$A67) -> 0 | I67: =SUMIFS(Medicion!$K$6:$K$511,Medicion!$G$6:$G$511,$B67,Medicion!$A$6:$A$511,$A67) -> 0 | J67: =MIN(E67,H67+I67) -> 0 | K67: =MIN(G67,H67*F67) -> 0 | L67: =MIN(G67-K67,I67*F67) -> 0 | M67: =K67+L67 -> 0 | N67: =MAX(0,G67-M67) -> 5157024.8 | O67: =IFERROR(J67/E67,0) -> 0 | P67: =IF(OR(H67+I67>E67+0.000001,H67<0,I67<0),"REVISAR","OK") -> OK
A68: 4 | B68: ='Presupuesto Base'!A15 -> 8 | C68: ='Presupuesto Base'!B15 -> Ejecución y compactación de capa cota -0,60 | D68: ='Presupuesto Base'!C15 -> ml | E68: ='Presupuesto Base'!D15 -> 4200 | F68: ='Presupuesto Base'!E15 -> 2592.1553 | G68: ='Presupuesto Base'!F15 -> 10887052 | H68: =SUMIFS(Medicion!$K$6:$K$511,Medicion!$G$6:$G$511,$B68,Medicion!$A$6:$A$511,"<"&$A68) -> 0 | I68: =SUMIFS(Medicion!$K$6:$K$511,Medicion!$G$6:$G$511,$B68,Medicion!$A$6:$A$511,$A68) -> 0 | J68: =MIN(E68,H68+I68) -> 0 | K68: =MIN(G68,H68*F68) -> 0 | L68: =MIN(G68-K68,I68*F68) -> 0 | M68: =K68+L68 -> 0 | N68: =MAX(0,G68-M68) -> 10887052 | O68: =IFERROR(J68/E68,0) -> 0 | P68: =IF(OR(H68+I68>E68+0.000001,H68<0,I68<0),"REVISAR","OK") -> OK
A69: 4 | B69: ='Presupuesto Base'!A16 -> 9 | C69: ='Presupuesto Base'!B16 -> Ejecución y compactación de capa cota -0,30 | D69: ='Presupuesto Base'!C16 -> ml | E69: ='Presupuesto Base'!D16 -> 4200 | F69: ='Presupuesto Base'!E16 -> 2182.8676 | G69: ='Presupuesto Base'!F16 -> 9168044.1 | H69: =SUMIFS(Medicion!$K$6:$K$511,Medicion!$G$6:$G$511,$B69,Medicion!$A$6:$A$511,"<"&$A69) -> 0 | I69: =SUMIFS(Medicion!$K$6:$K$511,Medicion!$G$6:$G$511,$B69,Medicion!$A$6:$A$511,$A69) -> 0 | J69: =MIN(E69,H69+I69) -> 0 | K69: =MIN(G69,H69*F69) -> 0 | L69: =MIN(G69-K69,I69*F69) -> 0 | M69: =K69+L69 -> 0 | N69: =MAX(0,G69-M69) -> 9168044.1 | O69: =IFERROR(J69/E69,0) -> 0 | P69: =IF(OR(H69+I69>E69+0.000001,H69<0,I69<0),"REVISAR","OK") -> OK
A70: 4 | B70: ='Presupuesto Base'!A17 -> 10.1 | C70: ='Presupuesto Base'!B17 -> Conexión domiciliaria sobre red Ø75 | D70: ='Presupuesto Base'!C17 -> un | E70: ='Presupuesto Base'!D17 -> 165 | F70: ='Presupuesto Base'!E17 -> 48618.416 | G70: ='Presupuesto Base'!F17 -> 8022038.6 | H70: =SUMIFS(Medicion!$K$6:$K$511,Medicion!$G$6:$G$511,$B70,Medicion!$A$6:$A$511,"<"&$A70) -> 5 | I70: =SUMIFS(Medicion!$K$6:$K$511,Medicion!$G$6:$G$511,$B70,Medicion!$A$6:$A$511,$A70) -> 0 | J70: =MIN(E70,H70+I70) -> 5 | K70: =MIN(G70,H70*F70) -> 243092.08 | L70: =MIN(G70-K70,I70*F70) -> 0 | M70: =K70+L70 -> 243092.08 | N70: =MAX(0,G70-M70) -> 7778946.5 | O70: =IFERROR(J70/E70,0) -> 0.03030303 | P70: =IF(OR(H70+I70>E70+0.000001,H70<0,I70<0),"REVISAR","OK") -> OK
A71: 4 | B71: ='Presupuesto Base'!A18 -> 10.2 | C71: ='Presupuesto Base'!B18 -> Conexión domiciliaria sobre red Ø110 | D71: ='Presupuesto Base'!C18 -> un | E71: ='Presupuesto Base'!D18 -> 62 | F71: ='Presupuesto Base'!E18 -> 55451.879 | G71: ='Presupuesto Base'!F18 -> 3438016.5 | H71: =SUMIFS(Medicion!$K$6:$K$511,Medicion!$G$6:$G$511,$B71,Medicion!$A$6:$A$511,"<"&$A71) -> 2 | I71: =SUMIFS(Medicion!$K$6:$K$511,Medicion!$G$6:$G$511,$B71,Medicion!$A$6:$A$511,$A71) -> 0 | J71: =MIN(E71,H71+I71) -> 2 | K71: =MIN(G71,H71*F71) -> 110903.76 | L71: =MIN(G71-K71,I71*F71) -> 0 | M71: =K71+L71 -> 110903.76 | N71: =MAX(0,G71-M71) -> 3327112.8 | O71: =IFERROR(J71/E71,0) -> 0.032258065 | P71: =IF(OR(H71+I71>E71+0.000001,H71<0,I71<0),"REVISAR","OK") -> OK
... A77: 4 | B77: ='Presupuesto Base'!A24 -> 13.3 | C77: ='Presupuesto Base'!B24 -> Documentación conforme a obra y cierre | D77: ='Presupuesto Base'!C24 -> gl | E77: ='Presupuesto Base'!D24 -> 1 | F77: ='Presupuesto Base'!E24 -> 859504.13 | G77: ='Presupuesto Base'!F24 -> 859504.13 | H77: =SUMIFS(Medicion!$K$6:$K$511,Medicion!$G$6:$G$511,$B77,Medicion!$A$6:$A$511,"<"&$A77) -> 0 | I77: =SUMIFS(Medicion!$K$6:$K$511,Medicion!$G$6:$G$511,$B77,Medicion!$A$6:$A$511,$A77) -> 0 | J77: =MIN(E77,H77+I77) -> 0 | K77: =MIN(G77,H77*F77) -> 0 | L77: =MIN(G77-K77,I77*F77) -> 0 | M77: =K77+L77 -> 0 | N77: =MAX(0,G77-M77) -> 859504.13 | O77: =IFERROR(J77/E77,0) -> 0 | P77: =IF(OR(H77+I77>E77+0.000001,H77<0,I77<0),"REVISAR","OK") -> OK
A78: 5 | B78: ='Presupuesto Base'!A7 -> 1 | C78: ='Presupuesto Base'!B7 -> Replanteo y marcación de traza | D78: ='Presupuesto Base'!C7 -> ml | E78: ='Presupuesto Base'!D7 -> 4200 | F78: ='Presupuesto Base'!E7 -> 204.64384 | G78: ='Presupuesto Base'!F7 -> 859504.13 | H78: =SUMIFS(Medicion!$K$6:$K$511,Medicion!$G$6:$G$511,$B78,Medicion!$A$6:$A$511,"<"&$A78) -> 845 | I78: =SUMIFS(Medicion!$K$6:$K$511,Medicion!$G$6:$G$511,$B78,Medicion!$A$6:$A$511,$A78) -> 0 | J78: =MIN(E78,H78+I78) -> 845 | K78: =MIN(G78,H78*F78) -> 172924.05 | L78: =MIN(G78-K78,I78*F78) -> 0 | M78: =K78+L78 -> 172924.05 | N78: =MAX(0,G78-M78) -> 686580.09 | O78: =IFERROR(J78/E78,0) -> 0.20119048 | P78: =IF(OR(H78+I78>E78+0.000001,H78<0,I78<0),"REVISAR","OK") -> OK
A79: 5 | B79: ='Presupuesto Base'!A8 -> 2 | C79: ='Presupuesto Base'!B8 -> Excavación de zanja | D79: ='Presupuesto Base'!C8 -> ml | E79: ='Presupuesto Base'!D8 -> 4200 | F79: ='Presupuesto Base'!E8 -> 3683.5891 | G79: ='Presupuesto Base'!F8 -> 15471074 | H79: =SUMIFS(Medicion!$K$6:$K$511,Medicion!$G$6:$G$511,$B79,Medicion!$A$6:$A$511,"<"&$A79) -> 845 | I79: =SUMIFS(Medicion!$K$6:$K$511,Medicion!$G$6:$G$511,$B79,Medicion!$A$6:$A$511,$A79) -> 0 | J79: =MIN(E79,H79+I79) -> 845 | K79: =MIN(G79,H79*F79) -> 3112632.8 | L79: =MIN(G79-K79,I79*F79) -> 0 | M79: =K79+L79 -> 3112632.8 | N79: =MAX(0,G79-M79) -> 12358442 | O79: =IFERROR(J79/E79,0) -> 0.20119048 | P79: =IF(OR(H79+I79>E79+0.000001,H79<0,I79<0),"REVISAR","OK") -> OK
A80: 5 | B80: ='Presupuesto Base'!A9 -> 3 | C80: ='Presupuesto Base'!B9 -> Nivelación y conformación del fondo de zanja | D80: ='Presupuesto Base'!C9 -> ml | E80: ='Presupuesto Base'!D9 -> 4200 | F80: ='Presupuesto Base'!E9 -> 477.5023 | G80: ='Presupuesto Base'!F9 -> 2005509.6 | H80: =SUMIFS(Medicion!$K$6:$K$511,Medicion!$G$6:$G$511,$B80,Medicion!$A$6:$A$511,"<"&$A80) -> 845 | I80: =SUMIFS(Medicion!$K$6:$K$511,Medicion!$G$6:$G$511,$B80,Medicion!$A$6:$A$511,$A80) -> 0 | J80: =MIN(E80,H80+I80) -> 845 | K80: =MIN(G80,H80*F80) -> 403489.44 | L80: =MIN(G80-K80,I80*F80) -> 0 | M80: =K80+L80 -> 403489.44 | N80: =MAX(0,G80-M80) -> 1602020.2 | O80: =IFERROR(J80/E80,0) -> 0.20119048 | P80: =IF(OR(H80+I80>E80+0.000001,H80<0,I80<0),"REVISAR","OK") -> OK
A81: 5 | B81: ='Presupuesto Base'!A10 -> 4 | C81: ='Presupuesto Base'!B10 -> Cama de asiento compactada | D81: ='Presupuesto Base'!C10 -> ml | E81: ='Presupuesto Base'!D10 -> 4200 | F81: ='Presupuesto Base'!E10 -> 1705.3653 | G81: ='Presupuesto Base'!F10 -> 7162534.4 | H81: =SUMIFS(Medicion!$K$6:$K$511,Medicion!$G$6:$G$511,$B81,Medicion!$A$6:$A$511,"<"&$A81) -> 845 | I81: =SUMIFS(Medicion!$K$6:$K$511,Medicion!$G$6:$G$511,$B81,Medicion!$A$6:$A$511,$A81) -> 0 | J81: =MIN(E81,H81+I81) -> 845 | K81: =MIN(G81,H81*F81) -> 1441033.7 | L81: =MIN(G81-K81,I81*F81) -> 0 | M81: =K81+L81 -> 1441033.7 | N81: =MAX(0,G81-M81) -> 5721500.7 | O81: =IFERROR(J81/E81,0) -> 0.20119048 | P81: =IF(OR(H81+I81>E81+0.000001,H81<0,I81<0),"REVISAR","OK") -> OK
A82: 5 | B82: ='Presupuesto Base'!A11 -> 5.1 | C82: ='Presupuesto Base'!B11 -> PEAD PN10 Ø75 – provisión e instalación | D82: ='Presupuesto Base'!C11 -> ml | E82: ='Presupuesto Base'!D11 -> 3170 | F82: ='Presupuesto Base'!E11 -> 5784.2549 | G82: ='Presupuesto Base'!F11 -> 18336088 | H82: =SUMIFS(Medicion!$K$6:$K$511,Medicion!$G$6:$G$511,$B82,Medicion!$A$6:$A$511,"<"&$A82) -> 558 | I82: =SUMIFS(Medicion!$K$6:$K$511,Medicion!$G$6:$G$511,$B82,Medicion!$A$6:$A$511,$A82) -> 0 | J82: =MIN(E82,H82+I82) -> 558 | K82: =MIN(G82,H82*F82) -> 3227614.3 | L82: =MIN(G82-K82,I82*F82) -> 0 | M82: =K82+L82 -> 3227614.3 | N82: =MAX(0,G82-M82) -> 15108474 | O82: =IFERROR(J82/E82,0) -> 0.17602524 | P82: =IF(OR(H82+I82>E82+0.000001,H82<0,I82<0),"REVISAR","OK") -> OK
A83: 5 | B83: ='Presupuesto Base'!A12 -> 5.2 | C83: ='Presupuesto Base'!B12 -> PEAD PN10 Ø110 – provisión e instalación | D83: ='Presupuesto Base'!C12 -> ml | E83: ='Presupuesto Base'!D12 -> 1030 | F83: ='Presupuesto Base'!E12 -> 12238.894 | G83: ='Presupuesto Base'!F12 -> 12606061 | H83: =SUMIFS(Medicion!$K$6:$K$511,Medicion!$G$6:$G$511,$B83,Medicion!$A$6:$A$511,"<"&$A83) -> 287 | I83: =SUMIFS(Medicion!$K$6:$K$511,Medicion!$G$6:$G$511,$B83,Medicion!$A$6:$A$511,$A83) -> 0 | J83: =MIN(E83,H83+I83) -> 287 | K83: =MIN(G83,H83*F83) -> 3512562.5 | L83: =MIN(G83-K83,I83*F83) -> 0 | M83: =K83+L83 -> 3512562.5 | N83: =MAX(0,G83-M83) -> 9093498.1 | O83: =IFERROR(J83/E83,0) -> 0.27864078 | P83: =IF(OR(H83+I83>E83+0.000001,H83<0,I83<0),"REVISAR","OK") -> OK
A84: 5 | B84: ='Presupuesto Base'!A13 -> 6 | C84: ='Presupuesto Base'!B13 -> Ejecución de paquete estructural de 30 cm | D84: ='Presupuesto Base'!C13 -> ml | E84: ='Presupuesto Base'!D13 -> 4200 | F84: ='Presupuesto Base'!E13 -> 3274.3015 | G84: ='Presupuesto Base'!F13 -> 13752066 | H84: =SUMIFS(Medicion!$K$6:$K$511,Medicion!$G$6:$G$511,$B84,Medicion!$A$6:$A$511,"<"&$A84) -> 763 | I84: =SUMIFS(Medicion!$K$6:$K$511,Medicion!$G$6:$G$511,$B84,Medicion!$A$6:$A$511,$A84) -> 0 | J84: =MIN(E84,H84+I84) -> 763 | K84: =MIN(G84,H84*F84) -> 2498292 | L84: =MIN(G84-K84,I84*F84) -> 0 | M84: =K84+L84 -> 2498292 | N84: =MAX(0,G84-M84) -> 11253774 | O84: =IFERROR(J84/E84,0) -> 0.18166667 | P84: =IF(OR(H84+I84>E84+0.000001,H84<0,I84<0),"REVISAR","OK") -> OK
A85: 5 | B85: ='Presupuesto Base'!A14 -> 7 | C85: ='Presupuesto Base'!B14 -> Compactación del paquete estructural de 30 cm | D85: ='Presupuesto Base'!C14 -> ml | E85: ='Presupuesto Base'!D14 -> 4200 | F85: ='Presupuesto Base'!E14 -> 1227.863 | G85: ='Presupuesto Base'!F14 -> 5157024.8 | H85: =SUMIFS(Medicion!$K$6:$K$511,Medicion!$G$6:$G$511,$B85,Medicion!$A$6:$A$511,"<"&$A85) -> 0 | I85: =SUMIFS(Medicion!$K$6:$K$511,Medicion!$G$6:$G$511,$B85,Medicion!$A$6:$A$511,$A85) -> 0 | J85: =MIN(E85,H85+I85) -> 0 | K85: =MIN(G85,H85*F85) -> 0 | L85: =MIN(G85-K85,I85*F85) -> 0 | M85: =K85+L85 -> 0 | N85: =MAX(0,G85-M85) -> 5157024.8 | O85: =IFERROR(J85/E85,0) -> 0 | P85: =IF(OR(H85+I85>E85+0.000001,H85<0,I85<0),"REVISAR","OK") -> OK
A86: 5 | B86: ='Presupuesto Base'!A15 -> 8 | C86: ='Presupuesto Base'!B15 -> Ejecución y compactación de capa cota -0,60 | D86: ='Presupuesto Base'!C15 -> ml | E86: ='Presupuesto Base'!D15 -> 4200 | F86: ='Presupuesto Base'!E15 -> 2592.1553 | G86: ='Presupuesto Base'!F15 -> 10887052 | H86: =SUMIFS(Medicion!$K$6:$K$511,Medicion!$G$6:$G$511,$B86,Medicion!$A$6:$A$511,"<"&$A86) -> 0 | I86: =SUMIFS(Medicion!$K$6:$K$511,Medicion!$G$6:$G$511,$B86,Medicion!$A$6:$A$511,$A86) -> 0 | J86: =MIN(E86,H86+I86) -> 0 | K86: =MIN(G86,H86*F86) -> 0 | L86: =MIN(G86-K86,I86*F86) -> 0 | M86: =K86+L86 -> 0 | N86: =MAX(0,G86-M86) -> 10887052 | O86: =IFERROR(J86/E86,0) -> 0 | P86: =IF(OR(H86+I86>E86+0.000001,H86<0,I86<0),"REVISAR","OK") -> OK
A87: 5 | B87: ='Presupuesto Base'!A16 -> 9 | C87: ='Presupuesto Base'!B16 -> Ejecución y compactación de capa cota -0,30 | D87: ='Presupuesto Base'!C16 -> ml | E87: ='Presupuesto Base'!D16 -> 4200 | F87: ='Presupuesto Base'!E16 -> 2182.8676 | G87: ='Presupuesto Base'!F16 -> 9168044.1 | H87: =SUMIFS(Medicion!$K$6:$K$511,Medicion!$G$6:$G$511,$B87,Medicion!$A$6:$A$511,"<"&$A87) -> 0 | I87: =SUMIFS(Medicion!$K$6:$K$511,Medicion!$G$6:$G$511,$B87,Medicion!$A$6:$A$511,$A87) -> 0 | J87: =MIN(E87,H87+I87) -> 0 | K87: =MIN(G87,H87*F87) -> 0 | L87: =MIN(G87-K87,I87*F87) -> 0 | M87: =K87+L87 -> 0 | N87: =MAX(0,G87-M87) -> 9168044.1 | O87: =IFERROR(J87/E87,0) -> 0 | P87: =IF(OR(H87+I87>E87+0.000001,H87<0,I87<0),"REVISAR","OK") -> OK
A88: 5 | B88: ='Presupuesto Base'!A17 -> 10.1 | C88: ='Presupuesto Base'!B17 -> Conexión domiciliaria sobre red Ø75 | D88: ='Presupuesto Base'!C17 -> un | E88: ='Presupuesto Base'!D17 -> 165 | F88: ='Presupuesto Base'!E17 -> 48618.416 | G88: ='Presupuesto Base'!F17 -> 8022038.6 | H88: =SUMIFS(Medicion!$K$6:$K$511,Medicion!$G$6:$G$511,$B88,Medicion!$A$6:$A$511,"<"&$A88) -> 5 | I88: =SUMIFS(Medicion!$K$6:$K$511,Medicion!$G$6:$G$511,$B88,Medicion!$A$6:$A$511,$A88) -> 0 | J88: =MIN(E88,H88+I88) -> 5 | K88: =MIN(G88,H88*F88) -> 243092.08 | L88: =MIN(G88-K88,I88*F88) -> 0 | M88: =K88+L88 -> 243092.08 | N88: =MAX(0,G88-M88) -> 7778946.5 | O88: =IFERROR(J88/E88,0) -> 0.03030303 | P88: =IF(OR(H88+I88>E88+0.000001,H88<0,I88<0),"REVISAR","OK") -> OK
A89: 5 | B89: ='Presupuesto Base'!A18 -> 10.2 | C89: ='Presupuesto Base'!B18 -> Conexión domiciliaria sobre red Ø110 | D89: ='Presupuesto Base'!C18 -> un | E89: ='Presupuesto Base'!D18 -> 62 | F89: ='Presupuesto Base'!E18 -> 55451.879 | G89: ='Presupuesto Base'!F18 -> 3438016.5 | H89: =SUMIFS(Medicion!$K$6:$K$511,Medicion!$G$6:$G$511,$B89,Medicion!$A$6:$A$511,"<"&$A89) -> 2 | I89: =SUMIFS(Medicion!$K$6:$K$511,Medicion!$G$6:$G$511,$B89,Medicion!$A$6:$A$511,$A89) -> 0 | J89: =MIN(E89,H89+I89) -> 2 | K89: =MIN(G89,H89*F89) -> 110903.76 | L89: =MIN(G89-K89,I89*F89) -> 0 | M89: =K89+L89 -> 110903.76 | N89: =MAX(0,G89-M89) -> 3327112.8 | O89: =IFERROR(J89/E89,0) -> 0.032258065 | P89: =IF(OR(H89+I89>E89+0.000001,H89<0,I89<0),"REVISAR","OK") -> OK
... A95: 5 | B95: ='Presupuesto Base'!A24 -> 13.3 | C95: ='Presupuesto Base'!B24 -> Documentación conforme a obra y cierre | D95: ='Presupuesto Base'!C24 -> gl | E95: ='Presupuesto Base'!D24 -> 1 | F95: ='Presupuesto Base'!E24 -> 859504.13 | G95: ='Presupuesto Base'!F24 -> 859504.13 | H95: =SUMIFS(Medicion!$K$6:$K$511,Medicion!$G$6:$G$511,$B95,Medicion!$A$6:$A$511,"<"&$A95) -> 0 | I95: =SUMIFS(Medicion!$K$6:$K$511,Medicion!$G$6:$G$511,$B95,Medicion!$A$6:$A$511,$A95) -> 0 | J95: =MIN(E95,H95+I95) -> 0 | K95: =MIN(G95,H95*F95) -> 0 | L95: =MIN(G95-K95,I95*F95) -> 0 | M95: =K95+L95 -> 0 | N95: =MAX(0,G95-M95) -> 859504.13 | O95: =IFERROR(J95/E95,0) -> 0 | P95: =IF(OR(H95+I95>E95+0.000001,H95<0,I95<0),"REVISAR","OK") -> OK
A96: 6 | B96: ='Presupuesto Base'!A7 -> 1 | C96: ='Presupuesto Base'!B7 -> Replanteo y marcación de traza | D96: ='Presupuesto Base'!C7 -> ml | E96: ='Presupuesto Base'!D7 -> 4200 | F96: ='Presupuesto Base'!E7 -> 204.64384 | G96: ='Presupuesto Base'!F7 -> 859504.13 | H96: =SUMIFS(Medicion!$K$6:$K$511,Medicion!$G$6:$G$511,$B96,Medicion!$A$6:$A$511,"<"&$A96) -> 845 | I96: =SUMIFS(Medicion!$K$6:$K$511,Medicion!$G$6:$G$511,$B96,Medicion!$A$6:$A$511,$A96) -> 0 | J96: =MIN(E96,H96+I96) -> 845 | K96: =MIN(G96,H96*F96) -> 172924.05 | L96: =MIN(G96-K96,I96*F96) -> 0 | M96: =K96+L96 -> 172924.05 | N96: =MAX(0,G96-M96) -> 686580.09 | O96: =IFERROR(J96/E96,0) -> 0.20119048 | P96: =IF(OR(H96+I96>E96+0.000001,H96<0,I96<0),"REVISAR","OK") -> OK
A97: 6 | B97: ='Presupuesto Base'!A8 -> 2 | C97: ='Presupuesto Base'!B8 -> Excavación de zanja | D97: ='Presupuesto Base'!C8 -> ml | E97: ='Presupuesto Base'!D8 -> 4200 | F97: ='Presupuesto Base'!E8 -> 3683.5891 | G97: ='Presupuesto Base'!F8 -> 15471074 | H97: =SUMIFS(Medicion!$K$6:$K$511,Medicion!$G$6:$G$511,$B97,Medicion!$A$6:$A$511,"<"&$A97) -> 845 | I97: =SUMIFS(Medicion!$K$6:$K$511,Medicion!$G$6:$G$511,$B97,Medicion!$A$6:$A$511,$A97) -> 0 | J97: =MIN(E97,H97+I97) -> 845 | K97: =MIN(G97,H97*F97) -> 3112632.8 | L97: =MIN(G97-K97,I97*F97) -> 0 | M97: =K97+L97 -> 3112632.8 | N97: =MAX(0,G97-M97) -> 12358442 | O97: =IFERROR(J97/E97,0) -> 0.20119048 | P97: =IF(OR(H97+I97>E97+0.000001,H97<0,I97<0),"REVISAR","OK") -> OK
A98: 6 | B98: ='Presupuesto Base'!A9 -> 3 | C98: ='Presupuesto Base'!B9 -> Nivelación y conformación del fondo de zanja | D98: ='Presupuesto Base'!C9 -> ml | E98: ='Presupuesto Base'!D9 -> 4200 | F98: ='Presupuesto Base'!E9 -> 477.5023 | G98: ='Presupuesto Base'!F9 -> 2005509.6 | H98: =SUMIFS(Medicion!$K$6:$K$511,Medicion!$G$6:$G$511,$B98,Medicion!$A$6:$A$511,"<"&$A98) -> 845 | I98: =SUMIFS(Medicion!$K$6:$K$511,Medicion!$G$6:$G$511,$B98,Medicion!$A$6:$A$511,$A98) -> 0 | J98: =MIN(E98,H98+I98) -> 845 | K98: =MIN(G98,H98*F98) -> 403489.44 | L98: =MIN(G98-K98,I98*F98) -> 0 | M98: =K98+L98 -> 403489.44 | N98: =MAX(0,G98-M98) -> 1602020.2 | O98: =IFERROR(J98/E98,0) -> 0.20119048 | P98: =IF(OR(H98+I98>E98+0.000001,H98<0,I98<0),"REVISAR","OK") -> OK
A99: 6 | B99: ='Presupuesto Base'!A10 -> 4 | C99: ='Presupuesto Base'!B10 -> Cama de asiento compactada | D99: ='Presupuesto Base'!C10 -> ml | E99: ='Presupuesto Base'!D10 -> 4200 | F99: ='Presupuesto Base'!E10 -> 1705.3653 | G99: ='Presupuesto Base'!F10 -> 7162534.4 | H99: =SUMIFS(Medicion!$K$6:$K$511,Medicion!$G$6:$G$511,$B99,Medicion!$A$6:$A$511,"<"&$A99) -> 845 | I99: =SUMIFS(Medicion!$K$6:$K$511,Medicion!$G$6:$G$511,$B99,Medicion!$A$6:$A$511,$A99) -> 0 | J99: =MIN(E99,H99+I99) -> 845 | K99: =MIN(G99,H99*F99) -> 1441033.7 | L99: =MIN(G99-K99,I99*F99) -> 0 | M99: =K99+L99 -> 1441033.7 | N99: =MAX(0,G99-M99) -> 5721500.7 | O99: =IFERROR(J99/E99,0) -> 0.20119048 | P99: =IF(OR(H99+I99>E99+0.000001,H99<0,I99<0),"REVISAR","OK") -> OK
A100: 6 | B100: ='Presupuesto Base'!A11 -> 5.1 | C100: ='Presupuesto Base'!B11 -> PEAD PN10 Ø75 – provisión e instalación | D100: ='Presupuesto Base'!C11 -> ml | E100: ='Presupuesto Base'!D11 -> 3170 | F100: ='Presupuesto Base'!E11 -> 5784.2549 | G100: ='Presupuesto Base'!F11 -> 18336088 | H100: =SUMIFS(Medicion!$K$6:$K$511,Medicion!$G$6:$G$511,$B100,Medicion!$A$6:$A$511,"<"&$A100) -> 558 | I100: =SUMIFS(Medicion!$K$6:$K$511,Medicion!$G$6:$G$511,$B100,Medicion!$A$6:$A$511,$A100) -> 0 | J100: =MIN(E100,H100+I100) -> 558 | K100: =MIN(G100,H100*F100) -> 3227614.3 | L100: =MIN(G100-K100,I100*F100) -> 0 | M100: =K100+L100 -> 3227614.3 | N100: =MAX(0,G100-M100) -> 15108474 | O100: =IFERROR(J100/E100,0) -> 0.17602524 | P100: =IF(OR(H100+I100>E100+0.000001,H100<0,I100<0),"REVISAR","OK") -> OK
A101: 6 | B101: ='Presupuesto Base'!A12 -> 5.2 | C101: ='Presupuesto Base'!B12 -> PEAD PN10 Ø110 – provisión e instalación | D101: ='Presupuesto Base'!C12 -> ml | E101: ='Presupuesto Base'!D12 -> 1030 | F101: ='Presupuesto Base'!E12 -> 12238.894 | G101: ='Presupuesto Base'!F12 -> 12606061 | H101: =SUMIFS(Medicion!$K$6:$K$511,Medicion!$G$6:$G$511,$B101,Medicion!$A$6:$A$511,"<"&$A101) -> 287 | I101: =SUMIFS(Medicion!$K$6:$K$511,Medicion!$G$6:$G$511,$B101,Medicion!$A$6:$A$511,$A101) -> 0 | J101: =MIN(E101,H101+I101) -> 287 | K101: =MIN(G101,H101*F101) -> 3512562.5 | L101: =MIN(G101-K101,I101*F101) -> 0 | M101: =K101+L101 -> 3512562.5 | N101: =MAX(0,G101-M101) -> 9093498.1 | O101: =IFERROR(J101/E101,0) -> 0.27864078 | P101: =IF(OR(H101+I101>E101+0.000001,H101<0,I101<0),"REVISAR","OK") -> OK
A102: 6 | B102: ='Presupuesto Base'!A13 -> 6 | C102: ='Presupuesto Base'!B13 -> Ejecución de paquete estructural de 30 cm | D102: ='Presupuesto Base'!C13 -> ml | E102: ='Presupuesto Base'!D13 -> 4200 | F102: ='Presupuesto Base'!E13 -> 3274.3015 | G102: ='Presupuesto Base'!F13 -> 13752066 | H102: =SUMIFS(Medicion!$K$6:$K$511,Medicion!$G$6:$G$511,$B102,Medicion!$A$6:$A$511,"<"&$A102) -> 763 | I102: =SUMIFS(Medicion!$K$6:$K$511,Medicion!$G$6:$G$511,$B102,Medicion!$A$6:$A$511,$A102) -> 0 | J102: =MIN(E102,H102+I102) -> 763 | K102: =MIN(G102,H102*F102) -> 2498292 | L102: =MIN(G102-K102,I102*F102) -> 0 | M102: =K102+L102 -> 2498292 | N102: =MAX(0,G102-M102) -> 11253774 | O102: =IFERROR(J102/E102,0) -> 0.18166667 | P102: =IF(OR(H102+I102>E102+0.000001,H102<0,I102<0),"REVISAR","OK") -> OK
A103: 6 | B103: ='Presupuesto Base'!A14 -> 7 | C103: ='Presupuesto Base'!B14 -> Compactación del paquete estructural de 30 cm | D103: ='Presupuesto Base'!C14 -> ml | E103: ='Presupuesto Base'!D14 -> 4200 | F103: ='Presupuesto Base'!E14 -> 1227.863 | G103: ='Presupuesto Base'!F14 -> 5157024.8 | H103: =SUMIFS(Medicion!$K$6:$K$511,Medicion!$G$6:$G$511,$B103,Medicion!$A$6:$A$511,"<"&$A103) -> 0 | I103: =SUMIFS(Medicion!$K$6:$K$511,Medicion!$G$6:$G$511,$B103,Medicion!$A$6:$A$511,$A103) -> 0 | J103: =MIN(E103,H103+I103) -> 0 | K103: =MIN(G103,H103*F103) -> 0 | L103: =MIN(G103-K103,I103*F103) -> 0 | M103: =K103+L103 -> 0 | N103: =MAX(0,G103-M103) -> 5157024.8 | O103: =IFERROR(J103/E103,0) -> 0 | P103: =IF(OR(H103+I103>E103+0.000001,H103<0,I103<0),"REVISAR","OK") -> OK
A104: 6 | B104: ='Presupuesto Base'!A15 -> 8 | C104: ='Presupuesto Base'!B15 -> Ejecución y compactación de capa cota -0,60 | D104: ='Presupuesto Base'!C15 -> ml | E104: ='Presupuesto Base'!D15 -> 4200 | F104: ='Presupuesto Base'!E15 -> 2592.1553 | G104: ='Presupuesto Base'!F15 -> 10887052 | H104: =SUMIFS(Medicion!$K$6:$K$511,Medicion!$G$6:$G$511,$B104,Medicion!$A$6:$A$511,"<"&$A104) -> 0 | I104: =SUMIFS(Medicion!$K$6:$K$511,Medicion!$G$6:$G$511,$B104,Medicion!$A$6:$A$511,$A104) -> 0 | J104: =MIN(E104,H104+I104) -> 0 | K104: =MIN(G104,H104*F104) -> 0 | L104: =MIN(G104-K104,I104*F104) -> 0 | M104: =K104+L104 -> 0 | N104: =MAX(0,G104-M104) -> 10887052 | O104: =IFERROR(J104/E104,0) -> 0 | P104: =IF(OR(H104+I104>E104+0.000001,H104<0,I104<0),"REVISAR","OK") -> OK
A105: 6 | B105: ='Presupuesto Base'!A16 -> 9 | C105: ='Presupuesto Base'!B16 -> Ejecución y compactación de capa cota -0,30 | D105: ='Presupuesto Base'!C16 -> ml | E105: ='Presupuesto Base'!D16 -> 4200 | F105: ='Presupuesto Base'!E16 -> 2182.8676 | G105: ='Presupuesto Base'!F16 -> 9168044.1 | H105: =SUMIFS(Medicion!$K$6:$K$511,Medicion!$G$6:$G$511,$B105,Medicion!$A$6:$A$511,"<"&$A105) -> 0 | I105: =SUMIFS(Medicion!$K$6:$K$511,Medicion!$G$6:$G$511,$B105,Medicion!$A$6:$A$511,$A105) -> 0 | J105: =MIN(E105,H105+I105) -> 0 | K105: =MIN(G105,H105*F105) -> 0 | L105: =MIN(G105-K105,I105*F105) -> 0 | M105: =K105+L105 -> 0 | N105: =MAX(0,G105-M105) -> 9168044.1 | O105: =IFERROR(J105/E105,0) -> 0 | P105: =IF(OR(H105+I105>E105+0.000001,H105<0,I105<0),"REVISAR","OK") -> OK
A106: 6 | B106: ='Presupuesto Base'!A17 -> 10.1 | C106: ='Presupuesto Base'!B17 -> Conexión domiciliaria sobre red Ø75 | D106: ='Presupuesto Base'!C17 -> un | E106: ='Presupuesto Base'!D17 -> 165 | F106: ='Presupuesto Base'!E17 -> 48618.416 | G106: ='Presupuesto Base'!F17 -> 8022038.6 | H106: =SUMIFS(Medicion!$K$6:$K$511,Medicion!$G$6:$G$511,$B106,Medicion!$A$6:$A$511,"<"&$A106) -> 5 | I106: =SUMIFS(Medicion!$K$6:$K$511,Medicion!$G$6:$G$511,$B106,Medicion!$A$6:$A$511,$A106) -> 0 | J106: =MIN(E106,H106+I106) -> 5 | K106: =MIN(G106,H106*F106) -> 243092.08 | L106: =MIN(G106-K106,I106*F106) -> 0 | M106: =K106+L106 -> 243092.08 | N106: =MAX(0,G106-M106) -> 7778946.5 | O106: =IFERROR(J106/E106,0) -> 0.03030303 | P106: =IF(OR(H106+I106>E106+0.000001,H106<0,I106<0),"REVISAR","OK") -> OK
A107: 6 | B107: ='Presupuesto Base'!A18 -> 10.2 | C107: ='Presupuesto Base'!B18 -> Conexión domiciliaria sobre red Ø110 | D107: ='Presupuesto Base'!C18 -> un | E107: ='Presupuesto Base'!D18 -> 62 | F107: ='Presupuesto Base'!E18 -> 55451.879 | G107: ='Presupuesto Base'!F18 -> 3438016.5 | H107: =SUMIFS(Medicion!$K$6:$K$511,Medicion!$G$6:$G$511,$B107,Medicion!$A$6:$A$511,"<"&$A107) -> 2 | I107: =SUMIFS(Medicion!$K$6:$K$511,Medicion!$G$6:$G$511,$B107,Medicion!$A$6:$A$511,$A107) -> 0 | J107: =MIN(E107,H107+I107) -> 2 | K107: =MIN(G107,H107*F107) -> 110903.76 | L107: =MIN(G107-K107,I107*F107) -> 0 | M107: =K107+L107 -> 110903.76 | N107: =MAX(0,G107-M107) -> 3327112.8 | O107: =IFERROR(J107/E107,0) -> 0.032258065 | P107: =IF(OR(H107+I107>E107+0.000001,H107<0,I107<0),"REVISAR","OK") -> OK
... A113: 6 | B113: ='Presupuesto Base'!A24 -> 13.3 | C113: ='Presupuesto Base'!B24 -> Documentación conforme a obra y cierre | D113: ='Presupuesto Base'!C24 -> gl | E113: ='Presupuesto Base'!D24 -> 1 | F113: ='Presupuesto Base'!E24 -> 859504.13 | G113: ='Presupuesto Base'!F24 -> 859504.13 | H113: =SUMIFS(Medicion!$K$6:$K$511,Medicion!$G$6:$G$511,$B113,Medicion!$A$6:$A$511,"<"&$A113) -> 0 | I113: =SUMIFS(Medicion!$K$6:$K$511,Medicion!$G$6:$G$511,$B113,Medicion!$A$6:$A$511,$A113) -> 0 | J113: =MIN(E113,H113+I113) -> 0 | K113: =MIN(G113,H113*F113) -> 0 | L113: =MIN(G113-K113,I113*F113) -> 0 | M113: =K113+L113 -> 0 | N113: =MAX(0,G113-M113) -> 859504.13 | O113: =IFERROR(J113/E113,0) -> 0 | P113: =IF(OR(H113+I113>E113+0.000001,H113<0,I113<0),"REVISAR","OK") -> OK
A114: 7 | B114: ='Presupuesto Base'!A7 -> 1 | C114: ='Presupuesto Base'!B7 -> Replanteo y marcación de traza | D114: ='Presupuesto Base'!C7 -> ml | E114: ='Presupuesto Base'!D7 -> 4200 | F114: ='Presupuesto Base'!E7 -> 204.64384 | G114: ='Presupuesto Base'!F7 -> 859504.13 | H114: =SUMIFS(Medicion!$K$6:$K$511,Medicion!$G$6:$G$511,$B114,Medicion!$A$6:$A$511,"<"&$A114) -> 845 | I114: =SUMIFS(Medicion!$K$6:$K$511,Medicion!$G$6:$G$511,$B114,Medicion!$A$6:$A$511,$A114) -> 0 | J114: =MIN(E114,H114+I114) -> 845 | K114: =MIN(G114,H114*F114) -> 172924.05 | L114: =MIN(G114-K114,I114*F114) -> 0 | M114: =K114+L114 -> 172924.05 | N114: =MAX(0,G114-M114) -> 686580.09 | O114: =IFERROR(J114/E114,0) -> 0.20119048 | P114: =IF(OR(H114+I114>E114+0.000001,H114<0,I114<0),"REVISAR","OK") -> OK
A115: 7 | B115: ='Presupuesto Base'!A8 -> 2 | C115: ='Presupuesto Base'!B8 -> Excavación de zanja | D115: ='Presupuesto Base'!C8 -> ml | E115: ='Presupuesto Base'!D8 -> 4200 | F115: ='Presupuesto Base'!E8 -> 3683.5891 | G115: ='Presupuesto Base'!F8 -> 15471074 | H115: =SUMIFS(Medicion!$K$6:$K$511,Medicion!$G$6:$G$511,$B115,Medicion!$A$6:$A$511,"<"&$A115) -> 845 | I115: =SUMIFS(Medicion!$K$6:$K$511,Medicion!$G$6:$G$511,$B115,Medicion!$A$6:$A$511,$A115) -> 0 | J115: =MIN(E115,H115+I115) -> 845 | K115: =MIN(G115,H115*F115) -> 3112632.8 | L115: =MIN(G115-K115,I115*F115) -> 0 | M115: =K115+L115 -> 3112632.8 | N115: =MAX(0,G115-M115) -> 12358442 | O115: =IFERROR(J115/E115,0) -> 0.20119048 | P115: =IF(OR(H115+I115>E115+0.000001,H115<0,I115<0),"REVISAR","OK") -> OK
A116: 7 | B116: ='Presupuesto Base'!A9 -> 3 | C116: ='Presupuesto Base'!B9 -> Nivelación y conformación del fondo de zanja | D116: ='Presupuesto Base'!C9 -> ml | E116: ='Presupuesto Base'!D9 -> 4200 | F116: ='Presupuesto Base'!E9 -> 477.5023 | G116: ='Presupuesto Base'!F9 -> 2005509.6 | H116: =SUMIFS(Medicion!$K$6:$K$511,Medicion!$G$6:$G$511,$B116,Medicion!$A$6:$A$511,"<"&$A116) -> 845 | I116: =SUMIFS(Medicion!$K$6:$K$511,Medicion!$G$6:$G$511,$B116,Medicion!$A$6:$A$511,$A116) -> 0 | J116: =MIN(E116,H116+I116) -> 845 | K116: =MIN(G116,H116*F116) -> 403489.44 | L116: =MIN(G116-K116,I116*F116) -> 0 | M116: =K116+L116 -> 403489.44 | N116: =MAX(0,G116-M116) -> 1602020.2 | O116: =IFERROR(J116/E116,0) -> 0.20119048 | P116: =IF(OR(H116+I116>E116+0.000001,H116<0,I116<0),"REVISAR","OK") -> OK
A117: 7 | B117: ='Presupuesto Base'!A10 -> 4 | C117: ='Presupuesto Base'!B10 -> Cama de asiento compactada | D117: ='Presupuesto Base'!C10 -> ml | E117: ='Presupuesto Base'!D10 -> 4200 | F117: ='Presupuesto Base'!E10 -> 1705.3653 | G117: ='Presupuesto Base'!F10 -> 7162534.4 | H117: =SUMIFS(Medicion!$K$6:$K$511,Medicion!$G$6:$G$511,$B117,Medicion!$A$6:$A$511,"<"&$A117) -> 845 | I117: =SUMIFS(Medicion!$K$6:$K$511,Medicion!$G$6:$G$511,$B117,Medicion!$A$6:$A$511,$A117) -> 0 | J117: =MIN(E117,H117+I117) -> 845 | K117: =MIN(G117,H117*F117) -> 1441033.7 | L117: =MIN(G117-K117,I117*F117) -> 0 | M117: =K117+L117 -> 1441033.7 | N117: =MAX(0,G117-M117) -> 5721500.7 | O117: =IFERROR(J117/E117,0) -> 0.20119048 | P117: =IF(OR(H117+I117>E117+0.000001,H117<0,I117<0),"REVISAR","OK") -> OK
A118: 7 | B118: ='Presupuesto Base'!A11 -> 5.1 | C118: ='Presupuesto Base'!B11 -> PEAD PN10 Ø75 – provisión e instalación | D118: ='Presupuesto Base'!C11 -> ml | E118: ='Presupuesto Base'!D11 -> 3170 | F118: ='Presupuesto Base'!E11 -> 5784.2549 | G118: ='Presupuesto Base'!F11 -> 18336088 | H118: =SUMIFS(Medicion!$K$6:$K$511,Medicion!$G$6:$G$511,$B118,Medicion!$A$6:$A$511,"<"&$A118) -> 558 | I118: =SUMIFS(Medicion!$K$6:$K$511,Medicion!$G$6:$G$511,$B118,Medicion!$A$6:$A$511,$A118) -> 0 | J118: =MIN(E118,H118+I118) -> 558 | K118: =MIN(G118,H118*F118) -> 3227614.3 | L118: =MIN(G118-K118,I118*F118) -> 0 | M118: =K118+L118 -> 3227614.3 | N118: =MAX(0,G118-M118) -> 15108474 | O118: =IFERROR(J118/E118,0) -> 0.17602524 | P118: =IF(OR(H118+I118>E118+0.000001,H118<0,I118<0),"REVISAR","OK") -> OK
A119: 7 | B119: ='Presupuesto Base'!A12 -> 5.2 | C119: ='Presupuesto Base'!B12 -> PEAD PN10 Ø110 – provisión e instalación | D119: ='Presupuesto Base'!C12 -> ml | E119: ='Presupuesto Base'!D12 -> 1030 | F119: ='Presupuesto Base'!E12 -> 12238.894 | G119: ='Presupuesto Base'!F12 -> 12606061 | H119: =SUMIFS(Medicion!$K$6:$K$511,Medicion!$G$6:$G$511,$B119,Medicion!$A$6:$A$511,"<"&$A119) -> 287 | I119: =SUMIFS(Medicion!$K$6:$K$511,Medicion!$G$6:$G$511,$B119,Medicion!$A$6:$A$511,$A119) -> 0 | J119: =MIN(E119,H119+I119) -> 287 | K119: =MIN(G119,H119*F119) -> 3512562.5 | L119: =MIN(G119-K119,I119*F119) -> 0 | M119: =K119+L119 -> 3512562.5 | N119: =MAX(0,G119-M119) -> 9093498.1 | O119: =IFERROR(J119/E119,0) -> 0.27864078 | P119: =IF(OR(H119+I119>E119+0.000001,H119<0,I119<0),"REVISAR","OK") -> OK
A120: 7 | B120: ='Presupuesto Base'!A13 -> 6 | C120: ='Presupuesto Base'!B13 -> Ejecución de paquete estructural de 30 cm | D120: ='Presupuesto Base'!C13 -> ml | E120: ='Presupuesto Base'!D13 -> 4200 | F120: ='Presupuesto Base'!E13 -> 3274.3015 | G120: ='Presupuesto Base'!F13 -> 13752066 | H120: =SUMIFS(Medicion!$K$6:$K$511,Medicion!$G$6:$G$511,$B120,Medicion!$A$6:$A$511,"<"&$A120) -> 763 | I120: =SUMIFS(Medicion!$K$6:$K$511,Medicion!$G$6:$G$511,$B120,Medicion!$A$6:$A$511,$A120) -> 0 | J120: =MIN(E120,H120+I120) -> 763 | K120: =MIN(G120,H120*F120) -> 2498292 | L120: =MIN(G120-K120,I120*F120) -> 0 | M120: =K120+L120 -> 2498292 | N120: =MAX(0,G120-M120) -> 11253774 | O120: =IFERROR(J120/E120,0) -> 0.18166667 | P120: =IF(OR(H120+I120>E120+0.000001,H120<0,I120<0),"REVISAR","OK") -> OK
A121: 7 | B121: ='Presupuesto Base'!A14 -> 7 | C121: ='Presupuesto Base'!B14 -> Compactación del paquete estructural de 30 cm | D121: ='Presupuesto Base'!C14 -> ml | E121: ='Presupuesto Base'!D14 -> 4200 | F121: ='Presupuesto Base'!E14 -> 1227.863 | G121: ='Presupuesto Base'!F14 -> 5157024.8 | H121: =SUMIFS(Medicion!$K$6:$K$511,Medicion!$G$6:$G$511,$B121,Medicion!$A$6:$A$511,"<"&$A121) -> 0 | I121: =SUMIFS(Medicion!$K$6:$K$511,Medicion!$G$6:$G$511,$B121,Medicion!$A$6:$A$511,$A121) -> 0 | J121: =MIN(E121,H121+I121) -> 0 | K121: =MIN(G121,H121*F121) -> 0 | L121: =MIN(G121-K121,I121*F121) -> 0 | M121: =K121+L121 -> 0 | N121: =MAX(0,G121-M121) -> 5157024.8 | O121: =IFERROR(J121/E121,0) -> 0 | P121: =IF(OR(H121+I121>E121+0.000001,H121<0,I121<0),"REVISAR","OK") -> OK
A122: 7 | B122: ='Presupuesto Base'!A15 -> 8 | C122: ='Presupuesto Base'!B15 -> Ejecución y compactación de capa cota -0,60 | D122: ='Presupuesto Base'!C15 -> ml | E122: ='Presupuesto Base'!D15 -> 4200 | F122: ='Presupuesto Base'!E15 -> 2592.1553 | G122: ='Presupuesto Base'!F15 -> 10887052 | H122: =SUMIFS(Medicion!$K$6:$K$511,Medicion!$G$6:$G$511,$B122,Medicion!$A$6:$A$511,"<"&$A122) -> 0 | I122: =SUMIFS(Medicion!$K$6:$K$511,Medicion!$G$6:$G$511,$B122,Medicion!$A$6:$A$511,$A122) -> 0 | J122: =MIN(E122,H122+I122) -> 0 | K122: =MIN(G122,H122*F122) -> 0 | L122: =MIN(G122-K122,I122*F122) -> 0 | M122: =K122+L122 -> 0 | N122: =MAX(0,G122-M122) -> 10887052 | O122: =IFERROR(J122/E122,0) -> 0 | P122: =IF(OR(H122+I122>E122+0.000001,H122<0,I122<0),"REVISAR","OK") -> OK
A123: 7 | B123: ='Presupuesto Base'!A16 -> 9 | C123: ='Presupuesto Base'!B16 -> Ejecución y compactación de capa cota -0,30 | D123: ='Presupuesto Base'!C16 -> ml | E123: ='Presupuesto Base'!D16 -> 4200 | F123: ='Presupuesto Base'!E16 -> 2182.8676 | G123: ='Presupuesto Base'!F16 -> 9168044.1 | H123: =SUMIFS(Medicion!$K$6:$K$511,Medicion!$G$6:$G$511,$B123,Medicion!$A$6:$A$511,"<"&$A123) -> 0 | I123: =SUMIFS(Medicion!$K$6:$K$511,Medicion!$G$6:$G$511,$B123,Medicion!$A$6:$A$511,$A123) -> 0 | J123: =MIN(E123,H123+I123) -> 0 | K123: =MIN(G123,H123*F123) -> 0 | L123: =MIN(G123-K123,I123*F123) -> 0 | M123: =K123+L123 -> 0 | N123: =MAX(0,G123-M123) -> 9168044.1 | O123: =IFERROR(J123/E123,0) -> 0 | P123: =IF(OR(H123+I123>E123+0.000001,H123<0,I123<0),"REVISAR","OK") -> OK
A124: 7 | B124: ='Presupuesto Base'!A17 -> 10.1 | C124: ='Presupuesto Base'!B17 -> Conexión domiciliaria sobre red Ø75 | D124: ='Presupuesto Base'!C17 -> un | E124: ='Presupuesto Base'!D17 -> 165 | F124: ='Presupuesto Base'!E17 -> 48618.416 | G124: ='Presupuesto Base'!F17 -> 8022038.6 | H124: =SUMIFS(Medicion!$K$6:$K$511,Medicion!$G$6:$G$511,$B124,Medicion!$A$6:$A$511,"<"&$A124) -> 5 | I124: =SUMIFS(Medicion!$K$6:$K$511,Medicion!$G$6:$G$511,$B124,Medicion!$A$6:$A$511,$A124) -> 0 | J124: =MIN(E124,H124+I124) -> 5 | K124: =MIN(G124,H124*F124) -> 243092.08 | L124: =MIN(G124-K124,I124*F124) -> 0 | M124: =K124+L124 -> 243092.08 | N124: =MAX(0,G124-M124) -> 7778946.5 | O124: =IFERROR(J124/E124,0) -> 0.03030303 | P124: =IF(OR(H124+I124>E124+0.000001,H124<0,I124<0),"REVISAR","OK") -> OK
A125: 7 | B125: ='Presupuesto Base'!A18 -> 10.2 | C125: ='Presupuesto Base'!B18 -> Conexión domiciliaria sobre red Ø110 | D125: ='Presupuesto Base'!C18 -> un | E125: ='Presupuesto Base'!D18 -> 62 | F125: ='Presupuesto Base'!E18 -> 55451.879 | G125: ='Presupuesto Base'!F18 -> 3438016.5 | H125: =SUMIFS(Medicion!$K$6:$K$511,Medicion!$G$6:$G$511,$B125,Medicion!$A$6:$A$511,"<"&$A125) -> 2 | I125: =SUMIFS(Medicion!$K$6:$K$511,Medicion!$G$6:$G$511,$B125,Medicion!$A$6:$A$511,$A125) -> 0 | J125: =MIN(E125,H125+I125) -> 2 | K125: =MIN(G125,H125*F125) -> 110903.76 | L125: =MIN(G125-K125,I125*F125) -> 0 | M125: =K125+L125 -> 110903.76 | N125: =MAX(0,G125-M125) -> 3327112.8 | O125: =IFERROR(J125/E125,0) -> 0.032258065 | P125: =IF(OR(H125+I125>E125+0.000001,H125<0,I125<0),"REVISAR","OK") -> OK
... A131: 7 | B131: ='Presupuesto Base'!A24 -> 13.3 | C131: ='Presupuesto Base'!B24 -> Documentación conforme a obra y cierre | D131: ='Presupuesto Base'!C24 -> gl | E131: ='Presupuesto Base'!D24 -> 1 | F131: ='Presupuesto Base'!E24 -> 859504.13 | G131: ='Presupuesto Base'!F24 -> 859504.13 | H131: =SUMIFS(Medicion!$K$6:$K$511,Medicion!$G$6:$G$511,$B131,Medicion!$A$6:$A$511,"<"&$A131) -> 0 | I131: =SUMIFS(Medicion!$K$6:$K$511,Medicion!$G$6:$G$511,$B131,Medicion!$A$6:$A$511,$A131) -> 0 | J131: =MIN(E131,H131+I131) -> 0 | K131: =MIN(G131,H131*F131) -> 0 | L131: =MIN(G131-K131,I131*F131) -> 0 | M131: =K131+L131 -> 0 | N131: =MAX(0,G131-M131) -> 859504.13 | O131: =IFERROR(J131/E131,0) -> 0 | P131: =IF(OR(H131+I131>E131+0.000001,H131<0,I131<0),"REVISAR","OK") -> OK
A132: 8 | B132: ='Presupuesto Base'!A7 -> 1 | C132: ='Presupuesto Base'!B7 -> Replanteo y marcación de traza | D132: ='Presupuesto Base'!C7 -> ml | E132: ='Presupuesto Base'!D7 -> 4200 | F132: ='Presupuesto Base'!E7 -> 204.64384 | G132: ='Presupuesto Base'!F7 -> 859504.13 | H132: =SUMIFS(Medicion!$K$6:$K$511,Medicion!$G$6:$G$511,$B132,Medicion!$A$6:$A$511,"<"&$A132) -> 845 | I132: =SUMIFS(Medicion!$K$6:$K$511,Medicion!$G$6:$G$511,$B132,Medicion!$A$6:$A$511,$A132) -> 0 | J132: =MIN(E132,H132+I132) -> 845 | K132: =MIN(G132,H132*F132) -> 172924.05 | L132: =MIN(G132-K132,I132*F132) -> 0 | M132: =K132+L132 -> 172924.05 | N132: =MAX(0,G132-M132) -> 686580.09 | O132: =IFERROR(J132/E132,0) -> 0.20119048 | P132: =IF(OR(H132+I132>E132+0.000001,H132<0,I132<0),"REVISAR","OK") -> OK
A133: 8 | B133: ='Presupuesto Base'!A8 -> 2 | C133: ='Presupuesto Base'!B8 -> Excavación de zanja | D133: ='Presupuesto Base'!C8 -> ml | E133: ='Presupuesto Base'!D8 -> 4200 | F133: ='Presupuesto Base'!E8 -> 3683.5891 | G133: ='Presupuesto Base'!F8 -> 15471074 | H133: =SUMIFS(Medicion!$K$6:$K$511,Medicion!$G$6:$G$511,$B133,Medicion!$A$6:$A$511,"<"&$A133) -> 845 | I133: =SUMIFS(Medicion!$K$6:$K$511,Medicion!$G$6:$G$511,$B133,Medicion!$A$6:$A$511,$A133) -> 0 | J133: =MIN(E133,H133+I133) -> 845 | K133: =MIN(G133,H133*F133) -> 3112632.8 | L133: =MIN(G133-K133,I133*F133) -> 0 | M133: =K133+L133 -> 3112632.8 | N133: =MAX(0,G133-M133) -> 12358442 | O133: =IFERROR(J133/E133,0) -> 0.20119048 | P133: =IF(OR(H133+I133>E133+0.000001,H133<0,I133<0),"REVISAR","OK") -> OK
A134: 8 | B134: ='Presupuesto Base'!A9 -> 3 | C134: ='Presupuesto Base'!B9 -> Nivelación y conformación del fondo de zanja | D134: ='Presupuesto Base'!C9 -> ml | E134: ='Presupuesto Base'!D9 -> 4200 | F134: ='Presupuesto Base'!E9 -> 477.5023 | G134: ='Presupuesto Base'!F9 -> 2005509.6 | H134: =SUMIFS(Medicion!$K$6:$K$511,Medicion!$G$6:$G$511,$B134,Medicion!$A$6:$A$511,"<"&$A134) -> 845 | I134: =SUMIFS(Medicion!$K$6:$K$511,Medicion!$G$6:$G$511,$B134,Medicion!$A$6:$A$511,$A134) -> 0 | J134: =MIN(E134,H134+I134) -> 845 | K134: =MIN(G134,H134*F134) -> 403489.44 | L134: =MIN(G134-K134,I134*F134) -> 0 | M134: =K134+L134 -> 403489.44 | N134: =MAX(0,G134-M134) -> 1602020.2 | O134: =IFERROR(J134/E134,0) -> 0.20119048 | P134: =IF(OR(H134+I134>E134+0.000001,H134<0,I134<0),"REVISAR","OK") -> OK
A135: 8 | B135: ='Presupuesto Base'!A10 -> 4 | C135: ='Presupuesto Base'!B10 -> Cama de asiento compactada | D135: ='Presupuesto Base'!C10 -> ml | E135: ='Presupuesto Base'!D10 -> 4200 | F135: ='Presupuesto Base'!E10 -> 1705.3653 | G135: ='Presupuesto Base'!F10 -> 7162534.4 | H135: =SUMIFS(Medicion!$K$6:$K$511,Medicion!$G$6:$G$511,$B135,Medicion!$A$6:$A$511,"<"&$A135) -> 845 | I135: =SUMIFS(Medicion!$K$6:$K$511,Medicion!$G$6:$G$511,$B135,Medicion!$A$6:$A$511,$A135) -> 0 | J135: =MIN(E135,H135+I135) -> 845 | K135: =MIN(G135,H135*F135) -> 1441033.7 | L135: =MIN(G135-K135,I135*F135) -> 0 | M135: =K135+L135 -> 1441033.7 | N135: =MAX(0,G135-M135) -> 5721500.7 | O135: =IFERROR(J135/E135,0) -> 0.20119048 | P135: =IF(OR(H135+I135>E135+0.000001,H135<0,I135<0),"REVISAR","OK") -> OK
A136: 8 | B136: ='Presupuesto Base'!A11 -> 5.1 | C136: ='Presupuesto Base'!B11 -> PEAD PN10 Ø75 – provisión e instalación | D136: ='Presupuesto Base'!C11 -> ml | E136: ='Presupuesto Base'!D11 -> 3170 | F136: ='Presupuesto Base'!E11 -> 5784.2549 | G136: ='Presupuesto Base'!F11 -> 18336088 | H136: =SUMIFS(Medicion!$K$6:$K$511,Medicion!$G$6:$G$511,$B136,Medicion!$A$6:$A$511,"<"&$A136) -> 558 | I136: =SUMIFS(Medicion!$K$6:$K$511,Medicion!$G$6:$G$511,$B136,Medicion!$A$6:$A$511,$A136) -> 0 | J136: =MIN(E136,H136+I136) -> 558 | K136: =MIN(G136,H136*F136) -> 3227614.3 | L136: =MIN(G136-K136,I136*F136) -> 0 | M136: =K136+L136 -> 3227614.3 | N136: =MAX(0,G136-M136) -> 15108474 | O136: =IFERROR(J136/E136,0) -> 0.17602524 | P136: =IF(OR(H136+I136>E136+0.000001,H136<0,I136<0),"REVISAR","OK") -> OK
A137: 8 | B137: ='Presupuesto Base'!A12 -> 5.2 | C137: ='Presupuesto Base'!B12 -> PEAD PN10 Ø110 – provisión e instalación | D137: ='Presupuesto Base'!C12 -> ml | E137: ='Presupuesto Base'!D12 -> 1030 | F137: ='Presupuesto Base'!E12 -> 12238.894 | G137: ='Presupuesto Base'!F12 -> 12606061 | H137: =SUMIFS(Medicion!$K$6:$K$511,Medicion!$G$6:$G$511,$B137,Medicion!$A$6:$A$511,"<"&$A137) -> 287 | I137: =SUMIFS(Medicion!$K$6:$K$511,Medicion!$G$6:$G$511,$B137,Medicion!$A$6:$A$511,$A137) -> 0 | J137: =MIN(E137,H137+I137) -> 287 | K137: =MIN(G137,H137*F137) -> 3512562.5 | L137: =MIN(G137-K137,I137*F137) -> 0 | M137: =K137+L137 -> 3512562.5 | N137: =MAX(0,G137-M137) -> 9093498.1 | O137: =IFERROR(J137/E137,0) -> 0.27864078 | P137: =IF(OR(H137+I137>E137+0.000001,H137<0,I137<0),"REVISAR","OK") -> OK
...
