Workbook
Name Lista_Anios: LISTAS!$G$2:$G$5
Name Lista_Cargas_Batan: 'CONTROL DE BATAN'!$A$2:$A$301
Name Lista_Codigos: LISTAS!$A$3:$A$202
Name Lista_EstadoProveedor: LISTAS!$F$2:$F$5
Name Lista_Meses: LISTAS!$H$2:$H$13
Name Lista_Meses_Dashboard: LISTAS!$I$2:$I$14
Name Lista_MetodoPago: LISTAS!$E$2:$E$5
Name Lista_Obras: 'MAESTRO DE OBRAS'!$B$2:$B$200
Name Lista_Obras_Dash: LISTAS!$C$2:$C$202
Name Lista_Proveedores: LISTAS!$J$2:$J$6
Name Lista_Responsables: 'MAESTRO DE RESPONSABLES'!$A$2:$A$200
Name Lista_Responsables_Dash: LISTAS!$B$2:$B$202
Name Lista_TipoCombustible: LISTAS!$D$2:$D$5
Name Lista_TipoCombustible_Dash: LISTAS!$D$7:$D$11
Name Lista_Unidades_Dashboard: LISTAS!$K$2:$K$202

Sheet INICIO
A1: CONTROL DE COMBUSTIBLE
A3: Planilla integral para registro, análisis y conciliación mensual con proveedor
A5: Objetivo | B5: Registrar cada carga, controlar consumos, detectar desvíos y validar el pago mensual al proveedor.
A6: Uso sugerido | B6: 1) Completar maestros. 2) Registrar cargas en la hoja principal. 3) Revisar alertas. 4) Conciliar factura en Control Mensual. 5) Analizar KPIs en Dashboard.
A8: Fecha de actualización | B8: =TODAY() -> 46160
A9: Hojas incluidas | B9: Inicio, Maestros, Cargas, Control Mensual Proveedor, Indicadores y Dashboard.
A11: Accesos rápidos
A12: Ir a cargas
A13: Ir a dashboard
A14: Ir a control mensual

Sheet MAESTRO DE UNIDADES
A1: Código interno | B1: Tipo de unidad | C1: Descripción | D1: Marca | E1: Modelo | F1: Patente | G1: Año | H1: Tipo de combustible | I1: Capacidad de tanque | J1: Área / sector | K1: Responsable habitual | L1: Estado
A2: C-001 | B2: Camioneta | C2: Toyota Hilux 2.4 | D2: Toyota | E2: Hilux | F2: AE829HD | G2: 2021 | H2: Diesel V-Power | I2: 80 | J2: G. General | K2: G. Regalado | L2: Activo
A3: C-002 | B3: Camioneta | C3: Toyota Hilux 2.4 | D3: Toyota | E3: Hilux | F3: AG839PV | G3: 2024 | H3: Diesel V-Power | I3: 80 | J3: Directorio | K3: C. Regalado | L3: Activo
A4: C-003 | B4: Camioneta | C4: RAM 1500 5.7 V8 LARAMIE4X4 | D4: RAM | E4: LARAMIE | F4: AE453FS | G4: 2021 | H4: Nafta | I4: 98 | J4: Directorio | K4: C. Regalado | L4: Activo
A5: C-004 | B5: Camioneta | C5: Peugeot Partner confort 1.6 HDI | D5: Peugeot | E5: Partner | F5: OWQ190 | G5: 2015 | H5: Diesel-Evolux | I5: 55 | J5: Obras | L5: Activo
A6: C-005 | B6: Camioneta | C6: Toyota Hilux 4X4 C/S DX2.4 TDI 6M/T | D6: Toyota | E6: Hilux | F6: AE167AT | G6: 2024 | H6: Diesel V-Power | I6: 80 | J6: Directorio | K6: C. Regalado | L6: Activo
A7: CM-001 | B7: Camión | C7: Iveco Tector | D7: Iveco | E7: Tector | F7: AC | G7: 2020 | H7: Diesel V-Power | I7: 150 | J7: Logística | L7: Activo
A8: CM-002 | B8: Camión | C8: IVECO Daily 70c17 PASO 4350 | D8: IVECO | E8: Daily | F8: AD478QW | G8: 2018 | H8: Diesel V-Power | I8: 100 | J8: Obras | L8: Activo
A9: EP-001 | B9: Equipo | C9: Motocompresor | H9: Diesel-Evolux | I9: 70 | J9: Obras | L9: Activo
A10: EP-002 | B10: Equipo | C10: Motosoldador | H10: Diesel-Evolux | J10: Obras
A11: EP-003 | B11: Equipo | C11: Montacarga | D11: Longking | H11: Diesel-Evolux
A12: MC-001 | B12: Mini cargadora | C12: CAT | D12: Caterpillar | G12: 2017 | H12: Diesel-Evolux | K12: Luis Martínez | L12: Activo
A13: MC-002 | B13: Mini cargadora | C13: Longking | H13: Diesel-Evolux
A14: RP-001 | B14: Retroexcavadora | C14: Hidromek | D14: HIDROMEK | G14: 2024 | H14: Diesel-Evolux | I14: 140 | J14: Obras | L14: Activo
A15: RP-002 | B15: Retroexcavadora | C15: MAXION 750 | H15: Diesel-Evolux | L15: Activo
A16: BT-001 | B16: Batan | C16: Batan de 200lts | G16: 2024 | H16: Diesel-Evolux | I16: 200
A17: C-006 | B17: Camioneta | C17: Toyota Hilux 2.4 | D17: Toyota | E17: Hilux | F17: ISB 928 | G17: 2011 | H17: Diesel-Evolux | I17: 80 | J17: Varios | K17: G. Regalado | L17: Activo

Sheet MAESTRO DE RESPONSABLES
A1: Nombre y apellido | B1: Cargo | C1: Área | D1: Observaciones
A2: Ariel Jofre | B2: Chofer | C2: Logística
A3: Bruno Guevara | B3: Encargado de obra | C3: Obras
A4: Enrico | B4: Gerencia | C4: Administracion
A5: Gustavo | B5: Gerencia | C5: Gerencia General
A6: Adolfo | B6: Gerencia | C6: Financiera
A7: Daniel Pereyra | B7: Maquinista | C7: Obras
A8: Martin | B8: Maquinista | C8: Obras
A9: Daniel | B9: Chofer | C9: Obras
A12: Nota: | B12: Para los que usan los vehiculos si o si tiene que tener gestionados los permisos de manejo y el carnet de conducir comun o prefesional según corresponda

Sheet MAESTRO DE OBRAS
A1: Código | B1: Obra / sector | C1: Cliente | D1: Ubicación | E1: Estado
A2: OB-001 | B2: Barrio Don Jose | C2: Gobierno | E2: Activa
A3: OB-002 | B3: Escuela Stgo del Estero | C3: Gobierno | E3: Activa
A4: OB-003 | B4: Mantenimiento Escuelas | C4: Gobierno | E4: Activa
A5: OB-004 | B5: Movimientos Internos | E5: Activa
A6: OB-005 | B6: Barrio ASEC | C6: Borrego | E6: Activa
A7: OB-006 | B7: Barrio San Martin | C7: Gobierno | E7: Activa

Sheet CARGAS DE COMBUSTIBLE
A1: ID de carga | B1: Fecha | C1: Mes | D1: Año | E1: Día de semana | F1: Vehículo / equipo | G1: Código interno | H1: Patente | I1: Tipo de unidad | J1: Responsable | K1: Obra / centro de costo | L1: Proveedor / estación | M1: Tipo de combustible | N1: Litros cargados | O1: Precio por litro | P1: Importe total | Q1: Kilometraje al cargar | R1: Horómetro al cargar | S1: Kilómetros recorridos desde la carga anterior | T1: Horas trabajadas desde la carga anterior | U1: Rendimiento estimado | V1: Método de pago | W1: VALE DE COMBUSTIBLE | X1: Observaciones | Y1: Validación / estado del registro | Z1: Origen de carga | AA1: ID carga de batán | AB1: Precio batán aplicado | AC1: Saldo batán luego de la carga
A2: =IF(B2="","","CARGA-"&TEXT(ROW()-1,"0000")) -> CARGA-0001 | B2: 46147 | C2: =IF(B2="","",CHOOSE(MONTH(B2),"Enero","Febrero","Marzo","Abril","Mayo","Junio","Julio","Agosto","Septiembre","Octubre","Noviembre","Diciembre")) -> Mayo | D2: =IF(B2="","",YEAR(B2)) -> 2026 | E2: =IF(B2="","",CHOOSE(WEEKDAY(B2,2),"Lunes","Martes","Miércoles","Jueves","Viernes","Sábado","Domingo")) -> Martes | F2: =+tblUnidades[[#This Row],[Descripción]] -> Toyota Hilux 2.4 | G2: C-002 | H2: =IF($G2="","",IFERROR(INDEX('MAESTRO DE UNIDADES'!$F$2:$F$208,MATCH($G2,'MAESTRO DE UNIDADES'!$A$2:$A$208,0)),"")) -> AG839PV | I2: =IF($G2="","",IFERROR(INDEX('MAESTRO DE UNIDADES'!$B$2:$B$208,MATCH($G2,'MAESTRO DE UNIDADES'!$A$2:$A$208,0)),"")) -> Camioneta | J2: Adolfo | K2: Movimientos Internos | L2: Shell Agro | M2: =IF($G2="","",IFERROR(INDEX('MAESTRO DE UNIDADES'!$H$2:$H$208,MATCH($G2,'MAESTRO DE UNIDADES'!$A$2:$A$208,0)),"")) -> Diesel V-Power | N2: 40 | P2: =IF($N2="","",IF($AA2<>"",IF($AB2="","",$N2*$AB2),IF($O2="","",$N2*$O2))) | S2: =IF(OR($G2="",$Q2="",COUNTIF($G$1:G2,$G2)=0),"",$Q2-LOOKUP(2,1/($G$1:G2=$G2),$Q$1:Q2)) | T2: =IF(OR($G2="",$R2="",COUNTIF($G$1:G2,$G2)=0),"",$R2-LOOKUP(2,1/($G$1:G2=$G2),$R$1:R2)) | U2: =IF(N2="","",IF(S2<>"",S2/N2,IF(T2<>"",T2/N2,""))) | W2: 205 | X2: N°205 / REMITO N° 7687 | Y2: =IF($B2="","",IF((IF($G2="","Sin unidad | ","")&IF($J2="","Sin responsable | ","")&IF($K2="","Sin obra | ","")&IF(AND($N2<>"",$G2<>"",$N2>IFERROR(INDEX('MAESTRO DE UNIDADES'!$I$2:$I$208,MATCH($G2,'MAESTRO DE UNIDADES'!$A$2:$A$208,0)),0)),"Litros > tanque | ","")&IF(AND($W2<>"",COUNTIF($W$2:$W2,$W2)>1),"Ticket duplicado | ","")&IF(AND($G2<>"",IFERROR(INDEX('MAESTRO DE UNIDADES'!$L$2:$L$208,MATCH($G2,'MAESTRO DE UNIDADES'!$A$2:$A$208,0)),"")="Inactivo"),"Unidad inactiva | ","")&IF(AND($AA2<>"",$N2=""),"Carga de batán sin litros | ","")&IF(AND($AA2<>"",$AC2<0),"Supera saldo batán | ",""))="","OK",LEFT((IF($G2="","Sin unidad | ","")&IF($J2="","Sin responsable | ","")&IF($K2="","Sin obra | ","")&IF(AND($N2<>"",$G2<>"",$N2>IFERROR(INDEX('MAESTRO DE UNIDADES'!$I$2:$I$208,MATCH($G2,'MAESTRO DE UNIDADES'!$A$2:$A$208,0)),0)),"Litros > tanque | ","")&IF(AND($W2<>"",COUNTIF($W$2:$W2,$W2)>1),"Ticket duplicado | ","")&IF(AND($G2<>"",IFERROR(INDEX('MAESTRO DE UNIDADES'!$L$2:$L$208,MATCH($G2,'MAESTRO DE UNIDADES'!$A$2:$A$208,0)),"")="Inactivo"),"Unidad inactiva | ","")&IF(AND($AA2<>"",$N2=""),"Carga de batán sin litros | ","")&IF(AND($AA2<>"",$AC2<0),"Supera saldo batán | ","")),LEN((IF($G2="","Sin unidad | ","")&IF($J2="","Sin responsable | ","")&IF($K2="","Sin obra | ","")&IF(AND($N2<>"",$G2<>"",$N2>IFERROR(INDEX('MAESTRO DE UNIDADES'!$I$2:$I$208,MATCH($G2,'MAESTRO DE UNIDADES'!$A$2:$A$208,0)),0)),"Litros > tanque | ","")&IF(AND($W2<>"",COUNTIF($W$2:$W2,$W2)>1),"Ticket duplicado | ","")&IF(AND($G2<>"",IFERROR(INDEX('MAESTRO DE UNIDADES'!$L$2:$L$208,MATCH($G2,'MAESTRO DE UNIDADES'!$A$2:$A$208,0)),"")="Inactivo"),"Unidad inactiva | ","")&IF(AND($AA2<>"",$N2=""),"Carga de batán sin litros | ","")&IF(AND($AA2<>"",$AC2<0),"Supera saldo batán | ","")))-3))) -> OK | Z2: =IF($B2="","",IF($AA2<>"","Batán","Estación de servicio")) -> Estación de servicio
A3: =IF(B3="","","CARGA-"&TEXT(ROW()-1,"0000")) -> CARGA-0002 | B3: 46157 | C3: =IF(B3="","",CHOOSE(MONTH(B3),"Enero","Febrero","Marzo","Abril","Mayo","Junio","Julio","Agosto","Septiembre","Octubre","Noviembre","Diciembre")) -> Mayo | D3: =IF(B3="","",YEAR(B3)) -> 2026 | E3: =IF(B3="","",CHOOSE(WEEKDAY(B3,2),"Lunes","Martes","Miércoles","Jueves","Viernes","Sábado","Domingo")) -> Viernes | F3: Iveco tector | G3: CM-002 | H3: =IF($G3="","",IFERROR(INDEX('MAESTRO DE UNIDADES'!$F$2:$F$208,MATCH($G3,'MAESTRO DE UNIDADES'!$A$2:$A$208,0)),"")) -> AD478QW | I3: =IF($G3="","",IFERROR(INDEX('MAESTRO DE UNIDADES'!$B$2:$B$208,MATCH($G3,'MAESTRO DE UNIDADES'!$A$2:$A$208,0)),"")) -> Camión | J3: Bruno Guevara | K3: Barrio Don Jose | L3: Shell Agro | M3: =IF($G3="","",IFERROR(INDEX('MAESTRO DE UNIDADES'!$H$2:$H$208,MATCH($G3,'MAESTRO DE UNIDADES'!$A$2:$A$208,0)),"")) -> Diesel V-Power | N3: 49.65 | W3: S-V | X3: 4174/ S-V | Y3: OK | Z3: Estación de servicio
A4: =IF(B4="","","CARGA-"&TEXT(ROW()-1,"0000")) -> CARGA-0003 | B4: 46157 | C4: =IF(B4="","",CHOOSE(MONTH(B4),"Enero","Febrero","Marzo","Abril","Mayo","Junio","Julio","Agosto","Septiembre","Octubre","Noviembre","Diciembre")) -> Mayo | D4: =IF(B4="","",YEAR(B4)) -> 2026 | E4: =IF(B4="","",CHOOSE(WEEKDAY(B4,2),"Lunes","Martes","Miércoles","Jueves","Viernes","Sábado","Domingo")) -> Viernes | F4: Toyota Hilux 2.4 | G4: C-002 | H4: =IF($G4="","",IFERROR(INDEX('MAESTRO DE UNIDADES'!$F$2:$F$208,MATCH($G4,'MAESTRO DE UNIDADES'!$A$2:$A$208,0)),"")) -> AG839PV | I4: =IF($G4="","",IFERROR(INDEX('MAESTRO DE UNIDADES'!$B$2:$B$208,MATCH($G4,'MAESTRO DE UNIDADES'!$A$2:$A$208,0)),"")) -> Camioneta | J4: Adolfo | K4: Movimientos Internos | L4: Shell Agro | M4: =IF($G4="","",IFERROR(INDEX('MAESTRO DE UNIDADES'!$H$2:$H$208,MATCH($G4,'MAESTRO DE UNIDADES'!$A$2:$A$208,0)),"")) -> Diesel V-Power | N4: 50 | P4: =IF($N4="","",IF($AA4<>"",IF($AB4="","",$N4*$AB4),IF($O4="","",$N4*$O4))) | S4: =IF(OR($G4="",$Q4="",COUNTIF($G$2:G3,$G4)=0),"",$Q4-LOOKUP(2,1/($G$2:G3=$G4),$Q$2:Q3)) | T4: =IF(OR($G4="",$R4="",COUNTIF($G$2:G3,$G4)=0),"",$R4-LOOKUP(2,1/($G$2:G3=$G4),$R$2:R3)) | U4: =IF(N4="","",IF(S4<>"",S4/N4,IF(T4<>"",T4/N4,""))) | W4: S-V | X4: 4175/S-V | Y4: OK | Z4: =IF($B4="","",IF($AA4<>"","Batán","Estación de servicio")) -> Estación de servicio
A5: =IF(B5="","","CARGA-"&TEXT(ROW()-1,"0000")) | C5: =IF(B5="","",CHOOSE(MONTH(B5),"Enero","Febrero","Marzo","Abril","Mayo","Junio","Julio","Agosto","Septiembre","Octubre","Noviembre","Diciembre")) | D5: =IF(B5="","",YEAR(B5)) | E5: =IF(B5="","",CHOOSE(WEEKDAY(B5,2),"Lunes","Martes","Miércoles","Jueves","Viernes","Sábado","Domingo")) | H5: =IF($G5="","",IFERROR(INDEX('MAESTRO DE UNIDADES'!$F$2:$F$208,MATCH($G5,'MAESTRO DE UNIDADES'!$A$2:$A$208,0)),"")) | I5: =IF($G5="","",IFERROR(INDEX('MAESTRO DE UNIDADES'!$B$2:$B$208,MATCH($G5,'MAESTRO DE UNIDADES'!$A$2:$A$208,0)),"")) | P5: =IF($N5="","",IF($AA5<>"",IF($AB5="","",$N5*$AB5),IF($O5="","",$N5*$O5))) | S5: =IF(OR($G5="",$Q5=""),"","") | T5: =IF(OR($G5="",$R5=""),"","") | U5: =IF(N5="","",IF(S5<>"",S5/N5,IF(T5<>"",T5/N5,""))) | Y5: =IF($B5="","",IF((IF($G5="","Sin unidad | ","")&IF($J5="","Sin responsable | ","")&IF($K5="","Sin obra | ","")&IF(AND($N5<>"",$G5<>"",$N5>IFERROR(INDEX('MAESTRO DE UNIDADES'!$I$2:$I$208,MATCH($G5,'MAESTRO DE UNIDADES'!$A$2:$A$208,0)),0)),"Litros > tanque | ","")&IF(AND($W5<>"",COUNTIF($W$2:$W5,$W5)>1),"Ticket duplicado | ","")&IF(AND($G5<>"",IFERROR(INDEX('MAESTRO DE UNIDADES'!$L$2:$L$208,MATCH($G5,'MAESTRO DE UNIDADES'!$A$2:$A$208,0)),"")="Inactivo"),"Unidad inactiva | ","")&IF(AND($AA5<>"",$N5=""),"Carga de batán sin litros | ","")&IF(AND($AA5<>"",$AC5<0),"Supera saldo batán | ",""))="","OK",LEFT((IF($G5="","Sin unidad | ","")&IF($J5="","Sin responsable | ","")&IF($K5="","Sin obra | ","")&IF(AND($N5<>"",$G5<>"",$N5>IFERROR(INDEX('MAESTRO DE UNIDADES'!$I$2:$I$208,MATCH($G5,'MAESTRO DE UNIDADES'!$A$2:$A$208,0)),0)),"Litros > tanque | ","")&IF(AND($W5<>"",COUNTIF($W$2:$W5,$W5)>1),"Ticket duplicado | ","")&IF(AND($G5<>"",IFERROR(INDEX('MAESTRO DE UNIDADES'!$L$2:$L$208,MATCH($G5,'MAESTRO DE UNIDADES'!$A$2:$A$208,0)),"")="Inactivo"),"Unidad inactiva | ","")&IF(AND($AA5<>"",$N5=""),"Carga de batán sin litros | ","")&IF(AND($AA5<>"",$AC5<0),"Supera saldo batán | ","")),LEN((IF($G5="","Sin unidad | ","")&IF($J5="","Sin responsable | ","")&IF($K5="","Sin obra | ","")&IF(AND($N5<>"",$G5<>"",$N5>IFERROR(INDEX('MAESTRO DE UNIDADES'!$I$2:$I$208,MATCH($G5,'MAESTRO DE UNIDADES'!$A$2:$A$208,0)),0)),"Litros > tanque | ","")&IF(AND($W5<>"",COUNTIF($W$2:$W5,$W5)>1),"Ticket duplicado | ","")&IF(AND($G5<>"",IFERROR(INDEX('MAESTRO DE UNIDADES'!$L$2:$L$208,MATCH($G5,'MAESTRO DE UNIDADES'!$A$2:$A$208,0)),"")="Inactivo"),"Unidad inactiva | ","")&IF(AND($AA5<>"",$N5=""),"Carga de batán sin litros | ","")&IF(AND($AA5<>"",$AC5<0),"Supera saldo batán | ","")))-3))) | Z5: =IF($B5="","",IF($AA5<>"","Batán","Estación de servicio"))
A6: =IF(B6="","","CARGA-"&TEXT(ROW()-1,"0000")) | C6: =IF(B6="","",CHOOSE(MONTH(B6),"Enero","Febrero","Marzo","Abril","Mayo","Junio","Julio","Agosto","Septiembre","Octubre","Noviembre","Diciembre")) | D6: =IF(B6="","",YEAR(B6)) | E6: =IF(B6="","",CHOOSE(WEEKDAY(B6,2),"Lunes","Martes","Miércoles","Jueves","Viernes","Sábado","Domingo")) | H6: =IF($G6="","",IFERROR(INDEX('MAESTRO DE UNIDADES'!$F$2:$F$208,MATCH($G6,'MAESTRO DE UNIDADES'!$A$2:$A$208,0)),"")) | I6: =IF($G6="","",IFERROR(INDEX('MAESTRO DE UNIDADES'!$B$2:$B$208,MATCH($G6,'MAESTRO DE UNIDADES'!$A$2:$A$208,0)),"")) | M6: =IF($G6="","",IFERROR(INDEX('MAESTRO DE UNIDADES'!$H$2:$H$208,MATCH($G6,'MAESTRO DE UNIDADES'!$A$2:$A$208,0)),"")) | P6: =IF($N6="","",IF($AA6<>"",IF($AB6="","",$N6*$AB6),IF($O6="","",$N6*$O6))) | S6: =IF(OR($G6="",$Q6="",COUNTIF($G$2:G5,$G6)=0),"",$Q6-LOOKUP(2,1/($G$2:G5=$G6),$Q$2:Q5)) | T6: =IF(OR($G6="",$R6="",COUNTIF($G$2:G5,$G6)=0),"",$R6-LOOKUP(2,1/($G$2:G5=$G6),$R$2:R5)) | U6: =IF(N6="","",IF(S6<>"",S6/N6,IF(T6<>"",T6/N6,""))) | Y6: =IF($B6="","",IF((IF($G6="","Sin unidad | ","")&IF($J6="","Sin responsable | ","")&IF($K6="","Sin obra | ","")&IF(AND($N6<>"",$G6<>"",$N6>IFERROR(INDEX('MAESTRO DE UNIDADES'!$I$2:$I$208,MATCH($G6,'MAESTRO DE UNIDADES'!$A$2:$A$208,0)),0)),"Litros > tanque | ","")&IF(AND($W6<>"",COUNTIF($W$2:$W6,$W6)>1),"Ticket duplicado | ","")&IF(AND($G6<>"",IFERROR(INDEX('MAESTRO DE UNIDADES'!$L$2:$L$208,MATCH($G6,'MAESTRO DE UNIDADES'!$A$2:$A$208,0)),"")="Inactivo"),"Unidad inactiva | ","")&IF(AND($AA6<>"",$N6=""),"Carga de batán sin litros | ","")&IF(AND($AA6<>"",$AC6<0),"Supera saldo batán | ",""))="","OK",LEFT((IF($G6="","Sin unidad | ","")&IF($J6="","Sin responsable | ","")&IF($K6="","Sin obra | ","")&IF(AND($N6<>"",$G6<>"",$N6>IFERROR(INDEX('MAESTRO DE UNIDADES'!$I$2:$I$208,MATCH($G6,'MAESTRO DE UNIDADES'!$A$2:$A$208,0)),0)),"Litros > tanque | ","")&IF(AND($W6<>"",COUNTIF($W$2:$W6,$W6)>1),"Ticket duplicado | ","")&IF(AND($G6<>"",IFERROR(INDEX('MAESTRO DE UNIDADES'!$L$2:$L$208,MATCH($G6,'MAESTRO DE UNIDADES'!$A$2:$A$208,0)),"")="Inactivo"),"Unidad inactiva | ","")&IF(AND($AA6<>"",$N6=""),"Carga de batán sin litros | ","")&IF(AND($AA6<>"",$AC6<0),"Supera saldo batán | ","")),LEN((IF($G6="","Sin unidad | ","")&IF($J6="","Sin responsable | ","")&IF($K6="","Sin obra | ","")&IF(AND($N6<>"",$G6<>"",$N6>IFERROR(INDEX('MAESTRO DE UNIDADES'!$I$2:$I$208,MATCH($G6,'MAESTRO DE UNIDADES'!$A$2:$A$208,0)),0)),"Litros > tanque | ","")&IF(AND($W6<>"",COUNTIF($W$2:$W6,$W6)>1),"Ticket duplicado | ","")&IF(AND($G6<>"",IFERROR(INDEX('MAESTRO DE UNIDADES'!$L$2:$L$208,MATCH($G6,'MAESTRO DE UNIDADES'!$A$2:$A$208,0)),"")="Inactivo"),"Unidad inactiva | ","")&IF(AND($AA6<>"",$N6=""),"Carga de batán sin litros | ","")&IF(AND($AA6<>"",$AC6<0),"Supera saldo batán | ","")))-3))) | Z6: =IF($B6="","",IF($AA6<>"","Batán","Estación de servicio"))
A7: =IF(B7="","","CARGA-"&TEXT(ROW()-1,"0000")) | C7: =IF(B7="","",CHOOSE(MONTH(B7),"Enero","Febrero","Marzo","Abril","Mayo","Junio","Julio","Agosto","Septiembre","Octubre","Noviembre","Diciembre")) | D7: =IF(B7="","",YEAR(B7)) | E7: =IF(B7="","",CHOOSE(WEEKDAY(B7,2),"Lunes","Martes","Miércoles","Jueves","Viernes","Sábado","Domingo")) | H7: =IF($G7="","",IFERROR(INDEX('MAESTRO DE UNIDADES'!$F$2:$F$208,MATCH($G7,'MAESTRO DE UNIDADES'!$A$2:$A$208,0)),"")) | I7: =IF($G7="","",IFERROR(INDEX('MAESTRO DE UNIDADES'!$B$2:$B$208,MATCH($G7,'MAESTRO DE UNIDADES'!$A$2:$A$208,0)),"")) | M7: =IF($G7="","",IFERROR(INDEX('MAESTRO DE UNIDADES'!$H$2:$H$208,MATCH($G7,'MAESTRO DE UNIDADES'!$A$2:$A$208,0)),"")) | P7: =IF($N7="","",IF($AA7<>"",IF($AB7="","",$N7*$AB7),IF($O7="","",$N7*$O7))) | S7: =IF(OR($G7="",$Q7="",COUNTIF($G$2:G6,$G7)=0),"",$Q7-LOOKUP(2,1/($G$2:G6=$G7),$Q$2:Q6)) | T7: =IF(OR($G7="",$R7="",COUNTIF($G$2:G6,$G7)=0),"",$R7-LOOKUP(2,1/($G$2:G6=$G7),$R$2:R6)) | U7: =IF(N7="","",IF(S7<>"",S7/N7,IF(T7<>"",T7/N7,""))) | Y7: =IF($B7="","",IF((IF($G7="","Sin unidad | ","")&IF($J7="","Sin responsable | ","")&IF($K7="","Sin obra | ","")&IF(AND($N7<>"",$G7<>"",$N7>IFERROR(INDEX('MAESTRO DE UNIDADES'!$I$2:$I$208,MATCH($G7,'MAESTRO DE UNIDADES'!$A$2:$A$208,0)),0)),"Litros > tanque | ","")&IF(AND($W7<>"",COUNTIF($W$2:$W7,$W7)>1),"Ticket duplicado | ","")&IF(AND($G7<>"",IFERROR(INDEX('MAESTRO DE UNIDADES'!$L$2:$L$208,MATCH($G7,'MAESTRO DE UNIDADES'!$A$2:$A$208,0)),"")="Inactivo"),"Unidad inactiva | ","")&IF(AND($AA7<>"",$N7=""),"Carga de batán sin litros | ","")&IF(AND($AA7<>"",$AC7<0),"Supera saldo batán | ",""))="","OK",LEFT((IF($G7="","Sin unidad | ","")&IF($J7="","Sin responsable | ","")&IF($K7="","Sin obra | ","")&IF(AND($N7<>"",$G7<>"",$N7>IFERROR(INDEX('MAESTRO DE UNIDADES'!$I$2:$I$208,MATCH($G7,'MAESTRO DE UNIDADES'!$A$2:$A$208,0)),0)),"Litros > tanque | ","")&IF(AND($W7<>"",COUNTIF($W$2:$W7,$W7)>1),"Ticket duplicado | ","")&IF(AND($G7<>"",IFERROR(INDEX('MAESTRO DE UNIDADES'!$L$2:$L$208,MATCH($G7,'MAESTRO DE UNIDADES'!$A$2:$A$208,0)),"")="Inactivo"),"Unidad inactiva | ","")&IF(AND($AA7<>"",$N7=""),"Carga de batán sin litros | ","")&IF(AND($AA7<>"",$AC7<0),"Supera saldo batán | ","")),LEN((IF($G7="","Sin unidad | ","")&IF($J7="","Sin responsable | ","")&IF($K7="","Sin obra | ","")&IF(AND($N7<>"",$G7<>"",$N7>IFERROR(INDEX('MAESTRO DE UNIDADES'!$I$2:$I$208,MATCH($G7,'MAESTRO DE UNIDADES'!$A$2:$A$208,0)),0)),"Litros > tanque | ","")&IF(AND($W7<>"",COUNTIF($W$2:$W7,$W7)>1),"Ticket duplicado | ","")&IF(AND($G7<>"",IFERROR(INDEX('MAESTRO DE UNIDADES'!$L$2:$L$208,MATCH($G7,'MAESTRO DE UNIDADES'!$A$2:$A$208,0)),"")="Inactivo"),"Unidad inactiva | ","")&IF(AND($AA7<>"",$N7=""),"Carga de batán sin litros | ","")&IF(AND($AA7<>"",$AC7<0),"Supera saldo batán | ","")))-3))) | Z7: =IF($B7="","",IF($AA7<>"","Batán","Estación de servicio"))
A8: =IF(B8="","","CARGA-"&TEXT(ROW()-1,"0000")) | C8: =IF(B8="","",CHOOSE(MONTH(B8),"Enero","Febrero","Marzo","Abril","Mayo","Junio","Julio","Agosto","Septiembre","Octubre","Noviembre","Diciembre")) | D8: =IF(B8="","",YEAR(B8)) | E8: =IF(B8="","",CHOOSE(WEEKDAY(B8,2),"Lunes","Martes","Miércoles","Jueves","Viernes","Sábado","Domingo")) | H8: =IF($G8="","",IFERROR(INDEX('MAESTRO DE UNIDADES'!$F$2:$F$208,MATCH($G8,'MAESTRO DE UNIDADES'!$A$2:$A$208,0)),"")) | I8: =IF($G8="","",IFERROR(INDEX('MAESTRO DE UNIDADES'!$B$2:$B$208,MATCH($G8,'MAESTRO DE UNIDADES'!$A$2:$A$208,0)),"")) | M8: =IF($G8="","",IFERROR(INDEX('MAESTRO DE UNIDADES'!$H$2:$H$208,MATCH($G8,'MAESTRO DE UNIDADES'!$A$2:$A$208,0)),"")) | P8: =IF($N8="","",IF($AA8<>"",IF($AB8="","",$N8*$AB8),IF($O8="","",$N8*$O8))) | S8: =IF(OR($G8="",$Q8="",COUNTIF($G$2:G7,$G8)=0),"",$Q8-LOOKUP(2,1/($G$2:G7=$G8),$Q$2:Q7)) | T8: =IF(OR($G8="",$R8="",COUNTIF($G$2:G7,$G8)=0),"",$R8-LOOKUP(2,1/($G$2:G7=$G8),$R$2:R7)) | U8: =IF(N8="","",IF(S8<>"",S8/N8,IF(T8<>"",T8/N8,""))) | Y8: =IF($B8="","",IF((IF($G8="","Sin unidad | ","")&IF($J8="","Sin responsable | ","")&IF($K8="","Sin obra | ","")&IF(AND($N8<>"",$G8<>"",$N8>IFERROR(INDEX('MAESTRO DE UNIDADES'!$I$2:$I$208,MATCH($G8,'MAESTRO DE UNIDADES'!$A$2:$A$208,0)),0)),"Litros > tanque | ","")&IF(AND($W8<>"",COUNTIF($W$2:$W8,$W8)>1),"Ticket duplicado | ","")&IF(AND($G8<>"",IFERROR(INDEX('MAESTRO DE UNIDADES'!$L$2:$L$208,MATCH($G8,'MAESTRO DE UNIDADES'!$A$2:$A$208,0)),"")="Inactivo"),"Unidad inactiva | ","")&IF(AND($AA8<>"",$N8=""),"Carga de batán sin litros | ","")&IF(AND($AA8<>"",$AC8<0),"Supera saldo batán | ",""))="","OK",LEFT((IF($G8="","Sin unidad | ","")&IF($J8="","Sin responsable | ","")&IF($K8="","Sin obra | ","")&IF(AND($N8<>"",$G8<>"",$N8>IFERROR(INDEX('MAESTRO DE UNIDADES'!$I$2:$I$208,MATCH($G8,'MAESTRO DE UNIDADES'!$A$2:$A$208,0)),0)),"Litros > tanque | ","")&IF(AND($W8<>"",COUNTIF($W$2:$W8,$W8)>1),"Ticket duplicado | ","")&IF(AND($G8<>"",IFERROR(INDEX('MAESTRO DE UNIDADES'!$L$2:$L$208,MATCH($G8,'MAESTRO DE UNIDADES'!$A$2:$A$208,0)),"")="Inactivo"),"Unidad inactiva | ","")&IF(AND($AA8<>"",$N8=""),"Carga de batán sin litros | ","")&IF(AND($AA8<>"",$AC8<0),"Supera saldo batán | ","")),LEN((IF($G8="","Sin unidad | ","")&IF($J8="","Sin responsable | ","")&IF($K8="","Sin obra | ","")&IF(AND($N8<>"",$G8<>"",$N8>IFERROR(INDEX('MAESTRO DE UNIDADES'!$I$2:$I$208,MATCH($G8,'MAESTRO DE UNIDADES'!$A$2:$A$208,0)),0)),"Litros > tanque | ","")&IF(AND($W8<>"",COUNTIF($W$2:$W8,$W8)>1),"Ticket duplicado | ","")&IF(AND($G8<>"",IFERROR(INDEX('MAESTRO DE UNIDADES'!$L$2:$L$208,MATCH($G8,'MAESTRO DE UNIDADES'!$A$2:$A$208,0)),"")="Inactivo"),"Unidad inactiva | ","")&IF(AND($AA8<>"",$N8=""),"Carga de batán sin litros | ","")&IF(AND($AA8<>"",$AC8<0),"Supera saldo batán | ","")))-3))) | Z8: =IF($B8="","",IF($AA8<>"","Batán","Estación de servicio"))
A9: =IF(B9="","","CARGA-"&TEXT(ROW()-1,"0000")) | C9: =IF(B9="","",CHOOSE(MONTH(B9),"Enero","Febrero","Marzo","Abril","Mayo","Junio","Julio","Agosto","Septiembre","Octubre","Noviembre","Diciembre")) | D9: =IF(B9="","",YEAR(B9)) | E9: =IF(B9="","",CHOOSE(WEEKDAY(B9,2),"Lunes","Martes","Miércoles","Jueves","Viernes","Sábado","Domingo")) | H9: =IF($G9="","",IFERROR(INDEX('MAESTRO DE UNIDADES'!$F$2:$F$208,MATCH($G9,'MAESTRO DE UNIDADES'!$A$2:$A$208,0)),"")) | I9: =IF($G9="","",IFERROR(INDEX('MAESTRO DE UNIDADES'!$B$2:$B$208,MATCH($G9,'MAESTRO DE UNIDADES'!$A$2:$A$208,0)),"")) | M9: =IF($G9="","",IFERROR(INDEX('MAESTRO DE UNIDADES'!$H$2:$H$208,MATCH($G9,'MAESTRO DE UNIDADES'!$A$2:$A$208,0)),"")) | P9: =IF($N9="","",IF($AA9<>"",IF($AB9="","",$N9*$AB9),IF($O9="","",$N9*$O9))) | S9: =IF(OR($G9="",$Q9="",COUNTIF($G$2:G8,$G9)=0),"",$Q9-LOOKUP(2,1/($G$2:G8=$G9),$Q$2:Q8)) | T9: =IF(OR($G9="",$R9="",COUNTIF($G$2:G8,$G9)=0),"",$R9-LOOKUP(2,1/($G$2:G8=$G9),$R$2:R8)) | U9: =IF(N9="","",IF(S9<>"",S9/N9,IF(T9<>"",T9/N9,""))) | Y9: =IF($B9="","",IF((IF($G9="","Sin unidad | ","")&IF($J9="","Sin responsable | ","")&IF($K9="","Sin obra | ","")&IF(AND($N9<>"",$G9<>"",$N9>IFERROR(INDEX('MAESTRO DE UNIDADES'!$I$2:$I$208,MATCH($G9,'MAESTRO DE UNIDADES'!$A$2:$A$208,0)),0)),"Litros > tanque | ","")&IF(AND($W9<>"",COUNTIF($W$2:$W9,$W9)>1),"Ticket duplicado | ","")&IF(AND($G9<>"",IFERROR(INDEX('MAESTRO DE UNIDADES'!$L$2:$L$208,MATCH($G9,'MAESTRO DE UNIDADES'!$A$2:$A$208,0)),"")="Inactivo"),"Unidad inactiva | ","")&IF(AND($AA9<>"",$N9=""),"Carga de batán sin litros | ","")&IF(AND($AA9<>"",$AC9<0),"Supera saldo batán | ",""))="","OK",LEFT((IF($G9="","Sin unidad | ","")&IF($J9="","Sin responsable | ","")&IF($K9="","Sin obra | ","")&IF(AND($N9<>"",$G9<>"",$N9>IFERROR(INDEX('MAESTRO DE UNIDADES'!$I$2:$I$208,MATCH($G9,'MAESTRO DE UNIDADES'!$A$2:$A$208,0)),0)),"Litros > tanque | ","")&IF(AND($W9<>"",COUNTIF($W$2:$W9,$W9)>1),"Ticket duplicado | ","")&IF(AND($G9<>"",IFERROR(INDEX('MAESTRO DE UNIDADES'!$L$2:$L$208,MATCH($G9,'MAESTRO DE UNIDADES'!$A$2:$A$208,0)),"")="Inactivo"),"Unidad inactiva | ","")&IF(AND($AA9<>"",$N9=""),"Carga de batán sin litros | ","")&IF(AND($AA9<>"",$AC9<0),"Supera saldo batán | ","")),LEN((IF($G9="","Sin unidad | ","")&IF($J9="","Sin responsable | ","")&IF($K9="","Sin obra | ","")&IF(AND($N9<>"",$G9<>"",$N9>IFERROR(INDEX('MAESTRO DE UNIDADES'!$I$2:$I$208,MATCH($G9,'MAESTRO DE UNIDADES'!$A$2:$A$208,0)),0)),"Litros > tanque | ","")&IF(AND($W9<>"",COUNTIF($W$2:$W9,$W9)>1),"Ticket duplicado | ","")&IF(AND($G9<>"",IFERROR(INDEX('MAESTRO DE UNIDADES'!$L$2:$L$208,MATCH($G9,'MAESTRO DE UNIDADES'!$A$2:$A$208,0)),"")="Inactivo"),"Unidad inactiva | ","")&IF(AND($AA9<>"",$N9=""),"Carga de batán sin litros | ","")&IF(AND($AA9<>"",$AC9<0),"Supera saldo batán | ","")))-3))) | Z9: =IF($B9="","",IF($AA9<>"","Batán","Estación de servicio"))
A10: =IF(B10="","","CARGA-"&TEXT(ROW()-1,"0000")) | C10: =IF(B10="","",CHOOSE(MONTH(B10),"Enero","Febrero","Marzo","Abril","Mayo","Junio","Julio","Agosto","Septiembre","Octubre","Noviembre","Diciembre")) | D10: =IF(B10="","",YEAR(B10)) | E10: =IF(B10="","",CHOOSE(WEEKDAY(B10,2),"Lunes","Martes","Miércoles","Jueves","Viernes","Sábado","Domingo")) | H10: =IF($G10="","",IFERROR(INDEX('MAESTRO DE UNIDADES'!$F$2:$F$208,MATCH($G10,'MAESTRO DE UNIDADES'!$A$2:$A$208,0)),"")) | I10: =IF($G10="","",IFERROR(INDEX('MAESTRO DE UNIDADES'!$B$2:$B$208,MATCH($G10,'MAESTRO DE UNIDADES'!$A$2:$A$208,0)),"")) | M10: =IF($G10="","",IFERROR(INDEX('MAESTRO DE UNIDADES'!$H$2:$H$208,MATCH($G10,'MAESTRO DE UNIDADES'!$A$2:$A$208,0)),"")) | P10: =IF($N10="","",IF($AA10<>"",IF($AB10="","",$N10*$AB10),IF($O10="","",$N10*$O10))) | S10: =IF(OR($G10="",$Q10="",COUNTIF($G$2:G9,$G10)=0),"",$Q10-LOOKUP(2,1/($G$2:G9=$G10),$Q$2:Q9)) | T10: =IF(OR($G10="",$R10="",COUNTIF($G$2:G9,$G10)=0),"",$R10-LOOKUP(2,1/($G$2:G9=$G10),$R$2:R9)) | U10: =IF(N10="","",IF(S10<>"",S10/N10,IF(T10<>"",T10/N10,""))) | Y10: =IF($B10="","",IF((IF($G10="","Sin unidad | ","")&IF($J10="","Sin responsable | ","")&IF($K10="","Sin obra | ","")&IF(AND($N10<>"",$G10<>"",$N10>IFERROR(INDEX('MAESTRO DE UNIDADES'!$I$2:$I$208,MATCH($G10,'MAESTRO DE UNIDADES'!$A$2:$A$208,0)),0)),"Litros > tanque | ","")&IF(AND($W10<>"",COUNTIF($W$2:$W10,$W10)>1),"Ticket duplicado | ","")&IF(AND($G10<>"",IFERROR(INDEX('MAESTRO DE UNIDADES'!$L$2:$L$208,MATCH($G10,'MAESTRO DE UNIDADES'!$A$2:$A$208,0)),"")="Inactivo"),"Unidad inactiva | ","")&IF(AND($AA10<>"",$N10=""),"Carga de batán sin litros | ","")&IF(AND($AA10<>"",$AC10<0),"Supera saldo batán | ",""))="","OK",LEFT((IF($G10="","Sin unidad | ","")&IF($J10="","Sin responsable | ","")&IF($K10="","Sin obra | ","")&IF(AND($N10<>"",$G10<>"",$N10>IFERROR(INDEX('MAESTRO DE UNIDADES'!$I$2:$I$208,MATCH($G10,'MAESTRO DE UNIDADES'!$A$2:$A$208,0)),0)),"Litros > tanque | ","")&IF(AND($W10<>"",COUNTIF($W$2:$W10,$W10)>1),"Ticket duplicado | ","")&IF(AND($G10<>"",IFERROR(INDEX('MAESTRO DE UNIDADES'!$L$2:$L$208,MATCH($G10,'MAESTRO DE UNIDADES'!$A$2:$A$208,0)),"")="Inactivo"),"Unidad inactiva | ","")&IF(AND($AA10<>"",$N10=""),"Carga de batán sin litros | ","")&IF(AND($AA10<>"",$AC10<0),"Supera saldo batán | ","")),LEN((IF($G10="","Sin unidad | ","")&IF($J10="","Sin responsable | ","")&IF($K10="","Sin obra | ","")&IF(AND($N10<>"",$G10<>"",$N10>IFERROR(INDEX('MAESTRO DE UNIDADES'!$I$2:$I$208,MATCH($G10,'MAESTRO DE UNIDADES'!$A$2:$A$208,0)),0)),"Litros > tanque | ","")&IF(AND($W10<>"",COUNTIF($W$2:$W10,$W10)>1),"Ticket duplicado | ","")&IF(AND($G10<>"",IFERROR(INDEX('MAESTRO DE UNIDADES'!$L$2:$L$208,MATCH($G10,'MAESTRO DE UNIDADES'!$A$2:$A$208,0)),"")="Inactivo"),"Unidad inactiva | ","")&IF(AND($AA10<>"",$N10=""),"Carga de batán sin litros | ","")&IF(AND($AA10<>"",$AC10<0),"Supera saldo batán | ","")))-3))) | Z10: =IF($B10="","",IF($AA10<>"","Batán","Estación de servicio"))
A11: =IF(B11="","","CARGA-"&TEXT(ROW()-1,"0000")) | C11: =IF(B11="","",CHOOSE(MONTH(B11),"Enero","Febrero","Marzo","Abril","Mayo","Junio","Julio","Agosto","Septiembre","Octubre","Noviembre","Diciembre")) | D11: =IF(B11="","",YEAR(B11)) | E11: =IF(B11="","",CHOOSE(WEEKDAY(B11,2),"Lunes","Martes","Miércoles","Jueves","Viernes","Sábado","Domingo")) | H11: =IF($G11="","",IFERROR(INDEX('MAESTRO DE UNIDADES'!$F$2:$F$208,MATCH($G11,'MAESTRO DE UNIDADES'!$A$2:$A$208,0)),"")) | I11: =IF($G11="","",IFERROR(INDEX('MAESTRO DE UNIDADES'!$B$2:$B$208,MATCH($G11,'MAESTRO DE UNIDADES'!$A$2:$A$208,0)),"")) | M11: =IF($G11="","",IFERROR(INDEX('MAESTRO DE UNIDADES'!$H$2:$H$208,MATCH($G11,'MAESTRO DE UNIDADES'!$A$2:$A$208,0)),"")) | P11: =IF($N11="","",IF($AA11<>"",IF($AB11="","",$N11*$AB11),IF($O11="","",$N11*$O11))) | S11: =IF(OR($G11="",$Q11="",COUNTIF($G$2:G10,$G11)=0),"",$Q11-LOOKUP(2,1/($G$2:G10=$G11),$Q$2:Q10)) | T11: =IF(OR($G11="",$R11="",COUNTIF($G$2:G10,$G11)=0),"",$R11-LOOKUP(2,1/($G$2:G10=$G11),$R$2:R10)) | U11: =IF(N11="","",IF(S11<>"",S11/N11,IF(T11<>"",T11/N11,""))) | Y11: =IF($B11="","",IF((IF($G11="","Sin unidad | ","")&IF($J11="","Sin responsable | ","")&IF($K11="","Sin obra | ","")&IF(AND($N11<>"",$G11<>"",$N11>IFERROR(INDEX('MAESTRO DE UNIDADES'!$I$2:$I$208,MATCH($G11,'MAESTRO DE UNIDADES'!$A$2:$A$208,0)),0)),"Litros > tanque | ","")&IF(AND($W11<>"",COUNTIF($W$2:$W11,$W11)>1),"Ticket duplicado | ","")&IF(AND($G11<>"",IFERROR(INDEX('MAESTRO DE UNIDADES'!$L$2:$L$208,MATCH($G11,'MAESTRO DE UNIDADES'!$A$2:$A$208,0)),"")="Inactivo"),"Unidad inactiva | ","")&IF(AND($AA11<>"",$N11=""),"Carga de batán sin litros | ","")&IF(AND($AA11<>"",$AC11<0),"Supera saldo batán | ",""))="","OK",LEFT((IF($G11="","Sin unidad | ","")&IF($J11="","Sin responsable | ","")&IF($K11="","Sin obra | ","")&IF(AND($N11<>"",$G11<>"",$N11>IFERROR(INDEX('MAESTRO DE UNIDADES'!$I$2:$I$208,MATCH($G11,'MAESTRO DE UNIDADES'!$A$2:$A$208,0)),0)),"Litros > tanque | ","")&IF(AND($W11<>"",COUNTIF($W$2:$W11,$W11)>1),"Ticket duplicado | ","")&IF(AND($G11<>"",IFERROR(INDEX('MAESTRO DE UNIDADES'!$L$2:$L$208,MATCH($G11,'MAESTRO DE UNIDADES'!$A$2:$A$208,0)),"")="Inactivo"),"Unidad inactiva | ","")&IF(AND($AA11<>"",$N11=""),"Carga de batán sin litros | ","")&IF(AND($AA11<>"",$AC11<0),"Supera saldo batán | ","")),LEN((IF($G11="","Sin unidad | ","")&IF($J11="","Sin responsable | ","")&IF($K11="","Sin obra | ","")&IF(AND($N11<>"",$G11<>"",$N11>IFERROR(INDEX('MAESTRO DE UNIDADES'!$I$2:$I$208,MATCH($G11,'MAESTRO DE UNIDADES'!$A$2:$A$208,0)),0)),"Litros > tanque | ","")&IF(AND($W11<>"",COUNTIF($W$2:$W11,$W11)>1),"Ticket duplicado | ","")&IF(AND($G11<>"",IFERROR(INDEX('MAESTRO DE UNIDADES'!$L$2:$L$208,MATCH($G11,'MAESTRO DE UNIDADES'!$A$2:$A$208,0)),"")="Inactivo"),"Unidad inactiva | ","")&IF(AND($AA11<>"",$N11=""),"Carga de batán sin litros | ","")&IF(AND($AA11<>"",$AC11<0),"Supera saldo batán | ","")))-3))) | Z11: =IF($B11="","",IF($AA11<>"","Batán","Estación de servicio"))
A12: =IF(B12="","","CARGA-"&TEXT(ROW()-1,"0000")) | C12: =IF(B12="","",CHOOSE(MONTH(B12),"Enero","Febrero","Marzo","Abril","Mayo","Junio","Julio","Agosto","Septiembre","Octubre","Noviembre","Diciembre")) | D12: =IF(B12="","",YEAR(B12)) | E12: =IF(B12="","",CHOOSE(WEEKDAY(B12,2),"Lunes","Martes","Miércoles","Jueves","Viernes","Sábado","Domingo")) | H12: =IF($G12="","",IFERROR(INDEX('MAESTRO DE UNIDADES'!$F$2:$F$208,MATCH($G12,'MAESTRO DE UNIDADES'!$A$2:$A$208,0)),"")) | I12: =IF($G12="","",IFERROR(INDEX('MAESTRO DE UNIDADES'!$B$2:$B$208,MATCH($G12,'MAESTRO DE UNIDADES'!$A$2:$A$208,0)),"")) | M12: =IF($G12="","",IFERROR(INDEX('MAESTRO DE UNIDADES'!$H$2:$H$208,MATCH($G12,'MAESTRO DE UNIDADES'!$A$2:$A$208,0)),"")) | P12: =IF($N12="","",IF($AA12<>"",IF($AB12="","",$N12*$AB12),IF($O12="","",$N12*$O12))) | S12: =IF(OR($G12="",$Q12="",COUNTIF($G$2:G11,$G12)=0),"",$Q12-LOOKUP(2,1/($G$2:G11=$G12),$Q$2:Q11)) | T12: =IF(OR($G12="",$R12="",COUNTIF($G$2:G11,$G12)=0),"",$R12-LOOKUP(2,1/($G$2:G11=$G12),$R$2:R11)) | U12: =IF(N12="","",IF(S12<>"",S12/N12,IF(T12<>"",T12/N12,""))) | Y12: =IF($B12="","",IF((IF($G12="","Sin unidad | ","")&IF($J12="","Sin responsable | ","")&IF($K12="","Sin obra | ","")&IF(AND($N12<>"",$G12<>"",$N12>IFERROR(INDEX('MAESTRO DE UNIDADES'!$I$2:$I$208,MATCH($G12,'MAESTRO DE UNIDADES'!$A$2:$A$208,0)),0)),"Litros > tanque | ","")&IF(AND($W12<>"",COUNTIF($W$2:$W12,$W12)>1),"Ticket duplicado | ","")&IF(AND($G12<>"",IFERROR(INDEX('MAESTRO DE UNIDADES'!$L$2:$L$208,MATCH($G12,'MAESTRO DE UNIDADES'!$A$2:$A$208,0)),"")="Inactivo"),"Unidad inactiva | ","")&IF(AND($AA12<>"",$N12=""),"Carga de batán sin litros | ","")&IF(AND($AA12<>"",$AC12<0),"Supera saldo batán | ",""))="","OK",LEFT((IF($G12="","Sin unidad | ","")&IF($J12="","Sin responsable | ","")&IF($K12="","Sin obra | ","")&IF(AND($N12<>"",$G12<>"",$N12>IFERROR(INDEX('MAESTRO DE UNIDADES'!$I$2:$I$208,MATCH($G12,'MAESTRO DE UNIDADES'!$A$2:$A$208,0)),0)),"Litros > tanque | ","")&IF(AND($W12<>"",COUNTIF($W$2:$W12,$W12)>1),"Ticket duplicado | ","")&IF(AND($G12<>"",IFERROR(INDEX('MAESTRO DE UNIDADES'!$L$2:$L$208,MATCH($G12,'MAESTRO DE UNIDADES'!$A$2:$A$208,0)),"")="Inactivo"),"Unidad inactiva | ","")&IF(AND($AA12<>"",$N12=""),"Carga de batán sin litros | ","")&IF(AND($AA12<>"",$AC12<0),"Supera saldo batán | ","")),LEN((IF($G12="","Sin unidad | ","")&IF($J12="","Sin responsable | ","")&IF($K12="","Sin obra | ","")&IF(AND($N12<>"",$G12<>"",$N12>IFERROR(INDEX('MAESTRO DE UNIDADES'!$I$2:$I$208,MATCH($G12,'MAESTRO DE UNIDADES'!$A$2:$A$208,0)),0)),"Litros > tanque | ","")&IF(AND($W12<>"",COUNTIF($W$2:$W12,$W12)>1),"Ticket duplicado | ","")&IF(AND($G12<>"",IFERROR(INDEX('MAESTRO DE UNIDADES'!$L$2:$L$208,MATCH($G12,'MAESTRO DE UNIDADES'!$A$2:$A$208,0)),"")="Inactivo"),"Unidad inactiva | ","")&IF(AND($AA12<>"",$N12=""),"Carga de batán sin litros | ","")&IF(AND($AA12<>"",$AC12<0),"Supera saldo batán | ","")))-3))) | Z12: =IF($B12="","",IF($AA12<>"","Batán","Estación de servicio"))
A13: =IF(B13="","","CARGA-"&TEXT(ROW()-1,"0000")) | C13: =IF(B13="","",CHOOSE(MONTH(B13),"Enero","Febrero","Marzo","Abril","Mayo","Junio","Julio","Agosto","Septiembre","Octubre","Noviembre","Diciembre")) | D13: =IF(B13="","",YEAR(B13)) | E13: =IF(B13="","",CHOOSE(WEEKDAY(B13,2),"Lunes","Martes","Miércoles","Jueves","Viernes","Sábado","Domingo")) | H13: =IF($G13="","",IFERROR(INDEX('MAESTRO DE UNIDADES'!$F$2:$F$208,MATCH($G13,'MAESTRO DE UNIDADES'!$A$2:$A$208,0)),"")) | I13: =IF($G13="","",IFERROR(INDEX('MAESTRO DE UNIDADES'!$B$2:$B$208,MATCH($G13,'MAESTRO DE UNIDADES'!$A$2:$A$208,0)),"")) | M13: =IF($G13="","",IFERROR(INDEX('MAESTRO DE UNIDADES'!$H$2:$H$208,MATCH($G13,'MAESTRO DE UNIDADES'!$A$2:$A$208,0)),"")) | P13: =IF($N13="","",IF($AA13<>"",IF($AB13="","",$N13*$AB13),IF($O13="","",$N13*$O13))) | S13: =IF(OR($G13="",$Q13="",COUNTIF($G$2:G12,$G13)=0),"",$Q13-LOOKUP(2,1/($G$2:G12=$G13),$Q$2:Q12)) | T13: =IF(OR($G13="",$R13="",COUNTIF($G$2:G12,$G13)=0),"",$R13-LOOKUP(2,1/($G$2:G12=$G13),$R$2:R12)) | U13: =IF(N13="","",IF(S13<>"",S13/N13,IF(T13<>"",T13/N13,""))) | Y13: =IF($B13="","",IF((IF($G13="","Sin unidad | ","")&IF($J13="","Sin responsable | ","")&IF($K13="","Sin obra | ","")&IF(AND($N13<>"",$G13<>"",$N13>IFERROR(INDEX('MAESTRO DE UNIDADES'!$I$2:$I$208,MATCH($G13,'MAESTRO DE UNIDADES'!$A$2:$A$208,0)),0)),"Litros > tanque | ","")&IF(AND($W13<>"",COUNTIF($W$2:$W13,$W13)>1),"Ticket duplicado | ","")&IF(AND($G13<>"",IFERROR(INDEX('MAESTRO DE UNIDADES'!$L$2:$L$208,MATCH($G13,'MAESTRO DE UNIDADES'!$A$2:$A$208,0)),"")="Inactivo"),"Unidad inactiva | ","")&IF(AND($AA13<>"",$N13=""),"Carga de batán sin litros | ","")&IF(AND($AA13<>"",$AC13<0),"Supera saldo batán | ",""))="","OK",LEFT((IF($G13="","Sin unidad | ","")&IF($J13="","Sin responsable | ","")&IF($K13="","Sin obra | ","")&IF(AND($N13<>"",$G13<>"",$N13>IFERROR(INDEX('MAESTRO DE UNIDADES'!$I$2:$I$208,MATCH($G13,'MAESTRO DE UNIDADES'!$A$2:$A$208,0)),0)),"Litros > tanque | ","")&IF(AND($W13<>"",COUNTIF($W$2:$W13,$W13)>1),"Ticket duplicado | ","")&IF(AND($G13<>"",IFERROR(INDEX('MAESTRO DE UNIDADES'!$L$2:$L$208,MATCH($G13,'MAESTRO DE UNIDADES'!$A$2:$A$208,0)),"")="Inactivo"),"Unidad inactiva | ","")&IF(AND($AA13<>"",$N13=""),"Carga de batán sin litros | ","")&IF(AND($AA13<>"",$AC13<0),"Supera saldo batán | ","")),LEN((IF($G13="","Sin unidad | ","")&IF($J13="","Sin responsable | ","")&IF($K13="","Sin obra | ","")&IF(AND($N13<>"",$G13<>"",$N13>IFERROR(INDEX('MAESTRO DE UNIDADES'!$I$2:$I$208,MATCH($G13,'MAESTRO DE UNIDADES'!$A$2:$A$208,0)),0)),"Litros > tanque | ","")&IF(AND($W13<>"",COUNTIF($W$2:$W13,$W13)>1),"Ticket duplicado | ","")&IF(AND($G13<>"",IFERROR(INDEX('MAESTRO DE UNIDADES'!$L$2:$L$208,MATCH($G13,'MAESTRO DE UNIDADES'!$A$2:$A$208,0)),"")="Inactivo"),"Unidad inactiva | ","")&IF(AND($AA13<>"",$N13=""),"Carga de batán sin litros | ","")&IF(AND($AA13<>"",$AC13<0),"Supera saldo batán | ","")))-3))) | Z13: =IF($B13="","",IF($AA13<>"","Batán","Estación de servicio"))
A14: =IF(B14="","","CARGA-"&TEXT(ROW()-1,"0000")) | C14: =IF(B14="","",CHOOSE(MONTH(B14),"Enero","Febrero","Marzo","Abril","Mayo","Junio","Julio","Agosto","Septiembre","Octubre","Noviembre","Diciembre")) | D14: =IF(B14="","",YEAR(B14)) | E14: =IF(B14="","",CHOOSE(WEEKDAY(B14,2),"Lunes","Martes","Miércoles","Jueves","Viernes","Sábado","Domingo")) | H14: =IF($G14="","",IFERROR(INDEX('MAESTRO DE UNIDADES'!$F$2:$F$208,MATCH($G14,'MAESTRO DE UNIDADES'!$A$2:$A$208,0)),"")) | I14: =IF($G14="","",IFERROR(INDEX('MAESTRO DE UNIDADES'!$B$2:$B$208,MATCH($G14,'MAESTRO DE UNIDADES'!$A$2:$A$208,0)),"")) | M14: =IF($G14="","",IFERROR(INDEX('MAESTRO DE UNIDADES'!$H$2:$H$208,MATCH($G14,'MAESTRO DE UNIDADES'!$A$2:$A$208,0)),"")) | P14: =IF($N14="","",IF($AA14<>"",IF($AB14="","",$N14*$AB14),IF($O14="","",$N14*$O14))) | S14: =IF(OR($G14="",$Q14="",COUNTIF($G$2:G13,$G14)=0),"",$Q14-LOOKUP(2,1/($G$2:G13=$G14),$Q$2:Q13)) | T14: =IF(OR($G14="",$R14="",COUNTIF($G$2:G13,$G14)=0),"",$R14-LOOKUP(2,1/($G$2:G13=$G14),$R$2:R13)) | U14: =IF(N14="","",IF(S14<>"",S14/N14,IF(T14<>"",T14/N14,""))) | Y14: =IF($B14="","",IF((IF($G14="","Sin unidad | ","")&IF($J14="","Sin responsable | ","")&IF($K14="","Sin obra | ","")&IF(AND($N14<>"",$G14<>"",$N14>IFERROR(INDEX('MAESTRO DE UNIDADES'!$I$2:$I$208,MATCH($G14,'MAESTRO DE UNIDADES'!$A$2:$A$208,0)),0)),"Litros > tanque | ","")&IF(AND($W14<>"",COUNTIF($W$2:$W14,$W14)>1),"Ticket duplicado | ","")&IF(AND($G14<>"",IFERROR(INDEX('MAESTRO DE UNIDADES'!$L$2:$L$208,MATCH($G14,'MAESTRO DE UNIDADES'!$A$2:$A$208,0)),"")="Inactivo"),"Unidad inactiva | ","")&IF(AND($AA14<>"",$N14=""),"Carga de batán sin litros | ","")&IF(AND($AA14<>"",$AC14<0),"Supera saldo batán | ",""))="","OK",LEFT((IF($G14="","Sin unidad | ","")&IF($J14="","Sin responsable | ","")&IF($K14="","Sin obra | ","")&IF(AND($N14<>"",$G14<>"",$N14>IFERROR(INDEX('MAESTRO DE UNIDADES'!$I$2:$I$208,MATCH($G14,'MAESTRO DE UNIDADES'!$A$2:$A$208,0)),0)),"Litros > tanque | ","")&IF(AND($W14<>"",COUNTIF($W$2:$W14,$W14)>1),"Ticket duplicado | ","")&IF(AND($G14<>"",IFERROR(INDEX('MAESTRO DE UNIDADES'!$L$2:$L$208,MATCH($G14,'MAESTRO DE UNIDADES'!$A$2:$A$208,0)),"")="Inactivo"),"Unidad inactiva | ","")&IF(AND($AA14<>"",$N14=""),"Carga de batán sin litros | ","")&IF(AND($AA14<>"",$AC14<0),"Supera saldo batán | ","")),LEN((IF($G14="","Sin unidad | ","")&IF($J14="","Sin responsable | ","")&IF($K14="","Sin obra | ","")&IF(AND($N14<>"",$G14<>"",$N14>IFERROR(INDEX('MAESTRO DE UNIDADES'!$I$2:$I$208,MATCH($G14,'MAESTRO DE UNIDADES'!$A$2:$A$208,0)),0)),"Litros > tanque | ","")&IF(AND($W14<>"",COUNTIF($W$2:$W14,$W14)>1),"Ticket duplicado | ","")&IF(AND($G14<>"",IFERROR(INDEX('MAESTRO DE UNIDADES'!$L$2:$L$208,MATCH($G14,'MAESTRO DE UNIDADES'!$A$2:$A$208,0)),"")="Inactivo"),"Unidad inactiva | ","")&IF(AND($AA14<>"",$N14=""),"Carga de batán sin litros | ","")&IF(AND($AA14<>"",$AC14<0),"Supera saldo batán | ","")))-3))) | Z14: =IF($B14="","",IF($AA14<>"","Batán","Estación de servicio"))
A15: =IF(B15="","","CARGA-"&TEXT(ROW()-1,"0000")) | C15: =IF(B15="","",CHOOSE(MONTH(B15),"Enero","Febrero","Marzo","Abril","Mayo","Junio","Julio","Agosto","Septiembre","Octubre","Noviembre","Diciembre")) | D15: =IF(B15="","",YEAR(B15)) | E15: =IF(B15="","",CHOOSE(WEEKDAY(B15,2),"Lunes","Martes","Miércoles","Jueves","Viernes","Sábado","Domingo")) | H15: =IF($G15="","",IFERROR(INDEX('MAESTRO DE UNIDADES'!$F$2:$F$208,MATCH($G15,'MAESTRO DE UNIDADES'!$A$2:$A$208,0)),"")) | I15: =IF($G15="","",IFERROR(INDEX('MAESTRO DE UNIDADES'!$B$2:$B$208,MATCH($G15,'MAESTRO DE UNIDADES'!$A$2:$A$208,0)),"")) | M15: =IF($G15="","",IFERROR(INDEX('MAESTRO DE UNIDADES'!$H$2:$H$208,MATCH($G15,'MAESTRO DE UNIDADES'!$A$2:$A$208,0)),"")) | P15: =IF($N15="","",IF($AA15<>"",IF($AB15="","",$N15*$AB15),IF($O15="","",$N15*$O15))) | S15: =IF(OR($G15="",$Q15="",COUNTIF($G$2:G14,$G15)=0),"",$Q15-LOOKUP(2,1/($G$2:G14=$G15),$Q$2:Q14)) | T15: =IF(OR($G15="",$R15="",COUNTIF($G$2:G14,$G15)=0),"",$R15-LOOKUP(2,1/($G$2:G14=$G15),$R$2:R14)) | U15: =IF(N15="","",IF(S15<>"",S15/N15,IF(T15<>"",T15/N15,""))) | Y15: =IF($B15="","",IF((IF($G15="","Sin unidad | ","")&IF($J15="","Sin responsable | ","")&IF($K15="","Sin obra | ","")&IF(AND($N15<>"",$G15<>"",$N15>IFERROR(INDEX('MAESTRO DE UNIDADES'!$I$2:$I$208,MATCH($G15,'MAESTRO DE UNIDADES'!$A$2:$A$208,0)),0)),"Litros > tanque | ","")&IF(AND($W15<>"",COUNTIF($W$2:$W15,$W15)>1),"Ticket duplicado | ","")&IF(AND($G15<>"",IFERROR(INDEX('MAESTRO DE UNIDADES'!$L$2:$L$208,MATCH($G15,'MAESTRO DE UNIDADES'!$A$2:$A$208,0)),"")="Inactivo"),"Unidad inactiva | ","")&IF(AND($AA15<>"",$N15=""),"Carga de batán sin litros | ","")&IF(AND($AA15<>"",$AC15<0),"Supera saldo batán | ",""))="","OK",LEFT((IF($G15="","Sin unidad | ","")&IF($J15="","Sin responsable | ","")&IF($K15="","Sin obra | ","")&IF(AND($N15<>"",$G15<>"",$N15>IFERROR(INDEX('MAESTRO DE UNIDADES'!$I$2:$I$208,MATCH($G15,'MAESTRO DE UNIDADES'!$A$2:$A$208,0)),0)),"Litros > tanque | ","")&IF(AND($W15<>"",COUNTIF($W$2:$W15,$W15)>1),"Ticket duplicado | ","")&IF(AND($G15<>"",IFERROR(INDEX('MAESTRO DE UNIDADES'!$L$2:$L$208,MATCH($G15,'MAESTRO DE UNIDADES'!$A$2:$A$208,0)),"")="Inactivo"),"Unidad inactiva | ","")&IF(AND($AA15<>"",$N15=""),"Carga de batán sin litros | ","")&IF(AND($AA15<>"",$AC15<0),"Supera saldo batán | ","")),LEN((IF($G15="","Sin unidad | ","")&IF($J15="","Sin responsable | ","")&IF($K15="","Sin obra | ","")&IF(AND($N15<>"",$G15<>"",$N15>IFERROR(INDEX('MAESTRO DE UNIDADES'!$I$2:$I$208,MATCH($G15,'MAESTRO DE UNIDADES'!$A$2:$A$208,0)),0)),"Litros > tanque | ","")&IF(AND($W15<>"",COUNTIF($W$2:$W15,$W15)>1),"Ticket duplicado | ","")&IF(AND($G15<>"",IFERROR(INDEX('MAESTRO DE UNIDADES'!$L$2:$L$208,MATCH($G15,'MAESTRO DE UNIDADES'!$A$2:$A$208,0)),"")="Inactivo"),"Unidad inactiva | ","")&IF(AND($AA15<>"",$N15=""),"Carga de batán sin litros | ","")&IF(AND($AA15<>"",$AC15<0),"Supera saldo batán | ","")))-3))) | Z15: =IF($B15="","",IF($AA15<>"","Batán","Estación de servicio"))
A16: =IF(B16="","","CARGA-"&TEXT(ROW()-1,"0000")) | C16: =IF(B16="","",CHOOSE(MONTH(B16),"Enero","Febrero","Marzo","Abril","Mayo","Junio","Julio","Agosto","Septiembre","Octubre","Noviembre","Diciembre")) | D16: =IF(B16="","",YEAR(B16)) | E16: =IF(B16="","",CHOOSE(WEEKDAY(B16,2),"Lunes","Martes","Miércoles","Jueves","Viernes","Sábado","Domingo")) | I16: =IF($G16="","",IFERROR(INDEX('MAESTRO DE UNIDADES'!$B$2:$B$208,MATCH($G16,'MAESTRO DE UNIDADES'!$A$2:$A$208,0)),"")) | M16: =IF($G16="","",IFERROR(INDEX('MAESTRO DE UNIDADES'!$H$2:$H$208,MATCH($G16,'MAESTRO DE UNIDADES'!$A$2:$A$208,0)),"")) | P16: =IF($N16="","",IF($AA16<>"",IF($AB16="","",$N16*$AB16),IF($O16="","",$N16*$O16))) | S16: =IF(OR($G16="",$Q16="",COUNTIF($G$2:G15,$G16)=0),"",$Q16-LOOKUP(2,1/($G$2:G15=$G16),$Q$2:Q15)) | T16: =IF(OR($G16="",$R16="",COUNTIF($G$2:G15,$G16)=0),"",$R16-LOOKUP(2,1/($G$2:G15=$G16),$R$2:R15)) | U16: =IF(N16="","",IF(S16<>"",S16/N16,IF(T16<>"",T16/N16,""))) | Y16: =IF($B16="","",IF((IF($G16="","Sin unidad | ","")&IF($J16="","Sin responsable | ","")&IF($K16="","Sin obra | ","")&IF(AND($N16<>"",$G16<>"",$N16>IFERROR(INDEX('MAESTRO DE UNIDADES'!$I$2:$I$208,MATCH($G16,'MAESTRO DE UNIDADES'!$A$2:$A$208,0)),0)),"Litros > tanque | ","")&IF(AND($W16<>"",COUNTIF($W$2:$W16,$W16)>1),"Ticket duplicado | ","")&IF(AND($G16<>"",IFERROR(INDEX('MAESTRO DE UNIDADES'!$L$2:$L$208,MATCH($G16,'MAESTRO DE UNIDADES'!$A$2:$A$208,0)),"")="Inactivo"),"Unidad inactiva | ","")&IF(AND($AA16<>"",$N16=""),"Carga de batán sin litros | ","")&IF(AND($AA16<>"",$AC16<0),"Supera saldo batán | ",""))="","OK",LEFT((IF($G16="","Sin unidad | ","")&IF($J16="","Sin responsable | ","")&IF($K16="","Sin obra | ","")&IF(AND($N16<>"",$G16<>"",$N16>IFERROR(INDEX('MAESTRO DE UNIDADES'!$I$2:$I$208,MATCH($G16,'MAESTRO DE UNIDADES'!$A$2:$A$208,0)),0)),"Litros > tanque | ","")&IF(AND($W16<>"",COUNTIF($W$2:$W16,$W16)>1),"Ticket duplicado | ","")&IF(AND($G16<>"",IFERROR(INDEX('MAESTRO DE UNIDADES'!$L$2:$L$208,MATCH($G16,'MAESTRO DE UNIDADES'!$A$2:$A$208,0)),"")="Inactivo"),"Unidad inactiva | ","")&IF(AND($AA16<>"",$N16=""),"Carga de batán sin litros | ","")&IF(AND($AA16<>"",$AC16<0),"Supera saldo batán | ","")),LEN((IF($G16="","Sin unidad | ","")&IF($J16="","Sin responsable | ","")&IF($K16="","Sin obra | ","")&IF(AND($N16<>"",$G16<>"",$N16>IFERROR(INDEX('MAESTRO DE UNIDADES'!$I$2:$I$208,MATCH($G16,'MAESTRO DE UNIDADES'!$A$2:$A$208,0)),0)),"Litros > tanque | ","")&IF(AND($W16<>"",COUNTIF($W$2:$W16,$W16)>1),"Ticket duplicado | ","")&IF(AND($G16<>"",IFERROR(INDEX('MAESTRO DE UNIDADES'!$L$2:$L$208,MATCH($G16,'MAESTRO DE UNIDADES'!$A$2:$A$208,0)),"")="Inactivo"),"Unidad inactiva | ","")&IF(AND($AA16<>"",$N16=""),"Carga de batán sin litros | ","")&IF(AND($AA16<>"",$AC16<0),"Supera saldo batán | ","")))-3))) | Z16: =IF($B16="","",IF($AA16<>"","Batán","Estación de servicio")) | AB16: =IF($AA16="","",IFERROR(INDEX('CONTROL DE BATAN'!$J$2:$J$301,MATCH($AA16,'CONTROL DE BATAN'!$A$2:$A$301,0)),"")) | AC16: =IF($AA16="","",IFERROR(INDEX('CONTROL DE BATAN'!$I$2:$I$301,MATCH($AA16,'CONTROL DE BATAN'!$A$2:$A$301,0)),0)-SUMIFS($N$2:$N16,$AA$2:$AA16,$AA16))
A17: =IF(B17="","","CARGA-"&TEXT(ROW()-1,"0000")) | C17: =IF(B17="","",CHOOSE(MONTH(B17),"Enero","Febrero","Marzo","Abril","Mayo","Junio","Julio","Agosto","Septiembre","Octubre","Noviembre","Diciembre")) | D17: =IF(B17="","",YEAR(B17)) | E17: =IF(B17="","",CHOOSE(WEEKDAY(B17,2),"Lunes","Martes","Miércoles","Jueves","Viernes","Sábado","Domingo")) | H17: =IF($G17="","",IFERROR(INDEX('MAESTRO DE UNIDADES'!$F$2:$F$208,MATCH($G17,'MAESTRO DE UNIDADES'!$A$2:$A$208,0)),"")) | I17: =IF($G17="","",IFERROR(INDEX('MAESTRO DE UNIDADES'!$B$2:$B$208,MATCH($G17,'MAESTRO DE UNIDADES'!$A$2:$A$208,0)),"")) | M17: =IF($G17="","",IFERROR(INDEX('MAESTRO DE UNIDADES'!$H$2:$H$208,MATCH($G17,'MAESTRO DE UNIDADES'!$A$2:$A$208,0)),"")) | P17: =IF($N17="","",IF($AA17<>"",IF($AB17="","",$N17*$AB17),IF($O17="","",$N17*$O17))) | S17: =IF(OR($G17="",$Q17="",COUNTIF($G$2:G16,$G17)=0),"",$Q17-LOOKUP(2,1/($G$2:G16=$G17),$Q$2:Q16)) | T17: =IF(OR($G17="",$R17="",COUNTIF($G$2:G16,$G17)=0),"",$R17-LOOKUP(2,1/($G$2:G16=$G17),$R$2:R16)) | U17: =IF(N17="","",IF(S17<>"",S17/N17,IF(T17<>"",T17/N17,""))) | Y17: =IF($B17="","",IF((IF($G17="","Sin unidad | ","")&IF($J17="","Sin responsable | ","")&IF($K17="","Sin obra | ","")&IF(AND($N17<>"",$G17<>"",$N17>IFERROR(INDEX('MAESTRO DE UNIDADES'!$I$2:$I$208,MATCH($G17,'MAESTRO DE UNIDADES'!$A$2:$A$208,0)),0)),"Litros > tanque | ","")&IF(AND($W17<>"",COUNTIF($W$2:$W17,$W17)>1),"Ticket duplicado | ","")&IF(AND($G17<>"",IFERROR(INDEX('MAESTRO DE UNIDADES'!$L$2:$L$208,MATCH($G17,'MAESTRO DE UNIDADES'!$A$2:$A$208,0)),"")="Inactivo"),"Unidad inactiva | ","")&IF(AND($AA17<>"",$N17=""),"Carga de batán sin litros | ","")&IF(AND($AA17<>"",$AC17<0),"Supera saldo batán | ",""))="","OK",LEFT((IF($G17="","Sin unidad | ","")&IF($J17="","Sin responsable | ","")&IF($K17="","Sin obra | ","")&IF(AND($N17<>"",$G17<>"",$N17>IFERROR(INDEX('MAESTRO DE UNIDADES'!$I$2:$I$208,MATCH($G17,'MAESTRO DE UNIDADES'!$A$2:$A$208,0)),0)),"Litros > tanque | ","")&IF(AND($W17<>"",COUNTIF($W$2:$W17,$W17)>1),"Ticket duplicado | ","")&IF(AND($G17<>"",IFERROR(INDEX('MAESTRO DE UNIDADES'!$L$2:$L$208,MATCH($G17,'MAESTRO DE UNIDADES'!$A$2:$A$208,0)),"")="Inactivo"),"Unidad inactiva | ","")&IF(AND($AA17<>"",$N17=""),"Carga de batán sin litros | ","")&IF(AND($AA17<>"",$AC17<0),"Supera saldo batán | ","")),LEN((IF($G17="","Sin unidad | ","")&IF($J17="","Sin responsable | ","")&IF($K17="","Sin obra | ","")&IF(AND($N17<>"",$G17<>"",$N17>IFERROR(INDEX('MAESTRO DE UNIDADES'!$I$2:$I$208,MATCH($G17,'MAESTRO DE UNIDADES'!$A$2:$A$208,0)),0)),"Litros > tanque | ","")&IF(AND($W17<>"",COUNTIF($W$2:$W17,$W17)>1),"Ticket duplicado | ","")&IF(AND($G17<>"",IFERROR(INDEX('MAESTRO DE UNIDADES'!$L$2:$L$208,MATCH($G17,'MAESTRO DE UNIDADES'!$A$2:$A$208,0)),"")="Inactivo"),"Unidad inactiva | ","")&IF(AND($AA17<>"",$N17=""),"Carga de batán sin litros | ","")&IF(AND($AA17<>"",$AC17<0),"Supera saldo batán | ","")))-3))) | Z17: =IF($B17="","",IF($AA17<>"","Batán","Estación de servicio")) | AB17: =IF($AA17="","",IFERROR(INDEX('CONTROL DE BATAN'!$J$2:$J$301,MATCH($AA17,'CONTROL DE BATAN'!$A$2:$A$301,0)),"")) | AC17: =IF($AA17="","",IFERROR(INDEX('CONTROL DE BATAN'!$I$2:$I$301,MATCH($AA17,'CONTROL DE BATAN'!$A$2:$A$301,0)),0)-SUMIFS($N$2:$N17,$AA$2:$AA17,$AA17))
A18: =IF(B18="","","CARGA-"&TEXT(ROW()-1,"0000")) | C18: =IF(B18="","",CHOOSE(MONTH(B18),"Enero","Febrero","Marzo","Abril","Mayo","Junio","Julio","Agosto","Septiembre","Octubre","Noviembre","Diciembre")) | D18: =IF(B18="","",YEAR(B18)) | E18: =IF(B18="","",CHOOSE(WEEKDAY(B18,2),"Lunes","Martes","Miércoles","Jueves","Viernes","Sábado","Domingo")) | H18: =IF($G18="","",IFERROR(INDEX('MAESTRO DE UNIDADES'!$F$2:$F$208,MATCH($G18,'MAESTRO DE UNIDADES'!$A$2:$A$208,0)),"")) | I18: =IF($G18="","",IFERROR(INDEX('MAESTRO DE UNIDADES'!$B$2:$B$208,MATCH($G18,'MAESTRO DE UNIDADES'!$A$2:$A$208,0)),"")) | M18: =IF($G18="","",IFERROR(INDEX('MAESTRO DE UNIDADES'!$H$2:$H$208,MATCH($G18,'MAESTRO DE UNIDADES'!$A$2:$A$208,0)),"")) | P18: =IF($N18="","",IF($AA18<>"",IF($AB18="","",$N18*$AB18),IF($O18="","",$N18*$O18))) | S18: =IF(OR($G18="",$Q18="",COUNTIF($G$2:G17,$G18)=0),"",$Q18-LOOKUP(2,1/($G$2:G17=$G18),$Q$2:Q17)) | T18: =IF(OR($G18="",$R18="",COUNTIF($G$2:G17,$G18)=0),"",$R18-LOOKUP(2,1/($G$2:G17=$G18),$R$2:R17)) | U18: =IF(N18="","",IF(S18<>"",S18/N18,IF(T18<>"",T18/N18,""))) | Y18: =IF($B18="","",IF((IF($G18="","Sin unidad | ","")&IF($J18="","Sin responsable | ","")&IF($K18="","Sin obra | ","")&IF(AND($N18<>"",$G18<>"",$N18>IFERROR(INDEX('MAESTRO DE UNIDADES'!$I$2:$I$208,MATCH($G18,'MAESTRO DE UNIDADES'!$A$2:$A$208,0)),0)),"Litros > tanque | ","")&IF(AND($W18<>"",COUNTIF($W$2:$W18,$W18)>1),"Ticket duplicado | ","")&IF(AND($G18<>"",IFERROR(INDEX('MAESTRO DE UNIDADES'!$L$2:$L$208,MATCH($G18,'MAESTRO DE UNIDADES'!$A$2:$A$208,0)),"")="Inactivo"),"Unidad inactiva | ","")&IF(AND($AA18<>"",$N18=""),"Carga de batán sin litros | ","")&IF(AND($AA18<>"",$AC18<0),"Supera saldo batán | ",""))="","OK",LEFT((IF($G18="","Sin unidad | ","")&IF($J18="","Sin responsable | ","")&IF($K18="","Sin obra | ","")&IF(AND($N18<>"",$G18<>"",$N18>IFERROR(INDEX('MAESTRO DE UNIDADES'!$I$2:$I$208,MATCH($G18,'MAESTRO DE UNIDADES'!$A$2:$A$208,0)),0)),"Litros > tanque | ","")&IF(AND($W18<>"",COUNTIF($W$2:$W18,$W18)>1),"Ticket duplicado | ","")&IF(AND($G18<>"",IFERROR(INDEX('MAESTRO DE UNIDADES'!$L$2:$L$208,MATCH($G18,'MAESTRO DE UNIDADES'!$A$2:$A$208,0)),"")="Inactivo"),"Unidad inactiva | ","")&IF(AND($AA18<>"",$N18=""),"Carga de batán sin litros | ","")&IF(AND($AA18<>"",$AC18<0),"Supera saldo batán | ","")),LEN((IF($G18="","Sin unidad | ","")&IF($J18="","Sin responsable | ","")&IF($K18="","Sin obra | ","")&IF(AND($N18<>"",$G18<>"",$N18>IFERROR(INDEX('MAESTRO DE UNIDADES'!$I$2:$I$208,MATCH($G18,'MAESTRO DE UNIDADES'!$A$2:$A$208,0)),0)),"Litros > tanque | ","")&IF(AND($W18<>"",COUNTIF($W$2:$W18,$W18)>1),"Ticket duplicado | ","")&IF(AND($G18<>"",IFERROR(INDEX('MAESTRO DE UNIDADES'!$L$2:$L$208,MATCH($G18,'MAESTRO DE UNIDADES'!$A$2:$A$208,0)),"")="Inactivo"),"Unidad inactiva | ","")&IF(AND($AA18<>"",$N18=""),"Carga de batán sin litros | ","")&IF(AND($AA18<>"",$AC18<0),"Supera saldo batán | ","")))-3))) | Z18: =IF($B18="","",IF($AA18<>"","Batán","Estación de servicio")) | AB18: =IF($AA18="","",IFERROR(INDEX('CONTROL DE BATAN'!$J$2:$J$301,MATCH($AA18,'CONTROL DE BATAN'!$A$2:$A$301,0)),"")) | AC18: =IF($AA18="","",IFERROR(INDEX('CONTROL DE BATAN'!$I$2:$I$301,MATCH($AA18,'CONTROL DE BATAN'!$A$2:$A$301,0)),0)-SUMIFS($N$2:$N18,$AA$2:$AA18,$AA18))
A19: =IF(B19="","","CARGA-"&TEXT(ROW()-1,"0000")) | C19: =IF(B19="","",CHOOSE(MONTH(B19),"Enero","Febrero","Marzo","Abril","Mayo","Junio","Julio","Agosto","Septiembre","Octubre","Noviembre","Diciembre")) | D19: =IF(B19="","",YEAR(B19)) | E19: =IF(B19="","",CHOOSE(WEEKDAY(B19,2),"Lunes","Martes","Miércoles","Jueves","Viernes","Sábado","Domingo")) | H19: =IF($G19="","",IFERROR(INDEX('MAESTRO DE UNIDADES'!$F$2:$F$208,MATCH($G19,'MAESTRO DE UNIDADES'!$A$2:$A$208,0)),"")) | I19: =IF($G19="","",IFERROR(INDEX('MAESTRO DE UNIDADES'!$B$2:$B$208,MATCH($G19,'MAESTRO DE UNIDADES'!$A$2:$A$208,0)),"")) | M19: =IF($G19="","",IFERROR(INDEX('MAESTRO DE UNIDADES'!$H$2:$H$208,MATCH($G19,'MAESTRO DE UNIDADES'!$A$2:$A$208,0)),"")) | P19: =IF($N19="","",IF($AA19<>"",IF($AB19="","",$N19*$AB19),IF($O19="","",$N19*$O19))) | S19: =IF(OR($G19="",$Q19="",COUNTIF($G$2:G18,$G19)=0),"",$Q19-LOOKUP(2,1/($G$2:G18=$G19),$Q$2:Q18)) | T19: =IF(OR($G19="",$R19="",COUNTIF($G$2:G18,$G19)=0),"",$R19-LOOKUP(2,1/($G$2:G18=$G19),$R$2:R18)) | U19: =IF(N19="","",IF(S19<>"",S19/N19,IF(T19<>"",T19/N19,""))) | Y19: =IF($B19="","",IF((IF($G19="","Sin unidad | ","")&IF($J19="","Sin responsable | ","")&IF($K19="","Sin obra | ","")&IF(AND($N19<>"",$G19<>"",$N19>IFERROR(INDEX('MAESTRO DE UNIDADES'!$I$2:$I$208,MATCH($G19,'MAESTRO DE UNIDADES'!$A$2:$A$208,0)),0)),"Litros > tanque | ","")&IF(AND($W19<>"",COUNTIF($W$2:$W19,$W19)>1),"Ticket duplicado | ","")&IF(AND($G19<>"",IFERROR(INDEX('MAESTRO DE UNIDADES'!$L$2:$L$208,MATCH($G19,'MAESTRO DE UNIDADES'!$A$2:$A$208,0)),"")="Inactivo"),"Unidad inactiva | ","")&IF(AND($AA19<>"",$N19=""),"Carga de batán sin litros | ","")&IF(AND($AA19<>"",$AC19<0),"Supera saldo batán | ",""))="","OK",LEFT((IF($G19="","Sin unidad | ","")&IF($J19="","Sin responsable | ","")&IF($K19="","Sin obra | ","")&IF(AND($N19<>"",$G19<>"",$N19>IFERROR(INDEX('MAESTRO DE UNIDADES'!$I$2:$I$208,MATCH($G19,'MAESTRO DE UNIDADES'!$A$2:$A$208,0)),0)),"Litros > tanque | ","")&IF(AND($W19<>"",COUNTIF($W$2:$W19,$W19)>1),"Ticket duplicado | ","")&IF(AND($G19<>"",IFERROR(INDEX('MAESTRO DE UNIDADES'!$L$2:$L$208,MATCH($G19,'MAESTRO DE UNIDADES'!$A$2:$A$208,0)),"")="Inactivo"),"Unidad inactiva | ","")&IF(AND($AA19<>"",$N19=""),"Carga de batán sin litros | ","")&IF(AND($AA19<>"",$AC19<0),"Supera saldo batán | ","")),LEN((IF($G19="","Sin unidad | ","")&IF($J19="","Sin responsable | ","")&IF($K19="","Sin obra | ","")&IF(AND($N19<>"",$G19<>"",$N19>IFERROR(INDEX('MAESTRO DE UNIDADES'!$I$2:$I$208,MATCH($G19,'MAESTRO DE UNIDADES'!$A$2:$A$208,0)),0)),"Litros > tanque | ","")&IF(AND($W19<>"",COUNTIF($W$2:$W19,$W19)>1),"Ticket duplicado | ","")&IF(AND($G19<>"",IFERROR(INDEX('MAESTRO DE UNIDADES'!$L$2:$L$208,MATCH($G19,'MAESTRO DE UNIDADES'!$A$2:$A$208,0)),"")="Inactivo"),"Unidad inactiva | ","")&IF(AND($AA19<>"",$N19=""),"Carga de batán sin litros | ","")&IF(AND($AA19<>"",$AC19<0),"Supera saldo batán | ","")))-3))) | Z19: =IF($B19="","",IF($AA19<>"","Batán","Estación de servicio")) | AB19: =IF($AA19="","",IFERROR(INDEX('CONTROL DE BATAN'!$J$2:$J$301,MATCH($AA19,'CONTROL DE BATAN'!$A$2:$A$301,0)),"")) | AC19: =IF($AA19="","",IFERROR(INDEX('CONTROL DE BATAN'!$I$2:$I$301,MATCH($AA19,'CONTROL DE BATAN'!$A$2:$A$301,0)),0)-SUMIFS($N$2:$N19,$AA$2:$AA19,$AA19))
A20: =IF(B20="","","CARGA-"&TEXT(ROW()-1,"0000")) | C20: =IF(B20="","",CHOOSE(MONTH(B20),"Enero","Febrero","Marzo","Abril","Mayo","Junio","Julio","Agosto","Septiembre","Octubre","Noviembre","Diciembre")) | D20: =IF(B20="","",YEAR(B20)) | E20: =IF(B20="","",CHOOSE(WEEKDAY(B20,2),"Lunes","Martes","Miércoles","Jueves","Viernes","Sábado","Domingo")) | H20: =IF($G20="","",IFERROR(INDEX('MAESTRO DE UNIDADES'!$F$2:$F$208,MATCH($G20,'MAESTRO DE UNIDADES'!$A$2:$A$208,0)),"")) | I20: =IF($G20="","",IFERROR(INDEX('MAESTRO DE UNIDADES'!$B$2:$B$208,MATCH($G20,'MAESTRO DE UNIDADES'!$A$2:$A$208,0)),"")) | P20: =IF($N20="","",IF($AA20<>"",IF($AB20="","",$N20*$AB20),IF($O20="","",$N20*$O20))) | S20: =IF(OR($G20="",$Q20="",COUNTIF($G$2:G19,$G20)=0),"",$Q20-LOOKUP(2,1/($G$2:G19=$G20),$Q$2:Q19)) | T20: =IF(OR($G20="",$R20="",COUNTIF($G$2:G19,$G20)=0),"",$R20-LOOKUP(2,1/($G$2:G19=$G20),$R$2:R19)) | U20: =IF(N20="","",IF(S20<>"",S20/N20,IF(T20<>"",T20/N20,""))) | Y20: =IF($B20="","",IF((IF($G20="","Sin unidad | ","")&IF($J20="","Sin responsable | ","")&IF($K20="","Sin obra | ","")&IF(AND($N20<>"",$G20<>"",$N20>IFERROR(INDEX('MAESTRO DE UNIDADES'!$I$2:$I$208,MATCH($G20,'MAESTRO DE UNIDADES'!$A$2:$A$208,0)),0)),"Litros > tanque | ","")&IF(AND($W20<>"",COUNTIF($W$2:$W20,$W20)>1),"Ticket duplicado | ","")&IF(AND($G20<>"",IFERROR(INDEX('MAESTRO DE UNIDADES'!$L$2:$L$208,MATCH($G20,'MAESTRO DE UNIDADES'!$A$2:$A$208,0)),"")="Inactivo"),"Unidad inactiva | ","")&IF(AND($AA20<>"",$N20=""),"Carga de batán sin litros | ","")&IF(AND($AA20<>"",$AC20<0),"Supera saldo batán | ",""))="","OK",LEFT((IF($G20="","Sin unidad | ","")&IF($J20="","Sin responsable | ","")&IF($K20="","Sin obra | ","")&IF(AND($N20<>"",$G20<>"",$N20>IFERROR(INDEX('MAESTRO DE UNIDADES'!$I$2:$I$208,MATCH($G20,'MAESTRO DE UNIDADES'!$A$2:$A$208,0)),0)),"Litros > tanque | ","")&IF(AND($W20<>"",COUNTIF($W$2:$W20,$W20)>1),"Ticket duplicado | ","")&IF(AND($G20<>"",IFERROR(INDEX('MAESTRO DE UNIDADES'!$L$2:$L$208,MATCH($G20,'MAESTRO DE UNIDADES'!$A$2:$A$208,0)),"")="Inactivo"),"Unidad inactiva | ","")&IF(AND($AA20<>"",$N20=""),"Carga de batán sin litros | ","")&IF(AND($AA20<>"",$AC20<0),"Supera saldo batán | ","")),LEN((IF($G20="","Sin unidad | ","")&IF($J20="","Sin responsable | ","")&IF($K20="","Sin obra | ","")&IF(AND($N20<>"",$G20<>"",$N20>IFERROR(INDEX('MAESTRO DE UNIDADES'!$I$2:$I$208,MATCH($G20,'MAESTRO DE UNIDADES'!$A$2:$A$208,0)),0)),"Litros > tanque | ","")&IF(AND($W20<>"",COUNTIF($W$2:$W20,$W20)>1),"Ticket duplicado | ","")&IF(AND($G20<>"",IFERROR(INDEX('MAESTRO DE UNIDADES'!$L$2:$L$208,MATCH($G20,'MAESTRO DE UNIDADES'!$A$2:$A$208,0)),"")="Inactivo"),"Unidad inactiva | ","")&IF(AND($AA20<>"",$N20=""),"Carga de batán sin litros | ","")&IF(AND($AA20<>"",$AC20<0),"Supera saldo batán | ","")))-3))) | Z20: =IF($B20="","",IF($AA20<>"","Batán","Estación de servicio")) | AB20: =IF($AA20="","",IFERROR(INDEX('CONTROL DE BATAN'!$J$2:$J$301,MATCH($AA20,'CONTROL DE BATAN'!$A$2:$A$301,0)),"")) | AC20: =IF($AA20="","",IFERROR(INDEX('CONTROL DE BATAN'!$I$2:$I$301,MATCH($AA20,'CONTROL DE BATAN'!$A$2:$A$301,0)),0)-SUMIFS($N$2:$N20,$AA$2:$AA20,$AA20))
A21: =IF(B21="","","CARGA-"&TEXT(ROW()-1,"0000")) | C21: =IF(B21="","",CHOOSE(MONTH(B21),"Enero","Febrero","Marzo","Abril","Mayo","Junio","Julio","Agosto","Septiembre","Octubre","Noviembre","Diciembre")) | D21: =IF(B21="","",YEAR(B21)) | E21: =IF(B21="","",CHOOSE(WEEKDAY(B21,2),"Lunes","Martes","Miércoles","Jueves","Viernes","Sábado","Domingo")) | H21: =IF($G21="","",IFERROR(INDEX('MAESTRO DE UNIDADES'!$F$2:$F$208,MATCH($G21,'MAESTRO DE UNIDADES'!$A$2:$A$208,0)),"")) | I21: =IF($G21="","",IFERROR(INDEX('MAESTRO DE UNIDADES'!$B$2:$B$208,MATCH($G21,'MAESTRO DE UNIDADES'!$A$2:$A$208,0)),"")) | M21: =IF($G21="","",IFERROR(INDEX('MAESTRO DE UNIDADES'!$H$2:$H$208,MATCH($G21,'MAESTRO DE UNIDADES'!$A$2:$A$208,0)),"")) | P21: =IF($N21="","",IF($AA21<>"",IF($AB21="","",$N21*$AB21),IF($O21="","",$N21*$O21))) | S21: =IF(OR($G21="",$Q21="",COUNTIF($G$2:G20,$G21)=0),"",$Q21-LOOKUP(2,1/($G$2:G20=$G21),$Q$2:Q20)) | T21: =IF(OR($G21="",$R21="",COUNTIF($G$2:G20,$G21)=0),"",$R21-LOOKUP(2,1/($G$2:G20=$G21),$R$2:R20)) | U21: =IF(N21="","",IF(S21<>"",S21/N21,IF(T21<>"",T21/N21,""))) | Y21: =IF($B21="","",IF((IF($G21="","Sin unidad | ","")&IF($J21="","Sin responsable | ","")&IF($K21="","Sin obra | ","")&IF(AND($N21<>"",$G21<>"",$N21>IFERROR(INDEX('MAESTRO DE UNIDADES'!$I$2:$I$208,MATCH($G21,'MAESTRO DE UNIDADES'!$A$2:$A$208,0)),0)),"Litros > tanque | ","")&IF(AND($W21<>"",COUNTIF($W$2:$W21,$W21)>1),"Ticket duplicado | ","")&IF(AND($G21<>"",IFERROR(INDEX('MAESTRO DE UNIDADES'!$L$2:$L$208,MATCH($G21,'MAESTRO DE UNIDADES'!$A$2:$A$208,0)),"")="Inactivo"),"Unidad inactiva | ","")&IF(AND($AA21<>"",$N21=""),"Carga de batán sin litros | ","")&IF(AND($AA21<>"",$AC21<0),"Supera saldo batán | ",""))="","OK",LEFT((IF($G21="","Sin unidad | ","")&IF($J21="","Sin responsable | ","")&IF($K21="","Sin obra | ","")&IF(AND($N21<>"",$G21<>"",$N21>IFERROR(INDEX('MAESTRO DE UNIDADES'!$I$2:$I$208,MATCH($G21,'MAESTRO DE UNIDADES'!$A$2:$A$208,0)),0)),"Litros > tanque | ","")&IF(AND($W21<>"",COUNTIF($W$2:$W21,$W21)>1),"Ticket duplicado | ","")&IF(AND($G21<>"",IFERROR(INDEX('MAESTRO DE UNIDADES'!$L$2:$L$208,MATCH($G21,'MAESTRO DE UNIDADES'!$A$2:$A$208,0)),"")="Inactivo"),"Unidad inactiva | ","")&IF(AND($AA21<>"",$N21=""),"Carga de batán sin litros | ","")&IF(AND($AA21<>"",$AC21<0),"Supera saldo batán | ","")),LEN((IF($G21="","Sin unidad | ","")&IF($J21="","Sin responsable | ","")&IF($K21="","Sin obra | ","")&IF(AND($N21<>"",$G21<>"",$N21>IFERROR(INDEX('MAESTRO DE UNIDADES'!$I$2:$I$208,MATCH($G21,'MAESTRO DE UNIDADES'!$A$2:$A$208,0)),0)),"Litros > tanque | ","")&IF(AND($W21<>"",COUNTIF($W$2:$W21,$W21)>1),"Ticket duplicado | ","")&IF(AND($G21<>"",IFERROR(INDEX('MAESTRO DE UNIDADES'!$L$2:$L$208,MATCH($G21,'MAESTRO DE UNIDADES'!$A$2:$A$208,0)),"")="Inactivo"),"Unidad inactiva | ","")&IF(AND($AA21<>"",$N21=""),"Carga de batán sin litros | ","")&IF(AND($AA21<>"",$AC21<0),"Supera saldo batán | ","")))-3))) | Z21: =IF($B21="","",IF($AA21<>"","Batán","Estación de servicio")) | AB21: =IF($AA21="","",IFERROR(INDEX('CONTROL DE BATAN'!$J$2:$J$301,MATCH($AA21,'CONTROL DE BATAN'!$A$2:$A$301,0)),"")) | AC21: =IF($AA21="","",IFERROR(INDEX('CONTROL DE BATAN'!$I$2:$I$301,MATCH($AA21,'CONTROL DE BATAN'!$A$2:$A$301,0)),0)-SUMIFS($N$2:$N21,$AA$2:$AA21,$AA21))
A22: =IF(B22="","","CARGA-"&TEXT(ROW()-1,"0000")) | C22: =IF(B22="","",CHOOSE(MONTH(B22),"Enero","Febrero","Marzo","Abril","Mayo","Junio","Julio","Agosto","Septiembre","Octubre","Noviembre","Diciembre")) | D22: =IF(B22="","",YEAR(B22)) | E22: =IF(B22="","",CHOOSE(WEEKDAY(B22,2),"Lunes","Martes","Miércoles","Jueves","Viernes","Sábado","Domingo")) | F22: =IF($G22="","",IFERROR(INDEX('MAESTRO DE UNIDADES'!$C$2:$C$208,MATCH($G22,'MAESTRO DE UNIDADES'!$A$2:$A$208,0)),"")) | H22: =IF($G22="","",IFERROR(INDEX('MAESTRO DE UNIDADES'!$F$2:$F$208,MATCH($G22,'MAESTRO DE UNIDADES'!$A$2:$A$208,0)),"")) | I22: =IF($G22="","",IFERROR(INDEX('MAESTRO DE UNIDADES'!$B$2:$B$208,MATCH($G22,'MAESTRO DE UNIDADES'!$A$2:$A$208,0)),"")) | M22: =IF($G22="","",IFERROR(INDEX('MAESTRO DE UNIDADES'!$H$2:$H$208,MATCH($G22,'MAESTRO DE UNIDADES'!$A$2:$A$208,0)),"")) | P22: =IF($N22="","",IF($AA22<>"",IF($AB22="","",$N22*$AB22),IF($O22="","",$N22*$O22))) | S22: =IF(OR($G22="",$Q22="",COUNTIF($G$2:G21,$G22)=0),"",$Q22-LOOKUP(2,1/($G$2:G21=$G22),$Q$2:Q21)) | T22: =IF(OR($G22="",$R22="",COUNTIF($G$2:G21,$G22)=0),"",$R22-LOOKUP(2,1/($G$2:G21=$G22),$R$2:R21)) | U22: =IF(N22="","",IF(S22<>"",S22/N22,IF(T22<>"",T22/N22,""))) | Y22: =IF($B22="","",IF((IF($G22="","Sin unidad | ","")&IF($J22="","Sin responsable | ","")&IF($K22="","Sin obra | ","")&IF(AND($N22<>"",$G22<>"",$N22>IFERROR(INDEX('MAESTRO DE UNIDADES'!$I$2:$I$208,MATCH($G22,'MAESTRO DE UNIDADES'!$A$2:$A$208,0)),0)),"Litros > tanque | ","")&IF(AND($W22<>"",COUNTIF($W$2:$W22,$W22)>1),"Ticket duplicado | ","")&IF(AND($G22<>"",IFERROR(INDEX('MAESTRO DE UNIDADES'!$L$2:$L$208,MATCH($G22,'MAESTRO DE UNIDADES'!$A$2:$A$208,0)),"")="Inactivo"),"Unidad inactiva | ","")&IF(AND($AA22<>"",$N22=""),"Carga de batán sin litros | ","")&IF(AND($AA22<>"",$AC22<0),"Supera saldo batán | ",""))="","OK",LEFT((IF($G22="","Sin unidad | ","")&IF($J22="","Sin responsable | ","")&IF($K22="","Sin obra | ","")&IF(AND($N22<>"",$G22<>"",$N22>IFERROR(INDEX('MAESTRO DE UNIDADES'!$I$2:$I$208,MATCH($G22,'MAESTRO DE UNIDADES'!$A$2:$A$208,0)),0)),"Litros > tanque | ","")&IF(AND($W22<>"",COUNTIF($W$2:$W22,$W22)>1),"Ticket duplicado | ","")&IF(AND($G22<>"",IFERROR(INDEX('MAESTRO DE UNIDADES'!$L$2:$L$208,MATCH($G22,'MAESTRO DE UNIDADES'!$A$2:$A$208,0)),"")="Inactivo"),"Unidad inactiva | ","")&IF(AND($AA22<>"",$N22=""),"Carga de batán sin litros | ","")&IF(AND($AA22<>"",$AC22<0),"Supera saldo batán | ","")),LEN((IF($G22="","Sin unidad | ","")&IF($J22="","Sin responsable | ","")&IF($K22="","Sin obra | ","")&IF(AND($N22<>"",$G22<>"",$N22>IFERROR(INDEX('MAESTRO DE UNIDADES'!$I$2:$I$208,MATCH($G22,'MAESTRO DE UNIDADES'!$A$2:$A$208,0)),0)),"Litros > tanque | ","")&IF(AND($W22<>"",COUNTIF($W$2:$W22,$W22)>1),"Ticket duplicado | ","")&IF(AND($G22<>"",IFERROR(INDEX('MAESTRO DE UNIDADES'!$L$2:$L$208,MATCH($G22,'MAESTRO DE UNIDADES'!$A$2:$A$208,0)),"")="Inactivo"),"Unidad inactiva | ","")&IF(AND($AA22<>"",$N22=""),"Carga de batán sin litros | ","")&IF(AND($AA22<>"",$AC22<0),"Supera saldo batán | ","")))-3))) | Z22: =IF($B22="","",IF($AA22<>"","Batán","Estación de servicio")) | AB22: =IF($AA22="","",IFERROR(INDEX('CONTROL DE BATAN'!$J$2:$J$301,MATCH($AA22,'CONTROL DE BATAN'!$A$2:$A$301,0)),"")) | AC22: =IF($AA22="","",IFERROR(INDEX('CONTROL DE BATAN'!$I$2:$I$301,MATCH($AA22,'CONTROL DE BATAN'!$A$2:$A$301,0)),0)-SUMIFS($N$2:$N22,$AA$2:$AA22,$AA22))
A23: =IF(B23="","","CARGA-"&TEXT(ROW()-1,"0000")) | C23: =IF(B23="","",CHOOSE(MONTH(B23),"Enero","Febrero","Marzo","Abril","Mayo","Junio","Julio","Agosto","Septiembre","Octubre","Noviembre","Diciembre")) | D23: =IF(B23="","",YEAR(B23)) | E23: =IF(B23="","",CHOOSE(WEEKDAY(B23,2),"Lunes","Martes","Miércoles","Jueves","Viernes","Sábado","Domingo")) | F23: =IF($G23="","",IFERROR(INDEX('MAESTRO DE UNIDADES'!$C$2:$C$208,MATCH($G23,'MAESTRO DE UNIDADES'!$A$2:$A$208,0)),"")) | H23: =IF($G23="","",IFERROR(INDEX('MAESTRO DE UNIDADES'!$F$2:$F$208,MATCH($G23,'MAESTRO DE UNIDADES'!$A$2:$A$208,0)),"")) | I23: =IF($G23="","",IFERROR(INDEX('MAESTRO DE UNIDADES'!$B$2:$B$208,MATCH($G23,'MAESTRO DE UNIDADES'!$A$2:$A$208,0)),"")) | M23: =IF($G23="","",IFERROR(INDEX('MAESTRO DE UNIDADES'!$H$2:$H$208,MATCH($G23,'MAESTRO DE UNIDADES'!$A$2:$A$208,0)),"")) | P23: =IF($N23="","",IF($AA23<>"",IF($AB23="","",$N23*$AB23),IF($O23="","",$N23*$O23))) | S23: =IF(OR($G23="",$Q23="",COUNTIF($G$2:G22,$G23)=0),"",$Q23-LOOKUP(2,1/($G$2:G22=$G23),$Q$2:Q22)) | T23: =IF(OR($G23="",$R23="",COUNTIF($G$2:G22,$G23)=0),"",$R23-LOOKUP(2,1/($G$2:G22=$G23),$R$2:R22)) | U23: =IF(N23="","",IF(S23<>"",S23/N23,IF(T23<>"",T23/N23,""))) | Y23: =IF($B23="","",IF((IF($G23="","Sin unidad | ","")&IF($J23="","Sin responsable | ","")&IF($K23="","Sin obra | ","")&IF(AND($N23<>"",$G23<>"",$N23>IFERROR(INDEX('MAESTRO DE UNIDADES'!$I$2:$I$208,MATCH($G23,'MAESTRO DE UNIDADES'!$A$2:$A$208,0)),0)),"Litros > tanque | ","")&IF(AND($W23<>"",COUNTIF($W$2:$W23,$W23)>1),"Ticket duplicado | ","")&IF(AND($G23<>"",IFERROR(INDEX('MAESTRO DE UNIDADES'!$L$2:$L$208,MATCH($G23,'MAESTRO DE UNIDADES'!$A$2:$A$208,0)),"")="Inactivo"),"Unidad inactiva | ","")&IF(AND($AA23<>"",$N23=""),"Carga de batán sin litros | ","")&IF(AND($AA23<>"",$AC23<0),"Supera saldo batán | ",""))="","OK",LEFT((IF($G23="","Sin unidad | ","")&IF($J23="","Sin responsable | ","")&IF($K23="","Sin obra | ","")&IF(AND($N23<>"",$G23<>"",$N23>IFERROR(INDEX('MAESTRO DE UNIDADES'!$I$2:$I$208,MATCH($G23,'MAESTRO DE UNIDADES'!$A$2:$A$208,0)),0)),"Litros > tanque | ","")&IF(AND($W23<>"",COUNTIF($W$2:$W23,$W23)>1),"Ticket duplicado | ","")&IF(AND($G23<>"",IFERROR(INDEX('MAESTRO DE UNIDADES'!$L$2:$L$208,MATCH($G23,'MAESTRO DE UNIDADES'!$A$2:$A$208,0)),"")="Inactivo"),"Unidad inactiva | ","")&IF(AND($AA23<>"",$N23=""),"Carga de batán sin litros | ","")&IF(AND($AA23<>"",$AC23<0),"Supera saldo batán | ","")),LEN((IF($G23="","Sin unidad | ","")&IF($J23="","Sin responsable | ","")&IF($K23="","Sin obra | ","")&IF(AND($N23<>"",$G23<>"",$N23>IFERROR(INDEX('MAESTRO DE UNIDADES'!$I$2:$I$208,MATCH($G23,'MAESTRO DE UNIDADES'!$A$2:$A$208,0)),0)),"Litros > tanque | ","")&IF(AND($W23<>"",COUNTIF($W$2:$W23,$W23)>1),"Ticket duplicado | ","")&IF(AND($G23<>"",IFERROR(INDEX('MAESTRO DE UNIDADES'!$L$2:$L$208,MATCH($G23,'MAESTRO DE UNIDADES'!$A$2:$A$208,0)),"")="Inactivo"),"Unidad inactiva | ","")&IF(AND($AA23<>"",$N23=""),"Carga de batán sin litros | ","")&IF(AND($AA23<>"",$AC23<0),"Supera saldo batán | ","")))-3))) | Z23: =IF($B23="","",IF($AA23<>"","Batán","Estación de servicio")) | AB23: =IF($AA23="","",IFERROR(INDEX('CONTROL DE BATAN'!$J$2:$J$301,MATCH($AA23,'CONTROL DE BATAN'!$A$2:$A$301,0)),"")) | AC23: =IF($AA23="","",IFERROR(INDEX('CONTROL DE BATAN'!$I$2:$I$301,MATCH($AA23,'CONTROL DE BATAN'!$A$2:$A$301,0)),0)-SUMIFS($N$2:$N23,$AA$2:$AA23,$AA23))
A24: =IF(B24="","","CARGA-"&TEXT(ROW()-1,"0000")) | C24: =IF(B24="","",CHOOSE(MONTH(B24),"Enero","Febrero","Marzo","Abril","Mayo","Junio","Julio","Agosto","Septiembre","Octubre","Noviembre","Diciembre")) | D24: =IF(B24="","",YEAR(B24)) | E24: =IF(B24="","",CHOOSE(WEEKDAY(B24,2),"Lunes","Martes","Miércoles","Jueves","Viernes","Sábado","Domingo")) | F24: =IF($G24="","",IFERROR(INDEX('MAESTRO DE UNIDADES'!$C$2:$C$208,MATCH($G24,'MAESTRO DE UNIDADES'!$A$2:$A$208,0)),"")) | H24: =IF($G24="","",IFERROR(INDEX('MAESTRO DE UNIDADES'!$F$2:$F$208,MATCH($G24,'MAESTRO DE UNIDADES'!$A$2:$A$208,0)),"")) | I24: =IF($G24="","",IFERROR(INDEX('MAESTRO DE UNIDADES'!$B$2:$B$208,MATCH($G24,'MAESTRO DE UNIDADES'!$A$2:$A$208,0)),"")) | M24: =IF($G24="","",IFERROR(INDEX('MAESTRO DE UNIDADES'!$H$2:$H$208,MATCH($G24,'MAESTRO DE UNIDADES'!$A$2:$A$208,0)),"")) | P24: =IF($N24="","",IF($AA24<>"",IF($AB24="","",$N24*$AB24),IF($O24="","",$N24*$O24))) | S24: =IF(OR($G24="",$Q24="",COUNTIF($G$2:G23,$G24)=0),"",$Q24-LOOKUP(2,1/($G$2:G23=$G24),$Q$2:Q23)) | T24: =IF(OR($G24="",$R24="",COUNTIF($G$2:G23,$G24)=0),"",$R24-LOOKUP(2,1/($G$2:G23=$G24),$R$2:R23)) | U24: =IF(N24="","",IF(S24<>"",S24/N24,IF(T24<>"",T24/N24,""))) | Y24: =IF($B24="","",IF((IF($G24="","Sin unidad | ","")&IF($J24="","Sin responsable | ","")&IF($K24="","Sin obra | ","")&IF(AND($N24<>"",$G24<>"",$N24>IFERROR(INDEX('MAESTRO DE UNIDADES'!$I$2:$I$208,MATCH($G24,'MAESTRO DE UNIDADES'!$A$2:$A$208,0)),0)),"Litros > tanque | ","")&IF(AND($W24<>"",COUNTIF($W$2:$W24,$W24)>1),"Ticket duplicado | ","")&IF(AND($G24<>"",IFERROR(INDEX('MAESTRO DE UNIDADES'!$L$2:$L$208,MATCH($G24,'MAESTRO DE UNIDADES'!$A$2:$A$208,0)),"")="Inactivo"),"Unidad inactiva | ","")&IF(AND($AA24<>"",$N24=""),"Carga de batán sin litros | ","")&IF(AND($AA24<>"",$AC24<0),"Supera saldo batán | ",""))="","OK",LEFT((IF($G24="","Sin unidad | ","")&IF($J24="","Sin responsable | ","")&IF($K24="","Sin obra | ","")&IF(AND($N24<>"",$G24<>"",$N24>IFERROR(INDEX('MAESTRO DE UNIDADES'!$I$2:$I$208,MATCH($G24,'MAESTRO DE UNIDADES'!$A$2:$A$208,0)),0)),"Litros > tanque | ","")&IF(AND($W24<>"",COUNTIF($W$2:$W24,$W24)>1),"Ticket duplicado | ","")&IF(AND($G24<>"",IFERROR(INDEX('MAESTRO DE UNIDADES'!$L$2:$L$208,MATCH($G24,'MAESTRO DE UNIDADES'!$A$2:$A$208,0)),"")="Inactivo"),"Unidad inactiva | ","")&IF(AND($AA24<>"",$N24=""),"Carga de batán sin litros | ","")&IF(AND($AA24<>"",$AC24<0),"Supera saldo batán | ","")),LEN((IF($G24="","Sin unidad | ","")&IF($J24="","Sin responsable | ","")&IF($K24="","Sin obra | ","")&IF(AND($N24<>"",$G24<>"",$N24>IFERROR(INDEX('MAESTRO DE UNIDADES'!$I$2:$I$208,MATCH($G24,'MAESTRO DE UNIDADES'!$A$2:$A$208,0)),0)),"Litros > tanque | ","")&IF(AND($W24<>"",COUNTIF($W$2:$W24,$W24)>1),"Ticket duplicado | ","")&IF(AND($G24<>"",IFERROR(INDEX('MAESTRO DE UNIDADES'!$L$2:$L$208,MATCH($G24,'MAESTRO DE UNIDADES'!$A$2:$A$208,0)),"")="Inactivo"),"Unidad inactiva | ","")&IF(AND($AA24<>"",$N24=""),"Carga de batán sin litros | ","")&IF(AND($AA24<>"",$AC24<0),"Supera saldo batán | ","")))-3))) | Z24: =IF($B24="","",IF($AA24<>"","Batán","Estación de servicio")) | AB24: =IF($AA24="","",IFERROR(INDEX('CONTROL DE BATAN'!$J$2:$J$301,MATCH($AA24,'CONTROL DE BATAN'!$A$2:$A$301,0)),"")) | AC24: =IF($AA24="","",IFERROR(INDEX('CONTROL DE BATAN'!$I$2:$I$301,MATCH($AA24,'CONTROL DE BATAN'!$A$2:$A$301,0)),0)-SUMIFS($N$2:$N24,$AA$2:$AA24,$AA24))
A25: =IF(B25="","","CARGA-"&TEXT(ROW()-1,"0000")) | C25: =IF(B25="","",CHOOSE(MONTH(B25),"Enero","Febrero","Marzo","Abril","Mayo","Junio","Julio","Agosto","Septiembre","Octubre","Noviembre","Diciembre")) | D25: =IF(B25="","",YEAR(B25)) | E25: =IF(B25="","",CHOOSE(WEEKDAY(B25,2),"Lunes","Martes","Miércoles","Jueves","Viernes","Sábado","Domingo")) | F25: =IF($G25="","",IFERROR(INDEX('MAESTRO DE UNIDADES'!$C$2:$C$208,MATCH($G25,'MAESTRO DE UNIDADES'!$A$2:$A$208,0)),"")) | H25: =IF($G25="","",IFERROR(INDEX('MAESTRO DE UNIDADES'!$F$2:$F$208,MATCH($G25,'MAESTRO DE UNIDADES'!$A$2:$A$208,0)),"")) | I25: =IF($G25="","",IFERROR(INDEX('MAESTRO DE UNIDADES'!$B$2:$B$208,MATCH($G25,'MAESTRO DE UNIDADES'!$A$2:$A$208,0)),"")) | M25: =IF($G25="","",IFERROR(INDEX('MAESTRO DE UNIDADES'!$H$2:$H$208,MATCH($G25,'MAESTRO DE UNIDADES'!$A$2:$A$208,0)),"")) | P25: =IF($N25="","",IF($AA25<>"",IF($AB25="","",$N25*$AB25),IF($O25="","",$N25*$O25))) | S25: =IF(OR($G25="",$Q25="",COUNTIF($G$2:G24,$G25)=0),"",$Q25-LOOKUP(2,1/($G$2:G24=$G25),$Q$2:Q24)) | T25: =IF(OR($G25="",$R25="",COUNTIF($G$2:G24,$G25)=0),"",$R25-LOOKUP(2,1/($G$2:G24=$G25),$R$2:R24)) | U25: =IF(N25="","",IF(S25<>"",S25/N25,IF(T25<>"",T25/N25,""))) | Y25: =IF($B25="","",IF((IF($G25="","Sin unidad | ","")&IF($J25="","Sin responsable | ","")&IF($K25="","Sin obra | ","")&IF(AND($N25<>"",$G25<>"",$N25>IFERROR(INDEX('MAESTRO DE UNIDADES'!$I$2:$I$208,MATCH($G25,'MAESTRO DE UNIDADES'!$A$2:$A$208,0)),0)),"Litros > tanque | ","")&IF(AND($W25<>"",COUNTIF($W$2:$W25,$W25)>1),"Ticket duplicado | ","")&IF(AND($G25<>"",IFERROR(INDEX('MAESTRO DE UNIDADES'!$L$2:$L$208,MATCH($G25,'MAESTRO DE UNIDADES'!$A$2:$A$208,0)),"")="Inactivo"),"Unidad inactiva | ","")&IF(AND($AA25<>"",$N25=""),"Carga de batán sin litros | ","")&IF(AND($AA25<>"",$AC25<0),"Supera saldo batán | ",""))="","OK",LEFT((IF($G25="","Sin unidad | ","")&IF($J25="","Sin responsable | ","")&IF($K25="","Sin obra | ","")&IF(AND($N25<>"",$G25<>"",$N25>IFERROR(INDEX('MAESTRO DE UNIDADES'!$I$2:$I$208,MATCH($G25,'MAESTRO DE UNIDADES'!$A$2:$A$208,0)),0)),"Litros > tanque | ","")&IF(AND($W25<>"",COUNTIF($W$2:$W25,$W25)>1),"Ticket duplicado | ","")&IF(AND($G25<>"",IFERROR(INDEX('MAESTRO DE UNIDADES'!$L$2:$L$208,MATCH($G25,'MAESTRO DE UNIDADES'!$A$2:$A$208,0)),"")="Inactivo"),"Unidad inactiva | ","")&IF(AND($AA25<>"",$N25=""),"Carga de batán sin litros | ","")&IF(AND($AA25<>"",$AC25<0),"Supera saldo batán | ","")),LEN((IF($G25="","Sin unidad | ","")&IF($J25="","Sin responsable | ","")&IF($K25="","Sin obra | ","")&IF(AND($N25<>"",$G25<>"",$N25>IFERROR(INDEX('MAESTRO DE UNIDADES'!$I$2:$I$208,MATCH($G25,'MAESTRO DE UNIDADES'!$A$2:$A$208,0)),0)),"Litros > tanque | ","")&IF(AND($W25<>"",COUNTIF($W$2:$W25,$W25)>1),"Ticket duplicado | ","")&IF(AND($G25<>"",IFERROR(INDEX('MAESTRO DE UNIDADES'!$L$2:$L$208,MATCH($G25,'MAESTRO DE UNIDADES'!$A$2:$A$208,0)),"")="Inactivo"),"Unidad inactiva | ","")&IF(AND($AA25<>"",$N25=""),"Carga de batán sin litros | ","")&IF(AND($AA25<>"",$AC25<0),"Supera saldo batán | ","")))-3))) | Z25: =IF($B25="","",IF($AA25<>"","Batán","Estación de servicio")) | AB25: =IF($AA25="","",IFERROR(INDEX('CONTROL DE BATAN'!$J$2:$J$301,MATCH($AA25,'CONTROL DE BATAN'!$A$2:$A$301,0)),"")) | AC25: =IF($AA25="","",IFERROR(INDEX('CONTROL DE BATAN'!$I$2:$I$301,MATCH($AA25,'CONTROL DE BATAN'!$A$2:$A$301,0)),0)-SUMIFS($N$2:$N25,$AA$2:$AA25,$AA25))
A26: =IF(B26="","","CARGA-"&TEXT(ROW()-1,"0000")) | C26: =IF(B26="","",CHOOSE(MONTH(B26),"Enero","Febrero","Marzo","Abril","Mayo","Junio","Julio","Agosto","Septiembre","Octubre","Noviembre","Diciembre")) | D26: =IF(B26="","",YEAR(B26)) | E26: =IF(B26="","",CHOOSE(WEEKDAY(B26,2),"Lunes","Martes","Miércoles","Jueves","Viernes","Sábado","Domingo")) | F26: =IF($G26="","",IFERROR(INDEX('MAESTRO DE UNIDADES'!$C$2:$C$208,MATCH($G26,'MAESTRO DE UNIDADES'!$A$2:$A$208,0)),"")) | H26: =IF($G26="","",IFERROR(INDEX('MAESTRO DE UNIDADES'!$F$2:$F$208,MATCH($G26,'MAESTRO DE UNIDADES'!$A$2:$A$208,0)),"")) | I26: =IF($G26="","",IFERROR(INDEX('MAESTRO DE UNIDADES'!$B$2:$B$208,MATCH($G26,'MAESTRO DE UNIDADES'!$A$2:$A$208,0)),"")) | M26: =IF($G26="","",IFERROR(INDEX('MAESTRO DE UNIDADES'!$H$2:$H$208,MATCH($G26,'MAESTRO DE UNIDADES'!$A$2:$A$208,0)),"")) | P26: =IF($N26="","",IF($AA26<>"",IF($AB26="","",$N26*$AB26),IF($O26="","",$N26*$O26))) | S26: =IF(OR($G26="",$Q26="",COUNTIF($G$2:G25,$G26)=0),"",$Q26-LOOKUP(2,1/($G$2:G25=$G26),$Q$2:Q25)) | T26: =IF(OR($G26="",$R26="",COUNTIF($G$2:G25,$G26)=0),"",$R26-LOOKUP(2,1/($G$2:G25=$G26),$R$2:R25)) | U26: =IF(N26="","",IF(S26<>"",S26/N26,IF(T26<>"",T26/N26,""))) | Y26: =IF($B26="","",IF((IF($G26="","Sin unidad | ","")&IF($J26="","Sin responsable | ","")&IF($K26="","Sin obra | ","")&IF(AND($N26<>"",$G26<>"",$N26>IFERROR(INDEX('MAESTRO DE UNIDADES'!$I$2:$I$208,MATCH($G26,'MAESTRO DE UNIDADES'!$A$2:$A$208,0)),0)),"Litros > tanque | ","")&IF(AND($W26<>"",COUNTIF($W$2:$W26,$W26)>1),"Ticket duplicado | ","")&IF(AND($G26<>"",IFERROR(INDEX('MAESTRO DE UNIDADES'!$L$2:$L$208,MATCH($G26,'MAESTRO DE UNIDADES'!$A$2:$A$208,0)),"")="Inactivo"),"Unidad inactiva | ","")&IF(AND($AA26<>"",$N26=""),"Carga de batán sin litros | ","")&IF(AND($AA26<>"",$AC26<0),"Supera saldo batán | ",""))="","OK",LEFT((IF($G26="","Sin unidad | ","")&IF($J26="","Sin responsable | ","")&IF($K26="","Sin obra | ","")&IF(AND($N26<>"",$G26<>"",$N26>IFERROR(INDEX('MAESTRO DE UNIDADES'!$I$2:$I$208,MATCH($G26,'MAESTRO DE UNIDADES'!$A$2:$A$208,0)),0)),"Litros > tanque | ","")&IF(AND($W26<>"",COUNTIF($W$2:$W26,$W26)>1),"Ticket duplicado | ","")&IF(AND($G26<>"",IFERROR(INDEX('MAESTRO DE UNIDADES'!$L$2:$L$208,MATCH($G26,'MAESTRO DE UNIDADES'!$A$2:$A$208,0)),"")="Inactivo"),"Unidad inactiva | ","")&IF(AND($AA26<>"",$N26=""),"Carga de batán sin litros | ","")&IF(AND($AA26<>"",$AC26<0),"Supera saldo batán | ","")),LEN((IF($G26="","Sin unidad | ","")&IF($J26="","Sin responsable | ","")&IF($K26="","Sin obra | ","")&IF(AND($N26<>"",$G26<>"",$N26>IFERROR(INDEX('MAESTRO DE UNIDADES'!$I$2:$I$208,MATCH($G26,'MAESTRO DE UNIDADES'!$A$2:$A$208,0)),0)),"Litros > tanque | ","")&IF(AND($W26<>"",COUNTIF($W$2:$W26,$W26)>1),"Ticket duplicado | ","")&IF(AND($G26<>"",IFERROR(INDEX('MAESTRO DE UNIDADES'!$L$2:$L$208,MATCH($G26,'MAESTRO DE UNIDADES'!$A$2:$A$208,0)),"")="Inactivo"),"Unidad inactiva | ","")&IF(AND($AA26<>"",$N26=""),"Carga de batán sin litros | ","")&IF(AND($AA26<>"",$AC26<0),"Supera saldo batán | ","")))-3))) | Z26: =IF($B26="","",IF($AA26<>"","Batán","Estación de servicio")) | AB26: =IF($AA26="","",IFERROR(INDEX('CONTROL DE BATAN'!$J$2:$J$301,MATCH($AA26,'CONTROL DE BATAN'!$A$2:$A$301,0)),"")) | AC26: =IF($AA26="","",IFERROR(INDEX('CONTROL DE BATAN'!$I$2:$I$301,MATCH($AA26,'CONTROL DE BATAN'!$A$2:$A$301,0)),0)-SUMIFS($N$2:$N26,$AA$2:$AA26,$AA26))
A27: =IF(B27="","","CARGA-"&TEXT(ROW()-1,"0000")) | C27: =IF(B27="","",CHOOSE(MONTH(B27),"Enero","Febrero","Marzo","Abril","Mayo","Junio","Julio","Agosto","Septiembre","Octubre","Noviembre","Diciembre")) | D27: =IF(B27="","",YEAR(B27)) | E27: =IF(B27="","",CHOOSE(WEEKDAY(B27,2),"Lunes","Martes","Miércoles","Jueves","Viernes","Sábado","Domingo")) | F27: =IF($G27="","",IFERROR(INDEX('MAESTRO DE UNIDADES'!$C$2:$C$208,MATCH($G27,'MAESTRO DE UNIDADES'!$A$2:$A$208,0)),"")) | H27: =IF($G27="","",IFERROR(INDEX('MAESTRO DE UNIDADES'!$F$2:$F$208,MATCH($G27,'MAESTRO DE UNIDADES'!$A$2:$A$208,0)),"")) | I27: =IF($G27="","",IFERROR(INDEX('MAESTRO DE UNIDADES'!$B$2:$B$208,MATCH($G27,'MAESTRO DE UNIDADES'!$A$2:$A$208,0)),"")) | M27: =IF($G27="","",IFERROR(INDEX('MAESTRO DE UNIDADES'!$H$2:$H$208,MATCH($G27,'MAESTRO DE UNIDADES'!$A$2:$A$208,0)),"")) | P27: =IF($N27="","",IF($AA27<>"",IF($AB27="","",$N27*$AB27),IF($O27="","",$N27*$O27))) | S27: =IF(OR($G27="",$Q27="",COUNTIF($G$2:G26,$G27)=0),"",$Q27-LOOKUP(2,1/($G$2:G26=$G27),$Q$2:Q26)) | T27: =IF(OR($G27="",$R27="",COUNTIF($G$2:G26,$G27)=0),"",$R27-LOOKUP(2,1/($G$2:G26=$G27),$R$2:R26)) | U27: =IF(N27="","",IF(S27<>"",S27/N27,IF(T27<>"",T27/N27,""))) | Y27: =IF($B27="","",IF((IF($G27="","Sin unidad | ","")&IF($J27="","Sin responsable | ","")&IF($K27="","Sin obra | ","")&IF(AND($N27<>"",$G27<>"",$N27>IFERROR(INDEX('MAESTRO DE UNIDADES'!$I$2:$I$208,MATCH($G27,'MAESTRO DE UNIDADES'!$A$2:$A$208,0)),0)),"Litros > tanque | ","")&IF(AND($W27<>"",COUNTIF($W$2:$W27,$W27)>1),"Ticket duplicado | ","")&IF(AND($G27<>"",IFERROR(INDEX('MAESTRO DE UNIDADES'!$L$2:$L$208,MATCH($G27,'MAESTRO DE UNIDADES'!$A$2:$A$208,0)),"")="Inactivo"),"Unidad inactiva | ","")&IF(AND($AA27<>"",$N27=""),"Carga de batán sin litros | ","")&IF(AND($AA27<>"",$AC27<0),"Supera saldo batán | ",""))="","OK",LEFT((IF($G27="","Sin unidad | ","")&IF($J27="","Sin responsable | ","")&IF($K27="","Sin obra | ","")&IF(AND($N27<>"",$G27<>"",$N27>IFERROR(INDEX('MAESTRO DE UNIDADES'!$I$2:$I$208,MATCH($G27,'MAESTRO DE UNIDADES'!$A$2:$A$208,0)),0)),"Litros > tanque | ","")&IF(AND($W27<>"",COUNTIF($W$2:$W27,$W27)>1),"Ticket duplicado | ","")&IF(AND($G27<>"",IFERROR(INDEX('MAESTRO DE UNIDADES'!$L$2:$L$208,MATCH($G27,'MAESTRO DE UNIDADES'!$A$2:$A$208,0)),"")="Inactivo"),"Unidad inactiva | ","")&IF(AND($AA27<>"",$N27=""),"Carga de batán sin litros | ","")&IF(AND($AA27<>"",$AC27<0),"Supera saldo batán | ","")),LEN((IF($G27="","Sin unidad | ","")&IF($J27="","Sin responsable | ","")&IF($K27="","Sin obra | ","")&IF(AND($N27<>"",$G27<>"",$N27>IFERROR(INDEX('MAESTRO DE UNIDADES'!$I$2:$I$208,MATCH($G27,'MAESTRO DE UNIDADES'!$A$2:$A$208,0)),0)),"Litros > tanque | ","")&IF(AND($W27<>"",COUNTIF($W$2:$W27,$W27)>1),"Ticket duplicado | ","")&IF(AND($G27<>"",IFERROR(INDEX('MAESTRO DE UNIDADES'!$L$2:$L$208,MATCH($G27,'MAESTRO DE UNIDADES'!$A$2:$A$208,0)),"")="Inactivo"),"Unidad inactiva | ","")&IF(AND($AA27<>"",$N27=""),"Carga de batán sin litros | ","")&IF(AND($AA27<>"",$AC27<0),"Supera saldo batán | ","")))-3))) | Z27: =IF($B27="","",IF($AA27<>"","Batán","Estación de servicio")) | AB27: =IF($AA27="","",IFERROR(INDEX('CONTROL DE BATAN'!$J$2:$J$301,MATCH($AA27,'CONTROL DE BATAN'!$A$2:$A$301,0)),"")) | AC27: =IF($AA27="","",IFERROR(INDEX('CONTROL DE BATAN'!$I$2:$I$301,MATCH($AA27,'CONTROL DE BATAN'!$A$2:$A$301,0)),0)-SUMIFS($N$2:$N27,$AA$2:$AA27,$AA27))
A28: =IF(B28="","","CARGA-"&TEXT(ROW()-1,"0000")) | C28: =IF(B28="","",CHOOSE(MONTH(B28),"Enero","Febrero","Marzo","Abril","Mayo","Junio","Julio","Agosto","Septiembre","Octubre","Noviembre","Diciembre")) | D28: =IF(B28="","",YEAR(B28)) | E28: =IF(B28="","",CHOOSE(WEEKDAY(B28,2),"Lunes","Martes","Miércoles","Jueves","Viernes","Sábado","Domingo")) | F28: =IF($G28="","",IFERROR(INDEX('MAESTRO DE UNIDADES'!$C$2:$C$208,MATCH($G28,'MAESTRO DE UNIDADES'!$A$2:$A$208,0)),"")) | H28: =IF($G28="","",IFERROR(INDEX('MAESTRO DE UNIDADES'!$F$2:$F$208,MATCH($G28,'MAESTRO DE UNIDADES'!$A$2:$A$208,0)),"")) | I28: =IF($G28="","",IFERROR(INDEX('MAESTRO DE UNIDADES'!$B$2:$B$208,MATCH($G28,'MAESTRO DE UNIDADES'!$A$2:$A$208,0)),"")) | M28: =IF($G28="","",IFERROR(INDEX('MAESTRO DE UNIDADES'!$H$2:$H$208,MATCH($G28,'MAESTRO DE UNIDADES'!$A$2:$A$208,0)),"")) | P28: =IF($N28="","",IF($AA28<>"",IF($AB28="","",$N28*$AB28),IF($O28="","",$N28*$O28))) | S28: =IF(OR($G28="",$Q28="",COUNTIF($G$2:G27,$G28)=0),"",$Q28-LOOKUP(2,1/($G$2:G27=$G28),$Q$2:Q27)) | T28: =IF(OR($G28="",$R28="",COUNTIF($G$2:G27,$G28)=0),"",$R28-LOOKUP(2,1/($G$2:G27=$G28),$R$2:R27)) | U28: =IF(N28="","",IF(S28<>"",S28/N28,IF(T28<>"",T28/N28,""))) | Y28: =IF($B28="","",IF((IF($G28="","Sin unidad | ","")&IF($J28="","Sin responsable | ","")&IF($K28="","Sin obra | ","")&IF(AND($N28<>"",$G28<>"",$N28>IFERROR(INDEX('MAESTRO DE UNIDADES'!$I$2:$I$208,MATCH($G28,'MAESTRO DE UNIDADES'!$A$2:$A$208,0)),0)),"Litros > tanque | ","")&IF(AND($W28<>"",COUNTIF($W$2:$W28,$W28)>1),"Ticket duplicado | ","")&IF(AND($G28<>"",IFERROR(INDEX('MAESTRO DE UNIDADES'!$L$2:$L$208,MATCH($G28,'MAESTRO DE UNIDADES'!$A$2:$A$208,0)),"")="Inactivo"),"Unidad inactiva | ","")&IF(AND($AA28<>"",$N28=""),"Carga de batán sin litros | ","")&IF(AND($AA28<>"",$AC28<0),"Supera saldo batán | ",""))="","OK",LEFT((IF($G28="","Sin unidad | ","")&IF($J28="","Sin responsable | ","")&IF($K28="","Sin obra | ","")&IF(AND($N28<>"",$G28<>"",$N28>IFERROR(INDEX('MAESTRO DE UNIDADES'!$I$2:$I$208,MATCH($G28,'MAESTRO DE UNIDADES'!$A$2:$A$208,0)),0)),"Litros > tanque | ","")&IF(AND($W28<>"",COUNTIF($W$2:$W28,$W28)>1),"Ticket duplicado | ","")&IF(AND($G28<>"",IFERROR(INDEX('MAESTRO DE UNIDADES'!$L$2:$L$208,MATCH($G28,'MAESTRO DE UNIDADES'!$A$2:$A$208,0)),"")="Inactivo"),"Unidad inactiva | ","")&IF(AND($AA28<>"",$N28=""),"Carga de batán sin litros | ","")&IF(AND($AA28<>"",$AC28<0),"Supera saldo batán | ","")),LEN((IF($G28="","Sin unidad | ","")&IF($J28="","Sin responsable | ","")&IF($K28="","Sin obra | ","")&IF(AND($N28<>"",$G28<>"",$N28>IFERROR(INDEX('MAESTRO DE UNIDADES'!$I$2:$I$208,MATCH($G28,'MAESTRO DE UNIDADES'!$A$2:$A$208,0)),0)),"Litros > tanque | ","")&IF(AND($W28<>"",COUNTIF($W$2:$W28,$W28)>1),"Ticket duplicado | ","")&IF(AND($G28<>"",IFERROR(INDEX('MAESTRO DE UNIDADES'!$L$2:$L$208,MATCH($G28,'MAESTRO DE UNIDADES'!$A$2:$A$208,0)),"")="Inactivo"),"Unidad inactiva | ","")&IF(AND($AA28<>"",$N28=""),"Carga de batán sin litros | ","")&IF(AND($AA28<>"",$AC28<0),"Supera saldo batán | ","")))-3))) | Z28: =IF($B28="","",IF($AA28<>"","Batán","Estación de servicio")) | AB28: =IF($AA28="","",IFERROR(INDEX('CONTROL DE BATAN'!$J$2:$J$301,MATCH($AA28,'CONTROL DE BATAN'!$A$2:$A$301,0)),"")) | AC28: =IF($AA28="","",IFERROR(INDEX('CONTROL DE BATAN'!$I$2:$I$301,MATCH($AA28,'CONTROL DE BATAN'!$A$2:$A$301,0)),0)-SUMIFS($N$2:$N28,$AA$2:$AA28,$AA28))
A29: =IF(B29="","","CARGA-"&TEXT(ROW()-1,"0000")) | C29: =IF(B29="","",CHOOSE(MONTH(B29),"Enero","Febrero","Marzo","Abril","Mayo","Junio","Julio","Agosto","Septiembre","Octubre","Noviembre","Diciembre")) | D29: =IF(B29="","",YEAR(B29)) | E29: =IF(B29="","",CHOOSE(WEEKDAY(B29,2),"Lunes","Martes","Miércoles","Jueves","Viernes","Sábado","Domingo")) | F29: =IF($G29="","",IFERROR(INDEX('MAESTRO DE UNIDADES'!$C$2:$C$208,MATCH($G29,'MAESTRO DE UNIDADES'!$A$2:$A$208,0)),"")) | H29: =IF($G29="","",IFERROR(INDEX('MAESTRO DE UNIDADES'!$F$2:$F$208,MATCH($G29,'MAESTRO DE UNIDADES'!$A$2:$A$208,0)),"")) | I29: =IF($G29="","",IFERROR(INDEX('MAESTRO DE UNIDADES'!$B$2:$B$208,MATCH($G29,'MAESTRO DE UNIDADES'!$A$2:$A$208,0)),"")) | M29: =IF($G29="","",IFERROR(INDEX('MAESTRO DE UNIDADES'!$H$2:$H$208,MATCH($G29,'MAESTRO DE UNIDADES'!$A$2:$A$208,0)),"")) | P29: =IF($N29="","",IF($AA29<>"",IF($AB29="","",$N29*$AB29),IF($O29="","",$N29*$O29))) | S29: =IF(OR($G29="",$Q29="",COUNTIF($G$2:G28,$G29)=0),"",$Q29-LOOKUP(2,1/($G$2:G28=$G29),$Q$2:Q28)) | T29: =IF(OR($G29="",$R29="",COUNTIF($G$2:G28,$G29)=0),"",$R29-LOOKUP(2,1/($G$2:G28=$G29),$R$2:R28)) | U29: =IF(N29="","",IF(S29<>"",S29/N29,IF(T29<>"",T29/N29,""))) | Y29: =IF($B29="","",IF((IF($G29="","Sin unidad | ","")&IF($J29="","Sin responsable | ","")&IF($K29="","Sin obra | ","")&IF(AND($N29<>"",$G29<>"",$N29>IFERROR(INDEX('MAESTRO DE UNIDADES'!$I$2:$I$208,MATCH($G29,'MAESTRO DE UNIDADES'!$A$2:$A$208,0)),0)),"Litros > tanque | ","")&IF(AND($W29<>"",COUNTIF($W$2:$W29,$W29)>1),"Ticket duplicado | ","")&IF(AND($G29<>"",IFERROR(INDEX('MAESTRO DE UNIDADES'!$L$2:$L$208,MATCH($G29,'MAESTRO DE UNIDADES'!$A$2:$A$208,0)),"")="Inactivo"),"Unidad inactiva | ","")&IF(AND($AA29<>"",$N29=""),"Carga de batán sin litros | ","")&IF(AND($AA29<>"",$AC29<0),"Supera saldo batán | ",""))="","OK",LEFT((IF($G29="","Sin unidad | ","")&IF($J29="","Sin responsable | ","")&IF($K29="","Sin obra | ","")&IF(AND($N29<>"",$G29<>"",$N29>IFERROR(INDEX('MAESTRO DE UNIDADES'!$I$2:$I$208,MATCH($G29,'MAESTRO DE UNIDADES'!$A$2:$A$208,0)),0)),"Litros > tanque | ","")&IF(AND($W29<>"",COUNTIF($W$2:$W29,$W29)>1),"Ticket duplicado | ","")&IF(AND($G29<>"",IFERROR(INDEX('MAESTRO DE UNIDADES'!$L$2:$L$208,MATCH($G29,'MAESTRO DE UNIDADES'!$A$2:$A$208,0)),"")="Inactivo"),"Unidad inactiva | ","")&IF(AND($AA29<>"",$N29=""),"Carga de batán sin litros | ","")&IF(AND($AA29<>"",$AC29<0),"Supera saldo batán | ","")),LEN((IF($G29="","Sin unidad | ","")&IF($J29="","Sin responsable | ","")&IF($K29="","Sin obra | ","")&IF(AND($N29<>"",$G29<>"",$N29>IFERROR(INDEX('MAESTRO DE UNIDADES'!$I$2:$I$208,MATCH($G29,'MAESTRO DE UNIDADES'!$A$2:$A$208,0)),0)),"Litros > tanque | ","")&IF(AND($W29<>"",COUNTIF($W$2:$W29,$W29)>1),"Ticket duplicado | ","")&IF(AND($G29<>"",IFERROR(INDEX('MAESTRO DE UNIDADES'!$L$2:$L$208,MATCH($G29,'MAESTRO DE UNIDADES'!$A$2:$A$208,0)),"")="Inactivo"),"Unidad inactiva | ","")&IF(AND($AA29<>"",$N29=""),"Carga de batán sin litros | ","")&IF(AND($AA29<>"",$AC29<0),"Supera saldo batán | ","")))-3))) | Z29: =IF($B29="","",IF($AA29<>"","Batán","Estación de servicio")) | AB29: =IF($AA29="","",IFERROR(INDEX('CONTROL DE BATAN'!$J$2:$J$301,MATCH($AA29,'CONTROL DE BATAN'!$A$2:$A$301,0)),"")) | AC29: =IF($AA29="","",IFERROR(INDEX('CONTROL DE BATAN'!$I$2:$I$301,MATCH($AA29,'CONTROL DE BATAN'!$A$2:$A$301,0)),0)-SUMIFS($N$2:$N29,$AA$2:$AA29,$AA29))
A30: =IF(B30="","","CARGA-"&TEXT(ROW()-1,"0000")) | C30: =IF(B30="","",CHOOSE(MONTH(B30),"Enero","Febrero","Marzo","Abril","Mayo","Junio","Julio","Agosto","Septiembre","Octubre","Noviembre","Diciembre")) | D30: =IF(B30="","",YEAR(B30)) | E30: =IF(B30="","",CHOOSE(WEEKDAY(B30,2),"Lunes","Martes","Miércoles","Jueves","Viernes","Sábado","Domingo")) | F30: =IF($G30="","",IFERROR(INDEX('MAESTRO DE UNIDADES'!$C$2:$C$208,MATCH($G30,'MAESTRO DE UNIDADES'!$A$2:$A$208,0)),"")) | H30: =IF($G30="","",IFERROR(INDEX('MAESTRO DE UNIDADES'!$F$2:$F$208,MATCH($G30,'MAESTRO DE UNIDADES'!$A$2:$A$208,0)),"")) | I30: =IF($G30="","",IFERROR(INDEX('MAESTRO DE UNIDADES'!$B$2:$B$208,MATCH($G30,'MAESTRO DE UNIDADES'!$A$2:$A$208,0)),"")) | M30: =IF($G30="","",IFERROR(INDEX('MAESTRO DE UNIDADES'!$H$2:$H$208,MATCH($G30,'MAESTRO DE UNIDADES'!$A$2:$A$208,0)),"")) | P30: =IF($N30="","",IF($AA30<>"",IF($AB30="","",$N30*$AB30),IF($O30="","",$N30*$O30))) | S30: =IF(OR($G30="",$Q30="",COUNTIF($G$2:G29,$G30)=0),"",$Q30-LOOKUP(2,1/($G$2:G29=$G30),$Q$2:Q29)) | T30: =IF(OR($G30="",$R30="",COUNTIF($G$2:G29,$G30)=0),"",$R30-LOOKUP(2,1/($G$2:G29=$G30),$R$2:R29)) | U30: =IF(N30="","",IF(S30<>"",S30/N30,IF(T30<>"",T30/N30,""))) | Y30: =IF($B30="","",IF((IF($G30="","Sin unidad | ","")&IF($J30="","Sin responsable | ","")&IF($K30="","Sin obra | ","")&IF(AND($N30<>"",$G30<>"",$N30>IFERROR(INDEX('MAESTRO DE UNIDADES'!$I$2:$I$208,MATCH($G30,'MAESTRO DE UNIDADES'!$A$2:$A$208,0)),0)),"Litros > tanque | ","")&IF(AND($W30<>"",COUNTIF($W$2:$W30,$W30)>1),"Ticket duplicado | ","")&IF(AND($G30<>"",IFERROR(INDEX('MAESTRO DE UNIDADES'!$L$2:$L$208,MATCH($G30,'MAESTRO DE UNIDADES'!$A$2:$A$208,0)),"")="Inactivo"),"Unidad inactiva | ","")&IF(AND($AA30<>"",$N30=""),"Carga de batán sin litros | ","")&IF(AND($AA30<>"",$AC30<0),"Supera saldo batán | ",""))="","OK",LEFT((IF($G30="","Sin unidad | ","")&IF($J30="","Sin responsable | ","")&IF($K30="","Sin obra | ","")&IF(AND($N30<>"",$G30<>"",$N30>IFERROR(INDEX('MAESTRO DE UNIDADES'!$I$2:$I$208,MATCH($G30,'MAESTRO DE UNIDADES'!$A$2:$A$208,0)),0)),"Litros > tanque | ","")&IF(AND($W30<>"",COUNTIF($W$2:$W30,$W30)>1),"Ticket duplicado | ","")&IF(AND($G30<>"",IFERROR(INDEX('MAESTRO DE UNIDADES'!$L$2:$L$208,MATCH($G30,'MAESTRO DE UNIDADES'!$A$2:$A$208,0)),"")="Inactivo"),"Unidad inactiva | ","")&IF(AND($AA30<>"",$N30=""),"Carga de batán sin litros | ","")&IF(AND($AA30<>"",$AC30<0),"Supera saldo batán | ","")),LEN((IF($G30="","Sin unidad | ","")&IF($J30="","Sin responsable | ","")&IF($K30="","Sin obra | ","")&IF(AND($N30<>"",$G30<>"",$N30>IFERROR(INDEX('MAESTRO DE UNIDADES'!$I$2:$I$208,MATCH($G30,'MAESTRO DE UNIDADES'!$A$2:$A$208,0)),0)),"Litros > tanque | ","")&IF(AND($W30<>"",COUNTIF($W$2:$W30,$W30)>1),"Ticket duplicado | ","")&IF(AND($G30<>"",IFERROR(INDEX('MAESTRO DE UNIDADES'!$L$2:$L$208,MATCH($G30,'MAESTRO DE UNIDADES'!$A$2:$A$208,0)),"")="Inactivo"),"Unidad inactiva | ","")&IF(AND($AA30<>"",$N30=""),"Carga de batán sin litros | ","")&IF(AND($AA30<>"",$AC30<0),"Supera saldo batán | ","")))-3))) | Z30: =IF($B30="","",IF($AA30<>"","Batán","Estación de servicio")) | AB30: =IF($AA30="","",IFERROR(INDEX('CONTROL DE BATAN'!$J$2:$J$301,MATCH($AA30,'CONTROL DE BATAN'!$A$2:$A$301,0)),"")) | AC30: =IF($AA30="","",IFERROR(INDEX('CONTROL DE BATAN'!$I$2:$I$301,MATCH($AA30,'CONTROL DE BATAN'!$A$2:$A$301,0)),0)-SUMIFS($N$2:$N30,$AA$2:$AA30,$AA30))
A31: =IF(B31="","","CARGA-"&TEXT(ROW()-1,"0000")) | C31: =IF(B31="","",CHOOSE(MONTH(B31),"Enero","Febrero","Marzo","Abril","Mayo","Junio","Julio","Agosto","Septiembre","Octubre","Noviembre","Diciembre")) | D31: =IF(B31="","",YEAR(B31)) | E31: =IF(B31="","",CHOOSE(WEEKDAY(B31,2),"Lunes","Martes","Miércoles","Jueves","Viernes","Sábado","Domingo")) | F31: =IF($G31="","",IFERROR(INDEX('MAESTRO DE UNIDADES'!$C$2:$C$208,MATCH($G31,'MAESTRO DE UNIDADES'!$A$2:$A$208,0)),"")) | H31: =IF($G31="","",IFERROR(INDEX('MAESTRO DE UNIDADES'!$F$2:$F$208,MATCH($G31,'MAESTRO DE UNIDADES'!$A$2:$A$208,0)),"")) | I31: =IF($G31="","",IFERROR(INDEX('MAESTRO DE UNIDADES'!$B$2:$B$208,MATCH($G31,'MAESTRO DE UNIDADES'!$A$2:$A$208,0)),"")) | M31: =IF($G31="","",IFERROR(INDEX('MAESTRO DE UNIDADES'!$H$2:$H$208,MATCH($G31,'MAESTRO DE UNIDADES'!$A$2:$A$208,0)),"")) | P31: =IF($N31="","",IF($AA31<>"",IF($AB31="","",$N31*$AB31),IF($O31="","",$N31*$O31))) | S31: =IF(OR($G31="",$Q31="",COUNTIF($G$2:G30,$G31)=0),"",$Q31-LOOKUP(2,1/($G$2:G30=$G31),$Q$2:Q30)) | T31: =IF(OR($G31="",$R31="",COUNTIF($G$2:G30,$G31)=0),"",$R31-LOOKUP(2,1/($G$2:G30=$G31),$R$2:R30)) | U31: =IF(N31="","",IF(S31<>"",S31/N31,IF(T31<>"",T31/N31,""))) | Y31: =IF($B31="","",IF((IF($G31="","Sin unidad | ","")&IF($J31="","Sin responsable | ","")&IF($K31="","Sin obra | ","")&IF(AND($N31<>"",$G31<>"",$N31>IFERROR(INDEX('MAESTRO DE UNIDADES'!$I$2:$I$208,MATCH($G31,'MAESTRO DE UNIDADES'!$A$2:$A$208,0)),0)),"Litros > tanque | ","")&IF(AND($W31<>"",COUNTIF($W$2:$W31,$W31)>1),"Ticket duplicado | ","")&IF(AND($G31<>"",IFERROR(INDEX('MAESTRO DE UNIDADES'!$L$2:$L$208,MATCH($G31,'MAESTRO DE UNIDADES'!$A$2:$A$208,0)),"")="Inactivo"),"Unidad inactiva | ","")&IF(AND($AA31<>"",$N31=""),"Carga de batán sin litros | ","")&IF(AND($AA31<>"",$AC31<0),"Supera saldo batán | ",""))="","OK",LEFT((IF($G31="","Sin unidad | ","")&IF($J31="","Sin responsable | ","")&IF($K31="","Sin obra | ","")&IF(AND($N31<>"",$G31<>"",$N31>IFERROR(INDEX('MAESTRO DE UNIDADES'!$I$2:$I$208,MATCH($G31,'MAESTRO DE UNIDADES'!$A$2:$A$208,0)),0)),"Litros > tanque | ","")&IF(AND($W31<>"",COUNTIF($W$2:$W31,$W31)>1),"Ticket duplicado | ","")&IF(AND($G31<>"",IFERROR(INDEX('MAESTRO DE UNIDADES'!$L$2:$L$208,MATCH($G31,'MAESTRO DE UNIDADES'!$A$2:$A$208,0)),"")="Inactivo"),"Unidad inactiva | ","")&IF(AND($AA31<>"",$N31=""),"Carga de batán sin litros | ","")&IF(AND($AA31<>"",$AC31<0),"Supera saldo batán | ","")),LEN((IF($G31="","Sin unidad | ","")&IF($J31="","Sin responsable | ","")&IF($K31="","Sin obra | ","")&IF(AND($N31<>"",$G31<>"",$N31>IFERROR(INDEX('MAESTRO DE UNIDADES'!$I$2:$I$208,MATCH($G31,'MAESTRO DE UNIDADES'!$A$2:$A$208,0)),0)),"Litros > tanque | ","")&IF(AND($W31<>"",COUNTIF($W$2:$W31,$W31)>1),"Ticket duplicado | ","")&IF(AND($G31<>"",IFERROR(INDEX('MAESTRO DE UNIDADES'!$L$2:$L$208,MATCH($G31,'MAESTRO DE UNIDADES'!$A$2:$A$208,0)),"")="Inactivo"),"Unidad inactiva | ","")&IF(AND($AA31<>"",$N31=""),"Carga de batán sin litros | ","")&IF(AND($AA31<>"",$AC31<0),"Supera saldo batán | ","")))-3))) | Z31: =IF($B31="","",IF($AA31<>"","Batán","Estación de servicio")) | AB31: =IF($AA31="","",IFERROR(INDEX('CONTROL DE BATAN'!$J$2:$J$301,MATCH($AA31,'CONTROL DE BATAN'!$A$2:$A$301,0)),"")) | AC31: =IF($AA31="","",IFERROR(INDEX('CONTROL DE BATAN'!$I$2:$I$301,MATCH($AA31,'CONTROL DE BATAN'!$A$2:$A$301,0)),0)-SUMIFS($N$2:$N31,$AA$2:$AA31,$AA31))
A32: =IF(B32="","","CARGA-"&TEXT(ROW()-1,"0000")) | C32: =IF(B32="","",CHOOSE(MONTH(B32),"Enero","Febrero","Marzo","Abril","Mayo","Junio","Julio","Agosto","Septiembre","Octubre","Noviembre","Diciembre")) | D32: =IF(B32="","",YEAR(B32)) | E32: =IF(B32="","",CHOOSE(WEEKDAY(B32,2),"Lunes","Martes","Miércoles","Jueves","Viernes","Sábado","Domingo")) | F32: =IF($G32="","",IFERROR(INDEX('MAESTRO DE UNIDADES'!$C$2:$C$208,MATCH($G32,'MAESTRO DE UNIDADES'!$A$2:$A$208,0)),"")) | H32: =IF($G32="","",IFERROR(INDEX('MAESTRO DE UNIDADES'!$F$2:$F$208,MATCH($G32,'MAESTRO DE UNIDADES'!$A$2:$A$208,0)),"")) | I32: =IF($G32="","",IFERROR(INDEX('MAESTRO DE UNIDADES'!$B$2:$B$208,MATCH($G32,'MAESTRO DE UNIDADES'!$A$2:$A$208,0)),"")) | M32: =IF($G32="","",IFERROR(INDEX('MAESTRO DE UNIDADES'!$H$2:$H$208,MATCH($G32,'MAESTRO DE UNIDADES'!$A$2:$A$208,0)),"")) | P32: =IF($N32="","",IF($AA32<>"",IF($AB32="","",$N32*$AB32),IF($O32="","",$N32*$O32))) | S32: =IF(OR($G32="",$Q32="",COUNTIF($G$2:G31,$G32)=0),"",$Q32-LOOKUP(2,1/($G$2:G31=$G32),$Q$2:Q31)) | T32: =IF(OR($G32="",$R32="",COUNTIF($G$2:G31,$G32)=0),"",$R32-LOOKUP(2,1/($G$2:G31=$G32),$R$2:R31)) | U32: =IF(N32="","",IF(S32<>"",S32/N32,IF(T32<>"",T32/N32,""))) | Y32: =IF($B32="","",IF((IF($G32="","Sin unidad | ","")&IF($J32="","Sin responsable | ","")&IF($K32="","Sin obra | ","")&IF(AND($N32<>"",$G32<>"",$N32>IFERROR(INDEX('MAESTRO DE UNIDADES'!$I$2:$I$208,MATCH($G32,'MAESTRO DE UNIDADES'!$A$2:$A$208,0)),0)),"Litros > tanque | ","")&IF(AND($W32<>"",COUNTIF($W$2:$W32,$W32)>1),"Ticket duplicado | ","")&IF(AND($G32<>"",IFERROR(INDEX('MAESTRO DE UNIDADES'!$L$2:$L$208,MATCH($G32,'MAESTRO DE UNIDADES'!$A$2:$A$208,0)),"")="Inactivo"),"Unidad inactiva | ","")&IF(AND($AA32<>"",$N32=""),"Carga de batán sin litros | ","")&IF(AND($AA32<>"",$AC32<0),"Supera saldo batán | ",""))="","OK",LEFT((IF($G32="","Sin unidad | ","")&IF($J32="","Sin responsable | ","")&IF($K32="","Sin obra | ","")&IF(AND($N32<>"",$G32<>"",$N32>IFERROR(INDEX('MAESTRO DE UNIDADES'!$I$2:$I$208,MATCH($G32,'MAESTRO DE UNIDADES'!$A$2:$A$208,0)),0)),"Litros > tanque | ","")&IF(AND($W32<>"",COUNTIF($W$2:$W32,$W32)>1),"Ticket duplicado | ","")&IF(AND($G32<>"",IFERROR(INDEX('MAESTRO DE UNIDADES'!$L$2:$L$208,MATCH($G32,'MAESTRO DE UNIDADES'!$A$2:$A$208,0)),"")="Inactivo"),"Unidad inactiva | ","")&IF(AND($AA32<>"",$N32=""),"Carga de batán sin litros | ","")&IF(AND($AA32<>"",$AC32<0),"Supera saldo batán | ","")),LEN((IF($G32="","Sin unidad | ","")&IF($J32="","Sin responsable | ","")&IF($K32="","Sin obra | ","")&IF(AND($N32<>"",$G32<>"",$N32>IFERROR(INDEX('MAESTRO DE UNIDADES'!$I$2:$I$208,MATCH($G32,'MAESTRO DE UNIDADES'!$A$2:$A$208,0)),0)),"Litros > tanque | ","")&IF(AND($W32<>"",COUNTIF($W$2:$W32,$W32)>1),"Ticket duplicado | ","")&IF(AND($G32<>"",IFERROR(INDEX('MAESTRO DE UNIDADES'!$L$2:$L$208,MATCH($G32,'MAESTRO DE UNIDADES'!$A$2:$A$208,0)),"")="Inactivo"),"Unidad inactiva | ","")&IF(AND($AA32<>"",$N32=""),"Carga de batán sin litros | ","")&IF(AND($AA32<>"",$AC32<0),"Supera saldo batán | ","")))-3))) | Z32: =IF($B32="","",IF($AA32<>"","Batán","Estación de servicio")) | AB32: =IF($AA32="","",IFERROR(INDEX('CONTROL DE BATAN'!$J$2:$J$301,MATCH($AA32,'CONTROL DE BATAN'!$A$2:$A$301,0)),"")) | AC32: =IF($AA32="","",IFERROR(INDEX('CONTROL DE BATAN'!$I$2:$I$301,MATCH($AA32,'CONTROL DE BATAN'!$A$2:$A$301,0)),0)-SUMIFS($N$2:$N32,$AA$2:$AA32,$AA32))
A33: =IF(B33="","","CARGA-"&TEXT(ROW()-1,"0000")) | C33: =IF(B33="","",CHOOSE(MONTH(B33),"Enero","Febrero","Marzo","Abril","Mayo","Junio","Julio","Agosto","Septiembre","Octubre","Noviembre","Diciembre")) | D33: =IF(B33="","",YEAR(B33)) | E33: =IF(B33="","",CHOOSE(WEEKDAY(B33,2),"Lunes","Martes","Miércoles","Jueves","Viernes","Sábado","Domingo")) | F33: =IF($G33="","",IFERROR(INDEX('MAESTRO DE UNIDADES'!$C$2:$C$208,MATCH($G33,'MAESTRO DE UNIDADES'!$A$2:$A$208,0)),"")) | H33: =IF($G33="","",IFERROR(INDEX('MAESTRO DE UNIDADES'!$F$2:$F$208,MATCH($G33,'MAESTRO DE UNIDADES'!$A$2:$A$208,0)),"")) | I33: =IF($G33="","",IFERROR(INDEX('MAESTRO DE UNIDADES'!$B$2:$B$208,MATCH($G33,'MAESTRO DE UNIDADES'!$A$2:$A$208,0)),"")) | M33: =IF($G33="","",IFERROR(INDEX('MAESTRO DE UNIDADES'!$H$2:$H$208,MATCH($G33,'MAESTRO DE UNIDADES'!$A$2:$A$208,0)),"")) | P33: =IF($N33="","",IF($AA33<>"",IF($AB33="","",$N33*$AB33),IF($O33="","",$N33*$O33))) | S33: =IF(OR($G33="",$Q33="",COUNTIF($G$2:G32,$G33)=0),"",$Q33-LOOKUP(2,1/($G$2:G32=$G33),$Q$2:Q32)) | T33: =IF(OR($G33="",$R33="",COUNTIF($G$2:G32,$G33)=0),"",$R33-LOOKUP(2,1/($G$2:G32=$G33),$R$2:R32)) | U33: =IF(N33="","",IF(S33<>"",S33/N33,IF(T33<>"",T33/N33,""))) | Y33: =IF($B33="","",IF((IF($G33="","Sin unidad | ","")&IF($J33="","Sin responsable | ","")&IF($K33="","Sin obra | ","")&IF(AND($N33<>"",$G33<>"",$N33>IFERROR(INDEX('MAESTRO DE UNIDADES'!$I$2:$I$208,MATCH($G33,'MAESTRO DE UNIDADES'!$A$2:$A$208,0)),0)),"Litros > tanque | ","")&IF(AND($W33<>"",COUNTIF($W$2:$W33,$W33)>1),"Ticket duplicado | ","")&IF(AND($G33<>"",IFERROR(INDEX('MAESTRO DE UNIDADES'!$L$2:$L$208,MATCH($G33,'MAESTRO DE UNIDADES'!$A$2:$A$208,0)),"")="Inactivo"),"Unidad inactiva | ","")&IF(AND($AA33<>"",$N33=""),"Carga de batán sin litros | ","")&IF(AND($AA33<>"",$AC33<0),"Supera saldo batán | ",""))="","OK",LEFT((IF($G33="","Sin unidad | ","")&IF($J33="","Sin responsable | ","")&IF($K33="","Sin obra | ","")&IF(AND($N33<>"",$G33<>"",$N33>IFERROR(INDEX('MAESTRO DE UNIDADES'!$I$2:$I$208,MATCH($G33,'MAESTRO DE UNIDADES'!$A$2:$A$208,0)),0)),"Litros > tanque | ","")&IF(AND($W33<>"",COUNTIF($W$2:$W33,$W33)>1),"Ticket duplicado | ","")&IF(AND($G33<>"",IFERROR(INDEX('MAESTRO DE UNIDADES'!$L$2:$L$208,MATCH($G33,'MAESTRO DE UNIDADES'!$A$2:$A$208,0)),"")="Inactivo"),"Unidad inactiva | ","")&IF(AND($AA33<>"",$N33=""),"Carga de batán sin litros | ","")&IF(AND($AA33<>"",$AC33<0),"Supera saldo batán | ","")),LEN((IF($G33="","Sin unidad | ","")&IF($J33="","Sin responsable | ","")&IF($K33="","Sin obra | ","")&IF(AND($N33<>"",$G33<>"",$N33>IFERROR(INDEX('MAESTRO DE UNIDADES'!$I$2:$I$208,MATCH($G33,'MAESTRO DE UNIDADES'!$A$2:$A$208,0)),0)),"Litros > tanque | ","")&IF(AND($W33<>"",COUNTIF($W$2:$W33,$W33)>1),"Ticket duplicado | ","")&IF(AND($G33<>"",IFERROR(INDEX('MAESTRO DE UNIDADES'!$L$2:$L$208,MATCH($G33,'MAESTRO DE UNIDADES'!$A$2:$A$208,0)),"")="Inactivo"),"Unidad inactiva | ","")&IF(AND($AA33<>"",$N33=""),"Carga de batán sin litros | ","")&IF(AND($AA33<>"",$AC33<0),"Supera saldo batán | ","")))-3))) | Z33: =IF($B33="","",IF($AA33<>"","Batán","Estación de servicio")) | AB33: =IF($AA33="","",IFERROR(INDEX('CONTROL DE BATAN'!$J$2:$J$301,MATCH($AA33,'CONTROL DE BATAN'!$A$2:$A$301,0)),"")) | AC33: =IF($AA33="","",IFERROR(INDEX('CONTROL DE BATAN'!$I$2:$I$301,MATCH($AA33,'CONTROL DE BATAN'!$A$2:$A$301,0)),0)-SUMIFS($N$2:$N33,$AA$2:$AA33,$AA33))
... A301: =IF(B301="","","CARGA-"&TEXT(ROW()-1,"0000")) | C301: =IF(B301="","",CHOOSE(MONTH(B301),"Enero","Febrero","Marzo","Abril","Mayo","Junio","Julio","Agosto","Septiembre","Octubre","Noviembre","Diciembre")) | D301: =IF(B301="","",YEAR(B301)) | E301: =IF(B301="","",CHOOSE(WEEKDAY(B301,2),"Lunes","Martes","Miércoles","Jueves","Viernes","Sábado","Domingo")) | F301: =IF($G301="","",IFERROR(INDEX('MAESTRO DE UNIDADES'!$C$2:$C$208,MATCH($G301,'MAESTRO DE UNIDADES'!$A$2:$A$208,0)),"")) | H301: =IF($G301="","",IFERROR(INDEX('MAESTRO DE UNIDADES'!$F$2:$F$208,MATCH($G301,'MAESTRO DE UNIDADES'!$A$2:$A$208,0)),"")) | I301: =IF($G301="","",IFERROR(INDEX('MAESTRO DE UNIDADES'!$B$2:$B$208,MATCH($G301,'MAESTRO DE UNIDADES'!$A$2:$A$208,0)),"")) | M301: =IF($G301="","",IFERROR(INDEX('MAESTRO DE UNIDADES'!$H$2:$H$208,MATCH($G301,'MAESTRO DE UNIDADES'!$A$2:$A$208,0)),"")) | P301: =IF($N301="","",IF($AA301<>"",IF($AB301="","",$N301*$AB301),IF($O301="","",$N301*$O301))) | S301: =IF(OR($G301="",$Q301="",COUNTIF($G$2:G300,$G301)=0),"",$Q301-LOOKUP(2,1/($G$2:G300=$G301),$Q$2:Q300)) | T301: =IF(OR($G301="",$R301="",COUNTIF($G$2:G300,$G301)=0),"",$R301-LOOKUP(2,1/($G$2:G300=$G301),$R$2:R300)) | U301: =IF(N301="","",IF(S301<>"",S301/N301,IF(T301<>"",T301/N301,""))) | Y301: =IF($B301="","",IF((IF($G301="","Sin unidad | ","")&IF($J301="","Sin responsable | ","")&IF($K301="","Sin obra | ","")&IF(AND($N301<>"",$G301<>"",$N301>IFERROR(INDEX('MAESTRO DE UNIDADES'!$I$2:$I$208,MATCH($G301,'MAESTRO DE UNIDADES'!$A$2:$A$208,0)),0)),"Litros > tanque | ","")&IF(AND($W301<>"",COUNTIF($W$2:$W301,$W301)>1),"Ticket duplicado | ","")&IF(AND($G301<>"",IFERROR(INDEX('MAESTRO DE UNIDADES'!$L$2:$L$208,MATCH($G301,'MAESTRO DE UNIDADES'!$A$2:$A$208,0)),"")="Inactivo"),"Unidad inactiva | ","")&IF(AND($AA301<>"",$N301=""),"Carga de batán sin litros | ","")&IF(AND($AA301<>"",$AC301<0),"Supera saldo batán | ",""))="","OK",LEFT((IF($G301="","Sin unidad | ","")&IF($J301="","Sin responsable | ","")&IF($K301="","Sin obra | ","")&IF(AND($N301<>"",$G301<>"",$N301>IFERROR(INDEX('MAESTRO DE UNIDADES'!$I$2:$I$208,MATCH($G301,'MAESTRO DE UNIDADES'!$A$2:$A$208,0)),0)),"Litros > tanque | ","")&IF(AND($W301<>"",COUNTIF($W$2:$W301,$W301)>1),"Ticket duplicado | ","")&IF(AND($G301<>"",IFERROR(INDEX('MAESTRO DE UNIDADES'!$L$2:$L$208,MATCH($G301,'MAESTRO DE UNIDADES'!$A$2:$A$208,0)),"")="Inactivo"),"Unidad inactiva | ","")&IF(AND($AA301<>"",$N301=""),"Carga de batán sin litros | ","")&IF(AND($AA301<>"",$AC301<0),"Supera saldo batán | ","")),LEN((IF($G301="","Sin unidad | ","")&IF($J301="","Sin responsable | ","")&IF($K301="","Sin obra | ","")&IF(AND($N301<>"",$G301<>"",$N301>IFERROR(INDEX('MAESTRO DE UNIDADES'!$I$2:$I$208,MATCH($G301,'MAESTRO DE UNIDADES'!$A$2:$A$208,0)),0)),"Litros > tanque | ","")&IF(AND($W301<>"",COUNTIF($W$2:$W301,$W301)>1),"Ticket duplicado | ","")&IF(AND($G301<>"",IFERROR(INDEX('MAESTRO DE UNIDADES'!$L$2:$L$208,MATCH($G301,'MAESTRO DE UNIDADES'!$A$2:$A$208,0)),"")="Inactivo"),"Unidad inactiva | ","")&IF(AND($AA301<>"",$N301=""),"Carga de batán sin litros | ","")&IF(AND($AA301<>"",$AC301<0),"Supera saldo batán | ","")))-3))) | Z301: =IF($B301="","",IF($AA301<>"","Batán","Estación de servicio")) | AB301: =IF($AA301="","",IFERROR(INDEX('CONTROL DE BATAN'!$J$2:$J$301,MATCH($AA301,'CONTROL DE BATAN'!$A$2:$A$301,0)),"")) | AC301: =IF($AA301="","",IFERROR(INDEX('CONTROL DE BATAN'!$I$2:$I$301,MATCH($AA301,'CONTROL DE BATAN'!$A$2:$A$301,0)),0)-SUMIFS($N$2:$N301,$AA$2:$AA301,$AA301))

Sheet CONTROL DE BATAN
A1: ID de carga batán | B1: Fecha | C1: Mes | D1: Año | E1: Batán / depósito | F1: Capacidad (L) | G1: Proveedor / estación | H1: Tipo de combustible | I1: Litros cargados al batán | J1: Precio por litro | K1: Importe total | L1: N° remito estación | M1: N° vale empresa | N1: Responsable | O1: Obra / centro de costo | P1: Litros descargados a equipos | Q1: Saldo del movimiento | R1: Estado del movimiento | S1: Observaciones
A2: =IF(B2="","","BATAN-"&TEXT(ROW()-1,"0000")) -> BATAN-0001 | B2: 46146 | C2: =IF(B2="","",CHOOSE(MONTH(B2),"Enero","Febrero","Marzo","Abril","Mayo","Junio","Julio","Agosto","Septiembre","Octubre","Noviembre","Diciembre")) -> Mayo | D2: =IF(B2="","",YEAR(B2)) -> 2026 | E2: =IF(B2="","","Batán 200 L") -> Batán 200 L | F2: =IF(B2="","",200) -> 200 | G2: Shell Agro | H2: Diesel - EVOLUX | I2: 200 | P2: =IF(A2="","",SUMIFS('CARGAS DE COMBUSTIBLE'!$N$2:$N$301,'CARGAS DE COMBUSTIBLE'!$AA$2:$AA$301,A2)) -> 0 | Q2: =IF(A2="","",IF(I2="","",I2-P2)) -> 200 | R2: =IF(A2="","",IF(Q2<0,"Excedido",IF(Q2=0,"Consumido","Disponible"))) -> Disponible
A3: =IF(B3="","","BATAN-"&TEXT(ROW()-1,"0000")) -> BATAN-0002 | B3: 46154 | C3: =IF(B3="","",CHOOSE(MONTH(B3),"Enero","Febrero","Marzo","Abril","Mayo","Junio","Julio","Agosto","Septiembre","Octubre","Noviembre","Diciembre")) -> Mayo | D3: =IF(B3="","",YEAR(B3)) -> 2026 | E3: =IF(B3="","","Batán 200 L") -> Batán 200 L | F3: =IF(B3="","",200) -> 200 | G3: Shell Agro | H3: Diesel - EVOLUX | I3: 200 | P3: =IF(A3="","",SUMIFS('CARGAS DE COMBUSTIBLE'!$N$2:$N$301,'CARGAS DE COMBUSTIBLE'!$AA$2:$AA$301,A3)) -> 0 | Q3: =IF(A3="","",IF(I3="","",I3-P3)) -> 200 | R3: =IF(A3="","",IF(Q3<0,"Excedido",IF(Q3=0,"Consumido","Disponible"))) -> Disponible
A4: =IF(B4="","","BATAN-"&TEXT(ROW()-1,"0000")) | C4: =IF(B4="","",CHOOSE(MONTH(B4),"Enero","Febrero","Marzo","Abril","Mayo","Junio","Julio","Agosto","Septiembre","Octubre","Noviembre","Diciembre")) | D4: =IF(B4="","",YEAR(B4)) | E4: =IF(B4="","","Batán 200 L") | F4: =IF(B4="","",200) | P4: =IF(A4="","",SUMIFS('CARGAS DE COMBUSTIBLE'!$N$2:$N$301,'CARGAS DE COMBUSTIBLE'!$AA$2:$AA$301,A4)) | Q4: =IF(A4="","",IF(I4="","",I4-P4)) | R4: =IF(A4="","",IF(Q4<0,"Excedido",IF(Q4=0,"Consumido","Disponible")))
A5: =IF(B5="","","BATAN-"&TEXT(ROW()-1,"0000")) | C5: =IF(B5="","",CHOOSE(MONTH(B5),"Enero","Febrero","Marzo","Abril","Mayo","Junio","Julio","Agosto","Septiembre","Octubre","Noviembre","Diciembre")) | D5: =IF(B5="","",YEAR(B5)) | E5: =IF(B5="","","Batán 200 L") | F5: =IF(B5="","",200) | P5: =IF(A5="","",SUMIFS('CARGAS DE COMBUSTIBLE'!$N$2:$N$301,'CARGAS DE COMBUSTIBLE'!$AA$2:$AA$301,A5)) | Q5: =IF(A5="","",IF(I5="","",I5-P5)) | R5: =IF(A5="","",IF(Q5<0,"Excedido",IF(Q5=0,"Consumido","Disponible")))
A6: =IF(B6="","","BATAN-"&TEXT(ROW()-1,"0000")) | C6: =IF(B6="","",CHOOSE(MONTH(B6),"Enero","Febrero","Marzo","Abril","Mayo","Junio","Julio","Agosto","Septiembre","Octubre","Noviembre","Diciembre")) | D6: =IF(B6="","",YEAR(B6)) | E6: =IF(B6="","","Batán 200 L") | F6: =IF(B6="","",200) | P6: =IF(A6="","",SUMIFS('CARGAS DE COMBUSTIBLE'!$N$2:$N$301,'CARGAS DE COMBUSTIBLE'!$AA$2:$AA$301,A6)) | Q6: =IF(A6="","",IF(I6="","",I6-P6)) | R6: =IF(A6="","",IF(Q6<0,"Excedido",IF(Q6=0,"Consumido","Disponible")))
A7: =IF(B7="","","BATAN-"&TEXT(ROW()-1,"0000")) | C7: =IF(B7="","",CHOOSE(MONTH(B7),"Enero","Febrero","Marzo","Abril","Mayo","Junio","Julio","Agosto","Septiembre","Octubre","Noviembre","Diciembre")) | D7: =IF(B7="","",YEAR(B7)) | E7: =IF(B7="","","Batán 200 L") | F7: =IF(B7="","",200) | K7: =IF(OR(I7="",J7=""),"",I7*J7) | P7: =IF(A7="","",SUMIFS('CARGAS DE COMBUSTIBLE'!$N$2:$N$301,'CARGAS DE COMBUSTIBLE'!$AA$2:$AA$301,A7)) | Q7: =IF(A7="","",IF(I7="","",I7-P7)) | R7: =IF(A7="","",IF(Q7<0,"Excedido",IF(Q7=0,"Consumido","Disponible")))
A8: =IF(B8="","","BATAN-"&TEXT(ROW()-1,"0000")) | C8: =IF(B8="","",CHOOSE(MONTH(B8),"Enero","Febrero","Marzo","Abril","Mayo","Junio","Julio","Agosto","Septiembre","Octubre","Noviembre","Diciembre")) | D8: =IF(B8="","",YEAR(B8)) | E8: =IF(B8="","","Batán 200 L") | F8: =IF(B8="","",200) | K8: =IF(OR(I8="",J8=""),"",I8*J8) | P8: =IF(A8="","",SUMIFS('CARGAS DE COMBUSTIBLE'!$N$2:$N$301,'CARGAS DE COMBUSTIBLE'!$AA$2:$AA$301,A8)) | Q8: =IF(A8="","",IF(I8="","",I8-P8)) | R8: =IF(A8="","",IF(Q8<0,"Excedido",IF(Q8=0,"Consumido","Disponible")))
A9: =IF(B9="","","BATAN-"&TEXT(ROW()-1,"0000")) | C9: =IF(B9="","",CHOOSE(MONTH(B9),"Enero","Febrero","Marzo","Abril","Mayo","Junio","Julio","Agosto","Septiembre","Octubre","Noviembre","Diciembre")) | D9: =IF(B9="","",YEAR(B9)) | E9: =IF(B9="","","Batán 200 L") | F9: =IF(B9="","",200) | K9: =IF(OR(I9="",J9=""),"",I9*J9) | P9: =IF(A9="","",SUMIFS('CARGAS DE COMBUSTIBLE'!$N$2:$N$301,'CARGAS DE COMBUSTIBLE'!$AA$2:$AA$301,A9)) | Q9: =IF(A9="","",IF(I9="","",I9-P9)) | R9: =IF(A9="","",IF(Q9<0,"Excedido",IF(Q9=0,"Consumido","Disponible")))
A10: =IF(B10="","","BATAN-"&TEXT(ROW()-1,"0000")) | C10: =IF(B10="","",CHOOSE(MONTH(B10),"Enero","Febrero","Marzo","Abril","Mayo","Junio","Julio","Agosto","Septiembre","Octubre","Noviembre","Diciembre")) | D10: =IF(B10="","",YEAR(B10)) | E10: =IF(B10="","","Batán 200 L") | F10: =IF(B10="","",200) | K10: =IF(OR(I10="",J10=""),"",I10*J10) | P10: =IF(A10="","",SUMIFS('CARGAS DE COMBUSTIBLE'!$N$2:$N$301,'CARGAS DE COMBUSTIBLE'!$AA$2:$AA$301,A10)) | Q10: =IF(A10="","",IF(I10="","",I10-P10)) | R10: =IF(A10="","",IF(Q10<0,"Excedido",IF(Q10=0,"Consumido","Disponible")))
A11: =IF(B11="","","BATAN-"&TEXT(ROW()-1,"0000")) | C11: =IF(B11="","",CHOOSE(MONTH(B11),"Enero","Febrero","Marzo","Abril","Mayo","Junio","Julio","Agosto","Septiembre","Octubre","Noviembre","Diciembre")) | D11: =IF(B11="","",YEAR(B11)) | E11: =IF(B11="","","Batán 200 L") | F11: =IF(B11="","",200) | K11: =IF(OR(I11="",J11=""),"",I11*J11) | P11: =IF(A11="","",SUMIFS('CARGAS DE COMBUSTIBLE'!$N$2:$N$301,'CARGAS DE COMBUSTIBLE'!$AA$2:$AA$301,A11)) | Q11: =IF(A11="","",IF(I11="","",I11-P11)) | R11: =IF(A11="","",IF(Q11<0,"Excedido",IF(Q11=0,"Consumido","Disponible")))
A12: =IF(B12="","","BATAN-"&TEXT(ROW()-1,"0000")) | C12: =IF(B12="","",CHOOSE(MONTH(B12),"Enero","Febrero","Marzo","Abril","Mayo","Junio","Julio","Agosto","Septiembre","Octubre","Noviembre","Diciembre")) | D12: =IF(B12="","",YEAR(B12)) | E12: =IF(B12="","","Batán 200 L") | F12: =IF(B12="","",200) | K12: =IF(OR(I12="",J12=""),"",I12*J12) | P12: =IF(A12="","",SUMIFS('CARGAS DE COMBUSTIBLE'!$N$2:$N$301,'CARGAS DE COMBUSTIBLE'!$AA$2:$AA$301,A12)) | Q12: =IF(A12="","",IF(I12="","",I12-P12)) | R12: =IF(A12="","",IF(Q12<0,"Excedido",IF(Q12=0,"Consumido","Disponible")))
A13: =IF(B13="","","BATAN-"&TEXT(ROW()-1,"0000")) | C13: =IF(B13="","",CHOOSE(MONTH(B13),"Enero","Febrero","Marzo","Abril","Mayo","Junio","Julio","Agosto","Septiembre","Octubre","Noviembre","Diciembre")) | D13: =IF(B13="","",YEAR(B13)) | E13: =IF(B13="","","Batán 200 L") | F13: =IF(B13="","",200) | K13: =IF(OR(I13="",J13=""),"",I13*J13) | P13: =IF(A13="","",SUMIFS('CARGAS DE COMBUSTIBLE'!$N$2:$N$301,'CARGAS DE COMBUSTIBLE'!$AA$2:$AA$301,A13)) | Q13: =IF(A13="","",IF(I13="","",I13-P13)) | R13: =IF(A13="","",IF(Q13<0,"Excedido",IF(Q13=0,"Consumido","Disponible")))
A14: =IF(B14="","","BATAN-"&TEXT(ROW()-1,"0000")) | C14: =IF(B14="","",CHOOSE(MONTH(B14),"Enero","Febrero","Marzo","Abril","Mayo","Junio","Julio","Agosto","Septiembre","Octubre","Noviembre","Diciembre")) | D14: =IF(B14="","",YEAR(B14)) | E14: =IF(B14="","","Batán 200 L") | F14: =IF(B14="","",200) | K14: =IF(OR(I14="",J14=""),"",I14*J14) | P14: =IF(A14="","",SUMIFS('CARGAS DE COMBUSTIBLE'!$N$2:$N$301,'CARGAS DE COMBUSTIBLE'!$AA$2:$AA$301,A14)) | Q14: =IF(A14="","",IF(I14="","",I14-P14)) | R14: =IF(A14="","",IF(Q14<0,"Excedido",IF(Q14=0,"Consumido","Disponible")))
A15: =IF(B15="","","BATAN-"&TEXT(ROW()-1,"0000")) | C15: =IF(B15="","",CHOOSE(MONTH(B15),"Enero","Febrero","Marzo","Abril","Mayo","Junio","Julio","Agosto","Septiembre","Octubre","Noviembre","Diciembre")) | D15: =IF(B15="","",YEAR(B15)) | E15: =IF(B15="","","Batán 200 L") | F15: =IF(B15="","",200) | K15: =IF(OR(I15="",J15=""),"",I15*J15) | P15: =IF(A15="","",SUMIFS('CARGAS DE COMBUSTIBLE'!$N$2:$N$301,'CARGAS DE COMBUSTIBLE'!$AA$2:$AA$301,A15)) | Q15: =IF(A15="","",IF(I15="","",I15-P15)) | R15: =IF(A15="","",IF(Q15<0,"Excedido",IF(Q15=0,"Consumido","Disponible")))
A16: =IF(B16="","","BATAN-"&TEXT(ROW()-1,"0000")) | C16: =IF(B16="","",CHOOSE(MONTH(B16),"Enero","Febrero","Marzo","Abril","Mayo","Junio","Julio","Agosto","Septiembre","Octubre","Noviembre","Diciembre")) | D16: =IF(B16="","",YEAR(B16)) | E16: =IF(B16="","","Batán 200 L") | F16: =IF(B16="","",200) | K16: =IF(OR(I16="",J16=""),"",I16*J16) | P16: =IF(A16="","",SUMIFS('CARGAS DE COMBUSTIBLE'!$N$2:$N$301,'CARGAS DE COMBUSTIBLE'!$AA$2:$AA$301,A16)) | Q16: =IF(A16="","",IF(I16="","",I16-P16)) | R16: =IF(A16="","",IF(Q16<0,"Excedido",IF(Q16=0,"Consumido","Disponible")))
A17: =IF(B17="","","BATAN-"&TEXT(ROW()-1,"0000")) | C17: =IF(B17="","",CHOOSE(MONTH(B17),"Enero","Febrero","Marzo","Abril","Mayo","Junio","Julio","Agosto","Septiembre","Octubre","Noviembre","Diciembre")) | D17: =IF(B17="","",YEAR(B17)) | E17: =IF(B17="","","Batán 200 L") | F17: =IF(B17="","",200) | K17: =IF(OR(I17="",J17=""),"",I17*J17) | P17: =IF(A17="","",SUMIFS('CARGAS DE COMBUSTIBLE'!$N$2:$N$301,'CARGAS DE COMBUSTIBLE'!$AA$2:$AA$301,A17)) | Q17: =IF(A17="","",IF(I17="","",I17-P17)) | R17: =IF(A17="","",IF(Q17<0,"Excedido",IF(Q17=0,"Consumido","Disponible")))
A18: =IF(B18="","","BATAN-"&TEXT(ROW()-1,"0000")) | C18: =IF(B18="","",CHOOSE(MONTH(B18),"Enero","Febrero","Marzo","Abril","Mayo","Junio","Julio","Agosto","Septiembre","Octubre","Noviembre","Diciembre")) | D18: =IF(B18="","",YEAR(B18)) | E18: =IF(B18="","","Batán 200 L") | F18: =IF(B18="","",200) | K18: =IF(OR(I18="",J18=""),"",I18*J18) | P18: =IF(A18="","",SUMIFS('CARGAS DE COMBUSTIBLE'!$N$2:$N$301,'CARGAS DE COMBUSTIBLE'!$AA$2:$AA$301,A18)) | Q18: =IF(A18="","",IF(I18="","",I18-P18)) | R18: =IF(A18="","",IF(Q18<0,"Excedido",IF(Q18=0,"Consumido","Disponible")))
... A301: =IF(B301="","","BATAN-"&TEXT(ROW()-1,"0000")) | C301: =IF(B301="","",CHOOSE(MONTH(B301),"Enero","Febrero","Marzo","Abril","Mayo","Junio","Julio","Agosto","Septiembre","Octubre","Noviembre","Diciembre")) | D301: =IF(B301="","",YEAR(B301)) | E301: =IF(B301="","","Batán 200 L") | F301: =IF(B301="","",200) | K301: =IF(OR(I301="",J301=""),"",I301*J301) | P301: =IF(A301="","",SUMIFS('CARGAS DE COMBUSTIBLE'!$N$2:$N$301,'CARGAS DE COMBUSTIBLE'!$AA$2:$AA$301,A301)) | Q301: =IF(A301="","",IF(I301="","",I301-P301)) | R301: =IF(A301="","",IF(Q301<0,"Excedido",IF(Q301=0,"Consumido","Disponible")))

Sheet CONTROL MENSUAL PROVEEDOR
A1: CONTROL MENSUAL Y CONCILIACIÓN CON PROVEEDOR
A2: Año a controlar | B2: =DASHBOARD!B3 -> 2026
A3: Mes | B3: Total de cargas | C3: Total litros | D3: Importe planilla | E3: Cantidad de tickets | F3: Promedio por carga | G3: Factura proveedor | H3: Diferencia | I3: Observaciones conciliación | J3: Estado
A4: Enero | B4: =COUNTIFS('CARGAS DE COMBUSTIBLE'!$D$2:$D$301,$B$2,'CARGAS DE COMBUSTIBLE'!$C$2:$C$301,$A4,'CARGAS DE COMBUSTIBLE'!$A$2:$A$301,"<>",'CARGAS DE COMBUSTIBLE'!$AA$2:$AA$301,"")+COUNTIFS('CONTROL DE BATAN'!$D$2:$D$301,$B$2,'CONTROL DE BATAN'!$C$2:$C$301,$A4,'CONTROL DE BATAN'!$A$2:$A$301,"<>") -> 0 | C4: =SUMIFS('CARGAS DE COMBUSTIBLE'!$N$2:$N$301,'CARGAS DE COMBUSTIBLE'!$D$2:$D$301,$B$2,'CARGAS DE COMBUSTIBLE'!$C$2:$C$301,$A4,'CARGAS DE COMBUSTIBLE'!$AA$2:$AA$301,"")+SUMIFS('CONTROL DE BATAN'!$I$2:$I$301,'CONTROL DE BATAN'!$D$2:$D$301,$B$2,'CONTROL DE BATAN'!$C$2:$C$301,$A4) -> 0 | D4: =SUMIFS('CARGAS DE COMBUSTIBLE'!$P$2:$P$301,'CARGAS DE COMBUSTIBLE'!$D$2:$D$301,$B$2,'CARGAS DE COMBUSTIBLE'!$C$2:$C$301,$A4,'CARGAS DE COMBUSTIBLE'!$AA$2:$AA$301,"")+SUMIFS('CONTROL DE BATAN'!$K$2:$K$301,'CONTROL DE BATAN'!$D$2:$D$301,$B$2,'CONTROL DE BATAN'!$C$2:$C$301,$A4) -> 0 | E4: =COUNTIFS('CARGAS DE COMBUSTIBLE'!$D$2:$D$301,$B$2,'CARGAS DE COMBUSTIBLE'!$C$2:$C$301,$A4,'CARGAS DE COMBUSTIBLE'!$W$2:$W$301,"<>",'CARGAS DE COMBUSTIBLE'!$AA$2:$AA$301,"")+COUNTIFS('CONTROL DE BATAN'!$D$2:$D$301,$B$2,'CONTROL DE BATAN'!$C$2:$C$301,$A4,'CONTROL DE BATAN'!$L$2:$L$301,"<>") -> 0 | F4: =IF(B4=0,"",D4/B4) | H4: =IF(G4="","",G4-D4) | J4: Controlado
A5: Febrero | B5: =COUNTIFS('CARGAS DE COMBUSTIBLE'!$D$2:$D$301,$B$2,'CARGAS DE COMBUSTIBLE'!$C$2:$C$301,$A5,'CARGAS DE COMBUSTIBLE'!$A$2:$A$301,"<>",'CARGAS DE COMBUSTIBLE'!$AA$2:$AA$301,"")+COUNTIFS('CONTROL DE BATAN'!$D$2:$D$301,$B$2,'CONTROL DE BATAN'!$C$2:$C$301,$A5,'CONTROL DE BATAN'!$A$2:$A$301,"<>") -> 0 | C5: =SUMIFS('CARGAS DE COMBUSTIBLE'!$N$2:$N$301,'CARGAS DE COMBUSTIBLE'!$D$2:$D$301,$B$2,'CARGAS DE COMBUSTIBLE'!$C$2:$C$301,$A5,'CARGAS DE COMBUSTIBLE'!$AA$2:$AA$301,"")+SUMIFS('CONTROL DE BATAN'!$I$2:$I$301,'CONTROL DE BATAN'!$D$2:$D$301,$B$2,'CONTROL DE BATAN'!$C$2:$C$301,$A5) -> 0 | D5: =SUMIFS('CARGAS DE COMBUSTIBLE'!$P$2:$P$301,'CARGAS DE COMBUSTIBLE'!$D$2:$D$301,$B$2,'CARGAS DE COMBUSTIBLE'!$C$2:$C$301,$A5,'CARGAS DE COMBUSTIBLE'!$AA$2:$AA$301,"")+SUMIFS('CONTROL DE BATAN'!$K$2:$K$301,'CONTROL DE BATAN'!$D$2:$D$301,$B$2,'CONTROL DE BATAN'!$C$2:$C$301,$A5) -> 0 | E5: =COUNTIFS('CARGAS DE COMBUSTIBLE'!$D$2:$D$301,$B$2,'CARGAS DE COMBUSTIBLE'!$C$2:$C$301,$A5,'CARGAS DE COMBUSTIBLE'!$W$2:$W$301,"<>",'CARGAS DE COMBUSTIBLE'!$AA$2:$AA$301,"")+COUNTIFS('CONTROL DE BATAN'!$D$2:$D$301,$B$2,'CONTROL DE BATAN'!$C$2:$C$301,$A5,'CONTROL DE BATAN'!$L$2:$L$301,"<>") -> 0 | F5: =IF(B5=0,"",D5/B5) | H5: =IF(G5="","",G5-D5) | J5: Controlado
A6: Marzo | B6: =COUNTIFS('CARGAS DE COMBUSTIBLE'!$D$2:$D$301,$B$2,'CARGAS DE COMBUSTIBLE'!$C$2:$C$301,$A6,'CARGAS DE COMBUSTIBLE'!$A$2:$A$301,"<>",'CARGAS DE COMBUSTIBLE'!$AA$2:$AA$301,"")+COUNTIFS('CONTROL DE BATAN'!$D$2:$D$301,$B$2,'CONTROL DE BATAN'!$C$2:$C$301,$A6,'CONTROL DE BATAN'!$A$2:$A$301,"<>") -> 0 | C6: =SUMIFS('CARGAS DE COMBUSTIBLE'!$N$2:$N$301,'CARGAS DE COMBUSTIBLE'!$D$2:$D$301,$B$2,'CARGAS DE COMBUSTIBLE'!$C$2:$C$301,$A6,'CARGAS DE COMBUSTIBLE'!$AA$2:$AA$301,"")+SUMIFS('CONTROL DE BATAN'!$I$2:$I$301,'CONTROL DE BATAN'!$D$2:$D$301,$B$2,'CONTROL DE BATAN'!$C$2:$C$301,$A6) -> 0 | D6: =SUMIFS('CARGAS DE COMBUSTIBLE'!$P$2:$P$301,'CARGAS DE COMBUSTIBLE'!$D$2:$D$301,$B$2,'CARGAS DE COMBUSTIBLE'!$C$2:$C$301,$A6,'CARGAS DE COMBUSTIBLE'!$AA$2:$AA$301,"")+SUMIFS('CONTROL DE BATAN'!$K$2:$K$301,'CONTROL DE BATAN'!$D$2:$D$301,$B$2,'CONTROL DE BATAN'!$C$2:$C$301,$A6) -> 0 | E6: =COUNTIFS('CARGAS DE COMBUSTIBLE'!$D$2:$D$301,$B$2,'CARGAS DE COMBUSTIBLE'!$C$2:$C$301,$A6,'CARGAS DE COMBUSTIBLE'!$W$2:$W$301,"<>",'CARGAS DE COMBUSTIBLE'!$AA$2:$AA$301,"")+COUNTIFS('CONTROL DE BATAN'!$D$2:$D$301,$B$2,'CONTROL DE BATAN'!$C$2:$C$301,$A6,'CONTROL DE BATAN'!$L$2:$L$301,"<>") -> 0 | F6: =IF(B6=0,"",D6/B6) | H6: =IF(G6="","",G6-D6) | J6: Controlado
A7: Abril | B7: =COUNTIFS('CARGAS DE COMBUSTIBLE'!$D$2:$D$301,$B$2,'CARGAS DE COMBUSTIBLE'!$C$2:$C$301,$A7,'CARGAS DE COMBUSTIBLE'!$A$2:$A$301,"<>",'CARGAS DE COMBUSTIBLE'!$AA$2:$AA$301,"")+COUNTIFS('CONTROL DE BATAN'!$D$2:$D$301,$B$2,'CONTROL DE BATAN'!$C$2:$C$301,$A7,'CONTROL DE BATAN'!$A$2:$A$301,"<>") -> 0 | C7: =SUMIFS('CARGAS DE COMBUSTIBLE'!$N$2:$N$301,'CARGAS DE COMBUSTIBLE'!$D$2:$D$301,$B$2,'CARGAS DE COMBUSTIBLE'!$C$2:$C$301,$A7,'CARGAS DE COMBUSTIBLE'!$AA$2:$AA$301,"")+SUMIFS('CONTROL DE BATAN'!$I$2:$I$301,'CONTROL DE BATAN'!$D$2:$D$301,$B$2,'CONTROL DE BATAN'!$C$2:$C$301,$A7) -> 0 | D7: =SUMIFS('CARGAS DE COMBUSTIBLE'!$P$2:$P$301,'CARGAS DE COMBUSTIBLE'!$D$2:$D$301,$B$2,'CARGAS DE COMBUSTIBLE'!$C$2:$C$301,$A7,'CARGAS DE COMBUSTIBLE'!$AA$2:$AA$301,"")+SUMIFS('CONTROL DE BATAN'!$K$2:$K$301,'CONTROL DE BATAN'!$D$2:$D$301,$B$2,'CONTROL DE BATAN'!$C$2:$C$301,$A7) -> 0 | E7: =COUNTIFS('CARGAS DE COMBUSTIBLE'!$D$2:$D$301,$B$2,'CARGAS DE COMBUSTIBLE'!$C$2:$C$301,$A7,'CARGAS DE COMBUSTIBLE'!$W$2:$W$301,"<>",'CARGAS DE COMBUSTIBLE'!$AA$2:$AA$301,"")+COUNTIFS('CONTROL DE BATAN'!$D$2:$D$301,$B$2,'CONTROL DE BATAN'!$C$2:$C$301,$A7,'CONTROL DE BATAN'!$L$2:$L$301,"<>") -> 0 | F7: =IF(B7=0,"",D7/B7) | G7: 656800 | H7: =IF(G7="","",G7-D7) -> 656800 | J7: Controlado
A8: Mayo | B8: =COUNTIFS('CARGAS DE COMBUSTIBLE'!$D$2:$D$301,$B$2,'CARGAS DE COMBUSTIBLE'!$C$2:$C$301,$A8,'CARGAS DE COMBUSTIBLE'!$A$2:$A$301,"<>",'CARGAS DE COMBUSTIBLE'!$AA$2:$AA$301,"")+COUNTIFS('CONTROL DE BATAN'!$D$2:$D$301,$B$2,'CONTROL DE BATAN'!$C$2:$C$301,$A8,'CONTROL DE BATAN'!$A$2:$A$301,"<>") -> 5 | C8: =SUMIFS('CARGAS DE COMBUSTIBLE'!$N$2:$N$301,'CARGAS DE COMBUSTIBLE'!$D$2:$D$301,$B$2,'CARGAS DE COMBUSTIBLE'!$C$2:$C$301,$A8,'CARGAS DE COMBUSTIBLE'!$AA$2:$AA$301,"")+SUMIFS('CONTROL DE BATAN'!$I$2:$I$301,'CONTROL DE BATAN'!$D$2:$D$301,$B$2,'CONTROL DE BATAN'!$C$2:$C$301,$A8) -> 539.65 | D8: =SUMIFS('CARGAS DE COMBUSTIBLE'!$P$2:$P$301,'CARGAS DE COMBUSTIBLE'!$D$2:$D$301,$B$2,'CARGAS DE COMBUSTIBLE'!$C$2:$C$301,$A8,'CARGAS DE COMBUSTIBLE'!$AA$2:$AA$301,"")+SUMIFS('CONTROL DE BATAN'!$K$2:$K$301,'CONTROL DE BATAN'!$D$2:$D$301,$B$2,'CONTROL DE BATAN'!$C$2:$C$301,$A8) -> 0 | E8: =COUNTIFS('CARGAS DE COMBUSTIBLE'!$D$2:$D$301,$B$2,'CARGAS DE COMBUSTIBLE'!$C$2:$C$301,$A8,'CARGAS DE COMBUSTIBLE'!$W$2:$W$301,"<>",'CARGAS DE COMBUSTIBLE'!$AA$2:$AA$301,"")+COUNTIFS('CONTROL DE BATAN'!$D$2:$D$301,$B$2,'CONTROL DE BATAN'!$C$2:$C$301,$A8,'CONTROL DE BATAN'!$L$2:$L$301,"<>") -> 3 | F8: =IF(B8=0,"",D8/B8) -> 0 | H8: =IF(G8="","",G8-D8)
A9: Junio | B9: =COUNTIFS('CARGAS DE COMBUSTIBLE'!$D$2:$D$301,$B$2,'CARGAS DE COMBUSTIBLE'!$C$2:$C$301,$A9,'CARGAS DE COMBUSTIBLE'!$A$2:$A$301,"<>",'CARGAS DE COMBUSTIBLE'!$AA$2:$AA$301,"")+COUNTIFS('CONTROL DE BATAN'!$D$2:$D$301,$B$2,'CONTROL DE BATAN'!$C$2:$C$301,$A9,'CONTROL DE BATAN'!$A$2:$A$301,"<>") -> 0 | C9: =SUMIFS('CARGAS DE COMBUSTIBLE'!$N$2:$N$301,'CARGAS DE COMBUSTIBLE'!$D$2:$D$301,$B$2,'CARGAS DE COMBUSTIBLE'!$C$2:$C$301,$A9,'CARGAS DE COMBUSTIBLE'!$AA$2:$AA$301,"")+SUMIFS('CONTROL DE BATAN'!$I$2:$I$301,'CONTROL DE BATAN'!$D$2:$D$301,$B$2,'CONTROL DE BATAN'!$C$2:$C$301,$A9) -> 0 | D9: =SUMIFS('CARGAS DE COMBUSTIBLE'!$P$2:$P$301,'CARGAS DE COMBUSTIBLE'!$D$2:$D$301,$B$2,'CARGAS DE COMBUSTIBLE'!$C$2:$C$301,$A9,'CARGAS DE COMBUSTIBLE'!$AA$2:$AA$301,"")+SUMIFS('CONTROL DE BATAN'!$K$2:$K$301,'CONTROL DE BATAN'!$D$2:$D$301,$B$2,'CONTROL DE BATAN'!$C$2:$C$301,$A9) -> 0 | E9: =COUNTIFS('CARGAS DE COMBUSTIBLE'!$D$2:$D$301,$B$2,'CARGAS DE COMBUSTIBLE'!$C$2:$C$301,$A9,'CARGAS DE COMBUSTIBLE'!$W$2:$W$301,"<>",'CARGAS DE COMBUSTIBLE'!$AA$2:$AA$301,"")+COUNTIFS('CONTROL DE BATAN'!$D$2:$D$301,$B$2,'CONTROL DE BATAN'!$C$2:$C$301,$A9,'CONTROL DE BATAN'!$L$2:$L$301,"<>") -> 0 | F9: =IF(B9=0,"",D9/B9) | H9: =IF(G9="","",G9-D9)
A10: Julio | B10: =COUNTIFS('CARGAS DE COMBUSTIBLE'!$D$2:$D$301,$B$2,'CARGAS DE COMBUSTIBLE'!$C$2:$C$301,$A10,'CARGAS DE COMBUSTIBLE'!$A$2:$A$301,"<>",'CARGAS DE COMBUSTIBLE'!$AA$2:$AA$301,"")+COUNTIFS('CONTROL DE BATAN'!$D$2:$D$301,$B$2,'CONTROL DE BATAN'!$C$2:$C$301,$A10,'CONTROL DE BATAN'!$A$2:$A$301,"<>") -> 0 | C10: =SUMIFS('CARGAS DE COMBUSTIBLE'!$N$2:$N$301,'CARGAS DE COMBUSTIBLE'!$D$2:$D$301,$B$2,'CARGAS DE COMBUSTIBLE'!$C$2:$C$301,$A10,'CARGAS DE COMBUSTIBLE'!$AA$2:$AA$301,"")+SUMIFS('CONTROL DE BATAN'!$I$2:$I$301,'CONTROL DE BATAN'!$D$2:$D$301,$B$2,'CONTROL DE BATAN'!$C$2:$C$301,$A10) -> 0 | D10: =SUMIFS('CARGAS DE COMBUSTIBLE'!$P$2:$P$301,'CARGAS DE COMBUSTIBLE'!$D$2:$D$301,$B$2,'CARGAS DE COMBUSTIBLE'!$C$2:$C$301,$A10,'CARGAS DE COMBUSTIBLE'!$AA$2:$AA$301,"")+SUMIFS('CONTROL DE BATAN'!$K$2:$K$301,'CONTROL DE BATAN'!$D$2:$D$301,$B$2,'CONTROL DE BATAN'!$C$2:$C$301,$A10) -> 0 | E10: =COUNTIFS('CARGAS DE COMBUSTIBLE'!$D$2:$D$301,$B$2,'CARGAS DE COMBUSTIBLE'!$C$2:$C$301,$A10,'CARGAS DE COMBUSTIBLE'!$W$2:$W$301,"<>",'CARGAS DE COMBUSTIBLE'!$AA$2:$AA$301,"")+COUNTIFS('CONTROL DE BATAN'!$D$2:$D$301,$B$2,'CONTROL DE BATAN'!$C$2:$C$301,$A10,'CONTROL DE BATAN'!$L$2:$L$301,"<>") -> 0 | F10: =IF(B10=0,"",D10/B10) | H10: =IF(G10="","",G10-D10)
A11: Agosto | B11: =COUNTIFS('CARGAS DE COMBUSTIBLE'!$D$2:$D$301,$B$2,'CARGAS DE COMBUSTIBLE'!$C$2:$C$301,$A11,'CARGAS DE COMBUSTIBLE'!$A$2:$A$301,"<>",'CARGAS DE COMBUSTIBLE'!$AA$2:$AA$301,"")+COUNTIFS('CONTROL DE BATAN'!$D$2:$D$301,$B$2,'CONTROL DE BATAN'!$C$2:$C$301,$A11,'CONTROL DE BATAN'!$A$2:$A$301,"<>") -> 0 | C11: =SUMIFS('CARGAS DE COMBUSTIBLE'!$N$2:$N$301,'CARGAS DE COMBUSTIBLE'!$D$2:$D$301,$B$2,'CARGAS DE COMBUSTIBLE'!$C$2:$C$301,$A11,'CARGAS DE COMBUSTIBLE'!$AA$2:$AA$301,"")+SUMIFS('CONTROL DE BATAN'!$I$2:$I$301,'CONTROL DE BATAN'!$D$2:$D$301,$B$2,'CONTROL DE BATAN'!$C$2:$C$301,$A11) -> 0 | D11: =SUMIFS('CARGAS DE COMBUSTIBLE'!$P$2:$P$301,'CARGAS DE COMBUSTIBLE'!$D$2:$D$301,$B$2,'CARGAS DE COMBUSTIBLE'!$C$2:$C$301,$A11,'CARGAS DE COMBUSTIBLE'!$AA$2:$AA$301,"")+SUMIFS('CONTROL DE BATAN'!$K$2:$K$301,'CONTROL DE BATAN'!$D$2:$D$301,$B$2,'CONTROL DE BATAN'!$C$2:$C$301,$A11) -> 0 | E11: =COUNTIFS('CARGAS DE COMBUSTIBLE'!$D$2:$D$301,$B$2,'CARGAS DE COMBUSTIBLE'!$C$2:$C$301,$A11,'CARGAS DE COMBUSTIBLE'!$W$2:$W$301,"<>",'CARGAS DE COMBUSTIBLE'!$AA$2:$AA$301,"")+COUNTIFS('CONTROL DE BATAN'!$D$2:$D$301,$B$2,'CONTROL DE BATAN'!$C$2:$C$301,$A11,'CONTROL DE BATAN'!$L$2:$L$301,"<>") -> 0 | F11: =IF(B11=0,"",D11/B11) | H11: =IF(G11="","",G11-D11)
A12: Septiembre | B12: =COUNTIFS('CARGAS DE COMBUSTIBLE'!$D$2:$D$301,$B$2,'CARGAS DE COMBUSTIBLE'!$C$2:$C$301,$A12,'CARGAS DE COMBUSTIBLE'!$A$2:$A$301,"<>",'CARGAS DE COMBUSTIBLE'!$AA$2:$AA$301,"")+COUNTIFS('CONTROL DE BATAN'!$D$2:$D$301,$B$2,'CONTROL DE BATAN'!$C$2:$C$301,$A12,'CONTROL DE BATAN'!$A$2:$A$301,"<>") -> 0 | C12: =SUMIFS('CARGAS DE COMBUSTIBLE'!$N$2:$N$301,'CARGAS DE COMBUSTIBLE'!$D$2:$D$301,$B$2,'CARGAS DE COMBUSTIBLE'!$C$2:$C$301,$A12,'CARGAS DE COMBUSTIBLE'!$AA$2:$AA$301,"")+SUMIFS('CONTROL DE BATAN'!$I$2:$I$301,'CONTROL DE BATAN'!$D$2:$D$301,$B$2,'CONTROL DE BATAN'!$C$2:$C$301,$A12) -> 0 | D12: =SUMIFS('CARGAS DE COMBUSTIBLE'!$P$2:$P$301,'CARGAS DE COMBUSTIBLE'!$D$2:$D$301,$B$2,'CARGAS DE COMBUSTIBLE'!$C$2:$C$301,$A12,'CARGAS DE COMBUSTIBLE'!$AA$2:$AA$301,"")+SUMIFS('CONTROL DE BATAN'!$K$2:$K$301,'CONTROL DE BATAN'!$D$2:$D$301,$B$2,'CONTROL DE BATAN'!$C$2:$C$301,$A12) -> 0 | E12: =COUNTIFS('CARGAS DE COMBUSTIBLE'!$D$2:$D$301,$B$2,'CARGAS DE COMBUSTIBLE'!$C$2:$C$301,$A12,'CARGAS DE COMBUSTIBLE'!$W$2:$W$301,"<>",'CARGAS DE COMBUSTIBLE'!$AA$2:$AA$301,"")+COUNTIFS('CONTROL DE BATAN'!$D$2:$D$301,$B$2,'CONTROL DE BATAN'!$C$2:$C$301,$A12,'CONTROL DE BATAN'!$L$2:$L$301,"<>") -> 0 | F12: =IF(B12=0,"",D12/B12) | H12: =IF(G12="","",G12-D12)
A13: Octubre | B13: =COUNTIFS('CARGAS DE COMBUSTIBLE'!$D$2:$D$301,$B$2,'CARGAS DE COMBUSTIBLE'!$C$2:$C$301,$A13,'CARGAS DE COMBUSTIBLE'!$A$2:$A$301,"<>",'CARGAS DE COMBUSTIBLE'!$AA$2:$AA$301,"")+COUNTIFS('CONTROL DE BATAN'!$D$2:$D$301,$B$2,'CONTROL DE BATAN'!$C$2:$C$301,$A13,'CONTROL DE BATAN'!$A$2:$A$301,"<>") -> 0 | C13: =SUMIFS('CARGAS DE COMBUSTIBLE'!$N$2:$N$301,'CARGAS DE COMBUSTIBLE'!$D$2:$D$301,$B$2,'CARGAS DE COMBUSTIBLE'!$C$2:$C$301,$A13,'CARGAS DE COMBUSTIBLE'!$AA$2:$AA$301,"")+SUMIFS('CONTROL DE BATAN'!$I$2:$I$301,'CONTROL DE BATAN'!$D$2:$D$301,$B$2,'CONTROL DE BATAN'!$C$2:$C$301,$A13) -> 0 | D13: =SUMIFS('CARGAS DE COMBUSTIBLE'!$P$2:$P$301,'CARGAS DE COMBUSTIBLE'!$D$2:$D$301,$B$2,'CARGAS DE COMBUSTIBLE'!$C$2:$C$301,$A13,'CARGAS DE COMBUSTIBLE'!$AA$2:$AA$301,"")+SUMIFS('CONTROL DE BATAN'!$K$2:$K$301,'CONTROL DE BATAN'!$D$2:$D$301,$B$2,'CONTROL DE BATAN'!$C$2:$C$301,$A13) -> 0 | E13: =COUNTIFS('CARGAS DE COMBUSTIBLE'!$D$2:$D$301,$B$2,'CARGAS DE COMBUSTIBLE'!$C$2:$C$301,$A13,'CARGAS DE COMBUSTIBLE'!$W$2:$W$301,"<>",'CARGAS DE COMBUSTIBLE'!$AA$2:$AA$301,"")+COUNTIFS('CONTROL DE BATAN'!$D$2:$D$301,$B$2,'CONTROL DE BATAN'!$C$2:$C$301,$A13,'CONTROL DE BATAN'!$L$2:$L$301,"<>") -> 0 | F13: =IF(B13=0,"",D13/B13) | H13: =IF(G13="","",G13-D13)
A14: Noviembre | B14: =COUNTIFS('CARGAS DE COMBUSTIBLE'!$D$2:$D$301,$B$2,'CARGAS DE COMBUSTIBLE'!$C$2:$C$301,$A14,'CARGAS DE COMBUSTIBLE'!$A$2:$A$301,"<>",'CARGAS DE COMBUSTIBLE'!$AA$2:$AA$301,"")+COUNTIFS('CONTROL DE BATAN'!$D$2:$D$301,$B$2,'CONTROL DE BATAN'!$C$2:$C$301,$A14,'CONTROL DE BATAN'!$A$2:$A$301,"<>") -> 0 | C14: =SUMIFS('CARGAS DE COMBUSTIBLE'!$N$2:$N$301,'CARGAS DE COMBUSTIBLE'!$D$2:$D$301,$B$2,'CARGAS DE COMBUSTIBLE'!$C$2:$C$301,$A14,'CARGAS DE COMBUSTIBLE'!$AA$2:$AA$301,"")+SUMIFS('CONTROL DE BATAN'!$I$2:$I$301,'CONTROL DE BATAN'!$D$2:$D$301,$B$2,'CONTROL DE BATAN'!$C$2:$C$301,$A14) -> 0 | D14: =SUMIFS('CARGAS DE COMBUSTIBLE'!$P$2:$P$301,'CARGAS DE COMBUSTIBLE'!$D$2:$D$301,$B$2,'CARGAS DE COMBUSTIBLE'!$C$2:$C$301,$A14,'CARGAS DE COMBUSTIBLE'!$AA$2:$AA$301,"")+SUMIFS('CONTROL DE BATAN'!$K$2:$K$301,'CONTROL DE BATAN'!$D$2:$D$301,$B$2,'CONTROL DE BATAN'!$C$2:$C$301,$A14) -> 0 | E14: =COUNTIFS('CARGAS DE COMBUSTIBLE'!$D$2:$D$301,$B$2,'CARGAS DE COMBUSTIBLE'!$C$2:$C$301,$A14,'CARGAS DE COMBUSTIBLE'!$W$2:$W$301,"<>",'CARGAS DE COMBUSTIBLE'!$AA$2:$AA$301,"")+COUNTIFS('CONTROL DE BATAN'!$D$2:$D$301,$B$2,'CONTROL DE BATAN'!$C$2:$C$301,$A14,'CONTROL DE BATAN'!$L$2:$L$301,"<>") -> 0 | F14: =IF(B14=0,"",D14/B14) | H14: =IF(G14="","",G14-D14)
A15: Diciembre | B15: =COUNTIFS('CARGAS DE COMBUSTIBLE'!$D$2:$D$301,$B$2,'CARGAS DE COMBUSTIBLE'!$C$2:$C$301,$A15,'CARGAS DE COMBUSTIBLE'!$A$2:$A$301,"<>",'CARGAS DE COMBUSTIBLE'!$AA$2:$AA$301,"")+COUNTIFS('CONTROL DE BATAN'!$D$2:$D$301,$B$2,'CONTROL DE BATAN'!$C$2:$C$301,$A15,'CONTROL DE BATAN'!$A$2:$A$301,"<>") -> 0 | C15: =SUMIFS('CARGAS DE COMBUSTIBLE'!$N$2:$N$301,'CARGAS DE COMBUSTIBLE'!$D$2:$D$301,$B$2,'CARGAS DE COMBUSTIBLE'!$C$2:$C$301,$A15,'CARGAS DE COMBUSTIBLE'!$AA$2:$AA$301,"")+SUMIFS('CONTROL DE BATAN'!$I$2:$I$301,'CONTROL DE BATAN'!$D$2:$D$301,$B$2,'CONTROL DE BATAN'!$C$2:$C$301,$A15) -> 0 | D15: =SUMIFS('CARGAS DE COMBUSTIBLE'!$P$2:$P$301,'CARGAS DE COMBUSTIBLE'!$D$2:$D$301,$B$2,'CARGAS DE COMBUSTIBLE'!$C$2:$C$301,$A15,'CARGAS DE COMBUSTIBLE'!$AA$2:$AA$301,"")+SUMIFS('CONTROL DE BATAN'!$K$2:$K$301,'CONTROL DE BATAN'!$D$2:$D$301,$B$2,'CONTROL DE BATAN'!$C$2:$C$301,$A15) -> 0 | E15: =COUNTIFS('CARGAS DE COMBUSTIBLE'!$D$2:$D$301,$B$2,'CARGAS DE COMBUSTIBLE'!$C$2:$C$301,$A15,'CARGAS DE COMBUSTIBLE'!$W$2:$W$301,"<>",'CARGAS DE COMBUSTIBLE'!$AA$2:$AA$301,"")+COUNTIFS('CONTROL DE BATAN'!$D$2:$D$301,$B$2,'CONTROL DE BATAN'!$C$2:$C$301,$A15,'CONTROL DE BATAN'!$L$2:$L$301,"<>") -> 0 | F15: =IF(B15=0,"",D15/B15) | H15: =IF(G15="","",G15-D15)
A16: TOTAL | B16: =SUM(B4:B15) -> 5 | C16: =SUM(C4:C15) -> 539.65 | D16: =SUM(D4:D15) -> 0 | E16: =SUM(E4:E15) -> 3 | F16: =IF(B16=0,"",D16/B16) -> 0 | G16: =SUM(G4:G15) -> 656800 | H16: =SUM(H4:H15) -> 656800

Sheet INDICADORES
A1: INDICADORES Y RESÚMENES AUTOMÁTICOS | B1: Año analizado | C1: =DASHBOARD!B3 -> 2026
A3: Evolución mensual | F3: Consumo por unidad | L3: Consumo por obra / centro de costo | Q3: Consumo por responsable | V3: Distribución por tipo de combustible
A4: Mes | B4: Litros | C4: Importe | D4: Cargas | F4: Unidad | G4: Código | H4: Litros | I4: Importe | J4: Cargas | L4: Obra | M4: Litros | N4: Importe | O4: Cargas | Q4: Responsable | R4: Litros | S4: Importe | T4: Cargas | V4: Tipo de combustible | W4: Litros | X4: Importe
A5: Enero | B5: =SUMIFS('CARGAS DE COMBUSTIBLE'!$N$2:$N$301,'CARGAS DE COMBUSTIBLE'!$D$2:$D$301,$C$1,'CARGAS DE COMBUSTIBLE'!$C$2:$C$301,$A5) -> 0 | C5: =SUMIFS('CARGAS DE COMBUSTIBLE'!$P$2:$P$301,'CARGAS DE COMBUSTIBLE'!$D$2:$D$301,$C$1,'CARGAS DE COMBUSTIBLE'!$C$2:$C$301,$A5) -> 0 | D5: =COUNTIFS('CARGAS DE COMBUSTIBLE'!$D$2:$D$301,$C$1,'CARGAS DE COMBUSTIBLE'!$C$2:$C$301,$A5,'CARGAS DE COMBUSTIBLE'!$A$2:$A$301,"<>") -> 0 | F5: =IFERROR(INDEX('MAESTRO DE UNIDADES'!$C$2:$C$208,ROW()-4),"") -> Toyota Hilux 2.4 | G5: =IFERROR(INDEX('MAESTRO DE UNIDADES'!$A$2:$A$208,ROW()-4),"") -> C-001 | H5: =SUMIFS('CARGAS DE COMBUSTIBLE'!$N$2:$N$301,'CARGAS DE COMBUSTIBLE'!$D$2:$D$301,$C$1,'CARGAS DE COMBUSTIBLE'!$F$2:$F$301,$F5) -> 90 | I5: =SUMIFS('CARGAS DE COMBUSTIBLE'!$P$2:$P$301,'CARGAS DE COMBUSTIBLE'!$D$2:$D$301,$C$1,'CARGAS DE COMBUSTIBLE'!$F$2:$F$301,$F5) -> 0 | J5: =COUNTIFS('CARGAS DE COMBUSTIBLE'!$D$2:$D$301,$C$1,'CARGAS DE COMBUSTIBLE'!$F$2:$F$301,$F5,'CARGAS DE COMBUSTIBLE'!$A$2:$A$301,"<>") -> 2 | L5: =IFERROR(INDEX('MAESTRO DE OBRAS'!$B$2:$B$200,ROW()-4),"") -> Barrio Don Jose | M5: =SUMIFS('CARGAS DE COMBUSTIBLE'!$N$2:$N$301,'CARGAS DE COMBUSTIBLE'!$D$2:$D$301,$C$1,'CARGAS DE COMBUSTIBLE'!$K$2:$K$301,$L5) -> 49.65 | N5: =SUMIFS('CARGAS DE COMBUSTIBLE'!$P$2:$P$301,'CARGAS DE COMBUSTIBLE'!$D$2:$D$301,$C$1,'CARGAS DE COMBUSTIBLE'!$K$2:$K$301,$L5) -> 0 | O5: =COUNTIFS('CARGAS DE COMBUSTIBLE'!$D$2:$D$301,$C$1,'CARGAS DE COMBUSTIBLE'!$K$2:$K$301,$L5,'CARGAS DE COMBUSTIBLE'!$A$2:$A$301,"<>") -> 1 | Q5: =IFERROR(INDEX('MAESTRO DE RESPONSABLES'!$A$2:$A$200,ROW()-4),"") -> Ariel Jofre | R5: =SUMIFS('CARGAS DE COMBUSTIBLE'!$N$2:$N$301,'CARGAS DE COMBUSTIBLE'!$D$2:$D$301,$C$1,'CARGAS DE COMBUSTIBLE'!$J$2:$J$301,$Q5) -> 0 | S5: =SUMIFS('CARGAS DE COMBUSTIBLE'!$P$2:$P$301,'CARGAS DE COMBUSTIBLE'!$D$2:$D$301,$C$1,'CARGAS DE COMBUSTIBLE'!$J$2:$J$301,$Q5) -> 0 | T5: =COUNTIFS('CARGAS DE COMBUSTIBLE'!$D$2:$D$301,$C$1,'CARGAS DE COMBUSTIBLE'!$J$2:$J$301,$Q5,'CARGAS DE COMBUSTIBLE'!$A$2:$A$301,"<>") -> 0 | V5: Diesel - EVOLUX | W5: =SUMIFS('CARGAS DE COMBUSTIBLE'!$N$2:$N$301,'CARGAS DE COMBUSTIBLE'!$D$2:$D$301,$C$1,'CARGAS DE COMBUSTIBLE'!$M$2:$M$301,$V5) -> 0 | X5: =SUMIFS('CARGAS DE COMBUSTIBLE'!$P$2:$P$301,'CARGAS DE COMBUSTIBLE'!$D$2:$D$301,$C$1,'CARGAS DE COMBUSTIBLE'!$M$2:$M$301,$V5) -> 0
A6: Febrero | B6: =SUMIFS('CARGAS DE COMBUSTIBLE'!$N$2:$N$301,'CARGAS DE COMBUSTIBLE'!$D$2:$D$301,$C$1,'CARGAS DE COMBUSTIBLE'!$C$2:$C$301,$A6) -> 0 | C6: =SUMIFS('CARGAS DE COMBUSTIBLE'!$P$2:$P$301,'CARGAS DE COMBUSTIBLE'!$D$2:$D$301,$C$1,'CARGAS DE COMBUSTIBLE'!$C$2:$C$301,$A6) -> 0 | D6: =COUNTIFS('CARGAS DE COMBUSTIBLE'!$D$2:$D$301,$C$1,'CARGAS DE COMBUSTIBLE'!$C$2:$C$301,$A6,'CARGAS DE COMBUSTIBLE'!$A$2:$A$301,"<>") -> 0 | F6: =IFERROR(INDEX('MAESTRO DE UNIDADES'!$C$2:$C$208,ROW()-4),"") -> Toyota Hilux 2.4 | G6: =IFERROR(INDEX('MAESTRO DE UNIDADES'!$A$2:$A$208,ROW()-4),"") -> C-002 | H6: =SUMIFS('CARGAS DE COMBUSTIBLE'!$N$2:$N$301,'CARGAS DE COMBUSTIBLE'!$D$2:$D$301,$C$1,'CARGAS DE COMBUSTIBLE'!$F$2:$F$301,$F6) -> 90 | I6: =SUMIFS('CARGAS DE COMBUSTIBLE'!$P$2:$P$301,'CARGAS DE COMBUSTIBLE'!$D$2:$D$301,$C$1,'CARGAS DE COMBUSTIBLE'!$F$2:$F$301,$F6) -> 0 | J6: =COUNTIFS('CARGAS DE COMBUSTIBLE'!$D$2:$D$301,$C$1,'CARGAS DE COMBUSTIBLE'!$F$2:$F$301,$F6,'CARGAS DE COMBUSTIBLE'!$A$2:$A$301,"<>") -> 2 | L6: =IFERROR(INDEX('MAESTRO DE OBRAS'!$B$2:$B$200,ROW()-4),"") -> Escuela Stgo del Estero | M6: =SUMIFS('CARGAS DE COMBUSTIBLE'!$N$2:$N$301,'CARGAS DE COMBUSTIBLE'!$D$2:$D$301,$C$1,'CARGAS DE COMBUSTIBLE'!$K$2:$K$301,$L6) -> 0 | N6: =SUMIFS('CARGAS DE COMBUSTIBLE'!$P$2:$P$301,'CARGAS DE COMBUSTIBLE'!$D$2:$D$301,$C$1,'CARGAS DE COMBUSTIBLE'!$K$2:$K$301,$L6) -> 0 | O6: =COUNTIFS('CARGAS DE COMBUSTIBLE'!$D$2:$D$301,$C$1,'CARGAS DE COMBUSTIBLE'!$K$2:$K$301,$L6,'CARGAS DE COMBUSTIBLE'!$A$2:$A$301,"<>") -> 0 | Q6: =IFERROR(INDEX('MAESTRO DE RESPONSABLES'!$A$2:$A$200,ROW()-4),"") -> Bruno Guevara | R6: =SUMIFS('CARGAS DE COMBUSTIBLE'!$N$2:$N$301,'CARGAS DE COMBUSTIBLE'!$D$2:$D$301,$C$1,'CARGAS DE COMBUSTIBLE'!$J$2:$J$301,$Q6) -> 49.65 | S6: =SUMIFS('CARGAS DE COMBUSTIBLE'!$P$2:$P$301,'CARGAS DE COMBUSTIBLE'!$D$2:$D$301,$C$1,'CARGAS DE COMBUSTIBLE'!$J$2:$J$301,$Q6) -> 0 | T6: =COUNTIFS('CARGAS DE COMBUSTIBLE'!$D$2:$D$301,$C$1,'CARGAS DE COMBUSTIBLE'!$J$2:$J$301,$Q6,'CARGAS DE COMBUSTIBLE'!$A$2:$A$301,"<>") -> 1 | V6: Diesel - VPower | W6: =SUMIFS('CARGAS DE COMBUSTIBLE'!$N$2:$N$301,'CARGAS DE COMBUSTIBLE'!$D$2:$D$301,$C$1,'CARGAS DE COMBUSTIBLE'!$M$2:$M$301,$V6) -> 0 | X6: =SUMIFS('CARGAS DE COMBUSTIBLE'!$P$2:$P$301,'CARGAS DE COMBUSTIBLE'!$D$2:$D$301,$C$1,'CARGAS DE COMBUSTIBLE'!$M$2:$M$301,$V6) -> 0
A7: Marzo | B7: =SUMIFS('CARGAS DE COMBUSTIBLE'!$N$2:$N$301,'CARGAS DE COMBUSTIBLE'!$D$2:$D$301,$C$1,'CARGAS DE COMBUSTIBLE'!$C$2:$C$301,$A7) -> 0 | C7: =SUMIFS('CARGAS DE COMBUSTIBLE'!$P$2:$P$301,'CARGAS DE COMBUSTIBLE'!$D$2:$D$301,$C$1,'CARGAS DE COMBUSTIBLE'!$C$2:$C$301,$A7) -> 0 | D7: =COUNTIFS('CARGAS DE COMBUSTIBLE'!$D$2:$D$301,$C$1,'CARGAS DE COMBUSTIBLE'!$C$2:$C$301,$A7,'CARGAS DE COMBUSTIBLE'!$A$2:$A$301,"<>") -> 0 | F7: =IFERROR(INDEX('MAESTRO DE UNIDADES'!$C$2:$C$208,ROW()-4),"") -> RAM 1500 5.7 V8 LARAMIE4X4 | G7: =IFERROR(INDEX('MAESTRO DE UNIDADES'!$A$2:$A$208,ROW()-4),"") -> C-003 | H7: =SUMIFS('CARGAS DE COMBUSTIBLE'!$N$2:$N$301,'CARGAS DE COMBUSTIBLE'!$D$2:$D$301,$C$1,'CARGAS DE COMBUSTIBLE'!$F$2:$F$301,$F7) -> 0 | I7: =SUMIFS('CARGAS DE COMBUSTIBLE'!$P$2:$P$301,'CARGAS DE COMBUSTIBLE'!$D$2:$D$301,$C$1,'CARGAS DE COMBUSTIBLE'!$F$2:$F$301,$F7) -> 0 | J7: =COUNTIFS('CARGAS DE COMBUSTIBLE'!$D$2:$D$301,$C$1,'CARGAS DE COMBUSTIBLE'!$F$2:$F$301,$F7,'CARGAS DE COMBUSTIBLE'!$A$2:$A$301,"<>") -> 0 | L7: =IFERROR(INDEX('MAESTRO DE OBRAS'!$B$2:$B$200,ROW()-4),"") -> Mantenimiento Escuelas | M7: =SUMIFS('CARGAS DE COMBUSTIBLE'!$N$2:$N$301,'CARGAS DE COMBUSTIBLE'!$D$2:$D$301,$C$1,'CARGAS DE COMBUSTIBLE'!$K$2:$K$301,$L7) -> 0 | N7: =SUMIFS('CARGAS DE COMBUSTIBLE'!$P$2:$P$301,'CARGAS DE COMBUSTIBLE'!$D$2:$D$301,$C$1,'CARGAS DE COMBUSTIBLE'!$K$2:$K$301,$L7) -> 0 | O7: =COUNTIFS('CARGAS DE COMBUSTIBLE'!$D$2:$D$301,$C$1,'CARGAS DE COMBUSTIBLE'!$K$2:$K$301,$L7,'CARGAS DE COMBUSTIBLE'!$A$2:$A$301,"<>") -> 0 | Q7: =IFERROR(INDEX('MAESTRO DE RESPONSABLES'!$A$2:$A$200,ROW()-4),"") -> Enrico | R7: =SUMIFS('CARGAS DE COMBUSTIBLE'!$N$2:$N$301,'CARGAS DE COMBUSTIBLE'!$D$2:$D$301,$C$1,'CARGAS DE COMBUSTIBLE'!$J$2:$J$301,$Q7) -> 0 | S7: =SUMIFS('CARGAS DE COMBUSTIBLE'!$P$2:$P$301,'CARGAS DE COMBUSTIBLE'!$D$2:$D$301,$C$1,'CARGAS DE COMBUSTIBLE'!$J$2:$J$301,$Q7) -> 0 | T7: =COUNTIFS('CARGAS DE COMBUSTIBLE'!$D$2:$D$301,$C$1,'CARGAS DE COMBUSTIBLE'!$J$2:$J$301,$Q7,'CARGAS DE COMBUSTIBLE'!$A$2:$A$301,"<>") -> 0 | V7: Nafta | W7: =SUMIFS('CARGAS DE COMBUSTIBLE'!$N$2:$N$301,'CARGAS DE COMBUSTIBLE'!$D$2:$D$301,$C$1,'CARGAS DE COMBUSTIBLE'!$M$2:$M$301,$V7) -> 0 | X7: =SUMIFS('CARGAS DE COMBUSTIBLE'!$P$2:$P$301,'CARGAS DE COMBUSTIBLE'!$D$2:$D$301,$C$1,'CARGAS DE COMBUSTIBLE'!$M$2:$M$301,$V7) -> 0
A8: Abril | B8: =SUMIFS('CARGAS DE COMBUSTIBLE'!$N$2:$N$301,'CARGAS DE COMBUSTIBLE'!$D$2:$D$301,$C$1,'CARGAS DE COMBUSTIBLE'!$C$2:$C$301,$A8) -> 0 | C8: =SUMIFS('CARGAS DE COMBUSTIBLE'!$P$2:$P$301,'CARGAS DE COMBUSTIBLE'!$D$2:$D$301,$C$1,'CARGAS DE COMBUSTIBLE'!$C$2:$C$301,$A8) -> 0 | D8: =COUNTIFS('CARGAS DE COMBUSTIBLE'!$D$2:$D$301,$C$1,'CARGAS DE COMBUSTIBLE'!$C$2:$C$301,$A8,'CARGAS DE COMBUSTIBLE'!$A$2:$A$301,"<>") -> 0 | F8: =IFERROR(INDEX('MAESTRO DE UNIDADES'!$C$2:$C$208,ROW()-4),"") -> Peugeot Partner confort 1.6 HDI | G8: =IFERROR(INDEX('MAESTRO DE UNIDADES'!$A$2:$A$208,ROW()-4),"") -> C-004 | H8: =SUMIFS('CARGAS DE COMBUSTIBLE'!$N$2:$N$301,'CARGAS DE COMBUSTIBLE'!$D$2:$D$301,$C$1,'CARGAS DE COMBUSTIBLE'!$F$2:$F$301,$F8) -> 0 | I8: =SUMIFS('CARGAS DE COMBUSTIBLE'!$P$2:$P$301,'CARGAS DE COMBUSTIBLE'!$D$2:$D$301,$C$1,'CARGAS DE COMBUSTIBLE'!$F$2:$F$301,$F8) -> 0 | J8: =COUNTIFS('CARGAS DE COMBUSTIBLE'!$D$2:$D$301,$C$1,'CARGAS DE COMBUSTIBLE'!$F$2:$F$301,$F8,'CARGAS DE COMBUSTIBLE'!$A$2:$A$301,"<>") -> 0 | L8: =IFERROR(INDEX('MAESTRO DE OBRAS'!$B$2:$B$200,ROW()-4),"") -> Movimientos Internos | M8: =SUMIFS('CARGAS DE COMBUSTIBLE'!$N$2:$N$301,'CARGAS DE COMBUSTIBLE'!$D$2:$D$301,$C$1,'CARGAS DE COMBUSTIBLE'!$K$2:$K$301,$L8) -> 90 | N8: =SUMIFS('CARGAS DE COMBUSTIBLE'!$P$2:$P$301,'CARGAS DE COMBUSTIBLE'!$D$2:$D$301,$C$1,'CARGAS DE COMBUSTIBLE'!$K$2:$K$301,$L8) -> 0 | O8: =COUNTIFS('CARGAS DE COMBUSTIBLE'!$D$2:$D$301,$C$1,'CARGAS DE COMBUSTIBLE'!$K$2:$K$301,$L8,'CARGAS DE COMBUSTIBLE'!$A$2:$A$301,"<>") -> 2 | Q8: =IFERROR(INDEX('MAESTRO DE RESPONSABLES'!$A$2:$A$200,ROW()-4),"") -> Gustavo | R8: =SUMIFS('CARGAS DE COMBUSTIBLE'!$N$2:$N$301,'CARGAS DE COMBUSTIBLE'!$D$2:$D$301,$C$1,'CARGAS DE COMBUSTIBLE'!$J$2:$J$301,$Q8) -> 0 | S8: =SUMIFS('CARGAS DE COMBUSTIBLE'!$P$2:$P$301,'CARGAS DE COMBUSTIBLE'!$D$2:$D$301,$C$1,'CARGAS DE COMBUSTIBLE'!$J$2:$J$301,$Q8) -> 0 | T8: =COUNTIFS('CARGAS DE COMBUSTIBLE'!$D$2:$D$301,$C$1,'CARGAS DE COMBUSTIBLE'!$J$2:$J$301,$Q8,'CARGAS DE COMBUSTIBLE'!$A$2:$A$301,"<>") -> 0 | V8: Aceite | W8: =SUMIFS('CARGAS DE COMBUSTIBLE'!$N$2:$N$301,'CARGAS DE COMBUSTIBLE'!$D$2:$D$301,$C$1,'CARGAS DE COMBUSTIBLE'!$M$2:$M$301,$V8) -> 0 | X8: =SUMIFS('CARGAS DE COMBUSTIBLE'!$P$2:$P$301,'CARGAS DE COMBUSTIBLE'!$D$2:$D$301,$C$1,'CARGAS DE COMBUSTIBLE'!$M$2:$M$301,$V8) -> 0
A9: Mayo | B9: =SUMIFS('CARGAS DE COMBUSTIBLE'!$N$2:$N$301,'CARGAS DE COMBUSTIBLE'!$D$2:$D$301,$C$1,'CARGAS DE COMBUSTIBLE'!$C$2:$C$301,$A9) -> 139.65 | C9: =SUMIFS('CARGAS DE COMBUSTIBLE'!$P$2:$P$301,'CARGAS DE COMBUSTIBLE'!$D$2:$D$301,$C$1,'CARGAS DE COMBUSTIBLE'!$C$2:$C$301,$A9) -> 0 | D9: =COUNTIFS('CARGAS DE COMBUSTIBLE'!$D$2:$D$301,$C$1,'CARGAS DE COMBUSTIBLE'!$C$2:$C$301,$A9,'CARGAS DE COMBUSTIBLE'!$A$2:$A$301,"<>") -> 3 | F9: =IFERROR(INDEX('MAESTRO DE UNIDADES'!$C$2:$C$208,ROW()-4),"") -> Toyota Hilux 4X4 C/S DX2.4 TDI 6M/T | G9: =IFERROR(INDEX('MAESTRO DE UNIDADES'!$A$2:$A$208,ROW()-4),"") -> C-005 | H9: =SUMIFS('CARGAS DE COMBUSTIBLE'!$N$2:$N$301,'CARGAS DE COMBUSTIBLE'!$D$2:$D$301,$C$1,'CARGAS DE COMBUSTIBLE'!$F$2:$F$301,$F9) -> 0 | I9: =SUMIFS('CARGAS DE COMBUSTIBLE'!$P$2:$P$301,'CARGAS DE COMBUSTIBLE'!$D$2:$D$301,$C$1,'CARGAS DE COMBUSTIBLE'!$F$2:$F$301,$F9) -> 0 | J9: =COUNTIFS('CARGAS DE COMBUSTIBLE'!$D$2:$D$301,$C$1,'CARGAS DE COMBUSTIBLE'!$F$2:$F$301,$F9,'CARGAS DE COMBUSTIBLE'!$A$2:$A$301,"<>") -> 0 | L9: =IFERROR(INDEX('MAESTRO DE OBRAS'!$B$2:$B$200,ROW()-4),"") -> Barrio ASEC | M9: =SUMIFS('CARGAS DE COMBUSTIBLE'!$N$2:$N$301,'CARGAS DE COMBUSTIBLE'!$D$2:$D$301,$C$1,'CARGAS DE COMBUSTIBLE'!$K$2:$K$301,$L9) -> 0 | N9: =SUMIFS('CARGAS DE COMBUSTIBLE'!$P$2:$P$301,'CARGAS DE COMBUSTIBLE'!$D$2:$D$301,$C$1,'CARGAS DE COMBUSTIBLE'!$K$2:$K$301,$L9) -> 0 | O9: =COUNTIFS('CARGAS DE COMBUSTIBLE'!$D$2:$D$301,$C$1,'CARGAS DE COMBUSTIBLE'!$K$2:$K$301,$L9,'CARGAS DE COMBUSTIBLE'!$A$2:$A$301,"<>") -> 0 | Q9: =IFERROR(INDEX('MAESTRO DE RESPONSABLES'!$A$2:$A$200,ROW()-4),"") -> Adolfo | R9: =SUMIFS('CARGAS DE COMBUSTIBLE'!$N$2:$N$301,'CARGAS DE COMBUSTIBLE'!$D$2:$D$301,$C$1,'CARGAS DE COMBUSTIBLE'!$J$2:$J$301,$Q9) -> 90 | S9: =SUMIFS('CARGAS DE COMBUSTIBLE'!$P$2:$P$301,'CARGAS DE COMBUSTIBLE'!$D$2:$D$301,$C$1,'CARGAS DE COMBUSTIBLE'!$J$2:$J$301,$Q9) -> 0 | T9: =COUNTIFS('CARGAS DE COMBUSTIBLE'!$D$2:$D$301,$C$1,'CARGAS DE COMBUSTIBLE'!$J$2:$J$301,$Q9,'CARGAS DE COMBUSTIBLE'!$A$2:$A$301,"<>") -> 2
A10: Junio | B10: =SUMIFS('CARGAS DE COMBUSTIBLE'!$N$2:$N$301,'CARGAS DE COMBUSTIBLE'!$D$2:$D$301,$C$1,'CARGAS DE COMBUSTIBLE'!$C$2:$C$301,$A10) -> 0 | C10: =SUMIFS('CARGAS DE COMBUSTIBLE'!$P$2:$P$301,'CARGAS DE COMBUSTIBLE'!$D$2:$D$301,$C$1,'CARGAS DE COMBUSTIBLE'!$C$2:$C$301,$A10) -> 0 | D10: =COUNTIFS('CARGAS DE COMBUSTIBLE'!$D$2:$D$301,$C$1,'CARGAS DE COMBUSTIBLE'!$C$2:$C$301,$A10,'CARGAS DE COMBUSTIBLE'!$A$2:$A$301,"<>") -> 0 | F10: =IFERROR(INDEX('MAESTRO DE UNIDADES'!$C$2:$C$208,ROW()-4),"") -> Iveco Tector | G10: =IFERROR(INDEX('MAESTRO DE UNIDADES'!$A$2:$A$208,ROW()-4),"") -> CM-001 | H10: =SUMIFS('CARGAS DE COMBUSTIBLE'!$N$2:$N$301,'CARGAS DE COMBUSTIBLE'!$D$2:$D$301,$C$1,'CARGAS DE COMBUSTIBLE'!$F$2:$F$301,$F10) -> 49.65 | I10: =SUMIFS('CARGAS DE COMBUSTIBLE'!$P$2:$P$301,'CARGAS DE COMBUSTIBLE'!$D$2:$D$301,$C$1,'CARGAS DE COMBUSTIBLE'!$F$2:$F$301,$F10) -> 0 | J10: =COUNTIFS('CARGAS DE COMBUSTIBLE'!$D$2:$D$301,$C$1,'CARGAS DE COMBUSTIBLE'!$F$2:$F$301,$F10,'CARGAS DE COMBUSTIBLE'!$A$2:$A$301,"<>") -> 1 | L10: =IFERROR(INDEX('MAESTRO DE OBRAS'!$B$2:$B$200,ROW()-4),"") -> Barrio San Martin | M10: =SUMIFS('CARGAS DE COMBUSTIBLE'!$N$2:$N$301,'CARGAS DE COMBUSTIBLE'!$D$2:$D$301,$C$1,'CARGAS DE COMBUSTIBLE'!$K$2:$K$301,$L10) -> 0 | N10: =SUMIFS('CARGAS DE COMBUSTIBLE'!$P$2:$P$301,'CARGAS DE COMBUSTIBLE'!$D$2:$D$301,$C$1,'CARGAS DE COMBUSTIBLE'!$K$2:$K$301,$L10) -> 0 | O10: =COUNTIFS('CARGAS DE COMBUSTIBLE'!$D$2:$D$301,$C$1,'CARGAS DE COMBUSTIBLE'!$K$2:$K$301,$L10,'CARGAS DE COMBUSTIBLE'!$A$2:$A$301,"<>") -> 0 | Q10: =IFERROR(INDEX('MAESTRO DE RESPONSABLES'!$A$2:$A$200,ROW()-4),"") -> Daniel Pereyra | R10: =SUMIFS('CARGAS DE COMBUSTIBLE'!$N$2:$N$301,'CARGAS DE COMBUSTIBLE'!$D$2:$D$301,$C$1,'CARGAS DE COMBUSTIBLE'!$J$2:$J$301,$Q10) -> 0 | S10: =SUMIFS('CARGAS DE COMBUSTIBLE'!$P$2:$P$301,'CARGAS DE COMBUSTIBLE'!$D$2:$D$301,$C$1,'CARGAS DE COMBUSTIBLE'!$J$2:$J$301,$Q10) -> 0 | T10: =COUNTIFS('CARGAS DE COMBUSTIBLE'!$D$2:$D$301,$C$1,'CARGAS DE COMBUSTIBLE'!$J$2:$J$301,$Q10,'CARGAS DE COMBUSTIBLE'!$A$2:$A$301,"<>") -> 0 | V10: Registros incompletos | W10: =COUNTIF('CARGAS DE COMBUSTIBLE'!$Y$2:$Y$301,"<>OK") -> 297
A11: Julio | B11: =SUMIFS('CARGAS DE COMBUSTIBLE'!$N$2:$N$301,'CARGAS DE COMBUSTIBLE'!$D$2:$D$301,$C$1,'CARGAS DE COMBUSTIBLE'!$C$2:$C$301,$A11) -> 0 | C11: =SUMIFS('CARGAS DE COMBUSTIBLE'!$P$2:$P$301,'CARGAS DE COMBUSTIBLE'!$D$2:$D$301,$C$1,'CARGAS DE COMBUSTIBLE'!$C$2:$C$301,$A11) -> 0 | D11: =COUNTIFS('CARGAS DE COMBUSTIBLE'!$D$2:$D$301,$C$1,'CARGAS DE COMBUSTIBLE'!$C$2:$C$301,$A11,'CARGAS DE COMBUSTIBLE'!$A$2:$A$301,"<>") -> 0 | F11: =IFERROR(INDEX('MAESTRO DE UNIDADES'!$C$2:$C$208,ROW()-4),"") -> IVECO Daily 70c17 PASO 4350 | G11: =IFERROR(INDEX('MAESTRO DE UNIDADES'!$A$2:$A$208,ROW()-4),"") -> CM-002 | H11: =SUMIFS('CARGAS DE COMBUSTIBLE'!$N$2:$N$301,'CARGAS DE COMBUSTIBLE'!$D$2:$D$301,$C$1,'CARGAS DE COMBUSTIBLE'!$F$2:$F$301,$F11) -> 0 | I11: =SUMIFS('CARGAS DE COMBUSTIBLE'!$P$2:$P$301,'CARGAS DE COMBUSTIBLE'!$D$2:$D$301,$C$1,'CARGAS DE COMBUSTIBLE'!$F$2:$F$301,$F11) -> 0 | J11: =COUNTIFS('CARGAS DE COMBUSTIBLE'!$D$2:$D$301,$C$1,'CARGAS DE COMBUSTIBLE'!$F$2:$F$301,$F11,'CARGAS DE COMBUSTIBLE'!$A$2:$A$301,"<>") -> 0 | Q11: =IFERROR(INDEX('MAESTRO DE RESPONSABLES'!$A$2:$A$200,ROW()-4),"") -> Martin | R11: =SUMIFS('CARGAS DE COMBUSTIBLE'!$N$2:$N$301,'CARGAS DE COMBUSTIBLE'!$D$2:$D$301,$C$1,'CARGAS DE COMBUSTIBLE'!$J$2:$J$301,$Q11) -> 0 | S11: =SUMIFS('CARGAS DE COMBUSTIBLE'!$P$2:$P$301,'CARGAS DE COMBUSTIBLE'!$D$2:$D$301,$C$1,'CARGAS DE COMBUSTIBLE'!$J$2:$J$301,$Q11) -> 0 | T11: =COUNTIFS('CARGAS DE COMBUSTIBLE'!$D$2:$D$301,$C$1,'CARGAS DE COMBUSTIBLE'!$J$2:$J$301,$Q11,'CARGAS DE COMBUSTIBLE'!$A$2:$A$301,"<>") -> 0 | V11: Variación mensual importe | W11: =IF(C8=0,"",(C8-C7)/C7)
A12: Agosto | B12: =SUMIFS('CARGAS DE COMBUSTIBLE'!$N$2:$N$301,'CARGAS DE COMBUSTIBLE'!$D$2:$D$301,$C$1,'CARGAS DE COMBUSTIBLE'!$C$2:$C$301,$A12) -> 0 | C12: =SUMIFS('CARGAS DE COMBUSTIBLE'!$P$2:$P$301,'CARGAS DE COMBUSTIBLE'!$D$2:$D$301,$C$1,'CARGAS DE COMBUSTIBLE'!$C$2:$C$301,$A12) -> 0 | D12: =COUNTIFS('CARGAS DE COMBUSTIBLE'!$D$2:$D$301,$C$1,'CARGAS DE COMBUSTIBLE'!$C$2:$C$301,$A12,'CARGAS DE COMBUSTIBLE'!$A$2:$A$301,"<>") -> 0 | F12: =IFERROR(INDEX('MAESTRO DE UNIDADES'!$C$2:$C$208,ROW()-4),"") -> Motocompresor | G12: =IFERROR(INDEX('MAESTRO DE UNIDADES'!$A$2:$A$208,ROW()-4),"") -> EP-001 | H12: =SUMIFS('CARGAS DE COMBUSTIBLE'!$N$2:$N$301,'CARGAS DE COMBUSTIBLE'!$D$2:$D$301,$C$1,'CARGAS DE COMBUSTIBLE'!$F$2:$F$301,$F12) -> 0 | I12: =SUMIFS('CARGAS DE COMBUSTIBLE'!$P$2:$P$301,'CARGAS DE COMBUSTIBLE'!$D$2:$D$301,$C$1,'CARGAS DE COMBUSTIBLE'!$F$2:$F$301,$F12) -> 0 | J12: =COUNTIFS('CARGAS DE COMBUSTIBLE'!$D$2:$D$301,$C$1,'CARGAS DE COMBUSTIBLE'!$F$2:$F$301,$F12,'CARGAS DE COMBUSTIBLE'!$A$2:$A$301,"<>") -> 0 | Q12: =IFERROR(INDEX('MAESTRO DE RESPONSABLES'!$A$2:$A$200,ROW()-4),"") -> Daniel | R12: =SUMIFS('CARGAS DE COMBUSTIBLE'!$N$2:$N$301,'CARGAS DE COMBUSTIBLE'!$D$2:$D$301,$C$1,'CARGAS DE COMBUSTIBLE'!$J$2:$J$301,$Q12) -> 0 | S12: =SUMIFS('CARGAS DE COMBUSTIBLE'!$P$2:$P$301,'CARGAS DE COMBUSTIBLE'!$D$2:$D$301,$C$1,'CARGAS DE COMBUSTIBLE'!$J$2:$J$301,$Q12) -> 0 | T12: =COUNTIFS('CARGAS DE COMBUSTIBLE'!$D$2:$D$301,$C$1,'CARGAS DE COMBUSTIBLE'!$J$2:$J$301,$Q12,'CARGAS DE COMBUSTIBLE'!$A$2:$A$301,"<>") -> 0 | V12: Promedio por carga | W12: =IF(SUM(D5:D16)=0,"",SUM(C5:C16)/SUM(D5:D16)) -> 0
A13: Septiembre | B13: =SUMIFS('CARGAS DE COMBUSTIBLE'!$N$2:$N$301,'CARGAS DE COMBUSTIBLE'!$D$2:$D$301,$C$1,'CARGAS DE COMBUSTIBLE'!$C$2:$C$301,$A13) -> 0 | C13: =SUMIFS('CARGAS DE COMBUSTIBLE'!$P$2:$P$301,'CARGAS DE COMBUSTIBLE'!$D$2:$D$301,$C$1,'CARGAS DE COMBUSTIBLE'!$C$2:$C$301,$A13) -> 0 | D13: =COUNTIFS('CARGAS DE COMBUSTIBLE'!$D$2:$D$301,$C$1,'CARGAS DE COMBUSTIBLE'!$C$2:$C$301,$A13,'CARGAS DE COMBUSTIBLE'!$A$2:$A$301,"<>") -> 0 | F13: =IFERROR(INDEX('MAESTRO DE UNIDADES'!$C$2:$C$208,ROW()-4),"") -> Motosoldador | G13: =IFERROR(INDEX('MAESTRO DE UNIDADES'!$A$2:$A$208,ROW()-4),"") -> EP-002 | H13: =SUMIFS('CARGAS DE COMBUSTIBLE'!$N$2:$N$301,'CARGAS DE COMBUSTIBLE'!$D$2:$D$301,$C$1,'CARGAS DE COMBUSTIBLE'!$F$2:$F$301,$F13) -> 0 | I13: =SUMIFS('CARGAS DE COMBUSTIBLE'!$P$2:$P$301,'CARGAS DE COMBUSTIBLE'!$D$2:$D$301,$C$1,'CARGAS DE COMBUSTIBLE'!$F$2:$F$301,$F13) -> 0 | J13: =COUNTIFS('CARGAS DE COMBUSTIBLE'!$D$2:$D$301,$C$1,'CARGAS DE COMBUSTIBLE'!$F$2:$F$301,$F13,'CARGAS DE COMBUSTIBLE'!$A$2:$A$301,"<>") -> 0
A14: Octubre | B14: =SUMIFS('CARGAS DE COMBUSTIBLE'!$N$2:$N$301,'CARGAS DE COMBUSTIBLE'!$D$2:$D$301,$C$1,'CARGAS DE COMBUSTIBLE'!$C$2:$C$301,$A14) -> 0 | C14: =SUMIFS('CARGAS DE COMBUSTIBLE'!$P$2:$P$301,'CARGAS DE COMBUSTIBLE'!$D$2:$D$301,$C$1,'CARGAS DE COMBUSTIBLE'!$C$2:$C$301,$A14) -> 0 | D14: =COUNTIFS('CARGAS DE COMBUSTIBLE'!$D$2:$D$301,$C$1,'CARGAS DE COMBUSTIBLE'!$C$2:$C$301,$A14,'CARGAS DE COMBUSTIBLE'!$A$2:$A$301,"<>") -> 0 | F14: =IFERROR(INDEX('MAESTRO DE UNIDADES'!$C$2:$C$208,ROW()-4),"") -> Montacarga | G14: =IFERROR(INDEX('MAESTRO DE UNIDADES'!$A$2:$A$208,ROW()-4),"") -> EP-003 | H14: =SUMIFS('CARGAS DE COMBUSTIBLE'!$N$2:$N$301,'CARGAS DE COMBUSTIBLE'!$D$2:$D$301,$C$1,'CARGAS DE COMBUSTIBLE'!$F$2:$F$301,$F14) -> 0 | I14: =SUMIFS('CARGAS DE COMBUSTIBLE'!$P$2:$P$301,'CARGAS DE COMBUSTIBLE'!$D$2:$D$301,$C$1,'CARGAS DE COMBUSTIBLE'!$F$2:$F$301,$F14) -> 0 | J14: =COUNTIFS('CARGAS DE COMBUSTIBLE'!$D$2:$D$301,$C$1,'CARGAS DE COMBUSTIBLE'!$F$2:$F$301,$F14,'CARGAS DE COMBUSTIBLE'!$A$2:$A$301,"<>") -> 0
A15: Noviembre | B15: =SUMIFS('CARGAS DE COMBUSTIBLE'!$N$2:$N$301,'CARGAS DE COMBUSTIBLE'!$D$2:$D$301,$C$1,'CARGAS DE COMBUSTIBLE'!$C$2:$C$301,$A15) -> 0 | C15: =SUMIFS('CARGAS DE COMBUSTIBLE'!$P$2:$P$301,'CARGAS DE COMBUSTIBLE'!$D$2:$D$301,$C$1,'CARGAS DE COMBUSTIBLE'!$C$2:$C$301,$A15) -> 0 | D15: =COUNTIFS('CARGAS DE COMBUSTIBLE'!$D$2:$D$301,$C$1,'CARGAS DE COMBUSTIBLE'!$C$2:$C$301,$A15,'CARGAS DE COMBUSTIBLE'!$A$2:$A$301,"<>") -> 0
A16: Diciembre | B16: =SUMIFS('CARGAS DE COMBUSTIBLE'!$N$2:$N$301,'CARGAS DE COMBUSTIBLE'!$D$2:$D$301,$C$1,'CARGAS DE COMBUSTIBLE'!$C$2:$C$301,$A16) -> 0 | C16: =SUMIFS('CARGAS DE COMBUSTIBLE'!$P$2:$P$301,'CARGAS DE COMBUSTIBLE'!$D$2:$D$301,$C$1,'CARGAS DE COMBUSTIBLE'!$C$2:$C$301,$A16) -> 0 | D16: =COUNTIFS('CARGAS DE COMBUSTIBLE'!$D$2:$D$301,$C$1,'CARGAS DE COMBUSTIBLE'!$C$2:$C$301,$A16,'CARGAS DE COMBUSTIBLE'!$A$2:$A$301,"<>") -> 0

Sheet DASHBOARD
A1: DASHBOARD EJECUTIVO - CONTROL DE COMBUSTIBLE
N2: =IFERROR(MATCH(B4,Lista_Meses,0),"") -> 4 | X2: =SUMPRODUCT(('CARGAS DE COMBUSTIBLE'!$P$2:$P$301)*--('CARGAS DE COMBUSTIBLE'!$D$2:$D$301=$B$3)*--((($B$4="Todos")+('CARGAS DE COMBUSTIBLE'!$C$2:$C$301=$B$4))>0)*--((($B$5="Todos")+('CARGAS DE COMBUSTIBLE'!$F$2:$F$301=$B$5))>0)*--((($B$6="Todos")+('CARGAS DE COMBUSTIBLE'!$K$2:$K$301=$B$6))>0)*--((($B$7="Todos")+('CARGAS DE COMBUSTIBLE'!$J$2:$J$301=$B$7))>0)*--((($B$8="Todos")+('CARGAS DE COMBUSTIBLE'!$M$2:$M$301=$B$8))>0)) -> #VALUE!
A3: Año | B3: 2026 | D3: Total cargado ($) | G3: Total litros | J3: Cantidad de cargas | M3: Ticket promedio | X3: =SUMPRODUCT(('CARGAS DE COMBUSTIBLE'!$N$2:$N$301)*--('CARGAS DE COMBUSTIBLE'!$D$2:$D$301=$B$3)*--((($B$4="Todos")+('CARGAS DE COMBUSTIBLE'!$C$2:$C$301=$B$4))>0)*--((($B$5="Todos")+('CARGAS DE COMBUSTIBLE'!$F$2:$F$301=$B$5))>0)*--((($B$6="Todos")+('CARGAS DE COMBUSTIBLE'!$K$2:$K$301=$B$6))>0)*--((($B$7="Todos")+('CARGAS DE COMBUSTIBLE'!$J$2:$J$301=$B$7))>0)*--((($B$8="Todos")+('CARGAS DE COMBUSTIBLE'!$M$2:$M$301=$B$8))>0)) -> 0
A4: Mes | B4: Abril | D4: =X2 -> #VALUE! | G4: =X3 -> 0 | J4: =X4 -> 0 | M4: =X5 | X4: =SUMPRODUCT(--('CARGAS DE COMBUSTIBLE'!$A$2:$A$301<>"")*--('CARGAS DE COMBUSTIBLE'!$D$2:$D$301=$B$3)*--((($B$4="Todos")+('CARGAS DE COMBUSTIBLE'!$C$2:$C$301=$B$4))>0)*--((($B$5="Todos")+('CARGAS DE COMBUSTIBLE'!$F$2:$F$301=$B$5))>0)*--((($B$6="Todos")+('CARGAS DE COMBUSTIBLE'!$K$2:$K$301=$B$6))>0)*--((($B$7="Todos")+('CARGAS DE COMBUSTIBLE'!$J$2:$J$301=$B$7))>0)*--((($B$8="Todos")+('CARGAS DE COMBUSTIBLE'!$M$2:$M$301=$B$8))>0)) -> 0
A5: Unidad | B5: Todos | X5: =IF(X4=0,"",X2/X4)
A6: Obra | B6: Todos | D6: Litros promedio por carga | G6: Unidad con mayor consumo | J6: Obra con mayor consumo | M6: Responsable con mayor consumo | X6: =IF(X4=0,"",X3/X4)
A7: Responsable | B7: Todos | D7: =X6 | G7: =X7 | J7: =X8 | M7: =X9 | X7: =IF(MAX($B$90:$B$99)=0,"",INDEX($A$90:$A$99,MATCH(MAX($B$90:$B$99),$B$90:$B$99,0)))
A8: Tipo combustible | B8: Todos | X8: =IF(MAX($E$90:$E$95)=0,"",INDEX($D$90:$D$95,MATCH(MAX($E$90:$E$95),$E$90:$E$95,0)))
D9: Dif. vs mes anterior | G9: Dif. vs factura proveedor | J9: Registros observados | X9: =IF(MAX($H$90:$H$97)=0,"",INDEX($G$90:$G$97,MATCH(MAX($H$90:$H$97),$H$90:$H$97,0)))
D10: =X10 -> #VALUE! | G10: =X11 -> 656800 | J10: =X12 -> 0 | X10: =IF(B4="Todos","",X2-SUMPRODUCT(('CARGAS DE COMBUSTIBLE'!$P$2:$P$301)*--('CARGAS DE COMBUSTIBLE'!$D$2:$D$301=IF(MATCH(B4,Lista_Meses,0)=1,B3-1,B3))*--('CARGAS DE COMBUSTIBLE'!$C$2:$C$301=CHOOSE(IF(MATCH(B4,Lista_Meses,0)=1,12,MATCH(B4,Lista_Meses,0)-1),"Enero","Febrero","Marzo","Abril","Mayo","Junio","Julio","Agosto","Septiembre","Octubre","Noviembre","Diciembre"))*--((($B$5="Todos")+('CARGAS DE COMBUSTIBLE'!$F$2:$F$301=$B$5))>0)*--((($B$6="Todos")+('CARGAS DE COMBUSTIBLE'!$K$2:$K$301=$B$6))>0)*--((($B$7="Todos")+('CARGAS DE COMBUSTIBLE'!$J$2:$J$301=$B$7))>0)*--((($B$8="Todos")+('CARGAS DE COMBUSTIBLE'!$M$2:$M$301=$B$8))>0))) -> #VALUE!
X11: =IF(B4="Todos","",IFERROR(INDEX('CONTROL MENSUAL PROVEEDOR'!$H$4:$H$15,MATCH(B4,'CONTROL MENSUAL PROVEEDOR'!$A$4:$A$15,0)),"")) -> 656800
A12: Evolución mensual | I12: Distribución operativa | X12: =SUMPRODUCT(--('CARGAS DE COMBUSTIBLE'!$Y$2:$Y$301<>"OK")*--('CARGAS DE COMBUSTIBLE'!$D$2:$D$301=$B$3)*--((($B$4="Todos")+('CARGAS DE COMBUSTIBLE'!$C$2:$C$301=$B$4))>0)*--((($B$5="Todos")+('CARGAS DE COMBUSTIBLE'!$F$2:$F$301=$B$5))>0)*--((($B$6="Todos")+('CARGAS DE COMBUSTIBLE'!$K$2:$K$301=$B$6))>0)*--((($B$7="Todos")+('CARGAS DE COMBUSTIBLE'!$J$2:$J$301=$B$7))>0)*--((($B$8="Todos")+('CARGAS DE COMBUSTIBLE'!$M$2:$M$301=$B$8))>0)) -> 0
A30: Consumo por unidad | I30: Consumo por obra / tipo
A48: Consumo por responsable | I48: Seguimiento y conciliación
A66: Planilla vs factura | I66: Cargas por mes
A90: =IFERROR(INDEX('MAESTRO DE UNIDADES'!$C$2:$C$208,ROW()-89),"") -> Toyota Hilux 2.4 | B90: =SUMPRODUCT(('CARGAS DE COMBUSTIBLE'!$N$2:$N$301)*--('CARGAS DE COMBUSTIBLE'!$D$2:$D$301=$B$3)*--((($B$4="Todos")+('CARGAS DE COMBUSTIBLE'!$C$2:$C$301=$B$4))>0)*--((($B$6="Todos")+('CARGAS DE COMBUSTIBLE'!$K$2:$K$301=$B$6))>0)*--((($B$7="Todos")+('CARGAS DE COMBUSTIBLE'!$J$2:$J$301=$B$7))>0)*--((($B$8="Todos")+('CARGAS DE COMBUSTIBLE'!$M$2:$M$301=$B$8))>0)*--('CARGAS DE COMBUSTIBLE'!$F$2:$F$301=$A90)*--((($B$5="Todos")+($A90=$B$5))>0)) -> 0 | D90: =IFERROR(INDEX('MAESTRO DE OBRAS'!$B$2:$B$200,ROW()-89),"") -> Barrio Don Jose | E90: =SUMPRODUCT(('CARGAS DE COMBUSTIBLE'!$N$2:$N$301)*--('CARGAS DE COMBUSTIBLE'!$D$2:$D$301=$B$3)*--((($B$4="Todos")+('CARGAS DE COMBUSTIBLE'!$C$2:$C$301=$B$4))>0)*--((($B$5="Todos")+('CARGAS DE COMBUSTIBLE'!$F$2:$F$301=$B$5))>0)*--((($B$7="Todos")+('CARGAS DE COMBUSTIBLE'!$J$2:$J$301=$B$7))>0)*--((($B$8="Todos")+('CARGAS DE COMBUSTIBLE'!$M$2:$M$301=$B$8))>0)*--('CARGAS DE COMBUSTIBLE'!$K$2:$K$301=$D90)*--((($B$6="Todos")+($D90=$B$6))>0)) -> 0 | G90: =IFERROR(INDEX('MAESTRO DE RESPONSABLES'!$A$2:$A$200,ROW()-89),"") -> Ariel Jofre | H90: =SUMPRODUCT(('CARGAS DE COMBUSTIBLE'!$N$2:$N$301)*--('CARGAS DE COMBUSTIBLE'!$D$2:$D$301=$B$3)*--((($B$4="Todos")+('CARGAS DE COMBUSTIBLE'!$C$2:$C$301=$B$4))>0)*--((($B$5="Todos")+('CARGAS DE COMBUSTIBLE'!$F$2:$F$301=$B$5))>0)*--((($B$6="Todos")+('CARGAS DE COMBUSTIBLE'!$K$2:$K$301=$B$6))>0)*--((($B$8="Todos")+('CARGAS DE COMBUSTIBLE'!$M$2:$M$301=$B$8))>0)*--('CARGAS DE COMBUSTIBLE'!$J$2:$J$301=$G90)*--((($B$7="Todos")+($G90=$B$7))>0)) -> 0
A91: =IFERROR(INDEX('MAESTRO DE UNIDADES'!$C$2:$C$208,ROW()-89),"") -> Toyota Hilux 2.4 | B91: =SUMPRODUCT(('CARGAS DE COMBUSTIBLE'!$N$2:$N$301)*--('CARGAS DE COMBUSTIBLE'!$D$2:$D$301=$B$3)*--((($B$4="Todos")+('CARGAS DE COMBUSTIBLE'!$C$2:$C$301=$B$4))>0)*--((($B$6="Todos")+('CARGAS DE COMBUSTIBLE'!$K$2:$K$301=$B$6))>0)*--((($B$7="Todos")+('CARGAS DE COMBUSTIBLE'!$J$2:$J$301=$B$7))>0)*--((($B$8="Todos")+('CARGAS DE COMBUSTIBLE'!$M$2:$M$301=$B$8))>0)*--('CARGAS DE COMBUSTIBLE'!$F$2:$F$301=$A91)*--((($B$5="Todos")+($A91=$B$5))>0)) -> 0 | D91: =IFERROR(INDEX('MAESTRO DE OBRAS'!$B$2:$B$200,ROW()-89),"") -> Escuela Stgo del Estero | E91: =SUMPRODUCT(('CARGAS DE COMBUSTIBLE'!$N$2:$N$301)*--('CARGAS DE COMBUSTIBLE'!$D$2:$D$301=$B$3)*--((($B$4="Todos")+('CARGAS DE COMBUSTIBLE'!$C$2:$C$301=$B$4))>0)*--((($B$5="Todos")+('CARGAS DE COMBUSTIBLE'!$F$2:$F$301=$B$5))>0)*--((($B$7="Todos")+('CARGAS DE COMBUSTIBLE'!$J$2:$J$301=$B$7))>0)*--((($B$8="Todos")+('CARGAS DE COMBUSTIBLE'!$M$2:$M$301=$B$8))>0)*--('CARGAS DE COMBUSTIBLE'!$K$2:$K$301=$D91)*--((($B$6="Todos")+($D91=$B$6))>0)) -> 0 | G91: =IFERROR(INDEX('MAESTRO DE RESPONSABLES'!$A$2:$A$200,ROW()-89),"") -> Bruno Guevara | H91: =SUMPRODUCT(('CARGAS DE COMBUSTIBLE'!$N$2:$N$301)*--('CARGAS DE COMBUSTIBLE'!$D$2:$D$301=$B$3)*--((($B$4="Todos")+('CARGAS DE COMBUSTIBLE'!$C$2:$C$301=$B$4))>0)*--((($B$5="Todos")+('CARGAS DE COMBUSTIBLE'!$F$2:$F$301=$B$5))>0)*--((($B$6="Todos")+('CARGAS DE COMBUSTIBLE'!$K$2:$K$301=$B$6))>0)*--((($B$8="Todos")+('CARGAS DE COMBUSTIBLE'!$M$2:$M$301=$B$8))>0)*--('CARGAS DE COMBUSTIBLE'!$J$2:$J$301=$G91)*--((($B$7="Todos")+($G91=$B$7))>0)) -> 0
A92: =IFERROR(INDEX('MAESTRO DE UNIDADES'!$C$2:$C$208,ROW()-89),"") -> RAM 1500 5.7 V8 LARAMIE4X4 | B92: =SUMPRODUCT(('CARGAS DE COMBUSTIBLE'!$N$2:$N$301)*--('CARGAS DE COMBUSTIBLE'!$D$2:$D$301=$B$3)*--((($B$4="Todos")+('CARGAS DE COMBUSTIBLE'!$C$2:$C$301=$B$4))>0)*--((($B$6="Todos")+('CARGAS DE COMBUSTIBLE'!$K$2:$K$301=$B$6))>0)*--((($B$7="Todos")+('CARGAS DE COMBUSTIBLE'!$J$2:$J$301=$B$7))>0)*--((($B$8="Todos")+('CARGAS DE COMBUSTIBLE'!$M$2:$M$301=$B$8))>0)*--('CARGAS DE COMBUSTIBLE'!$F$2:$F$301=$A92)*--((($B$5="Todos")+($A92=$B$5))>0)) -> 0 | D92: =IFERROR(INDEX('MAESTRO DE OBRAS'!$B$2:$B$200,ROW()-89),"") -> Mantenimiento Escuelas | E92: =SUMPRODUCT(('CARGAS DE COMBUSTIBLE'!$N$2:$N$301)*--('CARGAS DE COMBUSTIBLE'!$D$2:$D$301=$B$3)*--((($B$4="Todos")+('CARGAS DE COMBUSTIBLE'!$C$2:$C$301=$B$4))>0)*--((($B$5="Todos")+('CARGAS DE COMBUSTIBLE'!$F$2:$F$301=$B$5))>0)*--((($B$7="Todos")+('CARGAS DE COMBUSTIBLE'!$J$2:$J$301=$B$7))>0)*--((($B$8="Todos")+('CARGAS DE COMBUSTIBLE'!$M$2:$M$301=$B$8))>0)*--('CARGAS DE COMBUSTIBLE'!$K$2:$K$301=$D92)*--((($B$6="Todos")+($D92=$B$6))>0)) -> 0 | G92: =IFERROR(INDEX('MAESTRO DE RESPONSABLES'!$A$2:$A$200,ROW()-89),"") -> Enrico | H92: =SUMPRODUCT(('CARGAS DE COMBUSTIBLE'!$N$2:$N$301)*--('CARGAS DE COMBUSTIBLE'!$D$2:$D$301=$B$3)*--((($B$4="Todos")+('CARGAS DE COMBUSTIBLE'!$C$2:$C$301=$B$4))>0)*--((($B$5="Todos")+('CARGAS DE COMBUSTIBLE'!$F$2:$F$301=$B$5))>0)*--((($B$6="Todos")+('CARGAS DE COMBUSTIBLE'!$K$2:$K$301=$B$6))>0)*--((($B$8="Todos")+('CARGAS DE COMBUSTIBLE'!$M$2:$M$301=$B$8))>0)*--('CARGAS DE COMBUSTIBLE'!$J$2:$J$301=$G92)*--((($B$7="Todos")+($G92=$B$7))>0)) -> 0
A93: =IFERROR(INDEX('MAESTRO DE UNIDADES'!$C$2:$C$208,ROW()-89),"") -> Peugeot Partner confort 1.6 HDI | B93: =SUMPRODUCT(('CARGAS DE COMBUSTIBLE'!$N$2:$N$301)*--('CARGAS DE COMBUSTIBLE'!$D$2:$D$301=$B$3)*--((($B$4="Todos")+('CARGAS DE COMBUSTIBLE'!$C$2:$C$301=$B$4))>0)*--((($B$6="Todos")+('CARGAS DE COMBUSTIBLE'!$K$2:$K$301=$B$6))>0)*--((($B$7="Todos")+('CARGAS DE COMBUSTIBLE'!$J$2:$J$301=$B$7))>0)*--((($B$8="Todos")+('CARGAS DE COMBUSTIBLE'!$M$2:$M$301=$B$8))>0)*--('CARGAS DE COMBUSTIBLE'!$F$2:$F$301=$A93)*--((($B$5="Todos")+($A93=$B$5))>0)) -> 0 | D93: =IFERROR(INDEX('MAESTRO DE OBRAS'!$B$2:$B$200,ROW()-89),"") -> Movimientos Internos | E93: =SUMPRODUCT(('CARGAS DE COMBUSTIBLE'!$N$2:$N$301)*--('CARGAS DE COMBUSTIBLE'!$D$2:$D$301=$B$3)*--((($B$4="Todos")+('CARGAS DE COMBUSTIBLE'!$C$2:$C$301=$B$4))>0)*--((($B$5="Todos")+('CARGAS DE COMBUSTIBLE'!$F$2:$F$301=$B$5))>0)*--((($B$7="Todos")+('CARGAS DE COMBUSTIBLE'!$J$2:$J$301=$B$7))>0)*--((($B$8="Todos")+('CARGAS DE COMBUSTIBLE'!$M$2:$M$301=$B$8))>0)*--('CARGAS DE COMBUSTIBLE'!$K$2:$K$301=$D93)*--((($B$6="Todos")+($D93=$B$6))>0)) -> 0 | G93: =IFERROR(INDEX('MAESTRO DE RESPONSABLES'!$A$2:$A$200,ROW()-89),"") -> Gustavo | H93: =SUMPRODUCT(('CARGAS DE COMBUSTIBLE'!$N$2:$N$301)*--('CARGAS DE COMBUSTIBLE'!$D$2:$D$301=$B$3)*--((($B$4="Todos")+('CARGAS DE COMBUSTIBLE'!$C$2:$C$301=$B$4))>0)*--((($B$5="Todos")+('CARGAS DE COMBUSTIBLE'!$F$2:$F$301=$B$5))>0)*--((($B$6="Todos")+('CARGAS DE COMBUSTIBLE'!$K$2:$K$301=$B$6))>0)*--((($B$8="Todos")+('CARGAS DE COMBUSTIBLE'!$M$2:$M$301=$B$8))>0)*--('CARGAS DE COMBUSTIBLE'!$J$2:$J$301=$G93)*--((($B$7="Todos")+($G93=$B$7))>0)) -> 0
A94: =IFERROR(INDEX('MAESTRO DE UNIDADES'!$C$2:$C$208,ROW()-89),"") -> Toyota Hilux 4X4 C/S DX2.4 TDI 6M/T | B94: =SUMPRODUCT(('CARGAS DE COMBUSTIBLE'!$N$2:$N$301)*--('CARGAS DE COMBUSTIBLE'!$D$2:$D$301=$B$3)*--((($B$4="Todos")+('CARGAS DE COMBUSTIBLE'!$C$2:$C$301=$B$4))>0)*--((($B$6="Todos")+('CARGAS DE COMBUSTIBLE'!$K$2:$K$301=$B$6))>0)*--((($B$7="Todos")+('CARGAS DE COMBUSTIBLE'!$J$2:$J$301=$B$7))>0)*--((($B$8="Todos")+('CARGAS DE COMBUSTIBLE'!$M$2:$M$301=$B$8))>0)*--('CARGAS DE COMBUSTIBLE'!$F$2:$F$301=$A94)*--((($B$5="Todos")+($A94=$B$5))>0)) -> 0 | D94: =IFERROR(INDEX('MAESTRO DE OBRAS'!$B$2:$B$200,ROW()-89),"") -> Barrio ASEC | E94: =SUMPRODUCT(('CARGAS DE COMBUSTIBLE'!$N$2:$N$301)*--('CARGAS DE COMBUSTIBLE'!$D$2:$D$301=$B$3)*--((($B$4="Todos")+('CARGAS DE COMBUSTIBLE'!$C$2:$C$301=$B$4))>0)*--((($B$5="Todos")+('CARGAS DE COMBUSTIBLE'!$F$2:$F$301=$B$5))>0)*--((($B$7="Todos")+('CARGAS DE COMBUSTIBLE'!$J$2:$J$301=$B$7))>0)*--((($B$8="Todos")+('CARGAS DE COMBUSTIBLE'!$M$2:$M$301=$B$8))>0)*--('CARGAS DE COMBUSTIBLE'!$K$2:$K$301=$D94)*--((($B$6="Todos")+($D94=$B$6))>0)) -> 0 | G94: =IFERROR(INDEX('MAESTRO DE RESPONSABLES'!$A$2:$A$200,ROW()-89),"") -> Adolfo | H94: =SUMPRODUCT(('CARGAS DE COMBUSTIBLE'!$N$2:$N$301)*--('CARGAS DE COMBUSTIBLE'!$D$2:$D$301=$B$3)*--((($B$4="Todos")+('CARGAS DE COMBUSTIBLE'!$C$2:$C$301=$B$4))>0)*--((($B$5="Todos")+('CARGAS DE COMBUSTIBLE'!$F$2:$F$301=$B$5))>0)*--((($B$6="Todos")+('CARGAS DE COMBUSTIBLE'!$K$2:$K$301=$B$6))>0)*--((($B$8="Todos")+('CARGAS DE COMBUSTIBLE'!$M$2:$M$301=$B$8))>0)*--('CARGAS DE COMBUSTIBLE'!$J$2:$J$301=$G94)*--((($B$7="Todos")+($G94=$B$7))>0)) -> 0
A95: =IFERROR(INDEX('MAESTRO DE UNIDADES'!$C$2:$C$208,ROW()-89),"") -> Iveco Tector | B95: =SUMPRODUCT(('CARGAS DE COMBUSTIBLE'!$N$2:$N$301)*--('CARGAS DE COMBUSTIBLE'!$D$2:$D$301=$B$3)*--((($B$4="Todos")+('CARGAS DE COMBUSTIBLE'!$C$2:$C$301=$B$4))>0)*--((($B$6="Todos")+('CARGAS DE COMBUSTIBLE'!$K$2:$K$301=$B$6))>0)*--((($B$7="Todos")+('CARGAS DE COMBUSTIBLE'!$J$2:$J$301=$B$7))>0)*--((($B$8="Todos")+('CARGAS DE COMBUSTIBLE'!$M$2:$M$301=$B$8))>0)*--('CARGAS DE COMBUSTIBLE'!$F$2:$F$301=$A95)*--((($B$5="Todos")+($A95=$B$5))>0)) -> 0 | D95: =IFERROR(INDEX('MAESTRO DE OBRAS'!$B$2:$B$200,ROW()-89),"") -> Barrio San Martin | E95: =SUMPRODUCT(('CARGAS DE COMBUSTIBLE'!$N$2:$N$301)*--('CARGAS DE COMBUSTIBLE'!$D$2:$D$301=$B$3)*--((($B$4="Todos")+('CARGAS DE COMBUSTIBLE'!$C$2:$C$301=$B$4))>0)*--((($B$5="Todos")+('CARGAS DE COMBUSTIBLE'!$F$2:$F$301=$B$5))>0)*--((($B$7="Todos")+('CARGAS DE COMBUSTIBLE'!$J$2:$J$301=$B$7))>0)*--((($B$8="Todos")+('CARGAS DE COMBUSTIBLE'!$M$2:$M$301=$B$8))>0)*--('CARGAS DE COMBUSTIBLE'!$K$2:$K$301=$D95)*--((($B$6="Todos")+($D95=$B$6))>0)) -> 0 | G95: =IFERROR(INDEX('MAESTRO DE RESPONSABLES'!$A$2:$A$200,ROW()-89),"") -> Daniel Pereyra | H95: =SUMPRODUCT(('CARGAS DE COMBUSTIBLE'!$N$2:$N$301)*--('CARGAS DE COMBUSTIBLE'!$D$2:$D$301=$B$3)*--((($B$4="Todos")+('CARGAS DE COMBUSTIBLE'!$C$2:$C$301=$B$4))>0)*--((($B$5="Todos")+('CARGAS DE COMBUSTIBLE'!$F$2:$F$301=$B$5))>0)*--((($B$6="Todos")+('CARGAS DE COMBUSTIBLE'!$K$2:$K$301=$B$6))>0)*--((($B$8="Todos")+('CARGAS DE COMBUSTIBLE'!$M$2:$M$301=$B$8))>0)*--('CARGAS DE COMBUSTIBLE'!$J$2:$J$301=$G95)*--((($B$7="Todos")+($G95=$B$7))>0)) -> 0
A96: =IFERROR(INDEX('MAESTRO DE UNIDADES'!$C$2:$C$208,ROW()-89),"") -> IVECO Daily 70c17 PASO 4350 | B96: =SUMPRODUCT(('CARGAS DE COMBUSTIBLE'!$N$2:$N$301)*--('CARGAS DE COMBUSTIBLE'!$D$2:$D$301=$B$3)*--((($B$4="Todos")+('CARGAS DE COMBUSTIBLE'!$C$2:$C$301=$B$4))>0)*--((($B$6="Todos")+('CARGAS DE COMBUSTIBLE'!$K$2:$K$301=$B$6))>0)*--((($B$7="Todos")+('CARGAS DE COMBUSTIBLE'!$J$2:$J$301=$B$7))>0)*--((($B$8="Todos")+('CARGAS DE COMBUSTIBLE'!$M$2:$M$301=$B$8))>0)*--('CARGAS DE COMBUSTIBLE'!$F$2:$F$301=$A96)*--((($B$5="Todos")+($A96=$B$5))>0)) -> 0 | G96: =IFERROR(INDEX('MAESTRO DE RESPONSABLES'!$A$2:$A$200,ROW()-89),"") -> Martin | H96: =SUMPRODUCT(('CARGAS DE COMBUSTIBLE'!$N$2:$N$301)*--('CARGAS DE COMBUSTIBLE'!$D$2:$D$301=$B$3)*--((($B$4="Todos")+('CARGAS DE COMBUSTIBLE'!$C$2:$C$301=$B$4))>0)*--((($B$5="Todos")+('CARGAS DE COMBUSTIBLE'!$F$2:$F$301=$B$5))>0)*--((($B$6="Todos")+('CARGAS DE COMBUSTIBLE'!$K$2:$K$301=$B$6))>0)*--((($B$8="Todos")+('CARGAS DE COMBUSTIBLE'!$M$2:$M$301=$B$8))>0)*--('CARGAS DE COMBUSTIBLE'!$J$2:$J$301=$G96)*--((($B$7="Todos")+($G96=$B$7))>0)) -> 0
A97: =IFERROR(INDEX('MAESTRO DE UNIDADES'!$C$2:$C$208,ROW()-89),"") -> Motocompresor | B97: =SUMPRODUCT(('CARGAS DE COMBUSTIBLE'!$N$2:$N$301)*--('CARGAS DE COMBUSTIBLE'!$D$2:$D$301=$B$3)*--((($B$4="Todos")+('CARGAS DE COMBUSTIBLE'!$C$2:$C$301=$B$4))>0)*--((($B$6="Todos")+('CARGAS DE COMBUSTIBLE'!$K$2:$K$301=$B$6))>0)*--((($B$7="Todos")+('CARGAS DE COMBUSTIBLE'!$J$2:$J$301=$B$7))>0)*--((($B$8="Todos")+('CARGAS DE COMBUSTIBLE'!$M$2:$M$301=$B$8))>0)*--('CARGAS DE COMBUSTIBLE'!$F$2:$F$301=$A97)*--((($B$5="Todos")+($A97=$B$5))>0)) -> 0 | G97: =IFERROR(INDEX('MAESTRO DE RESPONSABLES'!$A$2:$A$200,ROW()-89),"") -> Daniel | H97: =SUMPRODUCT(('CARGAS DE COMBUSTIBLE'!$N$2:$N$301)*--('CARGAS DE COMBUSTIBLE'!$D$2:$D$301=$B$3)*--((($B$4="Todos")+('CARGAS DE COMBUSTIBLE'!$C$2:$C$301=$B$4))>0)*--((($B$5="Todos")+('CARGAS DE COMBUSTIBLE'!$F$2:$F$301=$B$5))>0)*--((($B$6="Todos")+('CARGAS DE COMBUSTIBLE'!$K$2:$K$301=$B$6))>0)*--((($B$8="Todos")+('CARGAS DE COMBUSTIBLE'!$M$2:$M$301=$B$8))>0)*--('CARGAS DE COMBUSTIBLE'!$J$2:$J$301=$G97)*--((($B$7="Todos")+($G97=$B$7))>0)) -> 0
A98: =IFERROR(INDEX('MAESTRO DE UNIDADES'!$C$2:$C$208,ROW()-89),"") -> Motosoldador | B98: =SUMPRODUCT(('CARGAS DE COMBUSTIBLE'!$N$2:$N$301)*--('CARGAS DE COMBUSTIBLE'!$D$2:$D$301=$B$3)*--((($B$4="Todos")+('CARGAS DE COMBUSTIBLE'!$C$2:$C$301=$B$4))>0)*--((($B$6="Todos")+('CARGAS DE COMBUSTIBLE'!$K$2:$K$301=$B$6))>0)*--((($B$7="Todos")+('CARGAS DE COMBUSTIBLE'!$J$2:$J$301=$B$7))>0)*--((($B$8="Todos")+('CARGAS DE COMBUSTIBLE'!$M$2:$M$301=$B$8))>0)*--('CARGAS DE COMBUSTIBLE'!$F$2:$F$301=$A98)*--((($B$5="Todos")+($A98=$B$5))>0)) -> 0
A99: =IFERROR(INDEX('MAESTRO DE UNIDADES'!$C$2:$C$208,ROW()-89),"") -> Montacarga | B99: =SUMPRODUCT(('CARGAS DE COMBUSTIBLE'!$N$2:$N$301)*--('CARGAS DE COMBUSTIBLE'!$D$2:$D$301=$B$3)*--((($B$4="Todos")+('CARGAS DE COMBUSTIBLE'!$C$2:$C$301=$B$4))>0)*--((($B$6="Todos")+('CARGAS DE COMBUSTIBLE'!$K$2:$K$301=$B$6))>0)*--((($B$7="Todos")+('CARGAS DE COMBUSTIBLE'!$J$2:$J$301=$B$7))>0)*--((($B$8="Todos")+('CARGAS DE COMBUSTIBLE'!$M$2:$M$301=$B$8))>0)*--('CARGAS DE COMBUSTIBLE'!$F$2:$F$301=$A99)*--((($B$5="Todos")+($A99=$B$5))>0)) -> 0

Sheet LISTAS
A1: Lista codigos | B1: Lista responsables | C1: Lista obras | K1: Lista unidades dashboard
B2: Todos | C2: Todos | D2: Diesel - EVOLUX | E2: Cuenta corriente | F2: Pendiente | G2: 2025 | H2: Enero | I2: Todos | J2: YPF Agro | K2: Todos | L2: 1 | M2: Enero
A3: =IFERROR(INDEX('MAESTRO DE UNIDADES'!$A$2:$A$208,ROW()-2),"") -> C-001 | B3: =IFERROR(INDEX('MAESTRO DE RESPONSABLES'!$A$2:$A$200,ROW()-2),"") -> Ariel Jofre | C3: =IFERROR(INDEX('MAESTRO DE OBRAS'!$B$2:$B$200,ROW()-2),"") -> Barrio Don Jose | D3: Diesel - VPower | E3: Tarjeta flota | F3: Controlado | G3: 2026 | H3: Febrero | I3: Enero | J3: Axion | K3: =IFERROR(INDEX('MAESTRO DE UNIDADES'!$C$2:$C$208,ROW()-2),"") -> Toyota Hilux 2.4 | L3: 2 | M3: Febrero
A4: =IFERROR(INDEX('MAESTRO DE UNIDADES'!$A$2:$A$208,ROW()-2),"") -> C-002 | B4: =IFERROR(INDEX('MAESTRO DE RESPONSABLES'!$A$2:$A$200,ROW()-2),"") -> Bruno Guevara | C4: =IFERROR(INDEX('MAESTRO DE OBRAS'!$B$2:$B$200,ROW()-2),"") -> Escuela Stgo del Estero | D4: Nafta | E4: Transferencia | F4: Validado | G4: 2027 | H4: Marzo | I4: Febrero | J4: Shell Agro | K4: =IFERROR(INDEX('MAESTRO DE UNIDADES'!$C$2:$C$208,ROW()-2),"") -> Toyota Hilux 2.4 | L4: 3 | M4: Marzo
A5: =IFERROR(INDEX('MAESTRO DE UNIDADES'!$A$2:$A$208,ROW()-2),"") -> C-003 | B5: =IFERROR(INDEX('MAESTRO DE RESPONSABLES'!$A$2:$A$200,ROW()-2),"") -> Enrico | C5: =IFERROR(INDEX('MAESTRO DE OBRAS'!$B$2:$B$200,ROW()-2),"") -> Mantenimiento Escuelas | D5: Aceite | E5: Efectivo | F5: Pagado | G5: 2028 | H5: Abril | I5: Marzo | J5: Puma | K5: =IFERROR(INDEX('MAESTRO DE UNIDADES'!$C$2:$C$208,ROW()-2),"") -> RAM 1500 5.7 V8 LARAMIE4X4 | L5: 4 | M5: Abril
A6: =IFERROR(INDEX('MAESTRO DE UNIDADES'!$A$2:$A$208,ROW()-2),"") -> C-004 | B6: =IFERROR(INDEX('MAESTRO DE RESPONSABLES'!$A$2:$A$200,ROW()-2),"") -> Gustavo | C6: =IFERROR(INDEX('MAESTRO DE OBRAS'!$B$2:$B$200,ROW()-2),"") -> Movimientos Internos | H6: Mayo | I6: Abril | J6: Otro | K6: =IFERROR(INDEX('MAESTRO DE UNIDADES'!$C$2:$C$208,ROW()-2),"") -> Peugeot Partner confort 1.6 HDI | L6: 5 | M6: Mayo
A7: =IFERROR(INDEX('MAESTRO DE UNIDADES'!$A$2:$A$208,ROW()-2),"") -> C-005 | B7: =IFERROR(INDEX('MAESTRO DE RESPONSABLES'!$A$2:$A$200,ROW()-2),"") -> Adolfo | C7: =IFERROR(INDEX('MAESTRO DE OBRAS'!$B$2:$B$200,ROW()-2),"") -> Barrio ASEC | D7: Todos | H7: Junio | I7: Mayo | K7: =IFERROR(INDEX('MAESTRO DE UNIDADES'!$C$2:$C$208,ROW()-2),"") -> Toyota Hilux 4X4 C/S DX2.4 TDI 6M/T | L7: 6 | M7: Junio
A8: =IFERROR(INDEX('MAESTRO DE UNIDADES'!$A$2:$A$208,ROW()-2),"") -> CM-001 | B8: =IFERROR(INDEX('MAESTRO DE RESPONSABLES'!$A$2:$A$200,ROW()-2),"") -> Daniel Pereyra | C8: =IFERROR(INDEX('MAESTRO DE OBRAS'!$B$2:$B$200,ROW()-2),"") -> Barrio San Martin | D8: Diesel - EVOLUX | H8: Julio | I8: Junio | K8: =IFERROR(INDEX('MAESTRO DE UNIDADES'!$C$2:$C$208,ROW()-2),"") -> Iveco Tector | L8: 7 | M8: Julio
A9: =IFERROR(INDEX('MAESTRO DE UNIDADES'!$A$2:$A$208,ROW()-2),"") -> CM-002 | B9: =IFERROR(INDEX('MAESTRO DE RESPONSABLES'!$A$2:$A$200,ROW()-2),"") -> Martin | C9: =IFERROR(INDEX('MAESTRO DE OBRAS'!$B$2:$B$200,ROW()-2),"") -> 0 | D9: Diesel - VPower | H9: Agosto | I9: Julio | K9: =IFERROR(INDEX('MAESTRO DE UNIDADES'!$C$2:$C$208,ROW()-2),"") -> IVECO Daily 70c17 PASO 4350 | L9: 8 | M9: Agosto
A10: =IFERROR(INDEX('MAESTRO DE UNIDADES'!$A$2:$A$208,ROW()-2),"") -> EP-001 | B10: =IFERROR(INDEX('MAESTRO DE RESPONSABLES'!$A$2:$A$200,ROW()-2),"") -> Daniel | C10: =IFERROR(INDEX('MAESTRO DE OBRAS'!$B$2:$B$200,ROW()-2),"") -> 0 | D10: Nafta | H10: Septiembre | I10: Agosto | K10: =IFERROR(INDEX('MAESTRO DE UNIDADES'!$C$2:$C$208,ROW()-2),"") -> Motocompresor | L10: 9 | M10: Septiembre
A11: =IFERROR(INDEX('MAESTRO DE UNIDADES'!$A$2:$A$208,ROW()-2),"") -> EP-002 | B11: =IFERROR(INDEX('MAESTRO DE RESPONSABLES'!$A$2:$A$200,ROW()-2),"") -> 0 | C11: =IFERROR(INDEX('MAESTRO DE OBRAS'!$B$2:$B$200,ROW()-2),"") -> 0 | D11: Aceite | H11: Octubre | I11: Septiembre | K11: =IFERROR(INDEX('MAESTRO DE UNIDADES'!$C$2:$C$208,ROW()-2),"") -> Motosoldador | L11: 10 | M11: Octubre
A12: =IFERROR(INDEX('MAESTRO DE UNIDADES'!$A$2:$A$208,ROW()-2),"") -> EP-003 | B12: =IFERROR(INDEX('MAESTRO DE RESPONSABLES'!$A$2:$A$200,ROW()-2),"") -> 0 | C12: =IFERROR(INDEX('MAESTRO DE OBRAS'!$B$2:$B$200,ROW()-2),"") -> 0 | H12: Noviembre | I12: Octubre | K12: =IFERROR(INDEX('MAESTRO DE UNIDADES'!$C$2:$C$208,ROW()-2),"") -> Montacarga | L12: 11 | M12: Noviembre
A13: =IFERROR(INDEX('MAESTRO DE UNIDADES'!$A$2:$A$208,ROW()-2),"") -> MC-001 | B13: =IFERROR(INDEX('MAESTRO DE RESPONSABLES'!$A$2:$A$200,ROW()-2),"") -> Nota: | C13: =IFERROR(INDEX('MAESTRO DE OBRAS'!$B$2:$B$200,ROW()-2),"") -> 0 | H13: Diciembre | I13: Noviembre | K13: =IFERROR(INDEX('MAESTRO DE UNIDADES'!$C$2:$C$208,ROW()-2),"") -> CAT | L13: 12 | M13: Diciembre
A14: =IFERROR(INDEX('MAESTRO DE UNIDADES'!$A$2:$A$208,ROW()-2),"") -> MC-002 | B14: =IFERROR(INDEX('MAESTRO DE RESPONSABLES'!$A$2:$A$200,ROW()-2),"") -> 0 | C14: =IFERROR(INDEX('MAESTRO DE OBRAS'!$B$2:$B$200,ROW()-2),"") -> 0 | I14: Diciembre | K14: =IFERROR(INDEX('MAESTRO DE UNIDADES'!$C$2:$C$208,ROW()-2),"") -> Longking
A15: =IFERROR(INDEX('MAESTRO DE UNIDADES'!$A$2:$A$208,ROW()-2),"") -> RP-001 | B15: =IFERROR(INDEX('MAESTRO DE RESPONSABLES'!$A$2:$A$200,ROW()-2),"") -> 0 | C15: =IFERROR(INDEX('MAESTRO DE OBRAS'!$B$2:$B$200,ROW()-2),"") -> 0 | K15: =IFERROR(INDEX('MAESTRO DE UNIDADES'!$C$2:$C$208,ROW()-2),"") -> Hidromek
A16: =IFERROR(INDEX('MAESTRO DE UNIDADES'!$A$2:$A$208,ROW()-2),"") -> RP-002 | B16: =IFERROR(INDEX('MAESTRO DE RESPONSABLES'!$A$2:$A$200,ROW()-2),"") -> 0 | C16: =IFERROR(INDEX('MAESTRO DE OBRAS'!$B$2:$B$200,ROW()-2),"") -> 0 | K16: =IFERROR(INDEX('MAESTRO DE UNIDADES'!$C$2:$C$208,ROW()-2),"") -> MAXION 750
A17: =IFERROR(INDEX('MAESTRO DE UNIDADES'!$A$2:$A$208,ROW()-2),"") -> BT-001 | B17: =IFERROR(INDEX('MAESTRO DE RESPONSABLES'!$A$2:$A$200,ROW()-2),"") -> 0 | C17: =IFERROR(INDEX('MAESTRO DE OBRAS'!$B$2:$B$200,ROW()-2),"") -> 0 | K17: =IFERROR(INDEX('MAESTRO DE UNIDADES'!$C$2:$C$208,ROW()-2),"") -> Batan de 200lts
A18: =IFERROR(INDEX('MAESTRO DE UNIDADES'!$A$2:$A$208,ROW()-2),"") -> C-006 | B18: =IFERROR(INDEX('MAESTRO DE RESPONSABLES'!$A$2:$A$200,ROW()-2),"") -> 0 | C18: =IFERROR(INDEX('MAESTRO DE OBRAS'!$B$2:$B$200,ROW()-2),"") -> 0 | K18: =IFERROR(INDEX('MAESTRO DE UNIDADES'!$C$2:$C$208,ROW()-2),"") -> Toyota Hilux 2.4
A19: =IFERROR(INDEX('MAESTRO DE UNIDADES'!$A$2:$A$208,ROW()-2),"") -> 0 | B19: =IFERROR(INDEX('MAESTRO DE RESPONSABLES'!$A$2:$A$200,ROW()-2),"") -> 0 | C19: =IFERROR(INDEX('MAESTRO DE OBRAS'!$B$2:$B$200,ROW()-2),"") -> 0 | K19: =IFERROR(INDEX('MAESTRO DE UNIDADES'!$C$2:$C$208,ROW()-2),"") -> 0
A20: =IFERROR(INDEX('MAESTRO DE UNIDADES'!$A$2:$A$208,ROW()-2),"") -> 0 | B20: =IFERROR(INDEX('MAESTRO DE RESPONSABLES'!$A$2:$A$200,ROW()-2),"") -> 0 | C20: =IFERROR(INDEX('MAESTRO DE OBRAS'!$B$2:$B$200,ROW()-2),"") -> 0 | K20: =IFERROR(INDEX('MAESTRO DE UNIDADES'!$C$2:$C$208,ROW()-2),"") -> 0
A21: =IFERROR(INDEX('MAESTRO DE UNIDADES'!$A$2:$A$208,ROW()-2),"") -> 0 | B21: =IFERROR(INDEX('MAESTRO DE RESPONSABLES'!$A$2:$A$200,ROW()-2),"") -> 0 | C21: =IFERROR(INDEX('MAESTRO DE OBRAS'!$B$2:$B$200,ROW()-2),"") -> 0 | K21: =IFERROR(INDEX('MAESTRO DE UNIDADES'!$C$2:$C$208,ROW()-2),"") -> 0
A22: =IFERROR(INDEX('MAESTRO DE UNIDADES'!$A$2:$A$208,ROW()-2),"") -> 0 | B22: =IFERROR(INDEX('MAESTRO DE RESPONSABLES'!$A$2:$A$200,ROW()-2),"") -> 0 | C22: =IFERROR(INDEX('MAESTRO DE OBRAS'!$B$2:$B$200,ROW()-2),"") -> 0 | K22: =IFERROR(INDEX('MAESTRO DE UNIDADES'!$C$2:$C$208,ROW()-2),"") -> 0
A23: =IFERROR(INDEX('MAESTRO DE UNIDADES'!$A$2:$A$208,ROW()-2),"") -> 0 | B23: =IFERROR(INDEX('MAESTRO DE RESPONSABLES'!$A$2:$A$200,ROW()-2),"") -> 0 | C23: =IFERROR(INDEX('MAESTRO DE OBRAS'!$B$2:$B$200,ROW()-2),"") -> 0 | K23: =IFERROR(INDEX('MAESTRO DE UNIDADES'!$C$2:$C$208,ROW()-2),"") -> 0
A24: =IFERROR(INDEX('MAESTRO DE UNIDADES'!$A$2:$A$208,ROW()-2),"") -> 0 | B24: =IFERROR(INDEX('MAESTRO DE RESPONSABLES'!$A$2:$A$200,ROW()-2),"") -> 0 | C24: =IFERROR(INDEX('MAESTRO DE OBRAS'!$B$2:$B$200,ROW()-2),"") -> 0 | K24: =IFERROR(INDEX('MAESTRO DE UNIDADES'!$C$2:$C$208,ROW()-2),"") -> 0
A25: =IFERROR(INDEX('MAESTRO DE UNIDADES'!$A$2:$A$208,ROW()-2),"") -> 0 | B25: =IFERROR(INDEX('MAESTRO DE RESPONSABLES'!$A$2:$A$200,ROW()-2),"") -> 0 | C25: =IFERROR(INDEX('MAESTRO DE OBRAS'!$B$2:$B$200,ROW()-2),"") -> 0 | K25: =IFERROR(INDEX('MAESTRO DE UNIDADES'!$C$2:$C$208,ROW()-2),"") -> 0
A26: =IFERROR(INDEX('MAESTRO DE UNIDADES'!$A$2:$A$208,ROW()-2),"") -> 0 | B26: =IFERROR(INDEX('MAESTRO DE RESPONSABLES'!$A$2:$A$200,ROW()-2),"") -> 0 | C26: =IFERROR(INDEX('MAESTRO DE OBRAS'!$B$2:$B$200,ROW()-2),"") -> 0 | K26: =IFERROR(INDEX('MAESTRO DE UNIDADES'!$C$2:$C$208,ROW()-2),"") -> 0
... A202: =IFERROR(INDEX('MAESTRO DE UNIDADES'!$A$2:$A$208,ROW()-2),"") -> 0 | B202: =IFERROR(INDEX('MAESTRO DE RESPONSABLES'!$A$2:$A$200,ROW()-2),"") | C202: =IFERROR(INDEX('MAESTRO DE OBRAS'!$B$2:$B$200,ROW()-2),"") | K202: =IFERROR(INDEX('MAESTRO DE UNIDADES'!$C$2:$C$208,ROW()-2),"") -> 0
