Workbook

Sheet RESUMEN DICIEMBRE 2025
A1: RESUMEN FINANCIERO DICIEMBRE 2025
A2: ECHEQ A DEVENGAR
A3: INVERSIONES BALANZ | B3: 55510999
A4: SALDO BANCO ECAR | B4: 840000
A5: DISPONIBILIDAD FINANCIERA DICIEMBRE 2025- ECAR | B5: =+SUM(B2:B4) -> 56350999
A6: FALTA PAGOS DICIEMBRE 2025 | B6: =+'GASTOS MENSUALES 2026 '!D55 -> 0
A7: DISPONIBILIDAD - DESEMBOLSO | B7: =+B5-B6 -> 56350999

Sheet RESUMEN FINANCIERO ENERO 2026
A1: RESUMEN FINANCIERO ENERO 2026
A2: ECHEQ A ACREDITAR
A3: INVERSIONES BALANZ | B3: =+B5-B4 -> 29936476
A4: SALDO BANCO ECAR | B4: 1658909.6
A5: DISPONIBILIDAD FINANCIERA ENERO 2026 - ECAR | B5: =+B7 -> 31595386
A6: FALTA PAGOS ENERO 2026
A7: DISPONIBILIDAD FINAL ENERO 2026 | B7: 31595386

Sheet RESUMEN FEBRERO 2026 
A1: RESUMEN FINANCIERO FEBRERO 2026
A2: ECHEQ A ACREDITAR
A3: INVERSIONES BALANZ | B3: 58849928
A4: SALDO BANCO ECAR | B4: 587574
A5: DISPONIBILIDAD FINANCIERA FEBRERO 2026 - ECAR | B5: =+SUM(B2:B4) -> 59437502
A6: FALTA PAGOS FEBRERO 2026 | B6: =+'GASTOS MENSUALES 2026 '!G55 -> 0
A7: DISPONIBILIDAD FINAL FEBRERO 2026 | B7: =+B5-B6 -> 59437502

Sheet RESUMEN MARZO 2026
A1: RESUMEN FINANCIERO MARZO 2026
A2: EFECTIVO | B2: 2723800
A3: INVERSIONES BALANZ | B3: 73647952 | C3: 22800000 | D3: venta de maxion 4x4
A4: SALDO BANCO ECAR | B4: 2939598
A5: DISPONIBILIDAD FINANCIERA MARZO 2026 - ECAR | B5: =+B3+B4+B2 -> 79311350
A6: FALTAN PAGOS ECAR MARZO 2026 | B6: =+'GASTOS MENSUALES 2026 '!I55 -> 0
A7: DISPONIBILIDAD FINAL MARZO 2026 AL 31/03/2026 | B7: =+B5-B6 -> 79311350

Sheet CHEQUES EMITIDOS 
A1: CHEQUES O ECHEQ EMITIDOS 2026
B2: MATRIGAS | C2: 337000 | D2: 46024 | E2: BCO. SANTANDER | F2: 46024
B3: FICAMEN | C3: 372236.18 | D3: 46024 | E3: BCO. SANTANDER | F3: 46024
A4: 477 | B4: HERREMAQ | C4: 423000 | D4: 46011 | E4: BCO. SANTANDER | F4: 46013
A5: ECHEQ | B5: UOCRA | C5: 206505.25 | D5: 46020 | E5: BCO. SANTANDER | F5: 46020 | G5: 30640033173 | H5: CUIT
A6: ECHEQ | B6: OSPECON | C6: 167036.5 | D6: 46020 | E6: BCO. SANTANDER | F6: 46020 | G6: 30640033173 | H6: CUIT
B7: PLACAS ARGENTINA | C7: 234000 | D7: 46028 | E7: BCO. SANTANDER | F7: 46028
A8: 480 | B8: MIASA | C8: 3466387 | D8: 46032 | E8: BCO. SANTANDER | F8: 45669
A9: ECEHQ | B9: MAR-SAN | C9: 151100 | D9: 46032 | E9: BCO. SANTANDER | F9: 45669
A10: 442 | B10: MATRIGAS | C10: 2427932.1 | D10: 46037 | E10: BCO. SANTANDER | F10: 46037
A11: ECHEQ | B11: ITAL VINIL | C11: 2542821 | D11: 46037 | E11: BCO. SANTANDER | F11: 46037 | H11: =+SUM(C2:C22) -> 58246232
A12: ECHEQ | B12: CUYO PARTS | C12: 486029.2 | D12: 46038 | E12: BCO. SANTANDER | F12: 46038
A13: 489 | B13: MARIO VILLARROEL | C13: 564923 | D13: 46038 | E13: BCO. SANTANDER | F13: 46038
A14: 431 | B14: FATE | C14: 236045 | D14: 46042 | E14: BCO. SANTANDER | F14: 46042
B15: TRANSP. GONZALITO | C15: 665500 | D15: 45677 | E15: BCO. SANTANDER | F15: 45677
A16: 488 | B16: ESTACION CENTRAL | C16: 2917830 | D16: 46045 | E16: BCO. SANTANDER | F16: 45680
A17: ECEHQ | B17: OSCAR SCORZA | C17: 13000000 | D17: 46048 | E17: BCO. SANTANDER | F17: 46048
B18: DANIEL BOLLATTI | C18: 378000 | D18: 45680 | E18: BCO. SANTANDER | F18: 45680
B19: 46023 | C19: =+SUM(C2:C18) -> 28576345
A20: 484 | B20: DISCO COMPUTADORA | C20: 720000 | D20: 46039 | E20: BCO. SANTANDER | F20: 46041
A21: ECHEQ 539 | B21: UOCRA | C21: 206505.25 | D21: 46051 | E21: BCO. SANTANDER | F21: 46051 | G21: 30640033173 | H21: CUIT
A22: ECHEQ 540 | B22: OSPECON | C22: 167036.5 | D22: 46051 | E22: BCO. SANTANDER | F22: 46051 | G22: 30640033173 | H22: CUIT
A23: ECHEQ | B23: ITAL VINIL | C23: 2542822 | D23: 46059 | E23: BCO. SANTANDER | F23: 46059
A24: 487 | B24: RESSI | C24: 319484.74 | D24: 46056 | E24: BCO. SANTANDER | F24: 46056
A25: 481 | B25: MIASA | C25: 3466387 | D25: 45698 | E25: BCO. SANTANDER | F25: 45698
A26: 492 | B26: VOXOIL ( RAM) | C26: 678568 | D26: 46068 | E26: BCO. SANTANDER | F26: 46071
A27: ECHEQ 542 | B27: ITAL VINIL | C27: 1851974.9 | D27: 46069 | E27: BCO. SANTANDER | F27: 46071
A28: 485 | B28: DISCO COMPUTADORA | C28: 720000 | D28: 46070 | E28: BCO. SANTANDER | F28: 46071
A29: 490 | B29: MARIO VILLARROEL | C29: 414409 | D29: 46069 | E29: BCO. SANTANDER | F29: 46071
B30: DANIEL BOLLATTI | C30: 378000 | D30: 46073 | E30: BCO. SANTANDER | F30: 46073 | G30: =+SUM(C20:C37) -> 28186931
A31: 491 | B31: INDUSTRIAS HORMAT | C31: 625000 | D31: 46076 | E31: BCO. SANTANDER | F31: 46076
A32: 514 | B32: ESTACION CENTRAL | C32: 2504575 | D32: 46076 | E32: BCO. SANTANDER | F32: 46076
A33: ECEHQ | B33: OSCAR SCORZA | C33: 13000000 | D33: 46079 | E33: BCO. SANTANDER | F33: 46079
B34: 46054 | G34: =+SUM(C20:C33) -> 27594762
A35: ECHEQ 544 | B35: DAGFALT | C35: 218626.88 | D35: 46084 | E35: BCO. SANTANDER | F35: 46084
A36: 38600001 | B36: UOCRA | C36: 206505.25 | D36: 46081 | E36: BCO. SANTANDER | F36: 46083 | G36: 30640033173 | H36: CUIT
A37: 38600002 | B37: OSPECON | C37: 167036.5 | D37: 46081 | E37: BCO. SANTANDER | F37: 46083 | G37: 30640033173 | H37: CUIT
A38: 512 | B38: KATSUDA | C38: 228737.47 | D38: 46084 | E38: BCO. SANTANDER | F38: 46084
A39: 513 | B39: JANIN | C39: 594400 | D39: 46087 | E39: BCO. SANTANDER | F39: 46087
A40: ECHEQ 541 | B40: ITAL VINIL | C40: 1851974.9 | D40: 46087 | E40: BCO. SANTANDER | F40: 46087
A41: 482 | B41: MIASA | C41: 3466387 | D41: 46091 | E41: BCO. SANTANDER | F41: 46091
A42: ECHEQ 546 | B42: BENAVIDEZ | C42: 295144.8 | D42: 46096 | E42: BCO. SANTANDER | F42: 46097
A43: 519 | B43: ESTACION CENTRAL | C43: 2091239.9 | D43: 46104 | E43: BCO. SANTANDER | F43: 46104
A44: ECHEQ | B44: MARSAN | C44: 778500 | D44: 46105 | E44: BCO. SANTANDER | F44: 46105
A45: 516 | B45: APALAN | C45: 1518684.6 | D45: 46106 | E45: BCO. SANTANDER | F45: 46106
A46: ECHEQ | B46: DECOM | C46: 1055241 | D46: 46109 | E46: BCO. SANTANDER | F46: 46111
A48: ECHEQ | B48: UOCRA | C48: 206505.25 | D48: 46110 | E48: BCO. SANTANDER | F48: 46111
A49: ECHEQ | B49: OSPECON | C49: 167036.5 | D49: 46110 | E49: BCO. SANTANDER | F49: 46111
A50: ECHEQ | B50: TRANSP. GONZALITO | C50: 726000 | D50: 46114 | E50: BCO. SANTANDER | F50: 46118
A51: ECHEQ 543 | B51: ITAL VINIL | C51: 1851974.9 | D51: 46118 | E51: BCO. SANTANDER | F51: 46118
A52: ECHEQ | B52: INDEME SAS | C52: 450000 | D52: 46121 | E52: BCO. SANTANDER | F52: 46121
A53: 515 | B53: MARIO GALLO | C53: 1291290 | D53: 46091 | E53: BCO. SANTANDER | F53: 46091
A54: 521 | B54: KATSUDA | C54: 462259.49 | D54: 46127 | E54: BCO. SANTANDER | F54: 46127
A55: ECHEQ | B55: HORMAT | C55: 712849.91 | D55: 46127 | E55: BCO. SANTANDER | F55: 46127
A56: 520 | B56: LEYTON | C56: 450000 | D56: 46127 | E56: BCO. SANTANDER | F56: 46127
A57: 516 | B57: APALAN | C57: 1518684 | D57: 46129 | E57: BCO. SANTANDER | F57: 46129
A58: ECHEQ | B58: DANIEL BOLLATTI | C58: 388600 | D58: 46129 | E58: BCO. SANTANDER | F58: 46129
A59: 522 | B59: PREMOLDEADOS RAWSON | C59: 570000 | D59: 46130 | E59: BCO. SANTANDER | F59: 46132
A60: 518 | B60: SOBERANO | C60: 920300 | D60: 46119 | E60: BCO. SANTANDER | F60: 46119
A61: 526 | B61: CRISTIAN BERON | C61: 305000 | D61: 46132 | E61: BCO. SANTANDER | F61: 46132
A62: ECHEQ | B62: INDEME SAS | C62: 450000 | D62: 46136 | E62: BCO. SANTANDER | F62: 46136
A63: 523 | B63: RESSI | C63: 419063.52 | D63: 46136 | E63: BCO. SANTANDER | F63: 46136
A64: 525 | B64: CONYCOM | C64: 1280000 | D64: 46137 | E64: BCO. SANTANDER | F64: 46139 | G64: =+SUM(C48:C64) -> 12169564
B65: 46113 | C65: =+SUM(C65:C68) -> 0
A66: 801 | B66: JONATAN MALDONDO | C66: 104214 | D66: 46142 | E66: BANCO SAN JUAN | F66: 46142
A67: 802 | B67: JUAN FLORES | C67: 64445 | D67: 46142 | E67: BANCO SAN JUAN | F67: 46142
A68: ECHEQ | B68: UOCRA | C68: 206505.25 | D68: 46141 | E68: BCO. SANTANDER | F68: 46141 | G68: 30640033173 | H68: CUIT
A69: ECHEQ | B69: OSPECON | C69: 167036.5 | D69: 46141 | E69: BCO. SANTANDER | F69: 46141 | G69: 30640033173 | H69: CUIT
A70: ECHEQ | B70: HORMAT | C70: 529219.99 | D70: 46142 | E70: BCO. SANTANDER | F70: 46142
A71: 532 | B71: ESTACION CENTRAL | C71: 3867479.1 | D71: 46147 | E71: BCO. SANTANDER | F71: 46147
A72: 803 | B72: BRUNO GONZALEZ | C72: 331919 | D72: 46142 | E72: BANCO SAN JUAN | F72: 46142
A73: 529 | B73: JOSE FRIAS(LONKING) | C73: 600000 | D73: 46147 | E73: BCO. SANTANDER | F73: 46147
A74: 528 | B74: APALAN | C74: 1569975 | D74: 46150 | E74: BCO. SANTANDER | F74: 46150
A75: 531 | B75: JANIN | C75: 880972.8 | D75: 46152 | E75: BCO. SANTANDER | F75: 46153
A76: 530 | B76: LEYTON | C76: 493500 | D76: 46157 | E76: BCO. SANTANDER | F76: 46157
A77: ECHEQ | B77: DANIEL BOLLATTI | C77: 388600 | D77: 46157 | E77: BCO. SANTANDER | F77: 46159
A78: 533 | B78: DISCO | C78: 583850 | D78: 46157 | E78: BCO. SANTANDER | F78: 46159
A79: 535 | B79: ESTILO HERRAJES | C79: 643417.89 | D79: 46160 | E79: BCO. SANTANDER | F79: 46160
A80: 527 | B80: CRISTIAN BERON | C80: 300000 | D80: 46162 | E80: BCO. SANTANDER | F80: 46162
A81: ECHEQ | B81: SANOD | C81: 677600 | D81: 46162 | E81: BCO. SANTANDER | F81: 46162
A82: 524 | B82: RESSI | C82: 419063.52 | D82: 46164 | E82: BCO. SANTANDER | F82: 46164
A83: ECHEQ | B83: HORMAT | C83: 575290.1 | D83: 46166 | E83: BCO. SANTANDER | F83: 46168
A84: 804 | B84: ESTACION CENTRAL | C84: 2960561.5 | D84: 46167 | E84: BANCO SAN JUAN | F84: 46168
A85: ECHEQ | B85: INDEME SAS | C85: 857000 | D85: 46171 | E85: BCO. SANTANDER | F85: 46171
A86: ECHEQ | B86: UOCRA | C86: 206505.25 | D86: 46171 | E86: BCO. SANTANDER | F86: 46171 | G86: 30640033173 | H86: CUIT
A87: ECHEQ | B87: OSPECON | C87: 167036.5 | D87: 46171 | E87: BCO. SANTANDER | F87: 46171 | G87: 30640033173 | H87: CUIT
B88: 46143 | C88: =+SUM(C72:C87) -> 11655292
A89: 536 | B89: JOSE FRIAS(LONKING) | C89: 325000 | D89: 46178 | E89: BCO. SANTANDER | F89: 46178
B90: ARMETAL | C90: 600000 | D90: 46181 | E90: BCO. SANTANDER | F90: 46181
A91: 534 | B91: DISCO | C91: 583850 | D91: 46183 | E91: BCO. SANTANDER | F91: 46183
A92: 561 | B92: SJO | C92: 1297429 | D92: 46183 | E92: BCO. SANTANDER
A93: ECHEQ | B93: UOCRA | C93: 206505.25 | D93: 46202 | E93: BCO. SANTANDER | F93: 46202 | G93: 30640033173 | H93: CUIT
A94: ECHEQ | B94: OSPECON | C94: 167036.5 | D94: 46202 | E94: BCO. SANTANDER | F94: 46202 | G94: 30640033173 | H94: CUIT
B95: 46174 | C95: =+SUM(C89:C94) -> 3179820.8
A96: 562 | B96: SJO | C96: 1297429 | D96: 46213
C97: =+C96 -> 1297429
A98: 563 | C98: 1297429 | D98: 46244
C99: =+C98 -> 1297429
A100: 564 | C100: 1297429 | D100: 46275
C101: =+C100 -> 1297429
...

Sheet ECHEQ RECIBIDOC
B1: ENERO
A2: Valdivieso Group SRL | B2: 46032 | C2: 1643018.4 | D2: 45669 | E2: COBRADO
C3: =+C2 -> 1643018.4
B4: ABRIL
A5: GALVARINI Y ASOCIADOS SRL | B5: 46134 | C5: 2814417.6 | D5: 46134 | E5: COBRADO

Sheet OBRAS
A1: RESUMEN OBRAS | J1: A COBRAR OBRAS | K1: COBRADO OCTUBRE 2025 | L1: COBRADO NOV 2025 | M1: A COBRAR DICIEMBRE | N1: A COBRADO ENERO 2026 | O1: COBRADO FEBRERO 2026 | P1: COBRADO MARZO 2026 | Q1: A COBRAR ABRIL 2026
S2: ESTIMADO A COBRAR
A3: CALIDRA OC N°1616 | B3: 70%( COBRADO) | C3: SALDO | S3: FACURADO
A4: 54891681 | B4: 38424177 | C4: =+A4-B4 -> 16467504 | D4: IVA INCLUIDO | J4: =+C4 -> 16467504 | S4: COBRADO
A6: REPARACIONES GALVARINI - CALIDRA | C6: 2985806
C7: 2814417.6 | Q7: =+C7 -> 2814417.6
A9: BARRIO SAN MARTIN
D10: CERTIFICADO 1 | E10: CERTIFICADO 2 | F10: CERTIFICADO 3 | G10: CERTIFICADO 4 | H10: CERTIFICADO 5 | I10: CERTIFICADO 6
A11: CONTRATO | B11: ANTICIPO(30%) | C11: REDETERMINACION ANTICIPO | D11: CERT REDETER. 01/09/2025 | E11: CERT REDETER. 02/10/2025 | F11: CERT REDETER. 03/11/2025 | G11: CERT REDETER. 04/12/2025 | H11: CERT REDETER. 18/02/2026 | I11: CERT REDETER. 31/03/2026
A12: 1.7266506e+08 | B12: 51799519 | C12: 2688941.3 | D12: 35260237 | E12: 22520107 | F12: 41962706 | G12: 2792808.1 | H12: 13535071 | I12: 4794614.4 | J12: =+A12-B12-D12-E12-F12-G12-H12 -> 4794614.4
D13: 1138182.9 | E13: 1846986.9 | F13: 3134739.9 | G13: 293203.69 | H13: 1740323.6 | I13: 635172.55 | O13: =+G15 -> 2941981.1
D14: =+D12+D13 -> 36398420 | E14: =+E12+E13 -> 24367094 | F14: =+F12+F13 -> 45097445 | G14: =+G12+G13 -> 3086011.8 | H14: =+H12+H13 -> 15275395 | I14: =+I12+I13 -> 5429786.9 | O14: =+F15 -> 42974364
A15: DEPOSITO BANCO | B15: 49073040 | C15: 2563615.6 | D15: 34685127 | E15: 23220566 | F15: 42974364 | G15: 2941981.1 | H15: 14509971 | K15: =+SUM(B15:C15) -> 51636655 | L15: =+D15 -> 34685127 | M15: =+E15 -> 23220566 | Q15: =+H15 -> 14509971
A17: ESCUELA SANTIAGO DEL ESTERO
D18: CERTIFICADO 1 | E18: CERTIFICADO 2 | F18: CERTIFICADO 3 | G18: CERTIFICADO 4
A19: CONTRATO | B19: ANTICIPO | C19: REDETERMINACION ANTICIPO | D19: CERT REDETER 09/2025 | E19: CERT REDETER. 02/10 | F19: CERT REDETER. 03/11 | G19: CERT REDETER. 04/12
A20: 79457864 | B20: 7945786.4 | C20: 229128.31 | D20: 30635324 | E20: 27296344 | F20: 7822754.6 | G20: 5757654.8 | J20: =+A20-B20-D20-E20-F20-G20 -> 0
D21: 784891.34 | E21: 1569281.9 | F21: 539013.17 | G21: 546710.77
D22: =+D20+D21 -> 31420215 | E22: =+E20+E21 -> 28865626 | F22: =+F20+F21 -> 8361767.8 | G22: =+G20+G21 -> 6304365.6
A23: DEPOSITO BANCO | B23: 7572824.2 | C23: 219678.05 | D23: 20019134 | E23: 27507184 | F23: 7969209.7 | G23: 6008726.5 | K23: =+SUM(B23:C23) -> 7792502.2 | M23: =+E23 -> 27507184 | N23: =+F23 -> 7969209.7 | O23: =+G23 -> 6008726.5
D24: 9922298.8 | G24: FINAL
D25: =+D23+D24 -> 29941433 | L25: =+D25 -> 29941433
A26: BARRIO ASEC I ( MDO )
A27: CONTRATO | B27: CERTIFICADO Nº1
A28: 67500000 | B28: 30037500 | J28: =+A28-B28 -> 37462500 | O28: 30037500
A30: BARRIO LA TRANQUERA (MDO )
A31: CONTRATO
A32: 42900000
A34: BARRIO DON JOSE
A35: CONTRATO | B35: ANTICIPO(10%) | C35: REDETERMINACION ANTICIPO | D35: CERTIFICADO 1 | E35: CERTIFICADO 2 | F35: CERTIFICADO 3 | G35: CERTIFICADO 4 | H35: CERTIFICADO 5
A36: 1.8175296e+08 | B36: 18175296 | C36: 1730179.3 | D36: CERT REDETER 01/11/2025 | E36: CERT REDETER. 02/12/2025 | F36: CERT REDETER. 03/01/2026 | G36: CERT REDETER. 04/2/2026 | H36: CERT REDETER. 04/2/2026 | J36: =+A36-B36-D37-E37-F37-G37 -> 84443390
D37: 10085647 | E37: 9343580.6 | F37: 14364663 | G37: 45340385 | H37: 50645033
D38: 931276.22 | E38: 925689.51 | F38: 1794766.2 | G38: 6631635.4 | H38: 8239263.2
A39: DEPOSITO BANCO | B39: 17125176 | C39: 1631429.7 | D39: =+SUM(D37:D38) -> 11016923 | E39: =+E37+E38 -> 10269270 | F39: =+F38+F37 -> 16159429 | G39: =+G37+G38 -> 51972021 | H39: =+H37+H38 -> 58884297 | N39: =+B39+C39 -> 18756606 | P39: =+F40 -> 15225930
D40: 10380924 | E40: 9676523.5 | F40: 15225930 | O40: =+D40 -> 10380924 | P40: 9676523.5
F41: 46122 | G41: 25459331
F42: 46125 | G42: 23507387
G43: =+G41+G42 -> 48966718 | Q43: =+G43 -> 48966718
A44: SERVICIOS BARRIO DON JOSE | C44: 28/02/206 | D44: 46090 | E44: 46099 | F44: 46112 | G44: MARZO
C45: 6000000 | D45: 1600000 | E45: 2300000 | F45: 2275000 | G45: =+SUM(C45:F45) -> 12175000 | P45: =+C45+D45+E45+F45 -> 12175000
C46: 46121 | D46: 46129 | E46: 46136 | F46: 46142 | G46: ABRIL
C47: =655000+470000 -> 1125000 | D47: 2010000 | E47: 675000 | F47: 1875000 | G47: =+SUM(C47:F47) -> 5685000 | Q47: =+C47+D47+E47+F47 -> 5685000
A51: MANTENIMIENTO DE ESCUELAS - CHIMBAS B
A52: CONTRATO | B52: ANTICIPO(10%) | C52: REDETERMINACION ANTICIPO
A53: 49040519 | B53: =+A53*10% -> 4904051.9 | J53: =+A53 -> 49040519
J55: =+SUM(J2:J54) -> 1.9220853e+08 | K55: =+K15+K23 -> 59429157 | L55: =+SUM(L4:L36) -> 64626560 | M55: =+SUM(M4:M39) -> 50727750 | O55: =+SUM(O2:O40) -> 92343495 | P55: =+P39+P40+P45 -> 37077453 | Q55: =+SUM(Q2:Q54) -> 71976107
O56: =+O14+O28+O40+O23+O13 -> 92343495 | P56: =+P55 -> 37077453 | Q56: =+Q55 -> 71976107
N57: =+'ECHEQ RECIBIDOC'!C2 -> 1643018.4
A58: FATURA VENTA MARZO
A59: COBRADO | B59: =+P56 -> 37077453 | C59: FACTURA Nº | K59: =+K55 -> 59429157 | L59: =+L55 -> 64626560 | M59: =+M55+M57 -> 50727750 | N59: =+N23+N39+N57 -> 28368834
A60: FACTURADO | B60: =+E39+F39+H14 -> 41704094 | C60: FACTURA Nº
B61: =+B60/1.21 -> 34466194
B62: =+B60-B61 -> 7237900.7
A64: FATURA VENTA ABRIL
A65: COBRADO | B65: =+P62 -> 0
A66: FACTURADO | B66: 8350500 | C66: FACTURA Nº 153 | D66: FACTURA FINAL COMPRA LOTES BARRIO ALTOS DEL ALBA
B67: 51972021 | C67: FACTURA Nº 142 | D67: EXPTE 500-000092-2026
B68: 15225880 | C68: FACTURA Nº 143 | D68: EXPTE 500-000093-2026
B69: 2985806 | C69: FACTURA Nº 154
B70: =+SUM(B66:B69) -> 78534207
B71: =+B70/1.21 -> 64904303
B72: =+B70-B71 -> 13629904
B73: 15275395 | C73: NOTA DE CREDITO Nº140
B74: =+B73/1.21 -> 12624293 | C74: IVA
B75: =+B73-B74 -> 2651101.6
B76: =+B72-B75 -> 10978802 | C76: IVA ABRIL

Sheet Hoja1

Sheet GASTOS MENSUALES 2026 
A1: RESUMEN GASTOS MESUALES 2025- 2026 ECAR
A2: DESCRIPCION | C2: 45992 | D2: PAGADO EN DIC | E2: 46023 | F2: 46054 | G2: FALTA PAGO FEBRERO 2026 | H2: 46082 | I2: FALTAN PAGOS MARZO 2026 | J2: 46113 | K2: 46143 | L2: FALTAN PAGOS MAYO 2026
A3: PERSONAL ECAR- HONORARIOS | B3: SUELDOS OBREROS | C3: 8462000 | E3: 875000 | F3: 2300985.3 | H3: 2970050 | J3: 1773760 | K3: 2200000
E4: 1875000 | F4: 1865000 | H4: 2054600 | J4: 2034760 | K4: 2200000
E5: 2030000 | F5: 1925000 | H5: 1710600 | J5: 1499520 | K5: 2200000
E6: 2531851.3 | F6: 1913800 | H6: 1706920 | J6: 1596800 | K6: 2200000
E7: 2155985.3 | J7: 1700480
B8: GUSTAVO REGALADO | C8: 2000000 | E8: 2225000 | F8: 2500000 | H8: 2500000 | J8: 3500000 | K8: 2500000
B9: ADOLFO | F9: 2500000 | K9: 2500000
B10: FERNANDO ORTIZ (DPRG) | C10: 700000 | J10: 500000
B11: ELIO | C11: 960000 | E11: 960000 | F11: =960000+480000 -> 1440000 | H11: 480000 | J11: 960000
B12: GABRIELA | C12: 400000 | E12: 500000
B13: ENRICO | F13: 480000 | H13: 500000 | J13: 500000 | K13: 500000
B14: DEBORA REC. HYS ALBARDON | C14: 220000 | F14: 300000 | H14: 300000 | J14: 300000 | K14: 300000
B15: BRUNO GUEVARA | C15: 200000 | E15: 400000 | F15: 500000 | H15: 500000 | J15: 1000000 | K15: 1000000
E16: 1000000 | J16: 1000000
A17: ESTUDIO CONTABLE(HONORARIOS)SE PAGA CON ECHEQ
A18: SEGUROS | B18: ACCID. PERSONALES
B19: SEGUROS LIDERAR | C19: 403700 | E19: 407600 | F19: 407600 | H19: 447600 | J19: =473500+240000 -> 713500 | K19: 240000
A20: SERVICIOS | B20: OSSE ALMAFUERTE Y SANTA FE | H20: =562589.64+566442.66 -> 1129032.3
B21: NATURGY ALMAFUERTE | C21: 109000 | E21: 48113.54 | F21: =64151.77+64925.23 -> 129077 | H21: 88310.69 | J21: 88099.02 | K21: 110119.81
B22: NATURGY CORDOBA | E22: 16493.47 | F22: 36160.56 | H22: 36947.36 | J22: 44166.02 | K22: 44148.85
B23: NATURGY Bº RIVADAVIA | E23: =2970.59+6287.59 -> 9258.18 | F23: =8642+8663.3 -> 17305.3 | H23: 4352.73 | J23: 8518.75
B24: NATURGY ORO | F24: 3026.32 | H24: 3118.57 | J24: 3492.78
B25: GAS CORDOBA | C25: 3973.33 | E25: 3747.49 | F25: =3983.62+3839.62 -> 7823.24 | H25: 4104.45 | J25: 4029.72
B26: GAS Bº RIVADAVIA | E26: 31492.47 | F26: 3765.87 | H26: =5252.13+3963.79 -> 9215.92 | J26: 4156.55
B27: GAS ORO | E27: 120367.79 | F27: 13823.25 | H27: 4044.23
B28: EXPENSAS CORDOBA | E28: 29000 | F28: 35000 | H28: 40000 | J28: 56000
B29: EXPENSAS ORO | E29: 31901.18 | F29: 16156.08 | H29: 26554.51 | J29: 91637.48
B30: TELEFONIA GUSTAVO | C30: 163000 | E30: 62120.45 | F30: 63562.55 | H30: 65521.7 | J30: 65965.08 | K30: 67592.39
B31: TELEFONIA ADOLFO | E31: 48600.01 | F31: 49849.91 | H31: 50699.99 | J31: 51695.14 | K31: 52695.14
B32: TELEFONIA GABRIELA | E32: 63814.21 | F32: 65480.22 | H32: 66699.6 | J32: 68128.63 | K32: 69525.12
B33: INTERNET DEPO | C33: 63000 | E33: 27400 | F33: 64151.77 | H33: 27000 | J33: 24800
B34: INTERNET OFICINA | E34: 75450.22 | F34: 0 | H34: 44942.41 | J34: 49839.74 | K34: 58069.59
A35: IMPUESTOS ARCA/ PROVINCIA | B35: FORM. 931 | C35: 2768061.8 | E35: 4315469.7 | F35: 2568957.7 | H35: 2254509.5 | J35: 3322811 | K35: 3322811
B36: AUTONOMOS | C36: 119660.24 | E36: 122460.3 | F36: 125485.06 | H36: 129061.38 | J36: 132778.36 | K36: 136628.92
B37: IVA | C37: 8237589.5 | E37: 4023724.5 | F37: 10293676 | H37: 3989738.8 | J37: 2823525.2 | K37: 7249102.5
B38: PLAN DE PAGO AFIP | C38: 113840.32 | E38: 111784.34 | F38: 109728.34 | H38: 107672.35 | J38: 101731.03
B39: AUTOMOTORES | C39: 238986 | K39: =25040.01+68281.49+125736.69+49781.51+63253.28 -> 332092.98
B40: INMOBILIARIO Vº AMERICA | F40: 44997.3
B41: INMOBILIARIO SUTYAGIF | F41: 12112.5
B42: IIBB
A43: GREMIOS | B43: IERIC Y FODECO(1%) | C43: 5109.98 | E43: =7560.35*2 -> 15120.7 | F43: 916.84 | H43: 8001.88 | J43: 11889.12
B44: UOCRA
A45: COMBUSTIBLES | C45: 233632.87
A46: PAGOS A TERCEROS/PRESTAMOS | B46: CHEQUE / ECHEQ EMITIDOS | C46: 30514218 | E46: 28576345 | F46: 27594762 | G46: =+'CHEQUES EMITIDOS '!C34 -> 0 | H46: 12472478 | J46: 12169564 | K46: 16594191
B47: GUSTAVO REGALADO | C47: 5000000 | F47: 1000000
B48: EDUARDO PADILLA | C48: 200000
A49: SERVICIOS HYS CONTRATADOS | B49: BAÑOS QUIMICOS | C49: 133100 | E49: 60500 | F49: 72600 | H49: 72600
B50: CONTEINER | E50: 242000 | F50: 302500
B51: LIMPIEZA OFICINA | F51: 30000
B52: TANQUITO | C52: 44580 | E52: 49190.08 | F52: 49190.08 | H52: 49190
A53: VIANDAS ECAR | C53: 84200 | E53: 145500
A54: VARIOS(ARREGLO MENORES MAQUINA , MATERIALES MENORES,COMPRAS MENORES TARJETA VISA,ETC) | C54: 4388346.7 | E54: 3882550.6 | F54: 4512967.5 | H54: 7622567.5 | J54: =6604530.97+247700.01+518590 -> 7370821
C55: =+SUM(C3:C54) -> 65765998 | D55: =+SUM(D3:D54) -> 0 | E55: =+SUM(E3:E54) -> 57072841 | F55: =+SUM(F3:F54) -> 63355461 | G55: =+SUM(G3:G54) -> 0 | H55: =+SUM(H3:H54) -> 41476134 | I55: =+SUM(I3:I53) -> 0 | J55: =+SUM(J3:J54) -> 43572468 | K55: =+SUM(K3:K54) -> 43876978
A58: RESUMEN ENERO 2026
A59: CAJA DE DICIEMBRE 2025 REAL | B59: 56350999
A60: TOTAL COBRADO - FACTURACION VENTAS OBRAS ENERO 2026 | B60: 28368834
A61: APOYO FINANCIERO A GUSTAVO DOLARES USD $1500( 1USD=$1500) | B61: 2225000
B62: =+B59+B60+B61 -> 86944833
A63: TOTAL GASTOS ECAR ENERO 2026 | B63: 57089335
A64: CAJA DE ENERO 2025 REAL | B64: 31595386
A65: CAJA ENERO 2025 | B65: =+B62-B63 -> 29855498
A67: RESUMEN FEBRERO 2026
A68: CAJA DE ENERO 2026 REAL | B68: =+B64 -> 31595386
A69: TOTAL COBRADO - FACTURACION VENTAS OBRAS FEBRERO 2026 | B69: =+OBRAS!O56 -> 92343495
A70: APOYO FINANCIERO | B70: 0
B71: =+B68+B69+B70 -> 1.2393888e+08
A72: TOTAL GASTOS ECAR FEBRERO 2026 | B72: =+F55 -> 63355461
A73: CAJA DE FEBRERO 2025 REAL | B73: =+'RESUMEN FEBRERO 2026 '!B7 -> 59437502
A74: CAJA FEBRERO 2025 PROYECTADA | B74: =+B71-B72 -> 60583420
A75: DIFERENCIA | B75: =+B73-B74 -> -1145917.9
A77: RESUMEN MARZO 2026
A78: CAJA FINAL FEBRERO 2026 REAL | B78: =+B73 -> 59437502
A79: TOTAL COBRADO - FACTURACION VENTAS OBRAS MARZO 2026 | B79: =+OBRAS!P56 -> 37077453
A80: VENTA DE MAXION 4X4 | B80: 22800000
A81: TOTAL RECIBIDO MARZO | B81: =+B78+B79+B80 -> 1.1931496e+08
A82: TOTAL GASTOS ECAR MARZO 2026 | B82: =+H55 -> 41476134
A83: CAJA FINAL MARZO 2026 PROYECTADA | B83: =+B81-B82 -> 77838821
A84: CAJA MARZO 2026 REAL | B84: =+'RESUMEN MARZO 2026'!B7 -> 79311350
A85: DIFERENCIA | B85: =+B84-B83 -> 1472529
A87: RESUMEN ABRIL 2026
A88: CAJA FINAL MARZO 2026 REAL | B88: =+B84 -> 79311350
A89: TOTAL COBRADO - FACTURACION VENTAS OBRAS ABRIL 2026 | B89: =+OBRAS!Q56 -> 71976107
A90: TOTAL RECIBIDO ABRIL | B90: =+B88+B89 -> 1.5128746e+08
A91: TOTAL GASTOS ECAR ABRIL 2026 | B91: =+J55 -> 43572468
A92: CAJA FINAL ABRIL 2026 PROYECTADA | B92: =+B90-B91 -> 1.0771499e+08
A93: CAJA FINAL ABRIL 2026 REAL | B93: =+'RESUMEN ABRIL 2026'!B7 -> 107525282
A94: DIFERENCIA | B94: =+B93-B92 -> -189706.89

Sheet RESUMEN ABRIL 2026
A1: RESUMEN FINANCIERO ABRIL 2026
A2: EFECTIVO | B2: 975000
A3: INVERSIONES BALANZ | B3: 103045454
A4: SALDO BANCO ECAR | B4: 3504828
A5: DISPONIBILIDAD FINANCIERA ABRIL 2026 - ECAR | B5: =+B3+B4+B2 -> 107525282
A6: PAGOS REALIZADOS ECAR ABRIL 2026
A7: DISPONIBILIDAD FINAL ABRIL 2026 | B7: =+B5-B6 -> 107525282
